Workbook

Sheet Sheet2
A3: Row Labels | B3: Count of Product Type | C3: Sum of Difference
A4: Paint | B4: 615 | C4: 11525.06
A5: Decrease | B5: 4 | C5: -12604.48
A6: Delete | B6: 14 | C6: 0
A7: Increase | B7: 331 | C7: 24129.54
A8: Same | B8: 266 | C8: 0
A9: Sundries | B9: 743 | C9: 1883.54
A10: Decrease | B10: 12 | C10: -1025.99
A11: Delete | B11: 45 | C11: 0
A12: Increase | B12: 347 | C12: 2909.53
A13: Same | B13: 339 | C13: 0
A14: Grand Total | B14: 1358 | C14: 13408.6

Sheet Akzo Sept 01 25  
A1: Enter your Item No We can't have duplicates in the system so if the cell highlights blue, you need to add ; at the end enough times to make unique Limited to 20 characters, yellow if more than this, need to cut down | B1: Enter your number (without any ; if you needed to add any in the 'No' field for duplicates) Again limited to 20 characters, need to cut down if yellow (Might be same as column A) | C1: Enter Vendor Number from Vendor List (new ERP number) | D1: Enter the suppliers name (doesn't need to be full legal one, this is just for description | E1: Paste in the suppliers description of the item | F1: Drag formula down after completing D & E Formula will combine the prior to cells We are though restricted to 50 characters so if the cell highlights in yellow it's too long, need to cut down, or move excess to description 2 column | G1: Enter if need more space to describe the Item | H1: Enter unit of measure | I1: Enter either "ITEM" or "PLANT" | J1: Enter "EXT-PLANT" or "ITEM" | K1: Enter category code to help group the items together, see "Category Code" for ones we've used so far Can add to this list though | L1: Enter Price of Item New cost 1st Jan 2024 | M1: Enter "STD20" unless you know it's not Vatable Alternatively, "REDUCED" or "ZERO" | N1: Enter a cost code for materials or plant (unless it's an overhead like stationery in which case can leave blank) | R1: 01/06/2023 Prices from 1st June | S1: Priced before 01/03/2023 | T1: Total Units Purchased 2023 | V1: Current | W1: Current Armstead -Rates on system 25th April | X1: New Deal | Y1: Old Deal | Z1: DIFF | AA1: AKZO Purchased | AB1: AKZO Price | AC1: Unit Difference | AQ1: Same | AR1: Delete | AS1: Decrease | AT1: Increase | AW1: Increase - Original Data | AX1: Increase - Updated MAT
A2: No | B2: Vendor Item No | C2: No 2 | D2: Suppliers Name | E2: Item Description | F2: Description for System | G2: Description 2 | H2: Base Unit of Measure | I2: Inventory Posting Group | J2: Gen Prod Posting Group | K2: Item Category Code | L2: Unit Cost | M2: VAT Prod Posting Group | N2: Global Dimension 2 Code | W2: Unit Cost | AL2: Inc Sundries | AM2: =COUNTIF(AP6:AP1363,"Increase")-AM3 -> 347 | AO2: New rate Sept 1 2025 | AP2: Orig | AQ2: =COUNTIF($AI:$AI,AQ1) -> 444 | AR2: =COUNTIF($AI:$AI,AR1) -> 228 | AS2: =COUNTIF($AI:$AI,AS1) -> 15 | AT2: =COUNTIF($AI:$AI,AT1) -> 671 | AU2: =SUM(AQ2:AT2) -> 1358 | AW2: =SUMIF($AP$6:$AP$1363,"Increase",AJ$6:AJ$1363) -> 948824.73 | AX2: =SUMIF($AP$6:$AP$1363,"Increase",AQ$6:AQ$1363) -> 599801.88
AL3: Inc Paint | AM3: =COUNTIFS(AL6:AL1363,"Paint",AP6:AP1363,"Increase") -> 331 | AP3: Updated | AQ3: =COUNTIF($AP:$AP,AQ1) -> 605 | AR3: =COUNTIF($AP:$AP,AR1) -> 59 | AS3: =COUNTIF($AP:$AP,AS1) -> 16 | AT3: =COUNTIF($AP:$AP,AT1) -> 678 | AU3: =SUM(AQ3:AT3) -> 1358 | AW3: =SUMIF($AP$6:$AP$1363,"Increase",AK$6:AK$1363) -> 973351.65 | AX3: =SUMIF($AP$6:$AP$1363,"Increase",AR$6:AR$1363) -> 616772.4 | AY3: =AX3-AX2 -> 16970.52 | AZ3: =AY3/AX2 -> 0.028293543
C5: DDEC01 | D5: Akzo DDC | H5: EA | I5: ITEM | J5: ITEM | K5: Paint | L5: 1.78 | M5: STD20 | N5: 3105 | S5: =SUM(R5*P5) -> 0 | T5: =SUM(R5*L5) -> 0 | AD5: PLC | AE5: Remove | AF5: May Price | AH5: Sept Price | AI5: Orig Comp | AJ5: May Val | AK5: Sept Val | AL5: Product Type | AM5: Updated PLC | AN5: Updated MAT Qty | AO5: Updated Sept Price | AP5: Updated Comp | AQ5: Updated May Val | AR5: Updated Sept Val | AS5: Difference
A6: 6188891 | B6: 6188891 | C6: DDEC01 | D6: Akzo DDC | E6: DDC Decorators Caulk White 380ML | F6: DDC Decorators Caulk White 380ML | H6: EA | I6: ITEM | J6: ITEM | K6: Paint | L6: 1.14 | M6: STD20 | N6: 3105 | R6: 1.78 | S6: 1.78 | T6: 21369 | V6: 1.14 | W6: 1.14 | X6: =SUM(V6*T6) -> 24360.66 | Y6: =SUM(L6*T6) -> 24360.66 | Z6: =SUM(X6-Y6) -> 0 | AA6: 21369 | AB6: =IFERROR(VLOOKUP(A6,'Tash Lookup'!A:E,3,FALSE),"") -> 24202 | AC6: =IFERROR(AA6-T6,"") -> 0 | AD6: Normal | AF6: 1.14 | AG6: =VLOOKUP(A6,Sheet1!$A$2:$C$1140,3,FALSE) -> 1.14 | AH6: 1.14 | AI6: =IF(ISNA(AH6),"Delete",IF(AH6=AF6,"Same",IF(AH6>AF6,"Increase","Decrease"))) -> Same | AJ6: =IFERROR(AA6*AF6,0) -> 24360.66 | AK6: =IFERROR(AA6*AH6,0) -> 24360.66 | AL6: Sundries / 3rd Party | AM6: Normal | AN6: 13797 | AO6: 1.14 | AP6: =IF(AM6="Delete","Delete",IF(AO6=AF6,"Same",IF(AO6>AF6,"Increase","Decrease"))) -> Same | AQ6: =AN6*AF6 -> 15728.58 | AR6: =AN6*AO6 -> 15728.58 | AS6: =AR6-AQ6 -> 0
A7: 6188903 | B7: 6188903 | C7: DDEC01 | D7: Akzo DDC | E7: DDC Masking Tape 48MM x 50M | F7: DDC Masking Tape 48MM x 50M | H7: EA | I7: ITEM | J7: ITEM | K7: Paint | L7: 1.22 | M7: STD20 | N7: 3105 | R7: 2.44 | S7: 2.44 | T7: 8541 | V7: 1.22 | W7: 1.22 | X7: =SUM(V7*T7) -> 10420.02 | Y7: =SUM(L7*T7) -> 10420.02 | Z7: =SUM(X7-Y7) -> 0 | AA7: 8541 | AB7: =IFERROR(VLOOKUP(A7,'Tash Lookup'!A:E,3,FALSE),"") -> 10114.89 | AC7: =IFERROR(AA7-T7,"") -> 0 | AD7: Normal | AF7: 1.22 | AG7: =VLOOKUP(A7,Sheet1!$A$2:$C$1140,3,FALSE) -> 1.24 | AH7: 1.24 | AI7: =IF(ISNA(AH7),"Delete",IF(AH7=AF7,"Same",IF(AH7>AF7,"Increase","Decrease"))) -> Increase | AJ7: =IFERROR(AA7*AF7,0) -> 10420.02 | AK7: =IFERROR(AA7*AH7,0) -> 10590.84 | AL7: Sundries / 3rd Party | AM7: Normal | AN7: 4378 | AO7: 1.24 | AP7: =IF(AM7="Delete","Delete",IF(AO7=AF7,"Same",IF(AO7>AF7,"Increase","Decrease"))) -> Increase | AQ7: =AN7*AF7 -> 5341.16 | AR7: =AN7*AO7 -> 5428.72 | AS7: =AR7-AQ7 -> 87.56
A8: 5090751 | B8: 5090751 | C8: DDEC01 | D8: Akzo DDC | E8: Dulux TR Diamond Matt Tinted Colours 5L | F8: Dulux TR Diamond Matt Tinted Colours 5L | H8: EA | I8: ITEM | J8: ITEM | K8: Paint | L8: 30.76 | M8: STD20 | N8: 3105 | R8: 31.74 | S8: 31.74 | T8: 4275 | V8: 28.1865 | W8: 30.76 | X8: =SUM(V8*T8) -> 120497.29 | Y8: =SUM(L8*T8) -> 131499 | Z8: =SUM(X8-Y8) -> -11001.713 | AA8: 4275 | AB8: =IFERROR(VLOOKUP(A8,'Tash Lookup'!A:E,3,FALSE),"") -> 131165.05 | AC8: =IFERROR(AA8-T8,"") -> 0 | AD8: Normal | AF8: 29.61 | AG8: =VLOOKUP(A8,Sheet1!$A$2:$C$1140,3,FALSE) -> 29.61 | AH8: 29.61 | AI8: =IF(ISNA(AH8),"Delete",IF(AH8=AF8,"Same",IF(AH8>AF8,"Increase","Decrease"))) -> Same | AJ8: =IFERROR(AA8*AF8,0) -> 126582.75 | AK8: =IFERROR(AA8*AH8,0) -> 126582.75 | AL8: Paint | AM8: Normal | AN8: 3449 | AO8: 29.61 | AP8: =IF(AM8="Delete","Delete",IF(AO8=AF8,"Same",IF(AO8>AF8,"Increase","Decrease"))) -> Same | AQ8: =AN8*AF8 -> 102124.89 | AR8: =AN8*AO8 -> 102124.89 | AS8: =AR8-AQ8 -> 0
A9: 5090809 | B9: 5090809 | C9: DDEC01 | D9: Akzo DDC | E9: Dulux TR Diamond Eggshell Tint Colours 5L | F9: Dulux TR Diamond Eggshell Tint Colours 5L | H9: EA | I9: ITEM | J9: ITEM | K9: Paint | L9: 35.09 | M9: STD20 | N9: 3105 | R9: 39.04 | S9: 39.04 | T9: 4196 | V9: 32.053 | W9: 35.09 | X9: =SUM(V9*T9) -> 134494.39 | Y9: =SUM(L9*T9) -> 147237.64 | Z9: =SUM(X9-Y9) -> -12743.252 | AA9: 4196 | AB9: =IFERROR(VLOOKUP(A9,'Tash Lookup'!A:E,3,FALSE),"") -> 145002.74 | AC9: =IFERROR(AA9-T9,"") -> 0 | AD9: Normal | AF9: 33.88 | AG9: =VLOOKUP(A9,Sheet1!$A$2:$C$1140,3,FALSE) -> 33.88 | AH9: 33.88 | AI9: =IF(ISNA(AH9),"Delete",IF(AH9=AF9,"Same",IF(AH9>AF9,"Increase","Decrease"))) -> Same | AJ9: =IFERROR(AA9*AF9,0) -> 142160.48 | AK9: =IFERROR(AA9*AH9,0) -> 142160.48 | AL9: Paint | AM9: Normal | AN9: 2501 | AO9: 33.88 | AP9: =IF(AM9="Delete","Delete",IF(AO9=AF9,"Same",IF(AO9>AF9,"Increase","Decrease"))) -> Same | AQ9: =AN9*AF9 -> 84733.88 | AR9: =AN9*AO9 -> 84733.88 | AS9: =AR9-AQ9 -> 0
A10: 5091663 | B10: 5091663 | C10: DDEC01 | D10: Akzo DDC | E10: DT Airsure Supermatt White 10L | F10: Dulux TR Airsure Supermatt White 10L | H10: EA | I10: ITEM | J10: ITEM | K10: Paint | L10: 30.37 | M10: STD20 | N10: 3105 | R10: 30.37 | S10: 30.37 | T10: 2692 | V10: 30.37 | W10: 30.37 | X10: =SUM(V10*T10) -> 81756.04 | Y10: =SUM(L10*T10) -> 81756.04 | Z10: =SUM(X10-Y10) -> 0 | AA10: 2692 | AB10: =IFERROR(VLOOKUP(A10,'Tash Lookup'!A:E,3,FALSE),"") -> 68395.37 | AC10: =IFERROR(AA10-T10,"") -> 0 | AD10: Normal | AF10: 29.14 | AG10: =VLOOKUP(A10,Sheet1!$A$2:$C$1140,3,FALSE) -> 29.14 | AH10: 29.14 | AI10: =IF(ISNA(AH10),"Delete",IF(AH10=AF10,"Same",IF(AH10>AF10,"Increase","Decrease"))) -> Same | AJ10: =IFERROR(AA10*AF10,0) -> 78444.88 | AK10: =IFERROR(AA10*AH10,0) -> 78444.88 | AL10: Paint | AM10: Normal | AN10: 2535 | AO10: 29.14 | AP10: =IF(AM10="Delete","Delete",IF(AO10=AF10,"Same",IF(AO10>AF10,"Increase","Decrease"))) -> Same | AQ10: =AN10*AF10 -> 73869.9 | AR10: =AN10*AO10 -> 73869.9 | AS10: =AR10-AQ10 -> 0
A11: 5293175 | B11: 5293175 | C11: DDEC01 | D11: Akzo DDC | E11: Dulux TR Supermatt White 10L (Airsure Trial Only) | F11: Dulux TR Supermatt White 10L (Airsure Trial Only) | H11: EA | I11: ITEM | J11: ITEM | K11: Paint | L11: 30.37 | M11: STD20 | N11: 3105 | R11: 30.37 | S11: 30.37 | T11: 2692 | V11: 30.37 | W11: 30.37 | X11: =SUM(V11*T11) -> 81756.04 | Y11: =SUM(L11*T11) -> 81756.04 | Z11: =SUM(X11-Y11) -> 0 | AA11: 2692 | AB11: =IFERROR(VLOOKUP(A11,'Tash Lookup'!A:E,3,FALSE),"") -> 68395.37 | AC11: =IFERROR(AA11-T11,"") -> 0 | AD11: Pre-phase-out | AF11: 30 | AG11: 30 | AH11: 30 | AI11: =IF(ISNA(AH11),"Delete",IF(AH11=AF11,"Same",IF(AH11>AF11,"Increase","Decrease"))) -> Same | AJ11: =IFERROR(AA11*AF11,0) -> 80760 | AK11: =IFERROR(AA11*AH11,0) -> 80760 | AL11: Paint | AM11: Pre-phase-out | AN11: 0 | AO11: 30 | AP11: =IF(AM11="Delete","Delete",IF(AO11=AF11,"Same",IF(AO11>AF11,"Increase","Decrease"))) -> Same | AQ11: =AN11*AF11 -> 0 | AR11: =AN11*AO11 -> 0 | AS11: =AR11-AQ11 -> 0
A12: 5218587 | B12: 5218587 | C12: DDEC01 | D12: Akzo DDC | E12: Armstead TR Contract Matt White 10L | F12: Armstead TR Contract Matt White 10L | H12: EA | I12: ITEM | J12: ITEM | K12: Paint | L12: 13.04 | M12: STD20 | N12: 3105 | R12: 15.4 | S12: 15.4 | T12: 2450 | V12: 12.388 | W12: 13.04 | X12: =SUM(V12*T12) -> 30350.6 | Y12: =SUM(L12*T12) -> 31948 | Z12: =SUM(X12-Y12) -> -1597.4 | AA12: 2450 | AB12: =IFERROR(VLOOKUP(A12,'Tash Lookup'!A:E,3,FALSE),"") -> 36831.22 | AC12: =IFERROR(AA12-T12,"") -> 0 | AD12: Normal | AF12: 12.5 | AG12: =VLOOKUP(A12,Sheet1!$A$2:$C$1140,3,FALSE) -> 12.5 | AH12: 12.5 | AI12: =IF(ISNA(AH12),"Delete",IF(AH12=AF12,"Same",IF(AH12>AF12,"Increase","Decrease"))) -> Same | AJ12: =IFERROR(AA12*AF12,0) -> 30625 | AK12: =IFERROR(AA12*AH12,0) -> 30625 | AL12: Paint | AM12: Normal | AN12: 666 | AO12: 12.5 | AP12: =IF(AM12="Delete","Delete",IF(AO12=AF12,"Same",IF(AO12>AF12,"Increase","Decrease"))) -> Same | AQ12: =AN12*AF12 -> 8325 | AR12: =AN12*AO12 -> 8325 | AS12: =AR12-AQ12 -> 0
A13: 5091671 | B13: 5091671 | C13: DDEC01 | D13: Akzo DDC | E13: Dulux TR AS Supermatt Almond White 10L | F13: Dulux TR AS Supermatt Almond White 10L | H13: EA | I13: ITEM | J13: ITEM | K13: Paint | L13: 27.84 | M13: STD20 | N13: 3105 | R13: 27.84 | S13: 27.84 | T13: 2040 | V13: 27.84 | W13: 27.84 | X13: =SUM(V13*T13) -> 56793.6 | Y13: =SUM(L13*T13) -> 56793.6 | Z13: =SUM(X13-Y13) -> 0 | AA13: 2040 | AB13: =IFERROR(VLOOKUP(A13,'Tash Lookup'!A:E,3,FALSE),"") -> 47611.45 | AC13: =IFERROR(AA13-T13,"") -> 0 | AD13: Normal | AF13: 26.7 | AG13: =VLOOKUP(A13,Sheet1!$A$2:$C$1140,3,FALSE) -> 26.7 | AH13: 26.7 | AI13: =IF(ISNA(AH13),"Delete",IF(AH13=AF13,"Same",IF(AH13>AF13,"Increase","Decrease"))) -> Same | AJ13: =IFERROR(AA13*AF13,0) -> 54468 | AK13: =IFERROR(AA13*AH13,0) -> 54468 | AL13: Paint | AM13: Normal | AN13: 1573 | AO13: 26.7 | AP13: =IF(AM13="Delete","Delete",IF(AO13=AF13,"Same",IF(AO13>AF13,"Increase","Decrease"))) -> Same | AQ13: =AN13*AF13 -> 41999.1 | AR13: =AN13*AO13 -> 41999.1 | AS13: =AR13-AQ13 -> 0
A14: 6410329 | B14: 6410329 | C14: DDEC01 | D14: Akzo DDC | E14: DT Pyroshield Eggshell Light BS Tinted 5L | F14: Dulux TR Pyroshield Eggshell Light BS Tinted 5L | H14: EA | I14: ITEM | J14: ITEM | K14: Paint | L14: 61.88 | M14: STD20 | N14: 3105 | R14: 73.35 | S14: 73.35 | T14: 1954 | V14: 61.88 | W14: 61.88 | X14: =SUM(V14*T14) -> 120913.52 | Y14: =SUM(L14*T14) -> 120913.52 | Z14: =SUM(X14-Y14) -> 0 | AA14: 1954 | AB14: =IFERROR(VLOOKUP(A14,'Tash Lookup'!A:E,3,FALSE),"") -> 121179.31 | AC14: =IFERROR(AA14-T14,"") -> 0 | AD14: Centrally stock allocated | AF14: 61.88 | AG14: =VLOOKUP(A14,Sheet1!$A$2:$C$1140,3,FALSE) -> 63.74 | AH14: 63.74 | AI14: =IF(ISNA(AH14),"Delete",IF(AH14=AF14,"Same",IF(AH14>AF14,"Increase","Decrease"))) -> Increase | AJ14: =IFERROR(AA14*AF14,0) -> 120913.52 | AK14: =IFERROR(AA14*AH14,0) -> 124547.96 | AL14: Paint | AM14: Centrally stock allocated | AN14: 718 | AO14: 63.74 | AP14: =IF(AM14="Delete","Delete",IF(AO14=AF14,"Same",IF(AO14>AF14,"Increase","Decrease"))) -> Increase | AQ14: =AN14*AF14 -> 44429.84 | AR14: =AN14*AO14 -> 45765.32 | AS14: =AR14-AQ14 -> 1335.48
A15: 5224812 | B15: 5224812 | C15: DDEC01 | D15: Akzo DDC | E15: Dulux TR Diamond Matt Tinted Colours 10L | F15: Dulux TR Diamond Matt Tinted Colours 10L | H15: EA | I15: ITEM | J15: ITEM | K15: Paint | L15: 56.91 | M15: STD20 | N15: 3105 | R15: 60.3 | S15: 60.3 | T15: 1922 | V15: 51.984 | W15: 56.91 | X15: =SUM(V15*T15) -> 99913.248 | Y15: =SUM(L15*T15) -> 109381.02 | Z15: =SUM(X15-Y15) -> -9467.772 | AA15: 1922 | AB15: =IFERROR(VLOOKUP(A15,'Tash Lookup'!A:E,3,FALSE),"") -> 110788.03 | AC15: =IFERROR(AA15-T15,"") -> 0 | AD15: Normal | AF15: 54.63 | AG15: =VLOOKUP(A15,Sheet1!$A$2:$C$1140,3,FALSE) -> 54.63 | AH15: 54.63 | AI15: =IF(ISNA(AH15),"Delete",IF(AH15=AF15,"Same",IF(AH15>AF15,"Increase","Decrease"))) -> Same | AJ15: =IFERROR(AA15*AF15,0) -> 104998.86 | AK15: =IFERROR(AA15*AH15,0) -> 104998.86 | AL15: Paint | AM15: Normal | AN15: 309 | AO15: 54.63 | AP15: =IF(AM15="Delete","Delete",IF(AO15=AF15,"Same",IF(AO15>AF15,"Increase","Decrease"))) -> Same | AQ15: =AN15*AF15 -> 16880.67 | AR15: =AN15*AO15 -> 16880.67 | AS15: =AR15-AQ15 -> 0
A16: 5090805 | B16: 5090805 | C16: DDEC01 | D16: Akzo DDC | E16: Dulux TR W/S Msnry Tinted Colours 5L | F16: Dulux TR W/S Msnry Tinted Colours 5L | H16: EA | I16: ITEM | J16: ITEM | K16: Paint | L16: 28.69 | M16: STD20 | N16: 3105 | R16: 28.69 | S16: 28.69 | T16: 1867 | V16: 28.69 | W16: 28.69 | X16: =SUM(V16*T16) -> 53564.23 | Y16: =SUM(L16*T16) -> 53564.23 | Z16: =SUM(X16-Y16) -> 0 | AA16: 1867 | AB16: =IFERROR(VLOOKUP(A16,'Tash Lookup'!A:E,3,FALSE),"") -> 53559.5 | AC16: =IFERROR(AA16-T16,"") -> 0 | AD16: Normal | AF16: 29.82 | AG16: =VLOOKUP(A16,Sheet1!$A$2:$C$1140,3,FALSE) -> 29.82 | AH16: 29.82 | AI16: =IF(ISNA(AH16),"Delete",IF(AH16=AF16,"Same",IF(AH16>AF16,"Increase","Decrease"))) -> Same | AJ16: =IFERROR(AA16*AF16,0) -> 55673.94 | AK16: =IFERROR(AA16*AH16,0) -> 55673.94 | AL16: Paint | AM16: Normal | AN16: 1869 | AO16: 29.82 | AP16: =IF(AM16="Delete","Delete",IF(AO16=AF16,"Same",IF(AO16>AF16,"Increase","Decrease"))) -> Same | AQ16: =AN16*AF16 -> 55733.58 | AR16: =AN16*AO16 -> 55733.58 | AS16: =AR16-AQ16 -> 0
A17: 5583720 | B17: 5583720 | C17: DDEC01 | D17: Akzo DDC | E17: Dulux TR W/S Msnry Smooth Magnolia 7.5L | F17: Dulux TR W/S Msnry Smooth Magnolia 7.5L | H17: EA | I17: ITEM | J17: ITEM | K17: Paint | L17: 25.99 | M17: STD20 | N17: 3105 | R17: 25.99 | S17: 25.99 | T17: 1865 | V17: 17.46 | W17: 25.99 | X17: =SUM(V17*T17) -> 32562.9 | Y17: =SUM(L17*T17) -> 48471.35 | Z17: =SUM(X17-Y17) -> -15908.45 | AA17: 1865 | AB17: =IFERROR(VLOOKUP(A17,'Tash Lookup'!A:E,3,FALSE),"") -> 48032.35 | AC17: =IFERROR(AA17-T17,"") -> 0 | AD17: Active Promo / Seasonal | AF17: 17.54 | AG17: =VLOOKUP(A17,Sheet1!$A$2:$C$1140,3,FALSE) -> 17.46 | AH17: 17.46 | AI17: =IF(ISNA(AH17),"Delete",IF(AH17=AF17,"Same",IF(AH17>AF17,"Increase","Decrease"))) -> Decrease | AJ17: =IFERROR(AA17*AF17,0) -> 32712.1 | AK17: =IFERROR(AA17*AH17,0) -> 32562.9 | AL17: Sundries / 3rd Party | AM17: Active Promo / Seasonal | AN17: 1927 | AO17: 17.46 | AP17: =IF(AM17="Delete","Delete",IF(AO17=AF17,"Same",IF(AO17>AF17,"Increase","Decrease"))) -> Decrease | AQ17: =AN17*AF17 -> 33799.58 | AR17: =AN17*AO17 -> 33645.42 | AS17: =AR17-AQ17 -> -154.16
A18: 5090801 | B18: 5090801 | C18: DDEC01 | D18: Akzo DDC | E18: Dulux TR V/Matt Tinted Colours 5L | F18: Dulux TR V/Matt Tinted Colours 5L | H18: EA | I18: ITEM | J18: ITEM | K18: Paint | L18: 25.73 | M18: STD20 | N18: 3105 | R18: 29.43 | S18: 29.43 | T18: 1758 | V18: 23.5125 | W18: 25.73 | X18: =SUM(V18*T18) -> 41334.975 | Y18: =SUM(L18*T18) -> 45233.34 | Z18: =SUM(X18-Y18) -> -3898.365 | AA18: 1758 | AB18: =IFERROR(VLOOKUP(A18,'Tash Lookup'!A:E,3,FALSE),"") -> 45451.42 | AC18: =IFERROR(AA18-T18,"") -> 0 | AD18: Normal | AF18: 24.55 | AG18: =VLOOKUP(A18,Sheet1!$A$2:$C$1140,3,FALSE) -> 24.55 | AH18: 24.55 | AI18: =IF(ISNA(AH18),"Delete",IF(AH18=AF18,"Same",IF(AH18>AF18,"Increase","Decrease"))) -> Same | AJ18: =IFERROR(AA18*AF18,0) -> 43158.9 | AK18: =IFERROR(AA18*AH18,0) -> 43158.9 | AL18: Paint | AM18: Normal | AN18: 1461 | AO18: 24.55 | AP18: =IF(AM18="Delete","Delete",IF(AO18=AF18,"Same",IF(AO18>AF18,"Increase","Decrease"))) -> Same | AQ18: =AN18*AF18 -> 35867.55 | AR18: =AN18*AO18 -> 35867.55 | AS18: =AR18-AQ18 -> 0
A19: 6188899 | B19: 6188899 | C19: DDEC01 | D19: Akzo DDC | E19: DDC Flexible Finishing Pad Medium/Coarse | F19: DDC Flexible Finishing Pad Medium/Coarse | H19: EA | I19: ITEM | J19: ITEM | K19: Paint | L19: 0.78 | M19: STD20 | N19: 3105 | R19: 0.78 | S19: 0.78 | T19: 1700 | V19: 0.78 | W19: 0.78 | X19: =SUM(V19*T19) -> 1326 | Y19: =SUM(L19*T19) -> 1326 | Z19: =SUM(X19-Y19) -> 0 | AA19: 1700 | AB19: =IFERROR(VLOOKUP(A19,'Tash Lookup'!A:E,3,FALSE),"") -> 1322.69 | AC19: =IFERROR(AA19-T19,"") -> 0 | AD19: Normal | AF19: 0.78 | AG19: =VLOOKUP(A19,Sheet1!$A$2:$C$1140,3,FALSE) -> 0.79 | AH19: 0.79 | AI19: =IF(ISNA(AH19),"Delete",IF(AH19=AF19,"Same",IF(AH19>AF19,"Increase","Decrease"))) -> Increase | AJ19: =IFERROR(AA19*AF19,0) -> 1326 | AK19: =IFERROR(AA19*AH19,0) -> 1343 | AL19: Sundries / 3rd Party | AM19: Normal | AN19: 1529 | AO19: 0.79 | AP19: =IF(AM19="Delete","Delete",IF(AO19=AF19,"Same",IF(AO19>AF19,"Increase","Decrease"))) -> Increase | AQ19: =AN19*AF19 -> 1192.62 | AR19: =AN19*AO19 -> 1207.91 | AS19: =AR19-AQ19 -> 15.29
A20: 5082320 | B20: 5082320 | C20: DDEC01 | D20: Akzo DDC | E20: Dulux TR Diamond Eggshell PBW 5L | F20: Dulux TR Diamond Eggshell PBW 5L | H20: EA | I20: ITEM | J20: ITEM | K20: Paint | L20: 31.79 | M20: STD20 | N20: 3105 | R20: 31.79 | S20: 31.79 | T20: 1590 | V20: 26.106 | W20: 31.79 | X20: =SUM(V20*T20) -> 41508.54 | Y20: =SUM(L20*T20) -> 50546.1 | Z20: =SUM(X20-Y20) -> -9037.56 | AA20: 1590 | AB20: =IFERROR(VLOOKUP(A20,'Tash Lookup'!A:E,3,FALSE),"") -> 49689.25 | AC20: =IFERROR(AA20-T20,"") -> 0 | AD20: Normal | AF20: 25.5 | AG20: =VLOOKUP(A20,Sheet1!$A$2:$C$1140,3,FALSE) -> 25.5 | AH20: 25.5 | AI20: =IF(ISNA(AH20),"Delete",IF(AH20=AF20,"Same",IF(AH20>AF20,"Increase","Decrease"))) -> Same | AJ20: =IFERROR(AA20*AF20,0) -> 40545 | AK20: =IFERROR(AA20*AH20,0) -> 40545 | AL20: Paint | AM20: Normal | AN20: 1701 | AO20: 25.5 | AP20: =IF(AM20="Delete","Delete",IF(AO20=AF20,"Same",IF(AO20>AF20,"Increase","Decrease"))) -> Same | AQ20: =AN20*AF20 -> 43375.5 | AR20: =AN20*AO20 -> 43375.5 | AS20: =AR20-AQ20 -> 0
A21: 5091649 | B21: 5091649 | C21: DDEC01 | D21: Akzo DDC | E21: Dulux TR V/Matt White 10L | F21: Dulux TR V/Matt White 10L | H21: EA | I21: ITEM | J21: ITEM | K21: Paint | L21: 33.56 | M21: STD20 | N21: 3105 | R21: 33.01 | S21: 33.01 | T21: 1410 | V21: 30.6565 | W21: 33.56 | X21: =SUM(V21*T21) -> 43225.665 | Y21: =SUM(L21*T21) -> 47319.6 | Z21: =SUM(X21-Y21) -> -4093.935 | AA21: 1410 | AB21: =IFERROR(VLOOKUP(A21,'Tash Lookup'!A:E,3,FALSE),"") -> 46714.51 | AC21: =IFERROR(AA21-T21,"") -> 0 | AD21: Normal | AF21: 30.61 | AG21: =VLOOKUP(A21,Sheet1!$A$2:$C$1140,3,FALSE) -> 30.61 | AH21: 30.61 | AI21: =IF(ISNA(AH21),"Delete",IF(AH21=AF21,"Same",IF(AH21>AF21,"Increase","Decrease"))) -> Same | AJ21: =IFERROR(AA21*AF21,0) -> 43160.1 | AK21: =IFERROR(AA21*AH21,0) -> 43160.1 | AL21: Paint | AM21: Normal | AN21: 1065 | AO21: 30.61 | AP21: =IF(AM21="Delete","Delete",IF(AO21=AF21,"Same",IF(AO21>AF21,"Increase","Decrease"))) -> Same | AQ21: =AN21*AF21 -> 32599.65 | AR21: =AN21*AO21 -> 32599.65 | AS21: =AR21-AQ21 -> 0
A22: 5583723 | B22: 5583723 | C22: DDEC01 | D22: Akzo DDC | E22: Dulux TR W/S Msnry Smooth PBW 7.5L | F22: Dulux TR W/S Msnry Smooth PBW 7.5L | H22: EA | I22: ITEM | J22: ITEM | K22: Paint | L22: 25.99 | M22: STD20 | N22: 3105 | R22: 25.99 | S22: 25.99 | T22: 1330 | V22: 17.46 | W22: 25.99 | X22: =SUM(V22*T22) -> 23221.8 | Y22: =SUM(L22*T22) -> 34566.7 | Z22: =SUM(X22-Y22) -> -11344.9 | AA22: 1330 | AB22: =IFERROR(VLOOKUP(A22,'Tash Lookup'!A:E,3,FALSE),"") -> 34298.7 | AC22: =IFERROR(AA22-T22,"") -> 0 | AD22: Active Promo / Seasonal | AF22: 17.64 | AG22: =VLOOKUP(A22,Sheet1!$A$2:$C$1140,3,FALSE) -> 17.46 | AH22: 17.46 | AI22: =IF(ISNA(AH22),"Delete",IF(AH22=AF22,"Same",IF(AH22>AF22,"Increase","Decrease"))) -> Decrease | AJ22: =IFERROR(AA22*AF22,0) -> 23461.2 | AK22: =IFERROR(AA22*AH22,0) -> 23221.8 | AL22: Sundries / 3rd Party | AM22: Active Promo / Seasonal | AN22: 1551 | AO22: 17.46 | AP22: =IF(AM22="Delete","Delete",IF(AO22=AF22,"Same",IF(AO22>AF22,"Increase","Decrease"))) -> Decrease | AQ22: =AN22*AF22 -> 27359.64 | AR22: =AN22*AO22 -> 27080.46 | AS22: =AR22-AQ22 -> -279.18
A23: 5110680 | B23: 5110680 | C23: DDEC01 | D23: Akzo DDC | E23: Dulux TR W/S Ult Opq Tint Colours 5L | F23: Dulux TR W/S Ult Opq Tint Colours 5L | H23: EA | I23: ITEM | J23: ITEM | K23: Paint | L23: 50.94 | M23: STD20 | N23: 3105 | R23: 67.84 | S23: 67.84 | T23: 1268 | V23: 55.5 | W23: 50.94 | X23: =SUM(V23*T23) -> 70374 | Y23: =SUM(L23*T23) -> 64591.92 | Z23: =SUM(X23-Y23) -> 5782.08 | AA23: 1268 | AB23: =IFERROR(VLOOKUP(A23,'Tash Lookup'!A:E,3,FALSE),"") -> 65856.05 | AC23: =IFERROR(AA23-T23,"") -> 0 | AD23: Normal | AF23: 55.74 | AG23: =VLOOKUP(A23,Sheet1!$A$2:$C$1140,3,FALSE) -> 57.41 | AH23: 57.41 | AI23: =IF(ISNA(AH23),"Delete",IF(AH23=AF23,"Same",IF(AH23>AF23,"Increase","Decrease"))) -> Increase | AJ23: =IFERROR(AA23*AF23,0) -> 70678.32 | AK23: =IFERROR(AA23*AH23,0) -> 72795.88 | AL23: Paint | AM23: Normal | AN23: 706 | AO23: 57.41 | AP23: =IF(AM23="Delete","Delete",IF(AO23=AF23,"Same",IF(AO23>AF23,"Increase","Decrease"))) -> Increase | AQ23: =AN23*AF23 -> 39352.44 | AR23: =AN23*AO23 -> 40531.46 | AS23: =AR23-AQ23 -> 1179.02
... A40: 6183864 | B40: 6183864 | C40: DDEC01 | D40: Akzo DDC | E40: DDC Long Pile Woven Sleeve 9IN | F40: DDC Long Pile Woven Sleeve 9IN | H40: EA | I40: ITEM | J40: ITEM | K40: Paint | L40: 1.61 | M40: STD20 | N40: 3105 | R40: 5.8 | S40: 5.8 | T40: 774 | V40: 5.8 | W40: 1.61 | X40: =SUM(V40*T40) -> 4489.2 | Y40: =SUM(L40*T40) -> 1246.14 | Z40: =SUM(X40-Y40) -> 3243.06 | AA40: 774 | AB40: =IFERROR(VLOOKUP(A40,'Tash Lookup'!A:E,3,FALSE),"") -> 1238.08 | AC40: =IFERROR(AA40-T40,"") -> 0 | AD40: Normal | AF40: 1.41 | AG40: =VLOOKUP(A40,Sheet1!$A$2:$C$1140,3,FALSE) -> 1.44 | AH40: 1.44 | AI40: =IF(ISNA(AH40),"Delete",IF(AH40=AF40,"Same",IF(AH40>AF40,"Increase","Decrease"))) -> Increase | AJ40: =IFERROR(AA40*AF40,0) -> 1091.34 | AK40: =IFERROR(AA40*AH40,0) -> 1114.56 | AL40: Sundries / 3rd Party | AM40: Normal | AN40: 1174 | AO40: 1.44 | AP40: =IF(AM40="Delete","Delete",IF(AO40=AF40,"Same",IF(AO40>AF40,"Increase","Decrease"))) -> Increase | AQ40: =AN40*AF40 -> 1655.34 | AR40: =AN40*AO40 -> 1690.56 | AS40: =AR40-AQ40 -> 35.22
A41: 5180498 | B41: 5180498 | C41: DDEC01 | D41: Akzo DDC | E41: Cuprinol Cladding & Fence Opq Rustic Walnut 10L | F41: Cuprinol Cladding & Fence Opq Rustic Walnut 10L | H41: EA | I41: ITEM | J41: ITEM | K41: Paint | L41: 35.4 | M41: STD20 | N41: 3105 | R41: 35.4 | S41: 35.4 | T41: 765 | V41: 35.4 | W41: 35.4 | X41: =SUM(V41*T41) -> 27081 | Y41: =SUM(L41*T41) -> 27081 | Z41: =SUM(X41-Y41) -> 0 | AA41: 765 | AB41: =IFERROR(VLOOKUP(A41,'Tash Lookup'!A:E,3,FALSE),"") -> 27087.18 | AC41: =IFERROR(AA41-T41,"") -> 0 | AD41: Pre-phase-out | AF41: 37.22 | AG41: =VLOOKUP(A41,Sheet1!$A$2:$C$1140,3,FALSE) -> #N/A | AH41: #N/A | AI41: =IF(ISNA(AH41),"Delete",IF(AH41=AF41,"Same",IF(AH41>AF41,"Increase","Decrease"))) -> Delete | AJ41: =IFERROR(AA41*AF41,0) -> 28473.3 | AK41: =IFERROR(AA41*AH41,0) -> 0 | AL41: Paint | AM41: Phase-out | AN41: 0 | AO41: 37.22 | AP41: =IF(AM41="Delete","Delete",IF(AO41=AF41,"Same",IF(AO41>AF41,"Increase","Decrease"))) -> Same | AQ41: =AN41*AF41 -> 0 | AR41: =AN41*AO41 -> 0 | AS41: =AR41-AQ41 -> 0
A42: 5092359 | B42: 5092359 | C42: DDEC01 | D42: Akzo DDC | E42: Dulux TR Diamond Eggshell Mag 5L | F42: Dulux TR Diamond Eggshell Mag 5L | H42: EA | I42: ITEM | J42: ITEM | K42: Paint | L42: 24.44 | M42: STD20 | N42: 3105 | R42: 24.44 | S42: 24.44 | T42: 729 | V42: 22.059 | W42: 24.44 | X42: =SUM(V42*T42) -> 16081.011 | Y42: =SUM(L42*T42) -> 17816.76 | Z42: =SUM(X42-Y42) -> -1735.749 | AA42: 729 | AB42: =IFERROR(VLOOKUP(A42,'Tash Lookup'!A:E,3,FALSE),"") -> 17637.53 | AC42: =IFERROR(AA42-T42,"") -> 0 | AD42: Normal | AF42: 24.52 | AG42: =VLOOKUP(A42,Sheet1!$A$2:$C$1140,3,FALSE) -> 24.52 | AH42: 24.52 | AI42: =IF(ISNA(AH42),"Delete",IF(AH42=AF42,"Same",IF(AH42>AF42,"Increase","Decrease"))) -> Same | AJ42: =IFERROR(AA42*AF42,0) -> 17875.08 | AK42: =IFERROR(AA42*AH42,0) -> 17875.08 | AL42: Paint | AM42: Normal | AN42: 433 | AO42: 24.52 | AP42: =IF(AM42="Delete","Delete",IF(AO42=AF42,"Same",IF(AO42>AF42,"Increase","Decrease"))) -> Same | AQ42: =AN42*AF42 -> 10617.16 | AR42: =AN42*AO42 -> 10617.16 | AS42: =AR42-AQ42 -> 0
A43: 5218683 | B43: 5218683 | C43: DDEC01 | D43: Akzo DDC | E43: Armstead TR V/Matt White 10L | F43: Armstead TR V/Matt White 10L | H43: EA | I43: ITEM | J43: ITEM | K43: Paint | L43: 20.05 | M43: STD20 | N43: 3105 | R43: 24.5 | S43: 24.5 | T43: 718 | V43: 20.05 | W43: 14.99 | X43: =SUM(V43*T43) -> 14395.9 | Y43: =SUM(L43*T43) -> 14395.9 | Z43: =SUM(X43-Y43) -> 0 | AA43: 718 | AB43: =IFERROR(VLOOKUP(A43,'Tash Lookup'!A:E,3,FALSE),"") -> 12437.27 | AC43: =IFERROR(AA43-T43,"") -> 0 | AD43: Normal | AF43: 19.32 | AG43: =VLOOKUP(A43,Sheet1!$A$2:$C$1140,3,FALSE) -> 19.32 | AH43: 19.32 | AI43: =IF(ISNA(AH43),"Delete",IF(AH43=AF43,"Same",IF(AH43>AF43,"Increase","Decrease"))) -> Same | AJ43: =IFERROR(AA43*AF43,0) -> 13871.76 | AK43: =IFERROR(AA43*AH43,0) -> 13871.76 | AL43: Paint | AM43: Normal | AN43: 189 | AO43: 19.32 | AP43: =IF(AM43="Delete","Delete",IF(AO43=AF43,"Same",IF(AO43>AF43,"Increase","Decrease"))) -> Same | AQ43: =AN43*AF43 -> 3651.48 | AR43: =AN43*AO43 -> 3651.48 | AS43: =AR43-AQ43 -> 0
A44: 5090796 | B44: 5090796 | C44: DDEC01 | D44: Akzo DDC | E44: Dulux TR Supermatt Tint Colours 10L | F44: Dulux TR Supermatt Tint Colours 10L | H44: EA | I44: ITEM | J44: ITEM | K44: Paint | L44: 35.84 | M44: STD20 | N44: 3105 | R44: 35.84 | S44: 35.84 | T44: 709 | V44: 35.84 | W44: 35.84 | X44: =SUM(V44*T44) -> 25410.56 | Y44: =SUM(L44*T44) -> 25410.56 | Z44: =SUM(X44-Y44) -> 0 | AA44: 709 | AB44: =IFERROR(VLOOKUP(A44,'Tash Lookup'!A:E,3,FALSE),"") -> 25361.15 | AC44: =IFERROR(AA44-T44,"") -> 0 | AD44: Normal | AF44: 40.03 | AG44: =VLOOKUP(A44,Sheet1!$A$2:$C$1140,3,FALSE) -> 40.03 | AH44: 40.03 | AI44: =IF(ISNA(AH44),"Delete",IF(AH44=AF44,"Same",IF(AH44>AF44,"Increase","Decrease"))) -> Same | AJ44: =IFERROR(AA44*AF44,0) -> 28381.27 | AK44: =IFERROR(AA44*AH44,0) -> 28381.27 | AL44: Paint | AM44: Normal | AN44: 447 | AO44: 40.03 | AP44: =IF(AM44="Delete","Delete",IF(AO44=AF44,"Same",IF(AO44>AF44,"Increase","Decrease"))) -> Same | AQ44: =AN44*AF44 -> 17893.41 | AR44: =AN44*AO44 -> 17893.41 | AS44: =AR44-AQ44 -> 0
A45: 5219317 | B45: 5219317 | C45: DDEC01 | D45: Akzo DDC | E45: Armstead TR Floor Paint Tinted Colours 5L | F45: Armstead TR Floor Paint Tinted Colours 5L | H45: EA | I45: ITEM | J45: ITEM | K45: Paint | L45: 24.6 | M45: STD20 | N45: 3105 | R45: 24.6 | S45: 24.6 | T45: 697 | V45: 24.6 | W45: 21.94 | X45: =SUM(V45*T45) -> 17146.2 | Y45: =SUM(L45*T45) -> 17146.2 | Z45: =SUM(X45-Y45) -> 0 | AA45: 697 | AB45: =IFERROR(VLOOKUP(A45,'Tash Lookup'!A:E,3,FALSE),"") -> 16646.21 | AC45: =IFERROR(AA45-T45,"") -> 0 | AD45: Normal | AF45: 26.86 | AG45: =VLOOKUP(A45,Sheet1!$A$2:$C$1140,3,FALSE) -> 27.67 | AH45: 27.67 | AI45: =IF(ISNA(AH45),"Delete",IF(AH45=AF45,"Same",IF(AH45>AF45,"Increase","Decrease"))) -> Increase | AJ45: =IFERROR(AA45*AF45,0) -> 18721.42 | AK45: =IFERROR(AA45*AH45,0) -> 19285.99 | AL45: Paint | AM45: Normal | AN45: 65 | AO45: 27.67 | AP45: =IF(AM45="Delete","Delete",IF(AO45=AF45,"Same",IF(AO45>AF45,"Increase","Decrease"))) -> Increase | AQ45: =AN45*AF45 -> 1745.9 | AR45: =AN45*AO45 -> 1798.55 | AS45: =AR45-AQ45 -> 52.65
A46: 5180448 | B46: 5180448 | C46: DDEC01 | D46: Akzo DDC | E46: Dulux TR W/S Ext Gloss PBW 5L | F46: Dulux TR W/S Ext Gloss PBW 5L | H46: EA | I46: ITEM | J46: ITEM | K46: Paint | L46: 35.16 | M46: STD20 | N46: 3105 | R46: 35.16 | S46: 35.16 | T46: 696 | V46: 35.16 | W46: 35.16 | X46: =SUM(V46*T46) -> 24471.36 | Y46: =SUM(L46*T46) -> 24471.36 | Z46: =SUM(X46-Y46) -> 0 | AA46: 696 | AB46: =IFERROR(VLOOKUP(A46,'Tash Lookup'!A:E,3,FALSE),"") -> 24301.93 | AC46: =IFERROR(AA46-T46,"") -> 0 | AD46: Normal | AF46: 36.44 | AG46: =VLOOKUP(A46,Sheet1!$A$2:$C$1140,3,FALSE) -> 36.44 | AH46: 36.44 | AI46: =IF(ISNA(AH46),"Delete",IF(AH46=AF46,"Same",IF(AH46>AF46,"Increase","Decrease"))) -> Same | AJ46: =IFERROR(AA46*AF46,0) -> 25362.24 | AK46: =IFERROR(AA46*AH46,0) -> 25362.24 | AL46: Paint | AM46: Normal | AN46: 563 | AO46: 36.44 | AP46: =IF(AM46="Delete","Delete",IF(AO46=AF46,"Same",IF(AO46>AF46,"Increase","Decrease"))) -> Same | AQ46: =AN46*AF46 -> 20515.72 | AR46: =AN46*AO46 -> 20515.72 | AS46: =AR46-AQ46 -> 0
A47: 5097226 | B47: 5097226 | C47: DDEC01 | D47: Akzo DDC | E47: Dulux TR M/Shield Satin Tinted Colours 5L | F47: Dulux TR M/Shield Satin Tinted Colours 5L | H47: EA | I47: ITEM | J47: ITEM | K47: Paint | L47: 63.18 | M47: STD20 | N47: 3105 | R47: 63.18 | S47: 63.18 | T47: 692 | V47: 63.18 | W47: 63.18 | X47: =SUM(V47*T47) -> 43720.56 | Y47: =SUM(L47*T47) -> 43720.56 | Z47: =SUM(X47-Y47) -> 0 | AA47: 692 | AB47: =IFERROR(VLOOKUP(A47,'Tash Lookup'!A:E,3,FALSE),"") -> 43014.02 | AC47: =IFERROR(AA47-T47,"") -> 0 | AD47: Normal | AF47: 66.78 | AG47: =VLOOKUP(A47,Sheet1!$A$2:$C$1140,3,FALSE) -> 68.78 | AH47: 68.78 | AI47: =IF(ISNA(AH47),"Delete",IF(AH47=AF47,"Same",IF(AH47>AF47,"Increase","Decrease"))) -> Increase | AJ47: =IFERROR(AA47*AF47,0) -> 46211.76 | AK47: =IFERROR(AA47*AH47,0) -> 47595.76 | AL47: Paint | AM47: Normal | AN47: 43 | AO47: 68.78 | AP47: =IF(AM47="Delete","Delete",IF(AO47=AF47,"Same",IF(AO47>AF47,"Increase","Decrease"))) -> Increase | AQ47: =AN47*AF47 -> 2871.54 | AR47: =AN47*AO47 -> 2957.54 | AS47: =AR47-AQ47 -> 86
A48: 6188902 | B48: 6188902 | C48: DDEC01 | D48: Akzo DDC | E48: DDC Masking Tape 36MM x 50M | F48: DDC Masking Tape 36MM x 50M | H48: EA | I48: ITEM | J48: ITEM | K48: Paint | L48: 1.93 | M48: STD20 | N48: 3105 | R48: 1.93 | S48: 1.93 | T48: 613 | V48: 1.93 | W48: 1.93 | X48: =SUM(V48*T48) -> 1183.09 | Y48: =SUM(L48*T48) -> 1183.09 | Z48: =SUM(X48-Y48) -> 0 | AA48: 613 | AB48: =IFERROR(VLOOKUP(A48,'Tash Lookup'!A:E,3,FALSE),"") -> 1159.26 | AC48: =IFERROR(AA48-T48,"") -> 0 | AD48: Normal | AF48: 1.93 | AG48: =VLOOKUP(A48,Sheet1!$A$2:$C$1140,3,FALSE) -> 1.97 | AH48: 1.97 | AI48: =IF(ISNA(AH48),"Delete",IF(AH48=AF48,"Same",IF(AH48>AF48,"Increase","Decrease"))) -> Increase | AJ48: =IFERROR(AA48*AF48,0) -> 1183.09 | AK48: =IFERROR(AA48*AH48,0) -> 1207.61 | AL48: Sundries / 3rd Party | AM48: Normal | AN48: 226 | AO48: 1.97 | AP48: =IF(AM48="Delete","Delete",IF(AO48=AF48,"Same",IF(AO48>AF48,"Increase","Decrease"))) -> Increase | AQ48: =AN48*AF48 -> 436.18 | AR48: =AN48*AO48 -> 445.22 | AS48: =AR48-AQ48 -> 9.04
A49: 6188900 | B49: 6188900 | C49: DDEC01 | D49: Akzo DDC | E49: DDC Flexible Finishing Pad Extra Fine/Fine | F49: DDC Flexible Finishing Pad Extra Fine/Fine | H49: EA | I49: ITEM | J49: ITEM | K49: Paint | L49: 0.78 | M49: STD20 | N49: 3105 | R49: 0.78 | S49: 0.78 | T49: 610 | V49: 0.78 | W49: 0.78 | X49: =SUM(V49*T49) -> 475.8 | Y49: =SUM(L49*T49) -> 475.8 | Z49: =SUM(X49-Y49) -> 0 | AA49: 610 | AB49: =IFERROR(VLOOKUP(A49,'Tash Lookup'!A:E,3,FALSE),"") -> 476.25 | AC49: =IFERROR(AA49-T49,"") -> 0 | AD49: Normal | AF49: 0.78 | AG49: =VLOOKUP(A49,Sheet1!$A$2:$C$1140,3,FALSE) -> 0.79 | AH49: 0.79 | AI49: =IF(ISNA(AH49),"Delete",IF(AH49=AF49,"Same",IF(AH49>AF49,"Increase","Decrease"))) -> Increase | AJ49: =IFERROR(AA49*AF49,0) -> 475.8 | AK49: =IFERROR(AA49*AH49,0) -> 481.9 | AL49: Sundries / 3rd Party | AM49: Normal | AN49: 856 | AO49: 0.79 | AP49: =IF(AM49="Delete","Delete",IF(AO49=AF49,"Same",IF(AO49>AF49,"Increase","Decrease"))) -> Increase | AQ49: =AN49*AF49 -> 667.68 | AR49: =AN49*AO49 -> 676.24 | AS49: =AR49-AQ49 -> 8.56
A50: 5556023 | B50: 5556023 | C50: DDEC01 | D50: Akzo DDC | E50: DT Pyroshield Matt White 5L | F50: Dulux TR Pyroshield Matt White 5L | H50: EA | I50: ITEM | J50: ITEM | K50: Paint | L50: 52.61 | M50: STD20 | N50: 3105 | R50: 52.61 | S50: 52.61 | T50: 605 | V50: 52.61 | W50: 52.61 | X50: =SUM(V50*T50) -> 31829.05 | Y50: =SUM(L50*T50) -> 31829.05 | Z50: =SUM(X50-Y50) -> 0 | AA50: 605 | AB50: =IFERROR(VLOOKUP(A50,'Tash Lookup'!A:E,3,FALSE),"") -> 30537.97 | AC50: =IFERROR(AA50-T50,"") -> 0 | AD50: Centrally stock allocated | AF50: 44.99 | AG50: =VLOOKUP(A50,Sheet1!$A$2:$C$1140,3,FALSE) -> 44.99 | AH50: 44.99 | AI50: =IF(ISNA(AH50),"Delete",IF(AH50=AF50,"Same",IF(AH50>AF50,"Increase","Decrease"))) -> Same | AJ50: =IFERROR(AA50*AF50,0) -> 27218.95 | AK50: =IFERROR(AA50*AH50,0) -> 27218.95 | AL50: Paint | AM50: Centrally stock allocated | AN50: 314 | AO50: 44.99 | AP50: =IF(AM50="Delete","Delete",IF(AO50=AF50,"Same",IF(AO50>AF50,"Increase","Decrease"))) -> Same | AQ50: =AN50*AF50 -> 14126.86 | AR50: =AN50*AO50 -> 14126.86 | AS50: =AR50-AQ50 -> 0
A51: 5196657 | B51: 5196657 | C51: DDEC01 | D51: Akzo DDC | E51: Dulux TR Drywall Primer Sealer 10L | F51: Dulux TR Drywall Primer Sealer 10L | H51: EA | I51: ITEM | J51: ITEM | K51: Paint | L51: 34.41 | M51: STD20 | N51: 3105 | R51: 34.41 | S51: 34.41 | T51: 604 | V51: 34.41 | W51: 34.41 | X51: =SUM(V51*T51) -> 20783.64 | Y51: =SUM(L51*T51) -> 20783.64 | Z51: =SUM(X51-Y51) -> 0 | AA51: 604 | AB51: =IFERROR(VLOOKUP(A51,'Tash Lookup'!A:E,3,FALSE),"") -> 20740.35 | AC51: =IFERROR(AA51-T51,"") -> 0 | AD51: Centrally stock allocated | AF51: 35.34 | AG51: =VLOOKUP(A51,Sheet1!$A$2:$C$1140,3,FALSE) -> 35.34 | AH51: 35.34 | AI51: =IF(ISNA(AH51),"Delete",IF(AH51=AF51,"Same",IF(AH51>AF51,"Increase","Decrease"))) -> Same | AJ51: =IFERROR(AA51*AF51,0) -> 21345.36 | AK51: =IFERROR(AA51*AH51,0) -> 21345.36 | AL51: Paint | AM51: Normal | AN51: 10 | AO51: 35.34 | AP51: =IF(AM51="Delete","Delete",IF(AO51=AF51,"Same",IF(AO51>AF51,"Increase","Decrease"))) -> Same | AQ51: =AN51*AF51 -> 353.4 | AR51: =AN51*AO51 -> 353.4 | AS51: =AR51-AQ51 -> 0
A52: 5218674 | B52: 5218674 | C52: DDEC01 | D52: Akzo DDC | E52: Armstead TR V/Matt Magnolia 10L | F52: Armstead TR V/Matt Magnolia 10L | H52: EA | I52: ITEM | J52: ITEM | K52: Paint | L52: 22.05 | M52: STD20 | N52: 3105 | R52: 26.94 | S52: 26.94 | T52: 594 | V52: 22.05 | W52: 16.47 | X52: =SUM(V52*T52) -> 13097.7 | Y52: =SUM(L52*T52) -> 13097.7 | Z52: =SUM(X52-Y52) -> 0 | AA52: 594 | AB52: =IFERROR(VLOOKUP(A52,'Tash Lookup'!A:E,3,FALSE),"") -> 11432.78 | AC52: =IFERROR(AA52-T52,"") -> 0 | AD52: Normal | AF52: 21.13 | AG52: =VLOOKUP(A52,Sheet1!$A$2:$C$1140,3,FALSE) -> 21.13 | AH52: 21.13 | AI52: =IF(ISNA(AH52),"Delete",IF(AH52=AF52,"Same",IF(AH52>AF52,"Increase","Decrease"))) -> Same | AJ52: =IFERROR(AA52*AF52,0) -> 12551.22 | AK52: =IFERROR(AA52*AH52,0) -> 12551.22 | AL52: Paint | AM52: Normal | AN52: 100 | AO52: 21.13 | AP52: =IF(AM52="Delete","Delete",IF(AO52=AF52,"Same",IF(AO52>AF52,"Increase","Decrease"))) -> Same | AQ52: =AN52*AF52 -> 2113 | AR52: =AN52*AO52 -> 2113 | AS52: =AR52-AQ52 -> 0
A53: 6365257 | B53: 6365257 | C53: DDEC01 | D53: Akzo DDC | E53: Ultragrime Huge Wipes Pack of 100 | F53: Ultragrime Huge Wipes Pack of 100 | H53: EA | I53: ITEM | J53: ITEM | K53: Paint | L53: 8.23 | M53: STD20 | N53: 3105 | R53: 8.23 | S53: 8.23 | T53: 570 | V53: 8.23 | W53: 8.23 | X53: =SUM(V53*T53) -> 4691.1 | Y53: =SUM(L53*T53) -> 4691.1 | Z53: =SUM(X53-Y53) -> 0 | AA53: 570 | AB53: =IFERROR(VLOOKUP(A53,'Tash Lookup'!A:E,3,FALSE),"") -> 4604.59 | AC53: =IFERROR(AA53-T53,"") -> 0 | AD53: Normal | AF53: 8.65 | AG53: =VLOOKUP(A53,Sheet1!$A$2:$C$1140,3,FALSE) -> 8.82 | AH53: 8.82 | AI53: =IF(ISNA(AH53),"Delete",IF(AH53=AF53,"Same",IF(AH53>AF53,"Increase","Decrease"))) -> Increase | AJ53: =IFERROR(AA53*AF53,0) -> 4930.5 | AK53: =IFERROR(AA53*AH53,0) -> 5027.4 | AL53: Sundries / 3rd Party | AM53: Normal | AN53: 225 | AO53: 8.82 | AP53: =IF(AM53="Delete","Delete",IF(AO53=AF53,"Same",IF(AO53>AF53,"Increase","Decrease"))) -> Increase | AQ53: =AN53*AF53 -> 1946.25 | AR53: =AN53*AO53 -> 1984.5 | AS53: =AR53-AQ53 -> 38.25
... A55: 5180449 | B55: 5180449 | C55: DDEC01 | D55: Akzo DDC | E55: Dulux TR W/S Ext U/Coat B/white 5L | F55: Dulux TR W/S Ext U/Coat B/white 5L | H55: EA | I55: ITEM | J55: ITEM | K55: Paint | L55: 38.32 | M55: STD20 | N55: 3105 | R55: 38.32 | S55: 38.32 | T55: 544 | V55: 38.32 | W55: 38.32 | X55: =SUM(V55*T55) -> 20846.08 | Y55: =SUM(L55*T55) -> 20846.08 | Z55: =SUM(X55-Y55) -> 0 | AA55: 544 | AB55: =IFERROR(VLOOKUP(A55,'Tash Lookup'!A:E,3,FALSE),"") -> 20525.88 | AC55: =IFERROR(AA55-T55,"") -> 0 | AD55: Normal | AF55: 36.44 | AG55: =VLOOKUP(A55,Sheet1!$A$2:$C$1140,3,FALSE) -> 36.44 | AH55: 36.44 | AI55: =IF(ISNA(AH55),"Delete",IF(AH55=AF55,"Same",IF(AH55>AF55,"Increase","Decrease"))) -> Same | AJ55: =IFERROR(AA55*AF55,0) -> 19823.36 | AK55: =IFERROR(AA55*AH55,0) -> 19823.36 | AL55: Paint | AM55: Normal | AN55: 329 | AO55: 36.44 | AP55: =IF(AM55="Delete","Delete",IF(AO55=AF55,"Same",IF(AO55>AF55,"Increase","Decrease"))) -> Same | AQ55: =AN55*AF55 -> 11988.76 | AR55: =AN55*AO55 -> 11988.76 | AS55: =AR55-AQ55 -> 0
A56: 6034079 | B56: 6034079 | C56: DDEC01 | D56: Akzo DDC | E56: Trade Brush - 2' | F56: Trade Brush - 2' | H56: EA | I56: ITEM | J56: ITEM | K56: Paint | L56: 1.91 | M56: STD20 | N56: 3105 | R56: 4.03 | S56: 4.03 | T56: 542 | V56: 1.91 | W56: 1.91 | X56: =SUM(V56*T56) -> 1035.22 | Y56: =SUM(L56*T56) -> 1035.22 | Z56: =SUM(X56-Y56) -> 0 | AA56: 542 | AB56: =IFERROR(VLOOKUP(A56,'Tash Lookup'!A:E,3,FALSE),"") -> 1026.37 | AC56: =IFERROR(AA56-T56,"") -> 0 | AD56: Normal | AF56: 1.72 | AG56: =VLOOKUP(A56,Sheet1!$A$2:$C$1140,3,FALSE) -> #N/A | AH56: #N/A | AI56: =IF(ISNA(AH56),"Delete",IF(AH56=AF56,"Same",IF(AH56>AF56,"Increase","Decrease"))) -> Delete | AJ56: =IFERROR(AA56*AF56,0) -> 932.24 | AK56: =IFERROR(AA56*AH56,0) -> 0 | AL56: Sundries / 3rd Party | AM56: Normal | AN56: 252 | AO56: 1.75 | AP56: =IF(AM56="Delete","Delete",IF(AO56=AF56,"Same",IF(AO56>AF56,"Increase","Decrease"))) -> Increase | AQ56: =AN56*AF56 -> 433.44 | AR56: =AN56*AO56 -> 441 | AS56: =AR56-AQ56 -> 7.56
A57: 6183866 | B57: 6183866 | C57: DDEC01 | D57: Akzo DDC | E57: DDC Medium Pile Woven Sleeve 9IN | F57: DDC Medium Pile Woven Sleeve 9IN | H57: EA | I57: ITEM | J57: ITEM | K57: Paint | L57: 2.05 | M57: STD20 | N57: 3105 | R57: 5.58 | S57: 5.58 | T57: 540 | V57: 2.05 | W57: 2.05 | X57: =SUM(V57*T57) -> 1107 | Y57: =SUM(L57*T57) -> 1107 | Z57: =SUM(X57-Y57) -> 0 | AA57: 540 | AB57: =IFERROR(VLOOKUP(A57,'Tash Lookup'!A:E,3,FALSE),"") -> 1096.41 | AC57: =IFERROR(AA57-T57,"") -> 0 | AD57: Normal | AF57: 2.05 | AG57: =VLOOKUP(A57,Sheet1!$A$2:$C$1140,3,FALSE) -> 2.09 | AH57: 2.09 | AI57: =IF(ISNA(AH57),"Delete",IF(AH57=AF57,"Same",IF(AH57>AF57,"Increase","Decrease"))) -> Increase | AJ57: =IFERROR(AA57*AF57,0) -> 1107 | AK57: =IFERROR(AA57*AH57,0) -> 1128.6 | AL57: Sundries / 3rd Party | AM57: Normal | AN57: 505 | AO57: 2.09 | AP57: =IF(AM57="Delete","Delete",IF(AO57=AF57,"Same",IF(AO57>AF57,"Increase","Decrease"))) -> Increase | AQ57: =AN57*AF57 -> 1035.25 | AR57: =AN57*AO57 -> 1055.45 | AS57: =AR57-AQ57 -> 20.2
A58: 5091026 | B58: 5091026 | C58: DDEC01 | D58: Akzo DDC | E58: Dulux TR Gloss PBW 5L | F58: Dulux TR Gloss PBW 5L | H58: EA | I58: ITEM | J58: ITEM | K58: Paint | L58: 25.83 | M58: STD20 | N58: 3105 | R58: 25.83 | S58: 25.83 | T58: 515 | V58: 25.83 | W58: 25.83 | X58: =SUM(V58*T58) -> 13302.45 | Y58: =SUM(L58*T58) -> 13302.45 | Z58: =SUM(X58-Y58) -> 0 | AA58: 515 | AB58: =IFERROR(VLOOKUP(A58,'Tash Lookup'!A:E,3,FALSE),"") -> 13189.47 | AC58: =IFERROR(AA58-T58,"") -> 0 | AD58: Normal | AF58: 26.59 | AG58: =VLOOKUP(A58,Sheet1!$A$2:$C$1140,3,FALSE) -> 26.59 | AH58: 26.59 | AI58: =IF(ISNA(AH58),"Delete",IF(AH58=AF58,"Same",IF(AH58>AF58,"Increase","Decrease"))) -> Same | AJ58: =IFERROR(AA58*AF58,0) -> 13693.85 | AK58: =IFERROR(AA58*AH58,0) -> 13693.85 | AL58: Paint | AM58: Normal | AN58: 192 | AO58: 26.59 | AP58: =IF(AM58="Delete","Delete",IF(AO58=AF58,"Same",IF(AO58>AF58,"Increase","Decrease"))) -> Same | AQ58: =AN58*AF58 -> 5105.28 | AR58: =AN58*AO58 -> 5105.28 | AS58: =AR58-AQ58 -> 0
A59: 5183437 | B59: 5183437 | C59: DDEC01 | D59: Akzo DDC | E59: Dulux TR Metalshield Gloss Black 5L | F59: Dulux TR Metalshield Gloss Black 5L | H59: EA | I59: ITEM | J59: ITEM | K59: Paint | L59: 63.18 | M59: STD20 | N59: 3105 | R59: 63.18 | S59: 63.18 | T59: 512 | V59: 63.18 | W59: 63.18 | X59: =SUM(V59*T59) -> 32348.16 | Y59: =SUM(L59*T59) -> 32348.16 | Z59: =SUM(X59-Y59) -> 0 | AA59: 512 | AB59: =IFERROR(VLOOKUP(A59,'Tash Lookup'!A:E,3,FALSE),"") -> 31781.16 | AC59: =IFERROR(AA59-T59,"") -> 0 | AD59: Normal | AF59: 66.78 | AG59: =VLOOKUP(A59,Sheet1!$A$2:$C$1140,3,FALSE) -> 68.78 | AH59: 68.78 | AI59: =IF(ISNA(AH59),"Delete",IF(AH59=AF59,"Same",IF(AH59>AF59,"Increase","Decrease"))) -> Increase | AJ59: =IFERROR(AA59*AF59,0) -> 34191.36 | AK59: =IFERROR(AA59*AH59,0) -> 35215.36 | AL59: Paint | AM59: Normal | AN59: 554 | AO59: 68.78 | AP59: =IF(AM59="Delete","Delete",IF(AO59=AF59,"Same",IF(AO59>AF59,"Increase","Decrease"))) -> Increase | AQ59: =AN59*AF59 -> 36996.12 | AR59: =AN59*AO59 -> 38104.12 | AS59: =AR59-AQ59 -> 1108
A60: 5090733 | B60: 5090733 | C60: DDEC01 | D60: Akzo DDC | E60: Dulux TR W/S Ext Gloss Tinted Colours 2.5L | F60: Dulux TR W/S Ext Gloss Tinted Colours 2.5L | H60: EA | I60: ITEM | J60: ITEM | K60: Paint | L60: 34.13 | M60: STD20 | N60: 3105 | R60: 34.13 | S60: 34.13 | T60: 512 | V60: 34.13 | W60: 34.13 | X60: =SUM(V60*T60) -> 17474.56 | Y60: =SUM(L60*T60) -> 17474.56 | Z60: =SUM(X60-Y60) -> 0 | AA60: 512 | AB60: =IFERROR(VLOOKUP(A60,'Tash Lookup'!A:E,3,FALSE),"") -> 17120.65 | AC60: =IFERROR(AA60-T60,"") -> 0 | AD60: Normal | AF60: 35.33 | AG60: =VLOOKUP(A60,Sheet1!$A$2:$C$1140,3,FALSE) -> 35.33 | AH60: 35.33 | AI60: =IF(ISNA(AH60),"Delete",IF(AH60=AF60,"Same",IF(AH60>AF60,"Increase","Decrease"))) -> Same | AJ60: =IFERROR(AA60*AF60,0) -> 18088.96 | AK60: =IFERROR(AA60*AH60,0) -> 18088.96 | AL60: Paint | AM60: Normal | AN60: 156 | AO60: 35.33 | AP60: =IF(AM60="Delete","Delete",IF(AO60=AF60,"Same",IF(AO60>AF60,"Increase","Decrease"))) -> Same | AQ60: =AN60*AF60 -> 5511.48 | AR60: =AN60*AO60 -> 5511.48 | AS60: =AR60-AQ60 -> 0
A61: 5091012 | B61: 5091012 | C61: DDEC01 | D61: Akzo DDC | E61: Dulux TR High Gloss White 5L | F61: Dulux TR High Gloss White 5L | H61: EA | I61: ITEM | J61: ITEM | K61: Paint | L61: 23.38 | M61: STD20 | N61: 3105 | R61: 23.38 | S61: 23.38 | T61: 503 | V61: 23.38 | W61: 23.38 | X61: =SUM(V61*T61) -> 11760.14 | Y61: =SUM(L61*T61) -> 11760.14 | Z61: =SUM(X61-Y61) -> 0 | AA61: 503 | AB61: =IFERROR(VLOOKUP(A61,'Tash Lookup'!A:E,3,FALSE),"") -> 11639.24 | AC61: =IFERROR(AA61-T61,"") -> 0 | AD61: Normal | AF61: 24.22 | AG61: =VLOOKUP(A61,Sheet1!$A$2:$C$1140,3,FALSE) -> 24.22 | AH61: 24.22 | AI61: =IF(ISNA(AH61),"Delete",IF(AH61=AF61,"Same",IF(AH61>AF61,"Increase","Decrease"))) -> Same | AJ61: =IFERROR(AA61*AF61,0) -> 12182.66 | AK61: =IFERROR(AA61*AH61,0) -> 12182.66 | AL61: Paint | AM61: Normal | AN61: 291 | AO61: 24.22 | AP61: =IF(AM61="Delete","Delete",IF(AO61=AF61,"Same",IF(AO61>AF61,"Increase","Decrease"))) -> Same | AQ61: =AN61*AF61 -> 7048.02 | AR61: =AN61*AO61 -> 7048.02 | AS61: =AR61-AQ61 -> 0
A62: 6183945 | B62: 6183945 | C62: DDEC01 | D62: Akzo DDC | E62: DDC Aluminium Oxide Roll 120G 10M | F62: DDC Aluminium Oxide Roll 120G 10M | H62: EA | I62: ITEM | J62: ITEM | K62: Paint | L62: 6.39 | M62: STD20 | N62: 3105 | R62: 6.39 | S62: 6.39 | T62: 498 | V62: 6.39 | W62: 6.39 | X62: =SUM(V62*T62) -> 3182.22 | Y62: =SUM(L62*T62) -> 3182.22 | Z62: =SUM(X62-Y62) -> 0 | AA62: 498 | AB62: =IFERROR(VLOOKUP(A62,'Tash Lookup'!A:E,3,FALSE),"") -> 3155.26 | AC62: =IFERROR(AA62-T62,"") -> 0 | AD62: Normal | AF62: 3.2 | AG62: =VLOOKUP(A62,Sheet1!$A$2:$C$1140,3,FALSE) -> 3.26 | AH62: 3.26 | AI62: =IF(ISNA(AH62),"Delete",IF(AH62=AF62,"Same",IF(AH62>AF62,"Increase","Decrease"))) -> Increase | AJ62: =IFERROR(AA62*AF62,0) -> 1593.6 | AK62: =IFERROR(AA62*AH62,0) -> 1623.48 | AL62: Sundries / 3rd Party | AM62: Normal | AN62: 219 | AO62: 3.26 | AP62: =IF(AM62="Delete","Delete",IF(AO62=AF62,"Same",IF(AO62>AF62,"Increase","Decrease"))) -> Increase | AQ62: =AN62*AF62 -> 700.8 | AR62: =AN62*AO62 -> 713.94 | AS62: =AR62-AQ62 -> 13.14
A63: 5220126 | B63: 5220126 | C63: DDEC01 | D63: Akzo DDC | E63: Dulux TR QD Gloss Pure Brilliant White 5L | F63: Dulux TR QD Gloss Pure Brilliant White 5L | H63: EA | I63: ITEM | J63: ITEM | K63: Paint | L63: 32.71 | M63: STD20 | N63: 3105 | R63: 32.71 | S63: 32.71 | T63: 462 | V63: 32.71 | W63: 32.71 | X63: =SUM(V63*T63) -> 15112.02 | Y63: =SUM(L63*T63) -> 15112.02 | Z63: =SUM(X63-Y63) -> 0 | AA63: 462 | AB63: =IFERROR(VLOOKUP(A63,'Tash Lookup'!A:E,3,FALSE),"") -> 14715.77 | AC63: =IFERROR(AA63-T63,"") -> 0 | AD63: Normal | AF63: 34.16 | AG63: =VLOOKUP(A63,Sheet1!$A$2:$C$1140,3,FALSE) -> 34.16 | AH63: 34.16 | AI63: =IF(ISNA(AH63),"Delete",IF(AH63=AF63,"Same",IF(AH63>AF63,"Increase","Decrease"))) -> Same | AJ63: =IFERROR(AA63*AF63,0) -> 15781.92 | AK63: =IFERROR(AA63*AH63,0) -> 15781.92 | AL63: Paint | AM63: Normal | AN63: 435 | AO63: 34.16 | AP63: =IF(AM63="Delete","Delete",IF(AO63=AF63,"Same",IF(AO63>AF63,"Increase","Decrease"))) -> Same | AQ63: =AN63*AF63 -> 14859.6 | AR63: =AN63*AO63 -> 14859.6 | AS63: =AR63-AQ63 -> 0
A64: 6183858 | B64: 6183858 | C64: DDEC01 | D64: Akzo DDC | E64: DDC All Purpose Cage Frame 9IN | F64: DDC All Purpose Cage Frame 9IN | H64: EA | I64: ITEM | J64: ITEM | K64: Paint | L64: 4.08 | M64: STD20 | N64: 3105 | R64: 4.08 | S64: 4.08 | T64: 457 | V64: 4.08 | W64: 4.08 | X64: =SUM(V64*T64) -> 1864.56 | Y64: =SUM(L64*T64) -> 1864.56 | Z64: =SUM(X64-Y64) -> 0 | AA64: 457 | AB64: =IFERROR(VLOOKUP(A64,'Tash Lookup'!A:E,3,FALSE),"") -> 1848.19 | AC64: =IFERROR(AA64-T64,"") -> 0 | AD64: Normal | AF64: 4.08 | AG64: =VLOOKUP(A64,Sheet1!$A$2:$C$1140,3,FALSE) -> 4.17 | AH64: 4.17 | AI64: =IF(ISNA(AH64),"Delete",IF(AH64=AF64,"Same",IF(AH64>AF64,"Increase","Decrease"))) -> Increase | AJ64: =IFERROR(AA64*AF64,0) -> 1864.56 | AK64: =IFERROR(AA64*AH64,0) -> 1905.69 | AL64: Sundries / 3rd Party | AM64: Normal | AN64: 360 | AO64: 4.17 | AP64: =IF(AM64="Delete","Delete",IF(AO64=AF64,"Same",IF(AO64>AF64,"Increase","Decrease"))) -> Increase | AQ64: =AN64*AF64 -> 1468.8 | AR64: =AN64*AO64 -> 1501.2 | AS64: =AR64-AQ64 -> 32.4
A65: 5220152 | B65: 5220152 | C65: DDEC01 | D65: Akzo DDC | E65: Dulux TR QD Undercoat White 5L | F65: Dulux TR QD Undercoat White 5L | H65: EA | I65: ITEM | J65: ITEM | K65: Paint | L65: 31.5 | M65: STD20 | N65: 3105 | R65: 31.5 | S65: 31.5 | T65: 452 | V65: 31.5 | W65: 31.5 | X65: =SUM(V65*T65) -> 14238 | Y65: =SUM(L65*T65) -> 14238 | Z65: =SUM(X65-Y65) -> 0 | AA65: 452 | AB65: =IFERROR(VLOOKUP(A65,'Tash Lookup'!A:E,3,FALSE),"") -> 13987.58 | AC65: =IFERROR(AA65-T65,"") -> 0 | AD65: Normal | AF65: 31.01 | AG65: =VLOOKUP(A65,Sheet1!$A$2:$C$1140,3,FALSE) -> 31.01 | AH65: 31.01 | AI65: =IF(ISNA(AH65),"Delete",IF(AH65=AF65,"Same",IF(AH65>AF65,"Increase","Decrease"))) -> Same | AJ65: =IFERROR(AA65*AF65,0) -> 14016.52 | AK65: =IFERROR(AA65*AH65,0) -> 14016.52 | AL65: Paint | AM65: Normal | AN65: 356 | AO65: 31.01 | AP65: =IF(AM65="Delete","Delete",IF(AO65=AF65,"Same",IF(AO65>AF65,"Increase","Decrease"))) -> Same | AQ65: =AN65*AF65 -> 11039.56 | AR65: =AN65*AO65 -> 11039.56 | AS65: =AR65-AQ65 -> 0
A66: 5180744 | B66: 5180744 | C66: DDEC01 | D66: Akzo DDC | E66: Dulux TR W/S Ult Opq Black 5L | F66: Dulux TR W/S Ult Opq Black 5L | H66: EA | I66: ITEM | J66: ITEM | K66: Paint | L66: 67.84 | M66: STD20 | N66: 3105 | R66: 67.84 | S66: 67.84 | T66: 431 | V66: 67.84 | W66: 67.84 | X66: =SUM(V66*T66) -> 29239.04 | Y66: =SUM(L66*T66) -> 29239.04 | Z66: =SUM(X66-Y66) -> 0 | AA66: 431 | AB66: =IFERROR(VLOOKUP(A66,'Tash Lookup'!A:E,3,FALSE),"") -> 29169.38 | AC66: =IFERROR(AA66-T66,"") -> 0 | AD66: Normal | AF66: 65.01 | AG66: =VLOOKUP(A66,Sheet1!$A$2:$C$1140,3,FALSE) -> 66.96 | AH66: 66.96 | AI66: =IF(ISNA(AH66),"Delete",IF(AH66=AF66,"Same",IF(AH66>AF66,"Increase","Decrease"))) -> Increase | AJ66: =IFERROR(AA66*AF66,0) -> 28019.31 | AK66: =IFERROR(AA66*AH66,0) -> 28859.76 | AL66: Paint | AM66: Normal | AN66: 222 | AO66: 66.96 | AP66: =IF(AM66="Delete","Delete",IF(AO66=AF66,"Same",IF(AO66>AF66,"Increase","Decrease"))) -> Increase | AQ66: =AN66*AF66 -> 14432.22 | AR66: =AN66*AO66 -> 14865.12 | AS66: =AR66-AQ66 -> 432.9
A67: 5092713 | B67: 5092713 | C67: DDEC01 | D67: Akzo DDC | E67: Cuprinol QD Cladding & Fence Opq Dk Oak 10L | F67: Cuprinol QD Cladding & Fence Opq Dk Oak 10L | H67: EA | I67: ITEM | J67: ITEM | K67: Paint | L67: 32.2 | M67: STD20 | N67: 3105 | R67: 0 | S67: 0 | T67: 424 | V67: 32.2 | W67: 32.2 | X67: =SUM(V67*T67) -> 13652.8 | Y67: =SUM(L67*T67) -> 13652.8 | Z67: =SUM(X67-Y67) -> 0 | AA67: 424 | AB67: =IFERROR(VLOOKUP(A67,'Tash Lookup'!A:E,3,FALSE),"") -> 14555.42 | AC67: =IFERROR(AA67-T67,"") -> 0 | AD67: Normal | AF67: 32.91 | AG67: =VLOOKUP(A67,Sheet1!$A$2:$C$1140,3,FALSE) -> 33.9 | AH67: 33.9 | AI67: =IF(ISNA(AH67),"Delete",IF(AH67=AF67,"Same",IF(AH67>AF67,"Increase","Decrease"))) -> Increase | AJ67: =IFERROR(AA67*AF67,0) -> 13953.84 | AK67: =IFERROR(AA67*AH67,0) -> 14373.6 | AL67: Paint | AM67: Normal | AN67: 183 | AO67: 33.9 | AP67: =IF(AM67="Delete","Delete",IF(AO67=AF67,"Same",IF(AO67>AF67,"Increase","Decrease"))) -> Increase | AQ67: =AN67*AF67 -> 6022.53 | AR67: =AN67*AO67 -> 6203.7 | AS67: =AR67-AQ67 -> 181.17
A68: 5090813 | B68: 5090813 | C68: DDEC01 | D68: Akzo DDC | E68: Dulux TR S/sheen Tinted Colours 5L | F68: Dulux TR S/sheen Tinted Colours 5L | H68: EA | I68: ITEM | J68: ITEM | K68: Paint | L68: 38.75 | M68: STD20 | N68: 3105 | R68: 38.75 | S68: 38.75 | T68: 415 | V68: 38.75 | W68: 38.75 | X68: =SUM(V68*T68) -> 16081.25 | Y68: =SUM(L68*T68) -> 16081.25 | Z68: =SUM(X68-Y68) -> 0 | AA68: 415 | AB68: =IFERROR(VLOOKUP(A68,'Tash Lookup'!A:E,3,FALSE),"") -> 16097.61 | AC68: =IFERROR(AA68-T68,"") -> 0 | AD68: Normal | AF68: 39.19 | AG68: =VLOOKUP(A68,Sheet1!$A$2:$C$1140,3,FALSE) -> 40.36 | AH68: 40.36 | AI68: =IF(ISNA(AH68),"Delete",IF(AH68=AF68,"Same",IF(AH68>AF68,"Increase","Decrease"))) -> Increase | AJ68: =IFERROR(AA68*AF68,0) -> 16263.85 | AK68: =IFERROR(AA68*AH68,0) -> 16749.4 | AL68: Paint | AM68: Normal | AN68: 270 | AO68: 40.36 | AP68: =IF(AM68="Delete","Delete",IF(AO68=AF68,"Same",IF(AO68>AF68,"Increase","Decrease"))) -> Increase | AQ68: =AN68*AF68 -> 10581.3 | AR68: =AN68*AO68 -> 10897.2 | AS68: =AR68-AQ68 -> 315.9
... A108: 6183836 | B108: 6183836 | C108: DDEC01 | D108: Akzo DDC | E108: DDC All Purpose Brush 6PK F/CERT | F108: DDC All Purpose Brush 6PK F/CERT | H108: EA | I108: ITEM | J108: ITEM | K108: Paint | L108: 8.22 | M108: STD20 | N108: 3105 | R108: 19.29 | S108: 19.29 | T108: 240 | V108: 19.29 | W108: 8.22 | X108: =SUM(V108*T108) -> 4629.6 | Y108: =SUM(L108*T108) -> 1972.8 | Z108: =SUM(X108-Y108) -> 2656.8 | AA108: 240 | AB108: =IFERROR(VLOOKUP(A108,'Tash Lookup'!A:E,3,FALSE),"") -> 1965.07 | AC108: =IFERROR(AA108-T108,"") -> 0 | AD108: Normal | AF108: 17.36 | AG108: =VLOOKUP(A108,Sheet1!$A$2:$C$1140,3,FALSE) -> 17.71 | AH108: 17.71 | AI108: =IF(ISNA(AH108),"Delete",IF(AH108=AF108,"Same",IF(AH108>AF108,"Increase","Decrease"))) -> Increase | AJ108: =IFERROR(AA108*AF108,0) -> 4166.4 | AK108: =IFERROR(AA108*AH108,0) -> 4250.4 | AL108: Sundries / 3rd Party | AM108: Normal | AN108: 81 | AO108: 17.71 | AP108: =IF(AM108="Delete","Delete",IF(AO108=AF108,"Same",IF(AO108>AF108,"Increase","Decrease"))) -> Increase | AQ108: =AN108*AF108 -> 1406.16 | AR108: =AN108*AO108 -> 1434.51 | AS108: =AR108-AQ108 -> 28.35
A109: 6092863 | B109: 6092863 | C109: DDEC01 | D109: Akzo DDC | E109: Trimaco Easy Mask Paper 12in 180FT | F109: Trimaco Easy Mask Paper 12in 180FT | H109: EA | I109: ITEM | J109: ITEM | K109: Paint | L109: 5.03 | M109: STD20 | N109: 3105 | R109: 6.01 | S109: 0 | T109: 238 | V109: 6.01 | W109: 5.03 | X109: =SUM(V109*T109) -> 1430.38 | Y109: =SUM(L109*T109) -> 1197.14 | Z109: =SUM(X109-Y109) -> 233.24 | AA109: 238 | AB109: =IFERROR(VLOOKUP(A109,'Tash Lookup'!A:E,3,FALSE),"") -> 1222.33 | AC109: =IFERROR(AA109-T109,"") -> 0 | AD109: Pre-Clearance | AF109: 6.01 | AG109: =VLOOKUP(A109,Sheet1!$A$2:$C$1140,3,FALSE) -> #N/A | AH109: #N/A | AI109: =IF(ISNA(AH109),"Delete",IF(AH109=AF109,"Same",IF(AH109>AF109,"Increase","Decrease"))) -> Delete | AJ109: =IFERROR(AA109*AF109,0) -> 1430.38 | AK109: =IFERROR(AA109*AH109,0) -> 0 | AL109: Sundries / 3rd Party | AM109: Phase-out | AN109: 0 | AO109: 6.01 | AP109: =IF(AM109="Delete","Delete",IF(AO109=AF109,"Same",IF(AO109>AF109,"Increase","Decrease"))) -> Same | AQ109: =AN109*AF109 -> 0 | AR109: =AN109*AO109 -> 0 | AS109: =AR109-AQ109 -> 0
A110: 5091366 | B110: 5091366 | C110: DDEC01 | D110: Akzo DDC | E110: Dulux TR QD Opaque Black 5L | F110: Dulux TR QD Opaque Black 5L | H110: EA | I110: ITEM | J110: ITEM | K110: Paint | L110: 64.45 | M110: STD20 | N110: 3105 | R110: 64.45 | S110: 64.45 | T110: 235 | V110: 64.45 | W110: 64.45 | X110: =SUM(V110*T110) -> 15145.75 | Y110: =SUM(L110*T110) -> 15145.75 | Z110: =SUM(X110-Y110) -> 0 | AA110: 235 | AB110: =IFERROR(VLOOKUP(A110,'Tash Lookup'!A:E,3,FALSE),"") -> 15182.5 | AC110: =IFERROR(AA110-T110,"") -> 0 | AD110: Normal | AF110: 65.66 | AG110: =VLOOKUP(A110,Sheet1!$A$2:$C$1140,3,FALSE) -> 67.63 | AH110: 67.63 | AI110: =IF(ISNA(AH110),"Delete",IF(AH110=AF110,"Same",IF(AH110>AF110,"Increase","Decrease"))) -> Increase | AJ110: =IFERROR(AA110*AF110,0) -> 15430.1 | AK110: =IFERROR(AA110*AH110,0) -> 15893.05 | AL110: Paint | AM110: Normal | AN110: 197 | AO110: 67.63 | AP110: =IF(AM110="Delete","Delete",IF(AO110=AF110,"Same",IF(AO110>AF110,"Increase","Decrease"))) -> Increase | AQ110: =AN110*AF110 -> 12935.02 | AR110: =AN110*AO110 -> 13323.11 | AS110: =AR110-AQ110 -> 388.09
A111: 6183944 | B111: 6183944 | C111: DDEC01 | D111: Akzo DDC | E111: DDC Aluminium Oxide Roll 80G 10M | F111: DDC Aluminium Oxide Roll 80G 10M | H111: EA | I111: ITEM | J111: ITEM | K111: Paint | L111: 6.39 | M111: STD20 | N111: 3105 | R111: 6.39 | S111: 6.39 | T111: 231 | V111: 6.39 | W111: 6.39 | X111: =SUM(V111*T111) -> 1476.09 | Y111: =SUM(L111*T111) -> 1476.09 | Z111: =SUM(X111-Y111) -> 0 | AA111: 231 | AB111: =IFERROR(VLOOKUP(A111,'Tash Lookup'!A:E,3,FALSE),"") -> 1466.93 | AC111: =IFERROR(AA111-T111,"") -> 0 | AD111: Normal | AF111: 6.39 | AG111: =VLOOKUP(A111,Sheet1!$A$2:$C$1140,3,FALSE) -> 6.52 | AH111: 6.52 | AI111: =IF(ISNA(AH111),"Delete",IF(AH111=AF111,"Same",IF(AH111>AF111,"Increase","Decrease"))) -> Increase | AJ111: =IFERROR(AA111*AF111,0) -> 1476.09 | AK111: =IFERROR(AA111*AH111,0) -> 1506.12 | AL111: Sundries / 3rd Party | AM111: Normal | AN111: 131 | AO111: 6.52 | AP111: =IF(AM111="Delete","Delete",IF(AO111=AF111,"Same",IF(AO111>AF111,"Increase","Decrease"))) -> Increase | AQ111: =AN111*AF111 -> 837.09 | AR111: =AN111*AO111 -> 854.12 | AS111: =AR111-AQ111 -> 17.03
A112: 6188760 | B112: 6188760 | C112: DDEC01 | D112: Akzo DDC | E112: DDC Cutting In Brush 18MM | F112: DDC Cutting In Brush 18MM | H112: EA | I112: ITEM | J112: ITEM | K112: Paint | L112: 3.55 | M112: STD20 | N112: 3105 | R112: 3.55 | S112: 3.55 | T112: 229 | V112: 3.55 | W112: 3.55 | X112: =SUM(V112*T112) -> 812.95 | Y112: =SUM(L112*T112) -> 812.95 | Z112: =SUM(X112-Y112) -> 0 | AA112: 229 | AB112: =IFERROR(VLOOKUP(A112,'Tash Lookup'!A:E,3,FALSE),"") -> 807.36 | AC112: =IFERROR(AA112-T112,"") -> 0 | AD112: Normal | AF112: 3.55 | AG112: =VLOOKUP(A112,Sheet1!$A$2:$C$1140,3,FALSE) -> 3.62 | AH112: 3.62 | AI112: =IF(ISNA(AH112),"Delete",IF(AH112=AF112,"Same",IF(AH112>AF112,"Increase","Decrease"))) -> Increase | AJ112: =IFERROR(AA112*AF112,0) -> 812.95 | AK112: =IFERROR(AA112*AH112,0) -> 828.98 | AL112: Sundries / 3rd Party | AM112: Normal | AN112: 165 | AO112: 3.62 | AP112: =IF(AM112="Delete","Delete",IF(AO112=AF112,"Same",IF(AO112>AF112,"Increase","Decrease"))) -> Increase | AQ112: =AN112*AF112 -> 585.75 | AR112: =AN112*AO112 -> 597.3 | AS112: =AR112-AQ112 -> 11.55
A113: 5180447 | B113: 5180447 | C113: DDEC01 | D113: Akzo DDC | E113: Dulux TR W/S Ext Gloss Black 5L | F113: Dulux TR W/S Ext Gloss Black 5L | H113: EA | I113: ITEM | J113: ITEM | K113: Paint | L113: 54.09 | M113: STD20 | N113: 3105 | R113: 54.09 | S113: 54.09 | T113: 229 | V113: 54.09 | W113: 54.09 | X113: =SUM(V113*T113) -> 12386.61 | Y113: =SUM(L113*T113) -> 12386.61 | Z113: =SUM(X113-Y113) -> 0 | AA113: 229 | AB113: =IFERROR(VLOOKUP(A113,'Tash Lookup'!A:E,3,FALSE),"") -> 12308.74 | AC113: =IFERROR(AA113-T113,"") -> 0 | AD113: Normal | AF113: 59.14 | AG113: =VLOOKUP(A113,Sheet1!$A$2:$C$1140,3,FALSE) -> 59.14 | AH113: 59.14 | AI113: =IF(ISNA(AH113),"Delete",IF(AH113=AF113,"Same",IF(AH113>AF113,"Increase","Decrease"))) -> Same | AJ113: =IFERROR(AA113*AF113,0) -> 13543.06 | AK113: =IFERROR(AA113*AH113,0) -> 13543.06 | AL113: Paint | AM113: Normal | AN113: 221 | AO113: 59.14 | AP113: =IF(AM113="Delete","Delete",IF(AO113=AF113,"Same",IF(AO113>AF113,"Increase","Decrease"))) -> Same | AQ113: =AN113*AF113 -> 13069.94 | AR113: =AN113*AO113 -> 13069.94 | AS113: =AR113-AQ113 -> 0
A114: 5089681 | B114: 5089681 | C114: DDEC01 | D114: Akzo DDC | E114: Dulux TR High Gloss White 2.5L | F114: Dulux TR High Gloss White 2.5L | H114: EA | I114: ITEM | J114: ITEM | K114: Paint | L114: 14 | M114: STD20 | N114: 3105 | R114: 14 | S114: 14 | T114: 228 | V114: 14 | W114: 14 | X114: =SUM(V114*T114) -> 3192 | Y114: =SUM(L114*T114) -> 3192 | Z114: =SUM(X114-Y114) -> 0 | AA114: 228 | AB114: =IFERROR(VLOOKUP(A114,'Tash Lookup'!A:E,3,FALSE),"") -> 3149.35 | AC114: =IFERROR(AA114-T114,"") -> 0 | AD114: Normal | AF114: 14.7 | AG114: =VLOOKUP(A114,Sheet1!$A$2:$C$1140,3,FALSE) -> 14.7 | AH114: 14.7 | AI114: =IF(ISNA(AH114),"Delete",IF(AH114=AF114,"Same",IF(AH114>AF114,"Increase","Decrease"))) -> Same | AJ114: =IFERROR(AA114*AF114,0) -> 3351.6 | AK114: =IFERROR(AA114*AH114,0) -> 3351.6 | AL114: Paint | AM114: Normal | AN114: 161 | AO114: 14.7 | AP114: =IF(AM114="Delete","Delete",IF(AO114=AF114,"Same",IF(AO114>AF114,"Increase","Decrease"))) -> Same | AQ114: =AN114*AF114 -> 2366.7 | AR114: =AN114*AO114 -> 2366.7 | AS114: =AR114-AQ114 -> 0
A115: 5242791 | B115: 5242791 | C115: DDEC01 | D115: Akzo DDC | E115: Dulux TR Quick Dry U/Coat Tinted Colours 5L | F115: Dulux TR Quick Dry U/Coat Tinted Colours 5L | H115: EA | I115: ITEM | J115: ITEM | K115: Paint | L115: 43.28 | M115: STD20 | N115: 3105 | R115: 43.28 | S115: 43.28 | T115: 223 | V115: 43.28 | W115: 43.28 | X115: =SUM(V115*T115) -> 9651.44 | Y115: =SUM(L115*T115) -> 9651.44 | Z115: =SUM(X115-Y115) -> 0 | AA115: 223 | AB115: =IFERROR(VLOOKUP(A115,'Tash Lookup'!A:E,3,FALSE),"") -> 9583.47 | AC115: =IFERROR(AA115-T115,"") -> 0 | AD115: Normal | AF115: 37.25 | AG115: =VLOOKUP(A115,Sheet1!$A$2:$C$1140,3,FALSE) -> 37.25 | AH115: 37.25 | AI115: =IF(ISNA(AH115),"Delete",IF(AH115=AF115,"Same",IF(AH115>AF115,"Increase","Decrease"))) -> Same | AJ115: =IFERROR(AA115*AF115,0) -> 8306.75 | AK115: =IFERROR(AA115*AH115,0) -> 8306.75 | AL115: Paint | AM115: Normal | AN115: 114 | AO115: 37.25 | AP115: =IF(AM115="Delete","Delete",IF(AO115=AF115,"Same",IF(AO115>AF115,"Increase","Decrease"))) -> Same | AQ115: =AN115*AF115 -> 4246.5 | AR115: =AN115*AO115 -> 4246.5 | AS115: =AR115-AQ115 -> 0
A116: 5220397 | B116: 5220397 | C116: DDEC01 | D116: Akzo DDC | E116: Dulux TR QD Gloss Tinted Colours 5L | F116: Dulux TR QD Gloss Tinted Colours 5L | H116: EA | I116: ITEM | J116: ITEM | K116: Paint | L116: 46.62 | M116: STD20 | N116: 3105 | R116: 46.62 | S116: 46.62 | T116: 217 | V116: 46.62 | W116: 46.62 | X116: =SUM(V116*T116) -> 10116.54 | Y116: =SUM(L116*T116) -> 10116.54 | Z116: =SUM(X116-Y116) -> 0 | AA116: 217 | AB116: =IFERROR(VLOOKUP(A116,'Tash Lookup'!A:E,3,FALSE),"") -> 9940.67 | AC116: =IFERROR(AA116-T116,"") -> 0 | AD116: Normal | AF116: 49 | AG116: =VLOOKUP(A116,Sheet1!$A$2:$C$1140,3,FALSE) -> 49 | AH116: 49 | AI116: =IF(ISNA(AH116),"Delete",IF(AH116=AF116,"Same",IF(AH116>AF116,"Increase","Decrease"))) -> Same | AJ116: =IFERROR(AA116*AF116,0) -> 10633 | AK116: =IFERROR(AA116*AH116,0) -> 10633 | AL116: Paint | AM116: Normal | AN116: 155 | AO116: 49 | AP116: =IF(AM116="Delete","Delete",IF(AO116=AF116,"Same",IF(AO116>AF116,"Increase","Decrease"))) -> Same | AQ116: =AN116*AF116 -> 7595 | AR116: =AN116*AO116 -> 7595 | AS116: =AR116-AQ116 -> 0
A117: 5090727 | B117: 5090727 | C117: DDEC01 | D117: Akzo DDC | E117: Dulux TR Gloss Tinted Colours 2.5L | F117: Dulux TR Gloss Tinted Colours 2.5L | H117: EA | I117: ITEM | J117: ITEM | K117: Paint | L117: 22.3 | M117: STD20 | N117: 3105 | R117: 22.3 | S117: 22.3 | T117: 216 | V117: 22.3 | W117: 22.3 | X117: =SUM(V117*T117) -> 4816.8 | Y117: =SUM(L117*T117) -> 4816.8 | Z117: =SUM(X117-Y117) -> 0 | AA117: 216 | AB117: =IFERROR(VLOOKUP(A117,'Tash Lookup'!A:E,3,FALSE),"") -> 4691.4 | AC117: =IFERROR(AA117-T117,"") -> 0 | AD117: Normal | AF117: 23.84 | AG117: =VLOOKUP(A117,Sheet1!$A$2:$C$1140,3,FALSE) -> 23.84 | AH117: 23.84 | AI117: =IF(ISNA(AH117),"Delete",IF(AH117=AF117,"Same",IF(AH117>AF117,"Increase","Decrease"))) -> Same | AJ117: =IFERROR(AA117*AF117,0) -> 5149.44 | AK117: =IFERROR(AA117*AH117,0) -> 5149.44 | AL117: Paint | AM117: Normal | AN117: 167 | AO117: 23.84 | AP117: =IF(AM117="Delete","Delete",IF(AO117=AF117,"Same",IF(AO117>AF117,"Increase","Decrease"))) -> Same | AQ117: =AN117*AF117 -> 3981.28 | AR117: =AN117*AO117 -> 3981.28 | AS117: =AR117-AQ117 -> 0
A118: 5180263 | B118: 5180263 | C118: DDEC01 | D118: Akzo DDC | E118: Dulux TR W/S Ext Gloss PBW 2.5L | F118: Dulux TR W/S Ext Gloss PBW 2.5L | H118: EA | I118: ITEM | J118: ITEM | K118: Paint | L118: 21.11 | M118: STD20 | N118: 3105 | R118: 21.11 | S118: 21.11 | T118: 211 | V118: 21.11 | W118: 21.11 | X118: =SUM(V118*T118) -> 4454.21 | Y118: =SUM(L118*T118) -> 4454.21 | Z118: =SUM(X118-Y118) -> 0 | AA118: 211 | AB118: =IFERROR(VLOOKUP(A118,'Tash Lookup'!A:E,3,FALSE),"") -> 4414.52 | AC118: =IFERROR(AA118-T118,"") -> 0 | AD118: Normal | AF118: 21.8 | AG118: =VLOOKUP(A118,Sheet1!$A$2:$C$1140,3,FALSE) -> 21.8 | AH118: 21.8 | AI118: =IF(ISNA(AH118),"Delete",IF(AH118=AF118,"Same",IF(AH118>AF118,"Increase","Decrease"))) -> Same | AJ118: =IFERROR(AA118*AF118,0) -> 4599.8 | AK118: =IFERROR(AA118*AH118,0) -> 4599.8 | AL118: Paint | AM118: Normal | AN118: 71 | AO118: 21.8 | AP118: =IF(AM118="Delete","Delete",IF(AO118=AF118,"Same",IF(AO118>AF118,"Increase","Decrease"))) -> Same | AQ118: =AN118*AF118 -> 1547.8 | AR118: =AN118*AO118 -> 1547.8 | AS118: =AR118-AQ118 -> 0
A119: 5090787 | B119: 5090787 | C119: DDEC01 | D119: Akzo DDC | E119: Dulux TR W/S QD Sat Tinted Colours 2.5L | F119: Dulux TR W/S QD Sat Tinted Colours 2.5L | H119: EA | I119: ITEM | J119: ITEM | K119: Paint | L119: 43.35 | M119: STD20 | N119: 3105 | R119: 43.35 | S119: 43.35 | T119: 206 | V119: 43.35 | W119: 43.35 | X119: =SUM(V119*T119) -> 8930.1 | Y119: =SUM(L119*T119) -> 8930.1 | Z119: =SUM(X119-Y119) -> 0 | AA119: 206 | AB119: =IFERROR(VLOOKUP(A119,'Tash Lookup'!A:E,3,FALSE),"") -> 8894.56 | AC119: =IFERROR(AA119-T119,"") -> 0 | AD119: Normal | AF119: 47.18 | AG119: =VLOOKUP(A119,Sheet1!$A$2:$C$1140,3,FALSE) -> 47.18 | AH119: 47.18 | AI119: =IF(ISNA(AH119),"Delete",IF(AH119=AF119,"Same",IF(AH119>AF119,"Increase","Decrease"))) -> Same | AJ119: =IFERROR(AA119*AF119,0) -> 9719.08 | AK119: =IFERROR(AA119*AH119,0) -> 9719.08 | AL119: Paint | AM119: Normal | AN119: 185 | AO119: 47.18 | AP119: =IF(AM119="Delete","Delete",IF(AO119=AF119,"Same",IF(AO119>AF119,"Increase","Decrease"))) -> Same | AQ119: =AN119*AF119 -> 8728.3 | AR119: =AN119*AO119 -> 8728.3 | AS119: =AR119-AQ119 -> 0
A120: 5090808 | B120: 5090808 | C120: DDEC01 | D120: Akzo DDC | E120: Dulux TR Diamond Eggshell Tint Colours 2.5L | F120: Dulux TR Diamond Eggshell Tint Colours 2.5L | H120: EA | I120: ITEM | J120: ITEM | K120: Paint | L120: 21.24 | M120: STD20 | N120: 3105 | R120: 21.24 | S120: 21.24 | T120: 200 | V120: 19.2375 | W120: 21.24 | X120: =SUM(V120*T120) -> 3847.5 | Y120: =SUM(L120*T120) -> 4248 | Z120: =SUM(X120-Y120) -> -400.5 | AA120: 200 | AB120: =IFERROR(VLOOKUP(A120,'Tash Lookup'!A:E,3,FALSE),"") -> 4192.55 | AC120: =IFERROR(AA120-T120,"") -> 0 | AD120: Normal | AF120: 20.41 | AG120: =VLOOKUP(A120,Sheet1!$A$2:$C$1140,3,FALSE) -> 20.41 | AH120: 20.41 | AI120: =IF(ISNA(AH120),"Delete",IF(AH120=AF120,"Same",IF(AH120>AF120,"Increase","Decrease"))) -> Same | AJ120: =IFERROR(AA120*AF120,0) -> 4082 | AK120: =IFERROR(AA120*AH120,0) -> 4082 | AL120: Paint | AM120: Normal | AN120: 334 | AO120: 20.41 | AP120: =IF(AM120="Delete","Delete",IF(AO120=AF120,"Same",IF(AO120>AF120,"Increase","Decrease"))) -> Same | AQ120: =AN120*AF120 -> 6816.94 | AR120: =AN120*AO120 -> 6816.94 | AS120: =AR120-AQ120 -> 0
A121: 5222325 | B121: 5222325 | C121: DDEC01 | D121: Akzo DDC | E121: Zinsser B-i-n 5L | F121: Zinsser B-i-n 5L | H121: EA | I121: ITEM | J121: ITEM | K121: Paint | L121: 79.56 | M121: STD20 | N121: 3105 | R121: 79.56 | S121: 79.56 | T121: 199 | V121: 79.56 | W121: 79.56 | X121: =SUM(V121*T121) -> 15832.44 | Y121: =SUM(L121*T121) -> 15832.44 | Z121: =SUM(X121-Y121) -> 0 | AA121: 199 | AB121: =IFERROR(VLOOKUP(A121,'Tash Lookup'!A:E,3,FALSE),"") -> 15650.78 | AC121: =IFERROR(AA121-T121,"") -> 0 | AD121: Normal | AF121: 82.74 | AG121: =VLOOKUP(A121,Sheet1!$A$2:$C$1140,3,FALSE) -> 82.74 | AH121: 82.74 | AI121: =IF(ISNA(AH121),"Delete",IF(AH121=AF121,"Same",IF(AH121>AF121,"Increase","Decrease"))) -> Same | AJ121: =IFERROR(AA121*AF121,0) -> 16465.26 | AK121: =IFERROR(AA121*AH121,0) -> 16465.26 | AL121: Sundries / 3rd Party | AM121: Normal | AN121: 92 | AO121: 82.74 | AP121: =IF(AM121="Delete","Delete",IF(AO121=AF121,"Same",IF(AO121>AF121,"Increase","Decrease"))) -> Same | AQ121: =AN121*AF121 -> 7612.08 | AR121: =AN121*AO121 -> 7612.08 | AS121: =AR121-AQ121 -> 0
A122: 5218563 | B122: 5218563 | C122: DDEC01 | D122: Akzo DDC | E122: Armstead TR QD Wood Primer U/coat 5L | F122: Armstead TR QD Wood Primer U/coat 5L | H122: EA | I122: ITEM | J122: ITEM | K122: Paint | L122: 21.04 | M122: STD20 | N122: 3105 | R122: 25.71 | S122: 25.71 | T122: 197 | V122: 21.04 | W122: 15.86 | X122: =SUM(V122*T122) -> 4144.88 | Y122: =SUM(L122*T122) -> 4144.88 | Z122: =SUM(X122-Y122) -> 0 | AA122: 197 | AB122: =IFERROR(VLOOKUP(A122,'Tash Lookup'!A:E,3,FALSE),"") -> 3664.5 | AC122: =IFERROR(AA122-T122,"") -> 0 | AD122: Normal | AF122: 21.92 | AG122: =VLOOKUP(A122,Sheet1!$A$2:$C$1140,3,FALSE) -> 22.58 | AH122: 22.58 | AI122: =IF(ISNA(AH122),"Delete",IF(AH122=AF122,"Same",IF(AH122>AF122,"Increase","Decrease"))) -> Increase | AJ122: =IFERROR(AA122*AF122,0) -> 4318.24 | AK122: =IFERROR(AA122*AH122,0) -> 4448.26 | AL122: Paint | AM122: Normal | AN122: 81 | AO122: 22.58 | AP122: =IF(AM122="Delete","Delete",IF(AO122=AF122,"Same",IF(AO122>AF122,"Increase","Decrease"))) -> Increase | AQ122: =AN122*AF122 -> 1775.52 | AR122: =AN122*AO122 -> 1828.98 | AS122: =AR122-AQ122 -> 53.46
A123: 5180492 | B123: 5180492 | C123: DDEC01 | D123: Akzo DDC | E123: Cuprinol Cladding & Fence Opq Dk Oak 10L | F123: Cuprinol Cladding & Fence Opq Dk Oak 10L | H123: EA | I123: ITEM | J123: ITEM | K123: Paint | L123: 35.4 | M123: STD20 | N123: 3105 | R123: 35.4 | S123: 35.4 | T123: 195 | V123: 35.4 | W123: 35.4 | X123: =SUM(V123*T123) -> 6903 | Y123: =SUM(L123*T123) -> 6903 | Z123: =SUM(X123-Y123) -> 0 | AA123: 195 | AB123: =IFERROR(VLOOKUP(A123,'Tash Lookup'!A:E,3,FALSE),"") -> 6905.55 | AC123: =IFERROR(AA123-T123,"") -> 0 | AD123: Pre-Clearance | AF123: 37.21 | AG123: =VLOOKUP(A123,Sheet1!$A$2:$C$1140,3,FALSE) -> #N/A | AH123: #N/A | AI123: =IF(ISNA(AH123),"Delete",IF(AH123=AF123,"Same",IF(AH123>AF123,"Increase","Decrease"))) -> Delete | AJ123: =IFERROR(AA123*AF123,0) -> 7255.95 | AK123: =IFERROR(AA123*AH123,0) -> 0 | AL123: Paint | AM123: Phase-out | AN123: 0 | AO123: 37.21 | AP123: =IF(AM123="Delete","Delete",IF(AO123=AF123,"Same",IF(AO123>AF123,"Increase","Decrease"))) -> Same | AQ123: =AN123*AF123 -> 0 | AR123: =AN123*AO123 -> 0 | AS123: =AR123-AQ123 -> 0
A124: 5218668 | B124: 5218668 | C124: DDEC01 | D124: Akzo DDC | E124: Armstead TR V/Matt BW 10L | F124: Armstead TR V/Matt BW 10L | H124: EA | I124: ITEM | J124: ITEM | K124: Paint | L124: 22.05 | M124: STD20 | N124: 3105 | R124: 26.94 | S124: 26.94 | T124: 194 | V124: 22.05 | W124: 16.48 | X124: =SUM(V124*T124) -> 4277.7 | Y124: =SUM(L124*T124) -> 4277.7 | Z124: =SUM(X124-Y124) -> 0 | AA124: 194 | AB124: =IFERROR(VLOOKUP(A124,'Tash Lookup'!A:E,3,FALSE),"") -> 3609.04 | AC124: =IFERROR(AA124-T124,"") -> 0 | AD124: Normal | AF124: 21.13 | AG124: =VLOOKUP(A124,Sheet1!$A$2:$C$1140,3,FALSE) -> 21.13 | AH124: 21.13 | AI124: =IF(ISNA(AH124),"Delete",IF(AH124=AF124,"Same",IF(AH124>AF124,"Increase","Decrease"))) -> Same | AJ124: =IFERROR(AA124*AF124,0) -> 4099.22 | AK124: =IFERROR(AA124*AH124,0) -> 4099.22 | AL124: Paint | AM124: Normal | AN124: 95 | AO124: 21.13 | AP124: =IF(AM124="Delete","Delete",IF(AO124=AF124,"Same",IF(AO124>AF124,"Increase","Decrease"))) -> Same | AQ124: =AN124*AF124 -> 2007.35 | AR124: =AN124*AO124 -> 2007.35 | AS124: =AR124-AQ124 -> 0
A125: 5191768 | B125: 5191768 | C125: DDEC01 | D125: Akzo DDC | E125: Dulux TR Diamond Matt Magnolia 5L | F125: Dulux TR Diamond Matt Magnolia 5L | H125: EA | I125: ITEM | J125: ITEM | K125: Paint | L125: 21.32 | M125: STD20 | N125: 3105 | R125: 21.32 | S125: 21.32 | T125: 194 | V125: 18.43 | W125: 21.32 | X125: =SUM(V125*T125) -> 3575.42 | Y125: =SUM(L125*T125) -> 4136.08 | Z125: =SUM(X125-Y125) -> -560.66 | AA125: 194 | AB125: =IFERROR(VLOOKUP(A125,'Tash Lookup'!A:E,3,FALSE),"") -> 4070.3 | AC125: =IFERROR(AA125-T125,"") -> 0 | AD125: Normal | AF125: 19.13 | AG125: =VLOOKUP(A125,Sheet1!$A$2:$C$1140,3,FALSE) -> 19.13 | AH125: 19.13 | AI125: =IF(ISNA(AH125),"Delete",IF(AH125=AF125,"Same",IF(AH125>AF125,"Increase","Decrease"))) -> Same | AJ125: =IFERROR(AA125*AF125,0) -> 3711.22 | AK125: =IFERROR(AA125*AH125,0) -> 3711.22 | AL125: Paint | AM125: Normal | AN125: 110 | AO125: 19.13 | AP125: =IF(AM125="Delete","Delete",IF(AO125=AF125,"Same",IF(AO125>AF125,"Increase","Decrease"))) -> Same | AQ125: =AN125*AF125 -> 2104.3 | AR125: =AN125*AO125 -> 2104.3 | AS125: =AR125-AQ125 -> 0
A126: 6183862 | B126: 6183862 | C126: DDEC01 | D126: Akzo DDC | E126: DDC Soft Grip Stick Frame 4IN | F126: DDC Soft Grip Stick Frame 4IN | H126: EA | I126: ITEM | J126: ITEM | K126: Paint | L126: 2.09 | M126: STD20 | N126: 3105 | R126: 2.09 | S126: 2.09 | T126: 188 | V126: 2.09 | W126: 2.09 | X126: =SUM(V126*T126) -> 392.92 | Y126: =SUM(L126*T126) -> 392.92 | Z126: =SUM(X126-Y126) -> 0 | AA126: 188 | AB126: =IFERROR(VLOOKUP(A126,'Tash Lookup'!A:E,3,FALSE),"") -> 392.07 | AC126: =IFERROR(AA126-T126,"") -> 0 | AD126: Normal | AF126: 2.09 | AG126: =VLOOKUP(A126,Sheet1!$A$2:$C$1140,3,FALSE) -> 2.14 | AH126: 2.14 | AI126: =IF(ISNA(AH126),"Delete",IF(AH126=AF126,"Same",IF(AH126>AF126,"Increase","Decrease"))) -> Increase | AJ126: =IFERROR(AA126*AF126,0) -> 392.92 | AK126: =IFERROR(AA126*AH126,0) -> 402.32 | AL126: Sundries / 3rd Party | AM126: Normal | AN126: 109 | AO126: 2.14 | AP126: =IF(AM126="Delete","Delete",IF(AO126=AF126,"Same",IF(AO126>AF126,"Increase","Decrease"))) -> Increase | AQ126: =AN126*AF126 -> 227.81 | AR126: =AN126*AO126 -> 233.26 | AS126: =AR126-AQ126 -> 5.45
A127: 5090797 | B127: 5090797 | C127: DDEC01 | D127: Akzo DDC | E127: Dulux TR W/S Max Exp Tinted Colours 5L | F127: Dulux TR W/S Max Exp Tinted Colours 5L | H127: EA | I127: ITEM | J127: ITEM | K127: Paint | L127: 38.63 | M127: STD20 | N127: 3105 | R127: 38.63 | S127: 38.63 | T127: 183 | V127: 38.63 | W127: 38.63 | X127: =SUM(V127*T127) -> 7069.29 | Y127: =SUM(L127*T127) -> 7069.29 | Z127: =SUM(X127-Y127) -> 0 | AA127: 183 | AB127: =IFERROR(VLOOKUP(A127,'Tash Lookup'!A:E,3,FALSE),"") -> 7027.4 | AC127: =IFERROR(AA127-T127,"") -> 0 | AD127: Normal | AF127: 40.46 | AG127: =VLOOKUP(A127,Sheet1!$A$2:$C$1140,3,FALSE) -> 40.46 | AH127: 40.46 | AI127: =IF(ISNA(AH127),"Delete",IF(AH127=AF127,"Same",IF(AH127>AF127,"Increase","Decrease"))) -> Same | AJ127: =IFERROR(AA127*AF127,0) -> 7404.18 | AK127: =IFERROR(AA127*AH127,0) -> 7404.18 | AL127: Paint | AM127: Normal | AN127: 5 | AO127: 40.46 | AP127: =IF(AM127="Delete","Delete",IF(AO127=AF127,"Same",IF(AO127>AF127,"Increase","Decrease"))) -> Same | AQ127: =AN127*AF127 -> 202.3 | AR127: =AN127*AO127 -> 202.3 | AS127: =AR127-AQ127 -> 0
A128: 6365220 | B128: 6365220 | C128: DDEC01 | D128: Akzo DDC | E128: Microfibre All Purpose Cloth 40cm x 40cm 10PK | F128: Microfibre All Purpose Cloth 40cm x 40cm 10PK | H128: EA | I128: ITEM | J128: ITEM | K128: Paint | L128: 6.22 | M128: STD20 | N128: 3105 | R128: 6.22 | S128: 6.22 | T128: 175 | V128: 6.22 | W128: 6.22 | X128: =SUM(V128*T128) -> 1088.5 | Y128: =SUM(L128*T128) -> 1088.5 | Z128: =SUM(X128-Y128) -> 0 | AA128: 175 | AB128: =IFERROR(VLOOKUP(A128,'Tash Lookup'!A:E,3,FALSE),"") -> 1049.85 | AC128: =IFERROR(AA128-T128,"") -> 0 | AD128: Normal | AF128: 6.22 | AG128: =VLOOKUP(A128,Sheet1!$A$2:$C$1140,3,FALSE) -> 6.34 | AH128: 6.34 | AI128: =IF(ISNA(AH128),"Delete",IF(AH128=AF128,"Same",IF(AH128>AF128,"Increase","Decrease"))) -> Increase | AJ128: =IFERROR(AA128*AF128,0) -> 1088.5 | AK128: =IFERROR(AA128*AH128,0) -> 1109.5 | AL128: Sundries / 3rd Party | AM128: Normal | AN128: 187 | AO128: 6.34 | AP128: =IF(AM128="Delete","Delete",IF(AO128=AF128,"Same",IF(AO128>AF128,"Increase","Decrease"))) -> Increase | AQ128: =AN128*AF128 -> 1163.14 | AR128: =AN128*AO128 -> 1185.58 | AS128: =AR128-AQ128 -> 22.44
A129: 6365228 | B129: 6365228 | C129: DDEC01 | D129: Akzo DDC | E129: HG Mould Spray 500ML | F129: HG Mould Spray 500ML | H129: EA | I129: ITEM | J129: ITEM | K129: Paint | L129: 3.79 | M129: STD20 | N129: 3105 | R129: 3.79 | S129: 3.79 | T129: 174 | V129: 3.79 | W129: 3.79 | X129: =SUM(V129*T129) -> 659.46 | Y129: =SUM(L129*T129) -> 659.46 | Z129: =SUM(X129-Y129) -> 0 | AA129: 174 | AB129: =IFERROR(VLOOKUP(A129,'Tash Lookup'!A:E,3,FALSE),"") -> 655.58 | AC129: =IFERROR(AA129-T129,"") -> 0 | AD129: Normal | AF129: 3.79 | AG129: =VLOOKUP(A129,Sheet1!$A$2:$C$1140,3,FALSE) -> 3.86 | AH129: 3.86 | AI129: =IF(ISNA(AH129),"Delete",IF(AH129=AF129,"Same",IF(AH129>AF129,"Increase","Decrease"))) -> Increase | AJ129: =IFERROR(AA129*AF129,0) -> 659.46 | AK129: =IFERROR(AA129*AH129,0) -> 671.64 | AL129: Sundries / 3rd Party | AM129: Normal | AN129: 129 | AO129: 3.86 | AP129: =IF(AM129="Delete","Delete",IF(AO129=AF129,"Same",IF(AO129>AF129,"Increase","Decrease"))) -> Increase | AQ129: =AN129*AF129 -> 488.91 | AR129: =AN129*AO129 -> 497.94 | AS129: =AR129-AQ129 -> 9.03
A130: 5218666 | B130: 5218666 | C130: DDEC01 | D130: Akzo DDC | E130: Armstead TR Undercoat White 5L | F130: Armstead TR Undercoat White 5L | H130: EA | I130: ITEM | J130: ITEM | K130: Paint | L130: 16 | M130: STD20 | N130: 3105 | R130: 19.56 | S130: 19.56 | T130: 168 | V130: 16 | W130: 12.23 | X130: =SUM(V130*T130) -> 2688 | Y130: =SUM(L130*T130) -> 2688 | Z130: =SUM(X130-Y130) -> 0 | AA130: 168 | AB130: =IFERROR(VLOOKUP(A130,'Tash Lookup'!A:E,3,FALSE),"") -> 2362.4 | AC130: =IFERROR(AA130-T130,"") -> 0 | AD130: Normal | AF130: 17.17 | AG130: =VLOOKUP(A130,Sheet1!$A$2:$C$1140,3,FALSE) -> 17.69 | AH130: 17.69 | AI130: =IF(ISNA(AH130),"Delete",IF(AH130=AF130,"Same",IF(AH130>AF130,"Increase","Decrease"))) -> Increase | AJ130: =IFERROR(AA130*AF130,0) -> 2884.56 | AK130: =IFERROR(AA130*AH130,0) -> 2971.92 | AL130: Paint | AM130: Normal | AN130: 84 | AO130: 17.69 | AP130: =IF(AM130="Delete","Delete",IF(AO130=AF130,"Same",IF(AO130>AF130,"Increase","Decrease"))) -> Increase | AQ130: =AN130*AF130 -> 1442.28 | AR130: =AN130*AO130 -> 1485.96 | AS130: =AR130-AQ130 -> 43.68
A131: 6188877 | B131: 6188877 | C131: DDEC01 | D131: Akzo DDC | E131: DDC Glosser Microfibre Sleeve 10PK 4IN | F131: DDC Glosser Microfibre Sleeve 10PK 4IN | H131: EA | I131: ITEM | J131: ITEM | K131: Paint | L131: 11.97 | M131: STD20 | N131: 3105 | R131: 11.97 | S131: 11.97 | T131: 168 | V131: 11.97 | W131: 11.97 | X131: =SUM(V131*T131) -> 2010.96 | Y131: =SUM(L131*T131) -> 2010.96 | Z131: =SUM(X131-Y131) -> 0 | AA131: 168 | AB131: =IFERROR(VLOOKUP(A131,'Tash Lookup'!A:E,3,FALSE),"") -> 1996.46 | AC131: =IFERROR(AA131-T131,"") -> 0 | AD131: Normal | AF131: 10.77 | AG131: =VLOOKUP(A131,Sheet1!$A$2:$C$1140,3,FALSE) -> 10.99 | AH131: 10.99 | AI131: =IF(ISNA(AH131),"Delete",IF(AH131=AF131,"Same",IF(AH131>AF131,"Increase","Decrease"))) -> Increase | AJ131: =IFERROR(AA131*AF131,0) -> 1809.36 | AK131: =IFERROR(AA131*AH131,0) -> 1846.32 | AL131: Sundries / 3rd Party | AM131: Normal | AN131: 104 | AO131: 10.99 | AP131: =IF(AM131="Delete","Delete",IF(AO131=AF131,"Same",IF(AO131>AF131,"Increase","Decrease"))) -> Increase | AQ131: =AN131*AF131 -> 1120.08 | AR131: =AN131*AO131 -> 1142.96 | AS131: =AR131-AQ131 -> 22.88
A132: 6183904 | B132: 6183904 | C132: DDEC01 | D132: Akzo DDC | E132: Advanced Duo Dust Sheet 12x9FT | F132: Advanced Duo Dust Sheet 12x9FT | H132: EA | I132: ITEM | J132: ITEM | K132: Paint | L132: 13.49 | M132: STD20 | N132: 3105 | R132: 13.49 | S132: 13.49 | T132: 167 | V132: 13.49 | W132: 13.49 | X132: =SUM(V132*T132) -> 2252.83 | Y132: =SUM(L132*T132) -> 2252.83 | Z132: =SUM(X132-Y132) -> 0 | AA132: 167 | AB132: =IFERROR(VLOOKUP(A132,'Tash Lookup'!A:E,3,FALSE),"") -> 2224.24 | AC132: =IFERROR(AA132-T132,"") -> 0 | AD132: Normal | AF132: 13.49 | AG132: =VLOOKUP(A132,Sheet1!$A$2:$C$1140,3,FALSE) -> 13.76 | AH132: 13.76 | AI132: =IF(ISNA(AH132),"Delete",IF(AH132=AF132,"Same",IF(AH132>AF132,"Increase","Decrease"))) -> Increase | AJ132: =IFERROR(AA132*AF132,0) -> 2252.83 | AK132: =IFERROR(AA132*AH132,0) -> 2297.92 | AL132: Sundries / 3rd Party | AM132: Normal | AN132: 99 | AO132: 13.76 | AP132: =IF(AM132="Delete","Delete",IF(AO132=AF132,"Same",IF(AO132>AF132,"Increase","Decrease"))) -> Increase | AQ132: =AN132*AF132 -> 1335.51 | AR132: =AN132*AO132 -> 1362.24 | AS132: =AR132-AQ132 -> 26.73
A133: 5091282 | B133: 5091282 | C133: DDEC01 | D133: Akzo DDC | E133: Dulux TR Fast Matt White 10L | F133: Dulux TR Fast Matt White 10L | H133: EA | I133: ITEM | J133: ITEM | K133: Paint | L133: 30.37 | M133: STD20 | N133: 3105 | R133: 30.37 | S133: 30.37 | T133: 166 | V133: 30.37 | W133: 30.37 | X133: =SUM(V133*T133) -> 5041.42 | Y133: =SUM(L133*T133) -> 5041.42 | Z133: =SUM(X133-Y133) -> 0 | AA133: 166 | AB133: =IFERROR(VLOOKUP(A133,'Tash Lookup'!A:E,3,FALSE),"") -> 4867.73 | AC133: =IFERROR(AA133-T133,"") -> 0 | AD133: Phase-out | AF133: 29.13 | AG133: =VLOOKUP(A133,Sheet1!$A$2:$C$1140,3,FALSE) -> 30.37 | AH133: 30.37 | AI133: =IF(ISNA(AH133),"Delete",IF(AH133=AF133,"Same",IF(AH133>AF133,"Increase","Decrease"))) -> Increase | AJ133: =IFERROR(AA133*AF133,0) -> 4835.58 | AK133: =IFERROR(AA133*AH133,0) -> 5041.42 | AL133: Paint | AM133: Phase-out | AN133: 6 | AO133: 30.37 | AP133: =IF(AM133="Delete","Delete",IF(AO133=AF133,"Same",IF(AO133>AF133,"Increase","Decrease"))) -> Increase | AQ133: =AN133*AF133 -> 174.78 | AR133: =AN133*AO133 -> 182.22 | AS133: =AR133-AQ133 -> 7.44
A134: 5090757 | B134: 5090757 | C134: DDEC01 | D134: Akzo DDC | E134: Dulux TR Undercoat Tinted Colours 5L | F134: Dulux TR Undercoat Tinted Colours 5L | H134: EA | I134: ITEM | J134: ITEM | K134: Paint | L134: 39.65 | M134: STD20 | N134: 3105 | R134: 39.65 | S134: 39.65 | T134: 166 | V134: 39.65 | W134: 39.65 | X134: =SUM(V134*T134) -> 6581.9 | Y134: =SUM(L134*T134) -> 6581.9 | Z134: =SUM(X134-Y134) -> 0 | AA134: 166 | AB134: =IFERROR(VLOOKUP(A134,'Tash Lookup'!A:E,3,FALSE),"") -> 6403.74 | AC134: =IFERROR(AA134-T134,"") -> 0 | AD134: Normal | AF134: 44.1 | AG134: =VLOOKUP(A134,Sheet1!$A$2:$C$1140,3,FALSE) -> 44.1 | AH134: 44.1 | AI134: =IF(ISNA(AH134),"Delete",IF(AH134=AF134,"Same",IF(AH134>AF134,"Increase","Decrease"))) -> Same | AJ134: =IFERROR(AA134*AF134,0) -> 7320.6 | AK134: =IFERROR(AA134*AH134,0) -> 7320.6 | AL134: Paint | AM134: Normal | AN134: 125 | AO134: 44.1 | AP134: =IF(AM134="Delete","Delete",IF(AO134=AF134,"Same",IF(AO134>AF134,"Increase","Decrease"))) -> Same | AQ134: =AN134*AF134 -> 5512.5 | AR134: =AN134*AO134 -> 5512.5 | AS134: =AR134-AQ134 -> 0
A135: 5083924 | B135: 5083924 | C135: DDEC01 | D135: Akzo DDC | E135: Dulux TR W/S M/surf Fung Wash 5L | F135: Dulux TR W/S M/surf Fung Wash 5L | H135: EA | I135: ITEM | J135: ITEM | K135: Paint | L135: 14.04 | M135: STD20 | N135: 3105 | R135: 14.04 | S135: 14.04 | T135: 163 | V135: 14.04 | W135: 14.04 | X135: =SUM(V135*T135) -> 2288.52 | Y135: =SUM(L135*T135) -> 2288.52 | Z135: =SUM(X135-Y135) -> 0 | AA135: 163 | AB135: =IFERROR(VLOOKUP(A135,'Tash Lookup'!A:E,3,FALSE),"") -> 2367.99 | AC135: =IFERROR(AA135-T135,"") -> 0 | AD135: Pre-Clearance | AF135: 15.34 | AG135: =VLOOKUP(A135,Sheet1!$A$2:$C$1140,3,FALSE) -> #N/A | AH135: #N/A | AI135: =IF(ISNA(AH135),"Delete",IF(AH135=AF135,"Same",IF(AH135>AF135,"Increase","Decrease"))) -> Delete | AJ135: =IFERROR(AA135*AF135,0) -> 2500.42 | AK135: =IFERROR(AA135*AH135,0) -> 0 | AL135: Paint | AM135: Phase-out | AN135: 0 | AO135: 15.34 | AP135: =IF(AM135="Delete","Delete",IF(AO135=AF135,"Same",IF(AO135>AF135,"Increase","Decrease"))) -> Same | AQ135: =AN135*AF135 -> 0 | AR135: =AN135*AO135 -> 0 | AS135: =AR135-AQ135 -> 0
A136: 5222655 | B136: 5222655 | C136: DDEC01 | D136: Akzo DDC | E136: Gyproc Promix Lite 17L | F136: Gyproc Promix Lite 17L | H136: EA | I136: ITEM | J136: ITEM | K136: Paint | L136: 32.53 | M136: STD20 | N136: 3105 | R136: 0 | S136: 0 | T136: 163 | V136: 32.53 | W136: 32.53 | X136: =SUM(V136*T136) -> 5302.39 | Y136: =SUM(L136*T136) -> 5302.39 | Z136: =SUM(X136-Y136) -> 0 | AA136: 163 | AB136: =IFERROR(VLOOKUP(A136,'Tash Lookup'!A:E,3,FALSE),"") -> 5302.34 | AC136: =IFERROR(AA136-T136,"") -> 0 | AD136: Phase-out | AF136: 32.53 | AG136: =VLOOKUP(A136,Sheet1!$A$2:$C$1140,3,FALSE) -> 32.53 | AH136: 32.53 | AI136: =IF(ISNA(AH136),"Delete",IF(AH136=AF136,"Same",IF(AH136>AF136,"Increase","Decrease"))) -> Same | AJ136: =IFERROR(AA136*AF136,0) -> 5302.39 | AK136: =IFERROR(AA136*AH136,0) -> 5302.39 | AL136: Sundries / 3rd Party | AM136: Phase-out | AN136: 5 | AO136: 32.53 | AP136: =IF(AM136="Delete","Delete",IF(AO136=AF136,"Same",IF(AO136>AF136,"Increase","Decrease"))) -> Same | AQ136: =AN136*AF136 -> 162.65 | AR136: =AN136*AO136 -> 162.65 | AS136: =AR136-AQ136 -> 0
A137: 5090783 | B137: 5090783 | C137: DDEC01 | D137: Akzo DDC | E137: Dulux TR QD Woodstain Tinted Colours 5L | F137: Dulux TR QD Woodstain Tinted Colours 5L | H137: EA | I137: ITEM | J137: ITEM | K137: Paint | L137: 67.84 | M137: STD20 | N137: 3105 | R137: 64.44 | S137: 0 | T137: 163 | V137: 64.44 | W137: 67.84 | X137: =SUM(V137*T137) -> 10503.72 | Y137: =SUM(L137*T137) -> 11057.92 | Z137: =SUM(X137-Y137) -> -554.2 | AA137: 163 | AB137: =IFERROR(VLOOKUP(A137,'Tash Lookup'!A:E,3,FALSE),"") -> 10625.33 | AC137: =IFERROR(AA137-T137,"") -> 0 | AD137: Normal | AF137: 68.13 | AG137: =VLOOKUP(A137,Sheet1!$A$2:$C$1140,3,FALSE) -> 70.17 | AH137: 70.17 | AI137: =IF(ISNA(AH137),"Delete",IF(AH137=AF137,"Same",IF(AH137>AF137,"Increase","Decrease"))) -> Increase | AJ137: =IFERROR(AA137*AF137,0) -> 11105.19 | AK137: =IFERROR(AA137*AH137,0) -> 11437.71 | AL137: Paint | AM137: Normal | AN137: 94 | AO137: 70.17 | AP137: =IF(AM137="Delete","Delete",IF(AO137=AF137,"Same",IF(AO137>AF137,"Increase","Decrease"))) -> Increase | AQ137: =AN137*AF137 -> 6404.22 | AR137: =AN137*AO137 -> 6595.98 | AS137: =AR137-AQ137 -> 191.76
A138: 5583719 | B138: 5583719 | C138: DDEC01 | D138: Akzo DDC | E138: Dulux TR W/S Msnry Smooth Magnolia 10L | F138: Dulux TR W/S Msnry Smooth Magnolia 10L | H138: EA | I138: ITEM | J138: ITEM | K138: Paint | L138: 31.59 | M138: STD20 | N138: 3105 | R138: 31.59 | S138: 31.59 | T138: 159 | V138: 31.59 | W138: 31.59 | X138: =SUM(V138*T138) -> 5022.81 | Y138: =SUM(L138*T138) -> 5022.81 | Z138: =SUM(X138-Y138) -> 0 | AA138: 159 | AB138: =IFERROR(VLOOKUP(A138,'Tash Lookup'!A:E,3,FALSE),"") -> 4892.5 | AC138: =IFERROR(AA138-T138,"") -> 0 | AD138: Normal | AF138: 30.6 | AG138: =VLOOKUP(A138,Sheet1!$A$2:$C$1140,3,FALSE) -> 30.6 | AH138: 30.6 | AI138: =IF(ISNA(AH138),"Delete",IF(AH138=AF138,"Same",IF(AH138>AF138,"Increase","Decrease"))) -> Same | AJ138: =IFERROR(AA138*AF138,0) -> 4865.4 | AK138: =IFERROR(AA138*AH138,0) -> 4865.4 | AL138: Paint | AM138: Normal | AN138: 71 | AO138: 30.6 | AP138: =IF(AM138="Delete","Delete",IF(AO138=AF138,"Same",IF(AO138>AF138,"Increase","Decrease"))) -> Same | AQ138: =AN138*AF138 -> 2172.6 | AR138: =AN138*AO138 -> 2172.6 | AS138: =AR138-AQ138 -> 0
A139: 5091647 | B139: 5091647 | C139: DDEC01 | D139: Akzo DDC | E139: Dulux TR V/Matt White 5L | F139: Dulux TR V/Matt White 5L | H139: EA | I139: ITEM | J139: ITEM | K139: Paint | L139: 19.41 | M139: STD20 | N139: 3105 | R139: 19.41 | S139: 19.41 | T139: 158 | V139: 16.1405 | W139: 19.41 | X139: =SUM(V139*T139) -> 2550.199 | Y139: =SUM(L139*T139) -> 3066.78 | Z139: =SUM(X139-Y139) -> -516.581 | AA139: 158 | AB139: =IFERROR(VLOOKUP(A139,'Tash Lookup'!A:E,3,FALSE),"") -> 2996.51 | AC139: =IFERROR(AA139-T139,"") -> 0 | AD139: Normal | AF139: 15.92 | AG139: =VLOOKUP(A139,Sheet1!$A$2:$C$1140,3,FALSE) -> 15.92 | AH139: 15.92 | AI139: =IF(ISNA(AH139),"Delete",IF(AH139=AF139,"Same",IF(AH139>AF139,"Increase","Decrease"))) -> Same | AJ139: =IFERROR(AA139*AF139,0) -> 2515.36 | AK139: =IFERROR(AA139*AH139,0) -> 2515.36 | AL139: Paint | AM139: Normal | AN139: 144 | AO139: 15.92 | AP139: =IF(AM139="Delete","Delete",IF(AO139=AF139,"Same",IF(AO139>AF139,"Increase","Decrease"))) -> Same | AQ139: =AN139*AF139 -> 2292.48 | AR139: =AN139*AO139 -> 2292.48 | AS139: =AR139-AQ139 -> 0
A140: 5220092 | B140: 5220092 | C140: DDEC01 | D140: Akzo DDC | E140: Dulux TR QD Gloss Pure Brilliant White 2.5L | F140: Dulux TR QD Gloss Pure Brilliant White 2.5L | H140: EA | I140: ITEM | J140: ITEM | K140: Paint | L140: 19.62 | M140: STD20 | N140: 3105 | R140: 19.62 | S140: 19.62 | T140: 157 | V140: 19.62 | W140: 19.62 | X140: =SUM(V140*T140) -> 3080.34 | Y140: =SUM(L140*T140) -> 3080.34 | Z140: =SUM(X140-Y140) -> 0 | AA140: 157 | AB140: =IFERROR(VLOOKUP(A140,'Tash Lookup'!A:E,3,FALSE),"") -> 2997.54 | AC140: =IFERROR(AA140-T140,"") -> 0 | AD140: Normal | AF140: 20.24 | AG140: =VLOOKUP(A140,Sheet1!$A$2:$C$1140,3,FALSE) -> 20.24 | AH140: 20.24 | AI140: =IF(ISNA(AH140),"Delete",IF(AH140=AF140,"Same",IF(AH140>AF140,"Increase","Decrease"))) -> Same | AJ140: =IFERROR(AA140*AF140,0) -> 3177.68 | AK140: =IFERROR(AA140*AH140,0) -> 3177.68 | AL140: Paint | AM140: Normal | AN140: 159 | AO140: 20.24 | AP140: =IF(AM140="Delete","Delete",IF(AO140=AF140,"Same",IF(AO140>AF140,"Increase","Decrease"))) -> Same | AQ140: =AN140*AF140 -> 3218.16 | AR140: =AN140*AO140 -> 3218.16 | AS140: =AR140-AQ140 -> 0
A141: 6034080 | B141: 6034080 | C141: DDEC01 | D141: Akzo DDC | E141: Trade Brush - 3' | F141: Trade Brush - 3' | H141: EA | I141: ITEM | J141: ITEM | K141: Paint | L141: 2.66 | M141: STD20 | N141: 3105 | R141: 5.51 | S141: 5.51 | T141: 157 | V141: 2.66 | W141: 2.66 | X141: =SUM(V141*T141) -> 417.62 | Y141: =SUM(L141*T141) -> 417.62 | Z141: =SUM(X141-Y141) -> 0 | AA141: 157 | AB141: =IFERROR(VLOOKUP(A141,'Tash Lookup'!A:E,3,FALSE),"") -> 415.1 | AC141: =IFERROR(AA141-T141,"") -> 0 | AD141: Normal | AF141: 2.39 | AG141: =VLOOKUP(A141,Sheet1!$A$2:$C$1140,3,FALSE) -> #N/A | AH141: #N/A | AI141: =IF(ISNA(AH141),"Delete",IF(AH141=AF141,"Same",IF(AH141>AF141,"Increase","Decrease"))) -> Delete | AJ141: =IFERROR(AA141*AF141,0) -> 375.23 | AK141: =IFERROR(AA141*AH141,0) -> 0 | AL141: Sundries / 3rd Party | AM141: Phase-out | AN141: 37 | AO141: 2.39 | AP141: =IF(AM141="Delete","Delete",IF(AO141=AF141,"Same",IF(AO141>AF141,"Increase","Decrease"))) -> Same | AQ141: =AN141*AF141 -> 88.43 | AR141: =AN141*AO141 -> 88.43 | AS141: =AR141-AQ141 -> 0
A142: 5184007 | B142: 5184007 | C142: DDEC01 | D142: Akzo DDC | E142: Dulux TR Gloss Black 5L | F142: Dulux TR Gloss Black 5L | H142: EA | I142: ITEM | J142: ITEM | K142: Paint | L142: 38.85 | M142: STD20 | N142: 3105 | R142: 38.85 | S142: 38.85 | T142: 156 | V142: 38.85 | W142: 38.85 | X142: =SUM(V142*T142) -> 6060.6 | Y142: =SUM(L142*T142) -> 6060.6 | Z142: =SUM(X142-Y142) -> 0 | AA142: 156 | AB142: =IFERROR(VLOOKUP(A142,'Tash Lookup'!A:E,3,FALSE),"") -> 5971.96 | AC142: =IFERROR(AA142-T142,"") -> 0 | AD142: Normal | AF142: 38.42 | AG142: =VLOOKUP(A142,Sheet1!$A$2:$C$1140,3,FALSE) -> 38.42 | AH142: 38.42 | AI142: =IF(ISNA(AH142),"Delete",IF(AH142=AF142,"Same",IF(AH142>AF142,"Increase","Decrease"))) -> Same | AJ142: =IFERROR(AA142*AF142,0) -> 5993.52 | AK142: =IFERROR(AA142*AH142,0) -> 5993.52 | AL142: Paint | AM142: Normal | AN142: 177 | AO142: 38.42 | AP142: =IF(AM142="Delete","Delete",IF(AO142=AF142,"Same",IF(AO142>AF142,"Increase","Decrease"))) -> Same | AQ142: =AN142*AF142 -> 6800.34 | AR142: =AN142*AO142 -> 6800.34 | AS142: =AR142-AQ142 -> 0
A143: 5219312 | B143: 5219312 | C143: DDEC01 | D143: Akzo DDC | E143: Armstead TR Contract Matt Tinted Colours 10L | F143: Armstead TR Contract Matt Tinted Colours 10L | H143: EA | I143: ITEM | J143: ITEM | K143: Paint | L143: 16.88 | M143: STD20 | N143: 3105 | R143: 28.65 | S143: 28.65 | T143: 154 | V143: 16.036 | W143: 16.88 | X143: =SUM(V143*T143) -> 2469.544 | Y143: =SUM(L143*T143) -> 2599.52 | Z143: =SUM(X143-Y143) -> -129.976 | AA143: 154 | AB143: =IFERROR(VLOOKUP(A143,'Tash Lookup'!A:E,3,FALSE),"") -> 2866.36 | AC143: =IFERROR(AA143-T143,"") -> 0 | AD143: Normal | AF143: 17.04 | AG143: =VLOOKUP(A143,Sheet1!$A$2:$C$1140,3,FALSE) -> 17.04 | AH143: 17.04 | AI143: =IF(ISNA(AH143),"Delete",IF(AH143=AF143,"Same",IF(AH143>AF143,"Increase","Decrease"))) -> Same | AJ143: =IFERROR(AA143*AF143,0) -> 2624.16 | AK143: =IFERROR(AA143*AH143,0) -> 2624.16 | AL143: Paint | AM143: Normal | AN143: 17 | AO143: 17.04 | AP143: =IF(AM143="Delete","Delete",IF(AO143=AF143,"Same",IF(AO143>AF143,"Increase","Decrease"))) -> Same | AQ143: =AN143*AF143 -> 289.68 | AR143: =AN143*AO143 -> 289.68 | AS143: =AR143-AQ143 -> 0
A144: 5219320 | B144: 5219320 | C144: DDEC01 | D144: Akzo DDC | E144: Armstead TR High Gloss Tinted Colours 5L | F144: Armstead TR High Gloss Tinted Colours 5L | H144: EA | I144: ITEM | J144: ITEM | K144: Paint | L144: 24.34 | M144: STD20 | N144: 3105 | R144: 26.77 | S144: 26.77 | T144: 152 | V144: 24.34 | W144: 17.71 | X144: =SUM(V144*T144) -> 3699.68 | Y144: =SUM(L144*T144) -> 3699.68 | Z144: =SUM(X144-Y144) -> 0 | AA144: 152 | AB144: =IFERROR(VLOOKUP(A144,'Tash Lookup'!A:E,3,FALSE),"") -> 3192.91 | AC144: =IFERROR(AA144-T144,"") -> 0 | AD144: Normal | AF144: 26.63 | AG144: =VLOOKUP(A144,Sheet1!$A$2:$C$1140,3,FALSE) -> 27.43 | AH144: 27.43 | AI144: =IF(ISNA(AH144),"Delete",IF(AH144=AF144,"Same",IF(AH144>AF144,"Increase","Decrease"))) -> Increase | AJ144: =IFERROR(AA144*AF144,0) -> 4047.76 | AK144: =IFERROR(AA144*AH144,0) -> 4169.36 | AL144: Paint | AM144: Normal | AN144: 162 | AO144: 27.43 | AP144: =IF(AM144="Delete","Delete",IF(AO144=AF144,"Same",IF(AO144>AF144,"Increase","Decrease"))) -> Increase | AQ144: =AN144*AF144 -> 4314.06 | AR144: =AN144*AO144 -> 4443.66 | AS144: =AR144-AQ144 -> 129.6
A145: 5219311 | B145: 5219311 | C145: DDEC01 | D145: Akzo DDC | E145: Armstead TR A/Mould V/Matt Tint Colours 5L | F145: Armstead TR A/Mould V/Matt Tint Colours 5L | H145: EA | I145: ITEM | J145: ITEM | K145: Paint | L145: 27.86 | M145: STD20 | N145: 3105 | R145: 27.86 | S145: 27.86 | T145: 151 | V145: 27.86 | W145: 19.98 | X145: =SUM(V145*T145) -> 4206.86 | Y145: =SUM(L145*T145) -> 4206.86 | Z145: =SUM(X145-Y145) -> 0 | AA145: 151 | AB145: =IFERROR(VLOOKUP(A145,'Tash Lookup'!A:E,3,FALSE),"") -> 3405.66 | AC145: =IFERROR(AA145-T145,"") -> 0 | AD145: Normal | AF145: 25.8 | AG145: =VLOOKUP(A145,Sheet1!$A$2:$C$1140,3,FALSE) -> 26.57 | AH145: 26.57 | AI145: =IF(ISNA(AH145),"Delete",IF(AH145=AF145,"Same",IF(AH145>AF145,"Increase","Decrease"))) -> Increase | AJ145: =IFERROR(AA145*AF145,0) -> 3895.8 | AK145: =IFERROR(AA145*AH145,0) -> 4012.07 | AL145: Paint | AM145: Normal | AN145: 52 | AO145: 26.57 | AP145: =IF(AM145="Delete","Delete",IF(AO145=AF145,"Same",IF(AO145>AF145,"Increase","Decrease"))) -> Increase | AQ145: =AN145*AF145 -> 1341.6 | AR145: =AN145*AO145 -> 1381.64 | AS145: =AR145-AQ145 -> 40.04
A146: 5220151 | B146: 5220151 | C146: DDEC01 | D146: Akzo DDC | E146: Dulux TR QD Undercoat White 2.5L | F146: Dulux TR QD Undercoat White 2.5L | H146: EA | I146: ITEM | J146: ITEM | K146: Paint | L146: 17.75 | M146: STD20 | N146: 3105 | R146: 17.75 | S146: 17.75 | T146: 149 | V146: 17.75 | W146: 17.75 | X146: =SUM(V146*T146) -> 2644.75 | Y146: =SUM(L146*T146) -> 2644.75 | Z146: =SUM(X146-Y146) -> 0 | AA146: 149 | AB146: =IFERROR(VLOOKUP(A146,'Tash Lookup'!A:E,3,FALSE),"") -> 2632.69 | AC146: =IFERROR(AA146-T146,"") -> 0 | AD146: Normal | AF146: 18.43 | AG146: =VLOOKUP(A146,Sheet1!$A$2:$C$1140,3,FALSE) -> 18.43 | AH146: 18.43 | AI146: =IF(ISNA(AH146),"Delete",IF(AH146=AF146,"Same",IF(AH146>AF146,"Increase","Decrease"))) -> Same | AJ146: =IFERROR(AA146*AF146,0) -> 2746.07 | AK146: =IFERROR(AA146*AH146,0) -> 2746.07 | AL146: Paint | AM146: Normal | AN146: 113 | AO146: 18.43 | AP146: =IF(AM146="Delete","Delete",IF(AO146=AF146,"Same",IF(AO146>AF146,"Increase","Decrease"))) -> Same | AQ146: =AN146*AF146 -> 2082.59 | AR146: =AN146*AO146 -> 2082.59 | AS146: =AR146-AQ146 -> 0
A147: 6188759 | B147: 6188759 | C147: DDEC01 | D147: Akzo DDC | E147: DDC Cutting In Brush 15MM | F147: DDC Cutting In Brush 15MM | H147: EA | I147: ITEM | J147: ITEM | K147: Paint | L147: 3.79 | M147: STD20 | N147: 3105 | R147: 3.79 | S147: 3.79 | T147: 147 | V147: 3.79 | W147: 3.79 | X147: =SUM(V147*T147) -> 557.13 | Y147: =SUM(L147*T147) -> 557.13 | Z147: =SUM(X147-Y147) -> 0 | AA147: 147 | AB147: =IFERROR(VLOOKUP(A147,'Tash Lookup'!A:E,3,FALSE),"") -> 554.87 | AC147: =IFERROR(AA147-T147,"") -> 0 | AD147: Normal | AF147: 3.41 | AG147: =VLOOKUP(A147,Sheet1!$A$2:$C$1140,3,FALSE) -> 3.48 | AH147: 3.48 | AI147: =IF(ISNA(AH147),"Delete",IF(AH147=AF147,"Same",IF(AH147>AF147,"Increase","Decrease"))) -> Increase | AJ147: =IFERROR(AA147*AF147,0) -> 501.27 | AK147: =IFERROR(AA147*AH147,0) -> 511.56 | AL147: Sundries / 3rd Party | AM147: Normal | AN147: 104 | AO147: 3.48 | AP147: =IF(AM147="Delete","Delete",IF(AO147=AF147,"Same",IF(AO147>AF147,"Increase","Decrease"))) -> Increase | AQ147: =AN147*AF147 -> 354.64 | AR147: =AN147*AO147 -> 361.92 | AS147: =AR147-AQ147 -> 7.28
A148: 6188831 | B148: 6188831 | C148: DDEC01 | D148: Akzo DDC | E148: DDC Cutting In Brush 21MM | F148: DDC Cutting In Brush 21MM | H148: EA | I148: ITEM | J148: ITEM | K148: Paint | L148: 4.26 | M148: STD20 | N148: 3105 | R148: 4.26 | S148: 4.26 | T148: 146 | V148: 4.26 | W148: 4.26 | X148: =SUM(V148*T148) -> 621.96 | Y148: =SUM(L148*T148) -> 621.96 | Z148: =SUM(X148-Y148) -> 0 | AA148: 146 | AB148: =IFERROR(VLOOKUP(A148,'Tash Lookup'!A:E,3,FALSE),"") -> 615.47 | AC148: =IFERROR(AA148-T148,"") -> 0 | AD148: Normal | AF148: 4.26 | AG148: =VLOOKUP(A148,Sheet1!$A$2:$C$1140,3,FALSE) -> 4.35 | AH148: 4.35 | AI148: =IF(ISNA(AH148),"Delete",IF(AH148=AF148,"Same",IF(AH148>AF148,"Increase","Decrease"))) -> Increase | AJ148: =IFERROR(AA148*AF148,0) -> 621.96 | AK148: =IFERROR(AA148*AH148,0) -> 635.1 | AL148: Sundries / 3rd Party | AM148: Normal | AN148: 37 | AO148: 4.35 | AP148: =IF(AM148="Delete","Delete",IF(AO148=AF148,"Same",IF(AO148>AF148,"Increase","Decrease"))) -> Increase | AQ148: =AN148*AF148 -> 157.62 | AR148: =AN148*AO148 -> 160.95 | AS148: =AR148-AQ148 -> 3.33
A149: 5110653 | B149: 5110653 | C149: DDEC01 | D149: Akzo DDC | E149: Dulux TR W/S Ult W/Stn Tnt Colours 5L | F149: Dulux TR W/S Ult W/Stn Tnt Colours 5L | H149: EA | I149: ITEM | J149: ITEM | K149: Paint | L149: 61.05 | M149: STD20 | N149: 3105 | R149: 58 | S149: 0 | T149: 146 | V149: 58 | W149: 61.05 | X149: =SUM(V149*T149) -> 8468 | Y149: =SUM(L149*T149) -> 8913.3 | Z149: =SUM(X149-Y149) -> -445.3 | AA149: 146 | AB149: =IFERROR(VLOOKUP(A149,'Tash Lookup'!A:E,3,FALSE),"") -> 8577.45 | AC149: =IFERROR(AA149-T149,"") -> 0 | AD149: Normal | AF149: 68.13 | AG149: =VLOOKUP(A149,Sheet1!$A$2:$C$1140,3,FALSE) -> 70.17 | AH149: 70.17 | AI149: =IF(ISNA(AH149),"Delete",IF(AH149=AF149,"Same",IF(AH149>AF149,"Increase","Decrease"))) -> Increase | AJ149: =IFERROR(AA149*AF149,0) -> 9946.98 | AK149: =IFERROR(AA149*AH149,0) -> 10244.82 | AL149: Paint | AM149: Normal | AN149: 95 | AO149: 70.17 | AP149: =IF(AM149="Delete","Delete",IF(AO149=AF149,"Same",IF(AO149>AF149,"Increase","Decrease"))) -> Increase | AQ149: =AN149*AF149 -> 6472.35 | AR149: =AN149*AO149 -> 6666.15 | AS149: =AR149-AQ149 -> 193.8
A150: 5218641 | B150: 5218641 | C150: DDEC01 | D150: Akzo DDC | E150: Armstead TR High Gloss White 5L | F150: Armstead TR High Gloss White 5L | H150: EA | I150: ITEM | J150: ITEM | K150: Paint | L150: 16.61 | M150: STD20 | N150: 3105 | R150: 20.3 | S150: 20.3 | T150: 144 | V150: 16.61 | W150: 12.23 | X150: =SUM(V150*T150) -> 2391.84 | Y150: =SUM(L150*T150) -> 2391.84 | Z150: =SUM(X150-Y150) -> 0 | AA150: 144 | AB150: =IFERROR(VLOOKUP(A150,'Tash Lookup'!A:E,3,FALSE),"") -> 2092.56 | AC150: =IFERROR(AA150-T150,"") -> 0 | AD150: Normal | AF150: 17.17 | AG150: =VLOOKUP(A150,Sheet1!$A$2:$C$1140,3,FALSE) -> 17.69 | AH150: 17.69 | AI150: =IF(ISNA(AH150),"Delete",IF(AH150=AF150,"Same",IF(AH150>AF150,"Increase","Decrease"))) -> Increase | AJ150: =IFERROR(AA150*AF150,0) -> 2472.48 | AK150: =IFERROR(AA150*AH150,0) -> 2547.36 | AL150: Paint | AM150: Normal | AN150: 60 | AO150: 17.69 | AP150: =IF(AM150="Delete","Delete",IF(AO150=AF150,"Same",IF(AO150>AF150,"Increase","Decrease"))) -> Increase | AQ150: =AN150*AF150 -> 1030.2 | AR150: =AN150*AO150 -> 1061.4 | AS150: =AR150-AQ150 -> 31.2
A151: 5180262 | B151: 5180262 | C151: DDEC01 | D151: Akzo DDC | E151: Dulux TR W/S Ext Gloss Black 2.5L | F151: Dulux TR W/S Ext Gloss Black 2.5L | H151: EA | I151: ITEM | J151: ITEM | K151: Paint | L151: 34.13 | M151: STD20 | N151: 3105 | R151: 34.13 | S151: 34.13 | T151: 143 | V151: 34.13 | W151: 34.13 | X151: =SUM(V151*T151) -> 4880.59 | Y151: =SUM(L151*T151) -> 4880.59 | Z151: =SUM(X151-Y151) -> 0 | AA151: 143 | AB151: =IFERROR(VLOOKUP(A151,'Tash Lookup'!A:E,3,FALSE),"") -> 4821.36 | AC151: =IFERROR(AA151-T151,"") -> 0 | AD151: Normal | AF151: 35.33 | AG151: =VLOOKUP(A151,Sheet1!$A$2:$C$1140,3,FALSE) -> 35.33 | AH151: 35.33 | AI151: =IF(ISNA(AH151),"Delete",IF(AH151=AF151,"Same",IF(AH151>AF151,"Increase","Decrease"))) -> Same | AJ151: =IFERROR(AA151*AF151,0) -> 5052.19 | AK151: =IFERROR(AA151*AH151,0) -> 5052.19 | AL151: Paint | AM151: Normal | AN151: 37 | AO151: 35.33 | AP151: =IF(AM151="Delete","Delete",IF(AO151=AF151,"Same",IF(AO151>AF151,"Increase","Decrease"))) -> Same | AQ151: =AN151*AF151 -> 1307.21 | AR151: =AN151*AO151 -> 1307.21 | AS151: =AR151-AQ151 -> 0
A152: 5090741 | B152: 5090741 | C152: DDEC01 | D152: Akzo DDC | E152: Dulux TR W/S Ext U/Coat Tint Colours 5L | F152: Dulux TR W/S Ext U/Coat Tint Colours 5L | H152: EA | I152: ITEM | J152: ITEM | K152: Paint | L152: 56.31 | M152: STD20 | N152: 3105 | R152: 56.31 | S152: 56.31 | T152: 143 | V152: 56.31 | W152: 56.31 | X152: =SUM(V152*T152) -> 8052.33 | Y152: =SUM(L152*T152) -> 8052.33 | Z152: =SUM(X152-Y152) -> 0 | AA152: 143 | AB152: =IFERROR(VLOOKUP(A152,'Tash Lookup'!A:E,3,FALSE),"") -> 8000.12 | AC152: =IFERROR(AA152-T152,"") -> 0 | AD152: Normal | AF152: 59.14 | AG152: =VLOOKUP(A152,Sheet1!$A$2:$C$1140,3,FALSE) -> 59.14 | AH152: 59.14 | AI152: =IF(ISNA(AH152),"Delete",IF(AH152=AF152,"Same",IF(AH152>AF152,"Increase","Decrease"))) -> Same | AJ152: =IFERROR(AA152*AF152,0) -> 8457.02 | AK152: =IFERROR(AA152*AH152,0) -> 8457.02 | AL152: Paint | AM152: Normal | AN152: 200 | AO152: 59.14 | AP152: =IF(AM152="Delete","Delete",IF(AO152=AF152,"Same",IF(AO152>AF152,"Increase","Decrease"))) -> Same | AQ152: =AN152*AF152 -> 11828 | AR152: =AN152*AO152 -> 11828 | AS152: =AR152-AQ152 -> 0
A153: 6392301 | B153: 6392301 | C153: DDEC01 | D153: Akzo DDC | E153: Hamilton Perfection 9IN Long Pile Roller Sleeve | F153: Hamilton Perfection 9IN Long Pile Roller Sleeve | H153: EA | I153: ITEM | J153: ITEM | K153: Paint | L153: 5.21 | M153: STD20 | N153: 3105 | R153: 5.21 | S153: 5.21 | T153: 142 | V153: 5.21 | W153: 5.21 | X153: =SUM(V153*T153) -> 739.82 | Y153: =SUM(L153*T153) -> 739.82 | Z153: =SUM(X153-Y153) -> 0 | AA153: 142 | AB153: =IFERROR(VLOOKUP(A153,'Tash Lookup'!A:E,3,FALSE),"") -> 735.15 | AC153: =IFERROR(AA153-T153,"") -> 0 | AD153: Normal | AF153: 4.95 | AG153: =VLOOKUP(A153,Sheet1!$A$2:$C$1140,3,FALSE) -> 5.05 | AH153: 5.05 | AI153: =IF(ISNA(AH153),"Delete",IF(AH153=AF153,"Same",IF(AH153>AF153,"Increase","Decrease"))) -> Increase | AJ153: =IFERROR(AA153*AF153,0) -> 702.9 | AK153: =IFERROR(AA153*AH153,0) -> 717.1 | AL153: Sundries / 3rd Party | AM153: Normal | AN153: 131 | AO153: 5.05 | AP153: =IF(AM153="Delete","Delete",IF(AO153=AF153,"Same",IF(AO153>AF153,"Increase","Decrease"))) -> Increase | AQ153: =AN153*AF153 -> 648.45 | AR153: =AN153*AO153 -> 661.55 | AS153: =AR153-AQ153 -> 13.1
... A170: 5222326 | B170: 5222326 | C170: DDEC01 | D170: Akzo DDC | E170: Zinsser B-i-n 2.5L | F170: Zinsser B-i-n 2.5L | H170: EA | I170: ITEM | J170: ITEM | K170: Paint | L170: 42.42 | M170: STD20 | N170: 3105 | R170: 42.42 | S170: 42.42 | T170: 122 | V170: 42.42 | W170: 42.42 | X170: =SUM(V170*T170) -> 5175.24 | Y170: =SUM(L170*T170) -> 5175.24 | Z170: =SUM(X170-Y170) -> 0 | AA170: 122 | AB170: =IFERROR(VLOOKUP(A170,'Tash Lookup'!A:E,3,FALSE),"") -> 5127.66 | AC170: =IFERROR(AA170-T170,"") -> 0 | AD170: Normal | AF170: 44.12 | AG170: =VLOOKUP(A170,Sheet1!$A$2:$C$1140,3,FALSE) -> 44.12 | AH170: 44.12 | AI170: =IF(ISNA(AH170),"Delete",IF(AH170=AF170,"Same",IF(AH170>AF170,"Increase","Decrease"))) -> Same | AJ170: =IFERROR(AA170*AF170,0) -> 5382.64 | AK170: =IFERROR(AA170*AH170,0) -> 5382.64 | AL170: Sundries / 3rd Party | AM170: Normal | AN170: 70 | AO170: 44.12 | AP170: =IF(AM170="Delete","Delete",IF(AO170=AF170,"Same",IF(AO170>AF170,"Increase","Decrease"))) -> Same | AQ170: =AN170*AF170 -> 3088.4 | AR170: =AN170*AO170 -> 3088.4 | AS170: =AR170-AQ170 -> 0
A171: 6183855 | B171: 6183855 | C171: DDEC01 | D171: Akzo DDC | E171: DDC Click-Lock Extension Pole 2-4FT | F171: DDC Click-Lock Extension Pole 2-4FT | H171: EA | I171: ITEM | J171: ITEM | K171: Paint | L171: 12.43 | M171: STD20 | N171: 3105 | R171: 12.43 | S171: 12.43 | T171: 122 | V171: 12.43 | W171: 12.43 | X171: =SUM(V171*T171) -> 1516.46 | Y171: =SUM(L171*T171) -> 1516.46 | Z171: =SUM(X171-Y171) -> 0 | AA171: 122 | AB171: =IFERROR(VLOOKUP(A171,'Tash Lookup'!A:E,3,FALSE),"") -> 1511.78 | AC171: =IFERROR(AA171-T171,"") -> 0 | AD171: Phase-out | AF171: 12.43 | AG171: =VLOOKUP(A171,Sheet1!$A$2:$C$1140,3,FALSE) -> #N/A | AH171: #N/A | AI171: =IF(ISNA(AH171),"Delete",IF(AH171=AF171,"Same",IF(AH171>AF171,"Increase","Decrease"))) -> Delete | AJ171: =IFERROR(AA171*AF171,0) -> 1516.46 | AK171: =IFERROR(AA171*AH171,0) -> 0 | AL171: Sundries / 3rd Party | AM171: Phase-out | AN171: 29 | AO171: 12.43 | AP171: =IF(AM171="Delete","Delete",IF(AO171=AF171,"Same",IF(AO171>AF171,"Increase","Decrease"))) -> Same | AQ171: =AN171*AF171 -> 360.47 | AR171: =AN171*AO171 -> 360.47 | AS171: =AR171-AQ171 -> 0
A172: 6107271 | B172: 6107271 | C172: DDEC01 | D172: Akzo DDC | E172: Gyproc Easi-fill 10KG | F172: Gyproc Easi-fill 10KG | H172: EA | I172: ITEM | J172: ITEM | K172: Paint | L172: 19.18 | M172: STD20 | N172: 3105 | R172: 19.18 | S172: 19.18 | T172: 121 | V172: 19.18 | W172: 19.18 | X172: =SUM(V172*T172) -> 2320.78 | Y172: =SUM(L172*T172) -> 2320.78 | Z172: =SUM(X172-Y172) -> 0 | AA172: 121 | AB172: =IFERROR(VLOOKUP(A172,'Tash Lookup'!A:E,3,FALSE),"") -> 2320.78 | AC172: =IFERROR(AA172-T172,"") -> 0 | AD172: Pre-Clearance | AF172: 19.18 | AG172: =VLOOKUP(A172,Sheet1!$A$2:$C$1140,3,FALSE) -> #N/A | AH172: #N/A | AI172: =IF(ISNA(AH172),"Delete",IF(AH172=AF172,"Same",IF(AH172>AF172,"Increase","Decrease"))) -> Delete | AJ172: =IFERROR(AA172*AF172,0) -> 2320.78 | AK172: =IFERROR(AA172*AH172,0) -> 0 | AL172: Sundries / 3rd Party | AM172: Pre-Phase-out | AN172: 0 | AO172: 19.18 | AP172: =IF(AM172="Delete","Delete",IF(AO172=AF172,"Same",IF(AO172>AF172,"Increase","Decrease"))) -> Same | AQ172: =AN172*AF172 -> 0 | AR172: =AN172*AO172 -> 0 | AS172: =AR172-AQ172 -> 0
A173: 6188890 | B173: 6188890 | C173: DDEC01 | D173: Akzo DDC | E173: DDC Decorators Caulk Brown 380ML | F173: DDC Decorators Caulk Brown 380ML | H173: EA | I173: ITEM | J173: ITEM | K173: Paint | L173: 1.12 | M173: STD20 | N173: 3105 | R173: 1.74 | S173: 1.74 | T173: 120 | V173: 1.74 | W173: 1.12 | X173: =SUM(V173*T173) -> 208.8 | Y173: =SUM(L173*T173) -> 134.4 | Z173: =SUM(X173-Y173) -> 74.4 | AA173: 120 | AB173: =IFERROR(VLOOKUP(A173,'Tash Lookup'!A:E,3,FALSE),"") -> 133.98 | AC173: =IFERROR(AA173-T173,"") -> 0 | AD173: Pre-Phase-out | AF173: 1.74 | AG173: =VLOOKUP(A173,Sheet1!$A$2:$C$1140,3,FALSE) -> 1.74 | AH173: 1.74 | AI173: =IF(ISNA(AH173),"Delete",IF(AH173=AF173,"Same",IF(AH173>AF173,"Increase","Decrease"))) -> Same | AJ173: =IFERROR(AA173*AF173,0) -> 208.8 | AK173: =IFERROR(AA173*AH173,0) -> 208.8 | AL173: Sundries / 3rd Party | AM173: Normal | AN173: 175 | AO173: 1.74 | AP173: =IF(AM173="Delete","Delete",IF(AO173=AF173,"Same",IF(AO173>AF173,"Increase","Decrease"))) -> Same | AQ173: =AN173*AF173 -> 304.5 | AR173: =AN173*AO173 -> 304.5 | AS173: =AR173-AQ173 -> 0
...

Sheet Sheet1
A2: 5218583 | B2: Armstead TR Contract Matt Gardenia 10L | C2: 16.99
A3: 5218584 | B3: Armstead TR Contract Matt Magnolia 10L | C3: 17.47
A4: 5218585 | B4: Armstead TR Contract Matt Magnolia 15L | C4: 24.61
A5: 5219312 | B5: Armstead Trade Contract Matt Tinted Colours 10L | C5: 17.04
A6: 5218587 | B6: Armstead TR Contract Matt White 10L | C6: 12.5
A7: 5218588 | B7: Armstead TR Contract Matt White 15L | C7: 20.9
A8: 5196657 | B8: Dulux TR Drywall Primer Sealer 10L | C8: 35.34
A9: 5091283 | B9: Dulux TR Fast Matt Magnolia 10L | C9: 33
A10: 5090769 | B10: Dulux Trade Fast Matt Tinted Colours 10L | C10: 31.28
A11: 5091282 | B11: Dulux TR Fast Matt White 10L | C11: 30.37
A12: 5091671 | B12: Dulux TR AS Supermatt Almond White 10L | C12: 26.7
A13: 5091670 | B13: Dulux TR Supermatt Gardenia 10L | C13: 30
... A1140: 6188976 | B1140: Ronseal H/P Wood Filler White 550G | C1140: 11.17

Sheet Remove Old Items 
A1: No. | B1: Description | C1: Unit Cost
A2: 5025582A | B2: Sikkens Cetol BL Primer White 2.5L | C2: 34.21
A3: 5028159 | B3: DDC - SI CETOL NOVATOP 006 CHENE CLAIR 5L | C3: 61.99
A4: 5060367A | B4: Sikkens Rubbol XD Gloss White 2.5L | C4: 41.08
A5: 5074297A | B5: Rubbol satura wit 1l | C5: 17.99
A6: 5074298A | B6: Rubbol satura wit 2.5l | C6: 36.92
A7: 5077776A | B7: Poly Tr Stain Block 1L | C7: 15.61
A8: 5077788A | B8: Poly Tr Stain Block 2.5L | C8: 32.69
A9: 5081949A | B9: Dulux TR QD WD Primer U/Coat 2.5L | C9: 22.06
A10: 5081950A | B10: Dulux TR QD WD Primer U/Coat 5L | C10: 39.96
A11: 5081964A | B11: Dulux TR S/sheen PBW 5L | C11: 28.76
A12: 5081985A | B12: Dulux TR QD Opaque White 1L | C12: 15.48
A13: 5081986A | B13: Dulux TR QD Opaque White 2.5L | C13: 33.63
... A1747: 8188865 | B1747: Akzo DDC - DDC SHORT HANDLE STICK FRAME 4IN | C1747: 0.96558

Sheet Sheet3
A1: Item Number (global) | C1: Qty YTD 01/2023-12/2023
A2: 5074297 | B2: RUBBOL SATURA WIT 1L | C2: 1
A3: 5074298 | B3: RUBBOL SATURA WIT 2.5L | C3: 11
A4: 5074299 | B4: RUBBOL SATURA ZWART 1L | C4: 3
A5: 5077776 | B5: POLY TR STAIN BLOCK 1L | C5: 18
A6: 5077788 | B6: POLY TR STAIN BLOCK 2.5L | C6: 25
A7: 5081949 | B7: DULUX TR QD WD PRIMER U/COAT 2.5L | C7: 65
A8: 5081950 | B8: DULUX TR QD WD PRIMER U/COAT 5L | C8: 902
A9: 5081964 | B9: DULUX TR S/SHEEN PBW 5L | C9: 19
A10: 5081985 | B10: DULUX TR QD OPAQUE WHITE 1L | C10: 2
A11: 5081986 | B11: DULUX TR QD OPAQUE WHITE 2.5L | C11: 16
A12: 5081987 | B12: DULUX TR QD OPAQUE BLACK 1L | C12: 3
A13: 5081988 | B13: DULUX TR QD OPAQUE BLACK 2.5L | C13: 40
... A1599: 8002380 | B1599: REFUND HERITAGE TESTER POT | C1599: -5

Sheet Tash Lookup
A1: Item Number (global) | B1: SKU Name | C1: Sales All | D1: Qty YTD 01/2023-12/2023 | E1: Generic
A2: 5074297 | B2: RUBBOL SATURA WIT 1L | C2: 17.99 | D2: 1 | E2: =_xlfn.XLOOKUP(A2,'[1]query (5)'!$C:$C,'[1]query (5)'!$A:$A) -> #N/A
A3: 5074298 | B3: RUBBOL SATURA WIT 2.5L | C3: 406.11 | D3: 11 | E3: =_xlfn.XLOOKUP(A3,'[1]query (5)'!$C:$C,'[1]query (5)'!$A:$A) -> #N/A
A4: 5074299 | B4: RUBBOL SATURA ZWART 1L | C4: 55.46 | D4: 3 | E4: =_xlfn.XLOOKUP(A4,'[1]query (5)'!$C:$C,'[1]query (5)'!$A:$A) -> #N/A
A5: 5077776 | B5: POLY TR STAIN BLOCK 1L | C5: 275.27 | D5: 18 | E5: =_xlfn.XLOOKUP(A5,'[1]query (5)'!$C:$C,'[1]query (5)'!$A:$A) -> #N/A
A6: 5077788 | B6: POLY TR STAIN BLOCK 2.5L | C6: 815.26 | D6: 25 | E6: =_xlfn.XLOOKUP(A6,'[1]query (5)'!$C:$C,'[1]query (5)'!$A:$A) -> #N/A
A7: 5081949 | B7: DULUX TR QD WD PRIMER U/COAT 2.5L | C7: 1545.06 | D7: 66 | E7: =_xlfn.XLOOKUP(A7,'[1]query (5)'!$C:$C,'[1]query (5)'!$A:$A) -> #N/A
A8: 5081950 | B8: DULUX TR QD WD PRIMER U/COAT 5L | C8: 35280.97 | D8: 902 | E8: =_xlfn.XLOOKUP(A8,'[1]query (5)'!$C:$C,'[1]query (5)'!$A:$A) -> #N/A
A9: 5081964 | B9: DULUX TR S/SHEEN PBW 5L | C9: 546.43 | D9: 19 | E9: =_xlfn.XLOOKUP(A9,'[1]query (5)'!$C:$C,'[1]query (5)'!$A:$A) -> #N/A
A10: 5081985 | B10: DULUX TR QD OPAQUE WHITE 1L | C10: 30.96 | D10: 2 | E10: =_xlfn.XLOOKUP(A10,'[1]query (5)'!$C:$C,'[1]query (5)'!$A:$A) -> #N/A
A11: 5081986 | B11: DULUX TR QD OPAQUE WHITE 2.5L | C11: 546.11 | D11: 16 | E11: =_xlfn.XLOOKUP(A11,'[1]query (5)'!$C:$C,'[1]query (5)'!$A:$A) -> #N/A
A12: 5081987 | B12: DULUX TR QD OPAQUE BLACK 1L | C12: 46.44 | D12: 3 | E12: =_xlfn.XLOOKUP(A12,'[1]query (5)'!$C:$C,'[1]query (5)'!$A:$A) -> #N/A
A13: 5081988 | B13: DULUX TR QD OPAQUE BLACK 2.5L | C13: 1361.28 | D13: 40 | E13: =_xlfn.XLOOKUP(A13,'[1]query (5)'!$C:$C,'[1]query (5)'!$A:$A) -> #N/A
... A1632: 8002696 | B1632: DIAMONDMATTSCRATCHCARD | C1632: 0 | D1632: 9 | E1632: =_xlfn.XLOOKUP(A1632,'[1]query (5)'!$C:$C,'[1]query (5)'!$A:$A) -> #N/A
A1633: GROUPED | B1633: GROUPED | C1633: -56.84 | D1633: 0 | E1633: =_xlfn.XLOOKUP(A1633,'[1]query (5)'!$C:$C,'[1]query (5)'!$A:$A) -> #N/A
A1634: SUPPL GROUPED | B1634: SUPPL GROUPED | C1634: -131.07 | D1634: 0 | E1634: =_xlfn.XLOOKUP(A1634,'[1]query (5)'!$C:$C,'[1]query (5)'!$A:$A) -> #N/A
A1635: # | B1635: Not assigned | C1635: -625471.84 | D1635: 0 | E1635: =_xlfn.XLOOKUP(A1635,'[1]query (5)'!$C:$C,'[1]query (5)'!$A:$A) -> #N/A
A1636: 5090575 | C1636: 122.63 | D1636: 3
A1637: 5090590 | C1637: 504.29 | D1637: 15
A1638: 5090718 | C1638: 34785.6 | D1638: 932
A1639: 5090726 | C1639: 1323.76 | D1639: 120
A1640: 5090727 | C1640: 4691.4 | D1640: 216
A1641: 5090728 | C1641: 13776.83 | D1641: 375
A1642: 5090729 | C1642: 196.5 | D1642: 14
A1643: 5090732 | C1643: 680.69 | D1643: 41
A1644: 5090733 | C1644: 17120.65 | D1644: 512
A1645: 5090734 | C1645: 19986.55 | D1645: 365
A1646: 5090739 | C1646: 219.82 | D1646: 12
A1647: 5090740 | C1647: 1654.79 | D1647: 50
... A1759: 6412815 | C1759: 29.12 | D1759: 13
