Workbook

Sheet Workings 
L1: OLD | M1: NEW
A2: 6061706 | B2: CROW01 | C2: CROWN | D2: DE PROF CAULK WHITE 380ML | E2: CROWN - DE PROF CAULK WHITE 380ML | G2: 1.134 | H2: 1.11 | I2: 2408.9153 | J2: Down | L2: =SUM(G2*I2) -> 2731.71 | M2: =SUM(H2*I2) -> 2673.896 | O2: =SUM(M2:M807) -> 359066.93 | P2: =SUM(L2:L807) -> 366827.48 | Q2: =SUM(O2-P2) -> -7760.5576
A3: 5023891 | B3: CROW01 | C3: CROWN | D3: CRT Covermatt Obliterating Emulsion | E3: CROWN - CRT Covermatt Obliterating Emulsion | F3: White | G3: 23.76 | H3: 23.76 | I3: 1842 | J3: No Change | L3: =SUM(G3*I3) -> 43765.92 | M3: =SUM(H3*I3) -> 43765.92
A4: 6046432 | B4: CROW01 | C4: CROWN | D4: WA ANAGLYPTA PRECISION ROYAL OAK RD7000 | E4: CROWN - WA ANAGLYPTA PRECISION ROYAL OAK RD7000 | G4: 7.76 | H4: 7.76 | I4: 1597 | J4: No Change | L4: =SUM(G4*I4) -> 12392.72 | M4: =SUM(H4*I4) -> 12392.72
A5: 6058266 | B5: CROW01 | C5: CROWN | D5: DS FLUXAF POWER CLEAN 750ML | E5: CROWN - DS FLUXAF POWER CLEAN 750ML | G5: 7.98 | H5: 7.98 | I5: 1201 | J5: No Change | L5: =SUM(G5*I5) -> 9583.98 | M5: =SUM(H5*I5) -> 9583.98 | P5: 806 | Q5: total Skus YTD
A6: 6040482 | B6: CROW01 | C6: CROWN | D6: WA AS CREATION CASABLANCA 4 WALL | E6: CROWN - WA AS CREATION CASABLANCA 4 WALL | G6: 6.363 | H6: 6.55389 | I6: 941.44272 | J6: Up | L6: =SUM(G6*I6) -> 5990.4 | M6: =SUM(H6*I6) -> 6170.112 | P6: 666 | Q6: Up
A7: 5040579 | B7: CROW01 | C7: CROWN | D7: CRT Timonox Matt | E7: CROWN - CRT Timonox Matt | F7: Brilliant White | G7: 41.12 | H7: 41.12 | I7: 609 | J7: No Change | L7: =SUM(G7*I7) -> 25042.08 | M7: =SUM(H7*I7) -> 25042.08 | P7: 94 | Q7: No Change
A8: 5024010 | B8: CROW01 | C8: CROWN | D8: CRT Stronghold Masonry Smooth | E8: CROWN - CRT Stronghold Masonry Smooth | F8: Magnolia | G8: 20.32 | H8: 20.32 | I8: 540 | J8: No Change | L8: =SUM(G8*I8) -> 10972.8 | M8: =SUM(H8*I8) -> 10972.8 | P8: 46 | Q8: Down
A9: 6041133 | B9: CROW01 | C9: CROWN | D9: DS INDASA MTE MASKING TAPE 48MM | E9: CROWN - DS INDASA MTE MASKING TAPE 48MM | G9: 3.5 | H9: 3.3 | I9: 536 | J9: Down | L9: =SUM(G9*I9) -> 1876 | M9: =SUM(H9*I9) -> 1768.8
A10: 6061706 | B10: CROW01 | C10: CROWN | D10: DE PROF CAULK WHITE 380ML | E10: CROWN - DE PROF CAULK WHITE 380ML | G10: 1.134 | H10: 1.11 | I10: 437.84295 | J10: No Change | L10: =SUM(G10*I10) -> 496.51391 | M10: =SUM(H10*I10) -> 486.00568 | P10: =SUM(P6:P8) -> 806
A11: 5026956 | B11: CROW01 | C11: CROWN | D11: CRT Solvent-borne Full Gloss | E11: CROWN - CRT Solvent-borne Full Gloss | F11: White | G11: 25.72 | H11: 25.72 | I11: 434 | J11: No Change | L11: =SUM(G11*I11) -> 11162.48 | M11: =SUM(H11*I11) -> 11162.48
A12: 5024059 | B12: CROW01 | C12: CROWN | D12: CRT Vinyl Matt | E12: CROWN - CRT Vinyl Matt | F12: White | G12: 21.64 | H12: 21.64 | I12: 376 | J12: No Change | L12: =SUM(G12*I12) -> 8136.64 | M12: =SUM(H12*I12) -> 8136.64
A13: 6041126 | B13: CROW01 | C13: CROWN | D13: DS INDASA MTG MASKING TAPE 50MM 45MT | E13: CROWN - DS INDASA MTG MASKING TAPE 50MM 45MT | G13: 1.4 | H13: 1.4 | I13: 366 | J13: No Change | L13: =SUM(G13*I13) -> 512.4 | M13: =SUM(H13*I13) -> 512.4
A14: 5024174 | B14: CROW01 | C14: CROWN | D14: CRT Acrylic Primer Undercoat | E14: CROWN - CRT Acrylic Primer Undercoat | F14: White | G14: 18 | H14: 18 | I14: 325 | J14: No Change | L14: =SUM(G14*I14) -> 5850 | M14: =SUM(H14*I14) -> 5850
A15: 6062944 | B15: CROW01 | C15: CROWN | D15: DS Q1 CONTRACTOR MASKING TAPE 50M 48MM | E15: CROWN - DS Q1 CONTRACTOR MASKING TAPE 50M 48MM | G15: 2.1 | H15: 2.1 | I15: 297 | J15: No Change | L15: =SUM(G15*I15) -> 623.7 | M15: =SUM(H15*I15) -> 623.7
A16: 5027127 | B16: CROW01 | C16: CROWN | D16: CRT Solvent-borne Undercoat | E16: CROWN - CRT Solvent-borne Undercoat | F16: White | G16: 24.2 | H16: 24.2 | I16: 289 | J16: No Change | L16: =SUM(G16*I16) -> 6993.8 | M16: =SUM(H16*I16) -> 6993.8
A17: 5024026 | B17: CROW01 | C17: CROWN | D17: CRT Stronghold Masonry Smooth | E17: CROWN - CRT Stronghold Masonry Smooth | F17: White | G17: 20.32 | H17: 20.32 | I17: 258 | J17: No Change | L17: =SUM(G17*I17) -> 5242.56 | M17: =SUM(H17*I17) -> 5242.56
A18: 5027850 | B18: CROW01 | C18: CROWN | D18: MAC Powerkote Masonry Smooth | E18: CROWN - MAC Powerkote Masonry Smooth | F18: Magnolia | G18: 22.45 | H18: 23.12 | I18: 194 | J18: Up | L18: =SUM(G18*I18) -> 4355.3 | M18: =SUM(H18*I18) -> 4485.28
A19: 5094753 | B19: CROW01 | C19: CROWN | D19: CRT Alkali Resistant Primer PX4 - W/BASED | E19: CROWN - CRT Alkali Resistant Primer PX4 - W/BASED | F19: Off White | G19: 35.56 | H19: 35.56 | I19: 184 | J19: No Change | L19: =SUM(G19*I19) -> 6543.04 | M19: =SUM(H19*I19) -> 6543.04
A20: 5061839 | B20: CROW01 | C20: CROWN | D20: CRT Clean Extreme | E20: CROWN - CRT Clean Extreme | F20: Magnolia | G20: 25.97 | H20: 25.97 | I20: 177 | J20: No Change | L20: =SUM(G20*I20) -> 4596.69 | M20: =SUM(H20*I20) -> 4596.69
A21: 5025052 | B21: CROW01 | C21: CROWN | D21: MAC Eclipse | E21: CROWN - MAC Eclipse | F21: Magnolia | G21: 19.92 | H21: 20.52 | I21: 162 | J21: Up | L21: =SUM(G21*I21) -> 3227.04 | M21: =SUM(H21*I21) -> 3324.24
A22: 6055142 | B22: CROW01 | C22: CROWN | D22: DS ULTRAGRIME PRO XXL+MULTI WIPES 100PK | E22: CROWN - DS ULTRAGRIME PRO XXL+MULTI WIPES 100PK | G22: 13.7445 | H22: 13.5 | I22: 159.33646 | J22: Down | L22: =SUM(G22*I22) -> 2190 | M22: =SUM(H22*I22) -> 2151.0422
A23: 5025056 | B23: CROW01 | C23: CROWN | D23: MAC Eclipse | E23: CROWN - MAC Eclipse | F23: Brilliant White | G23: 18.27 | H23: 18.82 | I23: 158 | J23: Up | L23: =SUM(G23*I23) -> 2886.66 | M23: =SUM(H23*I23) -> 2973.56
A24: 5061965 | B24: CROW01 | C24: CROWN | D24: CRT Clean Extreme | E24: CROWN - CRT Clean Extreme | F24: White | G24: 25.04 | H24: 25.04 | I24: 152 | J24: No Change | L24: =SUM(G24*I24) -> 3806.08 | M24: =SUM(H24*I24) -> 3806.08
A25: 5090804 | B25: CROW01 | C25: CROWN | D25: CRT Fastflow Quick Dry Gloss | E25: CROWN - CRT Fastflow Quick Dry Gloss | F25: White | G25: 25.29 | H25: 26.05 | I25: 151 | J25: Up | L25: =SUM(G25*I25) -> 3818.79 | M25: =SUM(H25*I25) -> 3933.55
A26: 6042334 | B26: CROW01 | C26: CROWN | D26: DS PRODEC EXTRA LONG POLYESTER ROL 9IN | E26: CROWN - DS PRODEC EXTRA LONG POLYESTER ROL 9IN | G26: 3.402 | H26: 3.4 | I26: 149.91182 | J26: No Change | L26: =SUM(G26*I26) -> 510 | M26: =SUM(H26*I26) -> 509.70018
A27: 5090816 | B27: CROW01 | C27: CROWN | D27: CRT Fastflow Quick Dry Primer Undercoat | E27: CROWN - CRT Fastflow Quick Dry Primer Undercoat | F27: White | G27: 26 | H27: 26 | I27: 147 | J27: No Change | L27: =SUM(G27*I27) -> 3822 | M27: =SUM(H27*I27) -> 3822
A28: 6055912 | B28: CROW01 | C28: CROWN | D28: DS TRIMACO BROWN MASKING PAPER 180FT | E28: CROWN - DS TRIMACO BROWN MASKING PAPER 180FT | G28: 5.25 | H28: 5.4075 | I28: 140 | J28: Up | L28: =SUM(G28*I28) -> 735 | M28: =SUM(H28*I28) -> 757.05
A29: 5024213 | B29: CROW01 | C29: CROWN | D29: CRT Silk | E29: CROWN - CRT Silk | F29: Magnolia | G29: 28.09 | H29: 28.09 | I29: 138 | J29: No Change | L29: =SUM(G29*I29) -> 3876.42 | M29: =SUM(H29*I29) -> 3876.42
A30: 5064671 | B30: CROW01 | C30: CROWN | D30: CRT Acrylic Eggshell | E30: CROWN - CRT Acrylic Eggshell | F30: Magnolia | G30: 26.14 | H30: 26.14 | I30: 135 | J30: No Change | L30: =SUM(G30*I30) -> 3528.9 | M30: =SUM(H30*I30) -> 3528.9
A31: 6055707 | B31: CROW01 | C31: CROWN | D31: DS OAKEY FLEXIBLE FINISH PADS EX MED/CRS | E31: CROWN - DS OAKEY FLEXIBLE FINISH PADS EX MED/CRS | G31: 1.11 | H31: 1.11 | I31: 133 | J31: No Change | L31: =SUM(G31*I31) -> 147.63 | M31: =SUM(H31*I31) -> 147.63
A32: 5093395 | B32: CROW01 | C32: CROWN | D32: CRT Clean Extreme Mould Inhibiting Matt | E32: CROWN - CRT Clean Extreme Mould Inhibiting Matt | F32: White | G32: 33.87 | H32: 33.87 | I32: 125 | J32: No Change | L32: =SUM(G32*I32) -> 4233.75 | M32: =SUM(H32*I32) -> 4233.75
A33: 5091987 | B33: CROW01 | C33: CROWN | D33: CRT Fastflow QD Satin | E33: CROWN - CRT Fastflow QD Satin | F33: White | G33: 28 | H33: 28 | I33: 122 | J33: No Change | L33: =SUM(G33*I33) -> 3416 | M33: =SUM(H33*I33) -> 3416
A34: 6061964 | B34: CROW01 | C34: CROWN | D34: DS HAMILTON MEDIUM PILE ROLLER 4IN 10PK | E34: CROWN - DS HAMILTON MEDIUM PILE ROLLER 4IN 10PK | G34: 4.095 | H34: 4.1 | I34: 119.1453 | J34: Up | L34: =SUM(G34*I34) -> 487.9 | M34: =SUM(H34*I34) -> 488.49573
A35: 5026990 | B35: CROW01 | C35: CROWN | D35: CRT Solvent-borne Full Gloss | E35: CROWN - CRT Solvent-borne Full Gloss | F35: Brilliant White | G35: 19.68 | H35: 20.27 | I35: 118 | J35: Up | L35: =SUM(G35*I35) -> 2322.24 | M35: =SUM(H35*I35) -> 2391.86
A36: 6040483 | B36: CROW01 | C36: CROWN | D36: WA AS CREATION CASABLANCA 4 WALL | E36: CROWN - WA AS CREATION CASABLANCA 4 WALL | G36: 5.25 | H36: 5.4075 | I36: 117.71429 | J36: Up | L36: =SUM(G36*I36) -> 618 | M36: =SUM(H36*I36) -> 636.54
A37: 5073961 | B37: CROW01 | C37: CROWN | D37: ST RUST INHIB PRIMER GREY 2.5L | E37: CROWN - ST RUST INHIB PRIMER GREY 2.5L | G37: 44.3209 | H37: 40 | I37: 112.99771 | J37: Down | L37: =SUM(G37*I37) -> 5008.16 | M37: =SUM(H37*I37) -> 4519.9082
A38: 6040125 | B38: CROW01 | C38: CROWN | D38: WA ANAGLYPTA TEXT VINYL WILL BO RD804301 | E38: CROWN - WA ANAGLYPTA TEXT VINYL WILL BO RD804301 | G38: 4.94 | H38: 5.0882 | I38: 107 | J38: Up | L38: =SUM(G38*I38) -> 528.58 | M38: =SUM(H38*I38) -> 544.4374
A39: 6055201 | B39: CROW01 | C39: CROWN | D39: DE ESS PAINT BRUSH 2IN(12) EACH | E39: CROWN - DE ESS PAINT BRUSH 2IN(12) EACH | G39: 1.42 | H39: 1.42 | I39: 103 | J39: No Change | L39: =SUM(G39*I39) -> 146.26 | M39: =SUM(H39*I39) -> 146.26
A40: 6062917 | B40: CROW01 | C40: CROWN | D40: WA FINE DECOR CONTRACTOR BOOK 23 A | E40: CROWN - WA FINE DECOR CONTRACTOR BOOK 23 A | G40: 10.5 | H40: 10.815 | I40: 102.85714 | J40: Up | L40: =SUM(G40*I40) -> 1080 | M40: =SUM(H40*I40) -> 1112.4
A41: 6042316 | B41: CROW01 | C41: CROWN | D41: DS BLACKROCK PAINTERS L/W GRIPPER GLOVES | E41: CROWN - DS BLACKROCK PAINTERS L/W GRIPPER GLOVES | G41: 3.4125 | H41: 3.41 | I41: 96.923077 | J41: No Change | L41: =SUM(G41*I41) -> 330.75 | M41: =SUM(H41*I41) -> 330.50769
A42: 6048267 | B42: CROW01 | C42: CROWN | D42: DE WHITE SPIRIT 2L | E42: CROWN - DE WHITE SPIRIT 2L | G42: 3.09 | H42: 3.09 | I42: 93 | J42: No Change | L42: =SUM(G42*I42) -> 287.37 | M42: =SUM(H42*I42) -> 287.37
A43: 6062918 | B43: CROW01 | C43: CROWN | D43: WA FINE DECOR CONTRACTOR BOOK 23 B | E43: CROWN - WA FINE DECOR CONTRACTOR BOOK 23 B | G43: 10.5 | H43: 10.815 | I43: 91.428571 | J43: Up | L43: =SUM(G43*I43) -> 960 | M43: =SUM(H43*I43) -> 988.8
A44: 6062122 | B44: CROW01 | C44: CROWN | D44: DS HIPPO MP BAMBOO DRY CLOTH 60 SHEETS | E44: CROWN - DS HIPPO MP BAMBOO DRY CLOTH 60 SHEETS | G44: 10.815 | H44: 10.82 | I44: 90.041609 | J44: No Change | L44: =SUM(G44*I44) -> 973.8 | M44: =SUM(H44*I44) -> 974.25021
A45: 5064686 | B45: CROW01 | C45: CROWN | D45: CRT Acrylic Eggshell | E45: CROWN - CRT Acrylic Eggshell | F45: White | G45: 24.03 | H45: 17.4 | I45: 89.313358 | J45: Down | L45: =SUM(G45*I45) -> 2146.2 | M45: =SUM(H45*I45) -> 1554.0524
A46: 5023888 | B46: CROW01 | C46: CROWN | D46: CRT Covermatt Obliterating Emulsion | E46: CROWN - CRT Covermatt Obliterating Emulsion | F46: Magnolia | G46: 23.44 | H46: 23.44 | I46: 89 | J46: No Change | L46: =SUM(G46*I46) -> 2086.16 | M46: =SUM(H46*I46) -> 2086.16
A47: 6048367 | B47: CROW01 | C47: CROWN | D47: DS ZINSSER DIF WALLPAPER STRIPPER 1L | E47: CROWN - DS ZINSSER DIF WALLPAPER STRIPPER 1L | G47: 10.76 | H47: 10.76 | I47: 86 | J47: No Change | L47: =SUM(G47*I47) -> 925.36 | M47: =SUM(H47*I47) -> 925.36
A48: 5028843 | B48: CROW01 | C48: CROWN | D48: SD SUPERDEC BASE CLEAR 065 5L | E48: CROWN - SD SUPERDEC BASE CLEAR 065 5L | F48: Clear | G48: 74.29 | H48: 35 | I48: 84.8028 | J48: Down | L48: =SUM(G48*I48) -> 6300 | M48: =SUM(H48*I48) -> 2968.098
A49: 5074313 | B49: CROW01 | C49: CROWN | D49: CRT Satin | E49: CROWN - CRT Satin | F49: White | G49: 26.39 | H49: 26.39 | I49: 82 | J49: No Change | L49: =SUM(G49*I49) -> 2163.98 | M49: =SUM(H49*I49) -> 2163.98
A50: 6042131 | B50: CROW01 | C50: CROWN | D50: DS PRESTIGE BUCKET 15L | E50: CROWN - DS PRESTIGE BUCKET 15L | G50: 4.97 | H50: 4.97 | I50: 82 | J50: No Change | L50: =SUM(G50*I50) -> 407.54 | M50: =SUM(H50*I50) -> 407.54
A51: 6040118 | B51: CROW01 | C51: CROWN | D51: WA ANAGLYPTA TEXT VINYL HAVERSHAM 34365 | E51: CROWN - WA ANAGLYPTA TEXT VINYL HAVERSHAM 34365 | G51: 4.94 | H51: 4.94 | I51: 79 | J51: No Change | L51: =SUM(G51*I51) -> 390.26 | M51: =SUM(H51*I51) -> 390.26
A52: 6042090 | B52: CROW01 | C52: CROWN | D52: DS PERFECTION ROLLER X LONG 9IN | E52: CROWN - DS PERFECTION ROLLER X LONG 9IN | G52: 5.75 | H52: 5.75 | I52: 78 | J52: No Change | L52: =SUM(G52*I52) -> 448.5 | M52: =SUM(H52*I52) -> 448.5
A53: 6040197 | B53: CROW01 | C53: CROWN | D53: WA ERFURT LINING 1200 DOUBLE | E53: CROWN - WA ERFURT LINING 1200 DOUBLE | G53: 4.19 | H53: 4.19 | I53: 78 | J53: No Change | L53: =SUM(G53*I53) -> 326.82 | M53: =SUM(H53*I53) -> 326.82
A54: 6060622 | B54: CROW01 | C54: CROWN | D54: DS ULTRAGRIME PRO POWER SCRUB XXL+ 80PK | E54: CROWN - DS ULTRAGRIME PRO POWER SCRUB XXL+ 80PK | G54: 15.0045 | H54: 15 | I54: 74.044453 | J54: No Change | L54: =SUM(G54*I54) -> 1111 | M54: =SUM(H54*I54) -> 1110.6668
A55: 6055424 | B55: CROW01 | C55: CROWN | D55: DE PROFESSIONAL MEDUIM GPUR ROLLER 4IN | E55: CROWN - DE PROFESSIONAL MEDUIM GPUR ROLLER 4IN | G55: 0.39 | H55: 0.39 | I55: 74 | J55: No Change | L55: =SUM(G55*I55) -> 28.86 | M55: =SUM(H55*I55) -> 28.86
A56: 6041657 | B56: CROW01 | C56: CROWN | D56: DS PRODEC REFUSE SACKS 10PK | E56: CROWN - DS PRODEC REFUSE SACKS 10PK | G56: 2.15 | H56: 2.15 | I56: 72 | J56: No Change | L56: =SUM(G56*I56) -> 154.8 | M56: =SUM(H56*I56) -> 154.8
A57: 6040768 | B57: CROW01 | C57: CROWN | D57: DS SOLVITE ALL PURPOSE +50% 30ROLL | E57: CROWN - DS SOLVITE ALL PURPOSE +50% 30ROLL | G57: 6.6465 | H57: 6.845895 | I57: 70.074475 | J57: Up | L57: =SUM(G57*I57) -> 465.75 | M57: =SUM(H57*I57) -> 479.7225
A58: 6042877 | B58: CROW01 | C58: CROWN | D58: DS CIRET BAG OF RAGS COLOURED 10K | E58: CROWN - DS CIRET BAG OF RAGS COLOURED 10K | G58: 33.0855 | H58: 33.09 | I58: 68.009249 | J58: No Change | L58: =SUM(G58*I58) -> 2250.12 | M58: =SUM(H58*I58) -> 2250.426
A59: 5093393 | B59: CROW01 | C59: CROWN | D59: CRT Clean Extreme Mould Inhibiting Matt | E59: CROWN - CRT Clean Extreme Mould Inhibiting Matt | F59: Magnolia | G59: 33.87 | H59: 33.87 | I59: 68 | J59: No Change | L59: =SUM(G59*I59) -> 2303.16 | M59: =SUM(H59*I59) -> 2303.16
A60: 5074787 | B60: CROW01 | C60: CROWN | D60: CRT Timonox Bonding Primer | E60: CROWN - CRT Timonox Bonding Primer | F60: White | G60: 44 | H60: 44 | I60: 66 | J60: No Change | L60: =SUM(G60*I60) -> 2904 | M60: =SUM(H60*I60) -> 2904
A61: 5088424 | B61: CROW01 | C61: CROWN | D61: CRT Flexarb Opaque | E61: CROWN - CRT Flexarb Opaque | F61: Brown | G61: 45 | H61: 45 | I61: 65 | J61: No Change | L61: =SUM(G61*I61) -> 2925 | M61: =SUM(H61*I61) -> 2925
A62: 6042088 | B62: CROW01 | C62: CROWN | D62: DS PERFECTION ROLLER MEDIUM 9IN | E62: CROWN - DS PERFECTION ROLLER MEDIUM 9IN | G62: 3.75 | H62: 3.75 | I62: 64 | J62: No Change | L62: =SUM(G62*I62) -> 240 | M62: =SUM(H62*I62) -> 240
A63: 6063177 | B63: CROW01 | C63: CROWN | D63: DS BARTOLINE 1876 AP ADHESIVE 30 ROLL | E63: CROWN - DS BARTOLINE 1876 AP ADHESIVE 30 ROLL | G63: 4.3785 | H63: 4.38 | I63: 59.06589 | J63: No Change | L63: =SUM(G63*I63) -> 258.62 | M63: =SUM(H63*I63) -> 258.7086
A64: 5028216 | B64: CROW01 | C64: CROWN | D64: ST 365 SMOOTH BRIL WHITE 5L | E64: CROWN - ST 365 SMOOTH BRIL WHITE 5L | G64: 39.4 | H64: 35 | I64: 59 | J64: Down | L64: =SUM(G64*I64) -> 2324.6 | M64: =SUM(H64*I64) -> 2065
A65: 6061968 | B65: CROW01 | C65: CROWN | D65: DS HAMILTON LONG PILE ROLLER 9IN | E65: CROWN - DS HAMILTON LONG PILE ROLLER 9IN | G65: 3.318 | H65: 3.32 | I65: 57.034358 | J65: Up | L65: =SUM(G65*I65) -> 189.24 | M65: =SUM(H65*I65) -> 189.35407
A66: 6055204 | B66: CROW01 | C66: CROWN | D66: DE ESS PAINT BRUSH BOX SET(1) EACH | E66: CROWN - DE ESS PAINT BRUSH BOX SET(1) EACH | G66: 6.86 | H66: 6.86 | I66: 57 | J66: No Change | L66: =SUM(G66*I66) -> 391.02 | M66: =SUM(H66*I66) -> 391.02
A67: 6048207 | B67: CROW01 | C67: CROWN | D67: DS REPAIR CARE DRY FLEX 4 | E67: CROWN - DS REPAIR CARE DRY FLEX 4 | G67: 56.7 | H67: 56.7 | I67: 56.266667 | J67: No Change | L67: =SUM(G67*I67) -> 3190.32 | M67: =SUM(H67*I67) -> 3190.32
A68: 5090815 | B68: CROW01 | C68: CROWN | D68: CRT Fastflow Quick Dry Primer Undercoat | E68: CROWN - CRT Fastflow Quick Dry Primer Undercoat | F68: White | G68: 14.01 | H68: 14.01 | I68: 56 | J68: No Change | L68: =SUM(G68*I68) -> 784.56 | M68: =SUM(H68*I68) -> 784.56
A69: 6040959 | B69: CROW01 | C69: CROWN | D69: DS GYPROC EASI-FILL 60 5K | E69: CROWN - DS GYPROC EASI-FILL 60 5K | G69: 12.2745 | H69: 12.642735 | I69: 54.979836 | J69: Up | L69: =SUM(G69*I69) -> 674.85 | M69: =SUM(H69*I69) -> 695.0955
A70: 5024058 | B70: CROW01 | C70: CROWN | D70: CRT Vinyl Matt | E70: CROWN - CRT Vinyl Matt | F70: White | G70: 12.1 | H70: 12.1 | I70: 54 | J70: No Change | L70: =SUM(G70*I70) -> 653.4 | M70: =SUM(H70*I70) -> 653.4
A71: 5090803 | B71: CROW01 | C71: CROWN | D71: CRT Fastflow Quick Dry Gloss | E71: CROWN - CRT Fastflow Quick Dry Gloss | F71: White | G71: 14.01 | H71: 14.42 | I71: 54 | J71: Up | L71: =SUM(G71*I71) -> 756.54 | M71: =SUM(H71*I71) -> 778.68
A72: 5024011 | B72: CROW01 | C72: CROWN | D72: CRT Stronghold Masonry Smooth | E72: CROWN - CRT Stronghold Masonry Smooth | F72: Magnolia | G72: 44.89 | H72: 39 | I72: 52.996213 | J72: Down | L72: =SUM(G72*I72) -> 2379 | M72: =SUM(H72*I72) -> 2066.8523
A73: 5070051 | B73: CROW01 | C73: CROWN | D73: CRT Clean Extreme | E73: CROWN - CRT Clean Extreme | F73: White | G73: 45.63 | H73: 45.63 | I73: 52 | J73: No Change | L73: =SUM(G73*I73) -> 2372.76 | M73: =SUM(H73*I73) -> 2372.76
A74: 5092102 | B74: CROW01 | C74: CROWN | D74: CRT Pro Co High Build Rust Inhibit Metal | E74: CROWN - CRT Pro Co High Build Rust Inhibit Metal | F74: Colour | G74: 21.93 | H74: 22.59 | I74: 51 | J74: Up | L74: =SUM(G74*I74) -> 1118.43 | M74: =SUM(H74*I74) -> 1152.09
A75: 5025084 | B75: CROW01 | C75: CROWN | D75: MAC Vinyl Matt | E75: CROWN - MAC Vinyl Matt | F75: Brilliant White | G75: 11 | H75: 11.33 | I75: 51 | J75: Up | L75: =SUM(G75*I75) -> 561 | M75: =SUM(H75*I75) -> 577.83
A76: 6042089 | B76: CROW01 | C76: CROWN | D76: DS PERFECTION ROLLER LONG 9IN | E76: CROWN - DS PERFECTION ROLLER LONG 9IN | G76: 4.5 | H76: 4.5 | I76: 49 | J76: No Change | L76: =SUM(G76*I76) -> 220.5 | M76: =SUM(H76*I76) -> 220.5
A77: 6062061 | B77: CROW01 | C77: CROWN | D77: WA GALERIE CDC HOME INSPIRATION B | E77: CROWN - WA GALERIE CDC HOME INSPIRATION B | G77: 18.375 | H77: 18.92625 | I77: 48.87619 | J77: Up | L77: =SUM(G77*I77) -> 898.1 | M77: =SUM(H77*I77) -> 925.043
A78: 6053484 | B78: CROW01 | C78: CROWN | D78: DS BLACKROCK PAINTERS LW GRIPPER GLOVE | E78: CROWN - DS BLACKROCK PAINTERS LW GRIPPER GLOVE | G78: 1.659 | H78: 1.66 | I78: 47.02833 | J78: No Change | L78: =SUM(G78*I78) -> 78.02 | M78: =SUM(H78*I78) -> 78.067028
A79: 6041658 | B79: CROW01 | C79: CROWN | D79: DS PRODEC REFUSE SACKS 50 ROLL | E79: CROWN - DS PRODEC REFUSE SACKS 50 ROLL | G79: 8.3055 | H79: 8.31 | I79: 47.025465 | J79: No Change | L79: =SUM(G79*I79) -> 390.57 | M79: =SUM(H79*I79) -> 390.78161
A80: 6042110 | B80: CROW01 | C80: CROWN | D80: DS PRESTIGE CAGE FRAME 9IN | E80: CROWN - DS PRESTIGE CAGE FRAME 9IN | G80: 5.75 | H80: 5.75 | I80: 47 | J80: No Change | L80: =SUM(G80*I80) -> 270.25 | M80: =SUM(H80*I80) -> 270.25
A81: 6040960 | B81: CROW01 | C81: CROWN | D81: DS GYPROC JOINT FILLER 12.5K | E81: CROWN - DS GYPROC JOINT FILLER 12.5K | G81: 16.7895 | H81: 17.293185 | I81: 45.54275 | J81: Up | L81: =SUM(G81*I81) -> 764.64 | M81: =SUM(H81*I81) -> 787.5792
A82: 6041059 | B82: CROW01 | C82: CROWN | D82: DS ZINSSER COVER STAIN 5L | E82: CROWN - DS ZINSSER COVER STAIN 5L | G82: 47.66 | H82: 47.66 | I82: 45 | J82: No Change | L82: =SUM(G82*I82) -> 2144.7 | M82: =SUM(H82*I82) -> 2144.7
A83: 6060533 | B83: CROW01 | C83: CROWN | D83: DS TOUPRET EXT MASONRY POWDER FILL 5K | E83: CROWN - DS TOUPRET EXT MASONRY POWDER FILL 5K | G83: 35.322 | H83: 26.93 | I83: 44.208425 | J83: Down | L83: =SUM(G83*I83) -> 1561.53 | M83: =SUM(H83*I83) -> 1190.5329
A84: 6046572 | B84: CROW01 | C84: CROWN | D84: DS INDASA TUNGSTEN CARBIDE BLADES 50MM | E84: CROWN - DS INDASA TUNGSTEN CARBIDE BLADES 50MM | G84: 10.5525 | H84: 10.869075 | I84: 44.065387 | J84: Up | L84: =SUM(G84*I84) -> 465 | M84: =SUM(H84*I84) -> 478.95
A85: 5088422 | B85: CROW01 | C85: CROWN | D85: CRT Flexarb Opaque | E85: CROWN - CRT Flexarb Opaque | F85: Black | G85: 45 | H85: 45 | I85: 44 | J85: No Change | L85: =SUM(G85*I85) -> 1980 | M85: =SUM(H85*I85) -> 1980
A86: 5026955 | B86: CROW01 | C86: CROWN | D86: CRT Solvent-borne Full Gloss | E86: CROWN - CRT Solvent-borne Full Gloss | F86: White | G86: 11.45 | H86: 11.79 | I86: 43 | J86: Up | L86: =SUM(G86*I86) -> 492.35 | M86: =SUM(H86*I86) -> 506.97
A87: 5025063 | B87: CROW01 | C87: CROWN | D87: MAC Acrylic Eggshell | E87: CROWN - MAC Acrylic Eggshell | F87: Magnolia | G87: 21.25 | H87: 21.88 | I87: 42 | J87: Up | L87: =SUM(G87*I87) -> 892.5 | M87: =SUM(H87*I87) -> 918.96
A88: 6041055 | B88: CROW01 | C88: CROWN | D88: DS ZINSSER BIN PRIMER WHITE 5L | E88: CROWN - DS ZINSSER BIN PRIMER WHITE 5L | G88: 77.29 | H88: 77.29 | I88: 42 | J88: No Change | L88: =SUM(G88*I88) -> 3246.18 | M88: =SUM(H88*I88) -> 3246.18
A89: 6055310 | B89: CROW01 | C89: CROWN | D89: DS PRODEC PREM SYN BRUSH SET + ANG 6PC | E89: CROWN - DS PRODEC PREM SYN BRUSH SET + ANG 6PC | G89: 17.514 | H89: 18.03942 | I89: 39.990864 | J89: Up | L89: =SUM(G89*I89) -> 700.4 | M89: =SUM(H89*I89) -> 721.412
A90: 5025077 | B90: CROW01 | C90: CROWN | D90: MAC Vinyl Matt | E90: CROWN - MAC Vinyl Matt | F90: Magnolia | G90: 23.54 | H90: 24.24 | I90: 39 | J90: Up | L90: =SUM(G90*I90) -> 918.06 | M90: =SUM(H90*I90) -> 945.36
A91: 5091205 | B91: CROW01 | C91: CROWN | D91: ST HIGHCOVER SMOOTH Plat Base 10L | E91: CROWN - ST HIGHCOVER SMOOTH Plat Base 10L | G91: 48.5027 | H91: 49.96 | I91: 38.997829 | J91: Up | L91: =SUM(G91*I91) -> 1891.5 | M91: =SUM(H91*I91) -> 1948.3315
A92: 6041136 | B92: CROW01 | C92: CROWN | D92: DS INDASA RHYNOLITE YEL 120G 115MMX10M | E92: CROWN - DS INDASA RHYNOLITE YEL 120G 115MMX10M | G92: 3.86 | H92: 3.86 | I92: 38 | J92: No Change | L92: =SUM(G92*I92) -> 146.68 | M92: =SUM(H92*I92) -> 146.68
A93: 5089340 | B93: CROW01 | C93: CROWN | D93: ST METAL GLOSS X-TRA BLACK 2.5L | E93: CROWN - ST METAL GLOSS X-TRA BLACK 2.5L | G93: 40.0876 | H93: 25.93 | I93: 37.002215 | J93: Down | L93: =SUM(G93*I93) -> 1483.33 | M93: =SUM(H93*I93) -> 959.46744
A94: 6041130 | B94: CROW01 | C94: CROWN | D94: DS INDASA COVERALL 1200MM 25M | E94: CROWN - DS INDASA COVERALL 1200MM 25M | G94: 7.707 | H94: 7.93821 | I94: 36.590113 | J94: Up | L94: =SUM(G94*I94) -> 282 | M94: =SUM(H94*I94) -> 290.46
A95: 6055212 | B95: CROW01 | C95: CROWN | D95: DE PROF SYN FLMNT BRUSH 2IN (12) EACH | E95: CROWN - DE PROF SYN FLMNT BRUSH 2IN (12) EACH | G95: 1.73 | H95: 1.78 | I95: 36 | J95: Up | L95: =SUM(G95*I95) -> 62.28 | M95: =SUM(H95*I95) -> 64.08
A96: 5024052 | B96: CROW01 | C96: CROWN | D96: CRT Vinyl Matt | E96: CROWN - CRT Vinyl Matt | F96: Magnolia | G96: 27.72 | H96: 23.5 | I96: 35.606061 | J96: Down | L96: =SUM(G96*I96) -> 987 | M96: =SUM(H96*I96) -> 836.74242
A97: 5024072 | B97: CROW01 | C97: CROWN | D97: CRT Vinyl Matt | E97: CROWN - CRT Vinyl Matt | F97: Brilliant White | G97: 28.06 | H97: 24.5 | I97: 34.92516 | J97: Down | L97: =SUM(G97*I97) -> 980 | M97: =SUM(H97*I97) -> 855.66643
A98: 6055214 | B98: CROW01 | C98: CROWN | D98: DE PROF SYN FLMNT BRUSH BOX SET(1) EACH | E98: CROWN - DE PROF SYN FLMNT BRUSH BOX SET(1) EACH | G98: 7.86 | H98: 7.86 | I98: 34 | J98: No Change | L98: =SUM(G98*I98) -> 267.24 | M98: =SUM(H98*I98) -> 267.24
A99: 6042135 | B99: CROW01 | C99: CROWN | D99: DS PERFORMANCE KETTLE 2.5L | E99: CROWN - DS PERFORMANCE KETTLE 2.5L | G99: 0.76 | H99: 0.78 | I99: 34 | J99: Up | L99: =SUM(G99*I99) -> 25.84 | M99: =SUM(H99*I99) -> 26.52
A100: 6056954 | B100: CROW01 | C100: CROWN | D100: DS PRODEC POLY DUST SHEET ROLL 50M | E100: CROWN - DS PRODEC POLY DUST SHEET ROLL 50M | G100: 3.6225 | H100: 3.731175 | I100: 33.976536 | J100: Up | L100: =SUM(G100*I100) -> 123.08 | M100: =SUM(H100*I100) -> 126.7724
...

Sheet Crown Aug Uploads 
A1: Enter your Item No We can't have duplicates in the system so if the cell highlights blue, you need to add ; at the end enough times to make unique Limited to 20 characters, yellow if more than this, need to cut down | B1: Enter your number (without any ; if you needed to add any in the 'No' field for duplicates) Again limited to 20 characters, need to cut down if yellow (Might be same as column A) | C1: Enter Vendor Number from Vendor List (new ERP number) | D1: Enter the suppliers name (doesn't need to be full legal one, this is just for description | E1: Paste in the suppliers description of the item | F1: Drag formula down after completing D & E Formula will combine the prior to cells We are though restricted to 50 characters so if the cell highlights in yellow it's too long, need to cut down, or move excess to description 2 column | G1: Enter if need more space to describe the Item | H1: Enter unit of measure | I1: Enter either "ITEM" or "PLANT" | J1: Enter "EXT-PLANT" or "ITEM" | K1: Enter category code to help group the items together, see "Category Code" for ones we've used so far Can add to this list though | L1: September 2022 Price | M1: Enter "STD20" unless you know it's not Vatable Alternatively, "REDUCED" or "ZERO" | N1: Enter a cost code for materials or plant (unless it's an overhead like stationery in which case can leave blank) | O1: Updated Template Pricing March 2023 | P1: QTY PURCHASED 2022 | Q1: June 2023 Price | R1: New Cost from Aug 2024 | S1: QTY PURCHASED 2024
A2: 6061706 | B2: 6061706 | C2: CROW01 | D2: CROWN | E2: =_xlfn.XLOOKUP(B2,Sheet1!A:A,Sheet1!B:B) -> DE PROF CAULK WHITE 380ML | F2: =D2&" - "&E2 -> CROWN - DE PROF CAULK WHITE 380ML | H2: Each | I2: Item | J2: Item | K2: Paint | M2: STD20 | N2: 3105 | O2: =_xlfn.XLOOKUP(B2,Sheet1!A:A,Sheet1!E:E) -> 1.08 | P2: =_xlfn.XLOOKUP(A2,Sheet2!F:F,Sheet2!H:H) -> 5364.9352 | Q2: =O2*1.05 -> 1.134 | R2: =_xlfn.XLOOKUP(B2,Sheet4!B:B,Sheet4!D:D) -> 1.11 | S2: 2408.9153 | T2: =IF(Q2>=R2,"No Change","Up") -> No Change | V2: =SUM(Q2*S2) -> 2731.71 | W2: =SUM(R2*S2) -> 2673.896
A3: 5023891 | B3: 5023891 | C3: CROW01 | D3: CROWN | E3: =_xlfn.XLOOKUP(B3,Sheet1!A:A,Sheet1!B:B) -> CRT Covermatt Obliterating Emulsion | F3: =D3&" - "&E3 -> CROWN - CRT Covermatt Obliterating Emulsion | G3: =_xlfn.XLOOKUP(B3,Sheet1!A:A,Sheet1!C:C) -> White | H3: =_xlfn.XLOOKUP(B3,Sheet1!A:A,Sheet1!D:D) -> 10L | I3: Item | J3: Item | K3: Paint | L3: 23.07 | M3: STD20 | N3: 3105 | O3: =_xlfn.XLOOKUP(B3,Sheet1!A:A,Sheet1!E:E) -> 23.07 | P3: =_xlfn.XLOOKUP(A3,Sheet2!F:F,Sheet2!H:H) -> 4058.7356 | Q3: =_xlfn.XLOOKUP(B3,April23!B:B,April23!D:D) -> 23.76 | R3: =_xlfn.XLOOKUP(B3,Sheet3!B:B,Sheet3!D:D) -> 23.76 | S3: 1842 | T3: =IF(Q3>=R3,"No Change","Up") -> No Change | V3: =SUM(Q3*S3) -> 43765.92 | W3: =SUM(R3*S3) -> 43765.92
A4: 6046432 | B4: 6046432 | C4: CROW01 | D4: CROWN | E4: =_xlfn.XLOOKUP(B4,Sheet1!A:A,Sheet1!B:B) -> WA ANAGLYPTA PRECISION ROYAL OAK RD7000 | F4: =D4&" - "&E4 -> CROWN - WA ANAGLYPTA PRECISION ROYAL OAK RD7000 | H4: Each | I4: Item | J4: Item | K4: Paint | L4: 7.53 | M4: STD20 | N4: 3105 | O4: =_xlfn.XLOOKUP(B4,Sheet1!A:A,Sheet1!E:E) -> 7.53 | P4: =_xlfn.XLOOKUP(A4,Sheet2!F:F,Sheet2!H:H) -> 1044.4422 | Q4: =_xlfn.XLOOKUP(B4,April23!B:B,April23!D:D) -> 7.76 | R4: =_xlfn.XLOOKUP(B4,Sheet4!B:B,Sheet4!D:D) -> 7.76 | S4: 1597 | T4: =IF(Q4>=R4,"No Change","Up") -> No Change | V4: =SUM(Q4*S4) -> 12392.72 | W4: =SUM(R4*S4) -> 12392.72
A5: 6058266 | B5: 6058266 | C5: CROW01 | D5: CROWN | E5: =_xlfn.XLOOKUP(B5,Sheet1!A:A,Sheet1!B:B) -> DS FLUXAF POWER CLEAN 750ML | F5: =D5&" - "&E5 -> CROWN - DS FLUXAF POWER CLEAN 750ML | H5: Each | I5: Item | J5: Item | K5: Paint | M5: STD20 | N5: 3105 | O5: =_xlfn.XLOOKUP(B5,Sheet1!A:A,Sheet1!E:E) -> 7.6 | P5: =_xlfn.XLOOKUP(A5,Sheet2!F:F,Sheet2!H:H) -> 3511.4342 | Q5: =O5*1.05 -> 7.98 | R5: 7.98 | S5: 1201 | T5: =IF(Q5>=R5,"No Change","Up") -> No Change | V5: =SUM(Q5*S5) -> 9583.98 | W5: =SUM(R5*S5) -> 9583.98
A6: 6040482 | B6: 6040482 | C6: CROW01 | D6: CROWN | E6: =_xlfn.XLOOKUP(B6,Sheet1!A:A,Sheet1!B:B) -> WA AS CREATION CASABLANCA 4 WALL | F6: =D6&" - "&E6 -> CROWN - WA AS CREATION CASABLANCA 4 WALL | H6: Each | I6: Item | J6: Item | K6: Paint | M6: STD20 | N6: 3105 | O6: =_xlfn.XLOOKUP(B6,Sheet1!A:A,Sheet1!E:E) -> 6.06 | P6: =_xlfn.XLOOKUP(A6,Sheet2!F:F,Sheet2!H:H) -> 789.9802 | Q6: =O6*1.05 -> 6.363 | R6: =Q6*1.03 -> 6.55389 | S6: 941.44272 | T6: =IF(Q6>=R6,"No Change","Up") -> Up | V6: =SUM(Q6*S6) -> 5990.4 | W6: =SUM(R6*S6) -> 6170.112
A7: 5040579 | B7: 5040579 | C7: CROW01 | D7: CROWN | E7: =_xlfn.XLOOKUP(B7,Sheet1!A:A,Sheet1!B:B) -> CRT Timonox Matt | F7: =D7&" - "&E7 -> CROWN - CRT Timonox Matt | G7: =_xlfn.XLOOKUP(B7,Sheet1!A:A,Sheet1!C:C) -> Brilliant White | H7: =_xlfn.XLOOKUP(B7,Sheet1!A:A,Sheet1!D:D) -> 5L | I7: Item | J7: Item | K7: Paint | L7: 50.41 | M7: STD20 | N7: 3105 | O7: =_xlfn.XLOOKUP(B7,Sheet1!A:A,Sheet1!E:E) -> 50.41 | P7: =_xlfn.XLOOKUP(A7,Sheet2!F:F,Sheet2!H:H) -> 978.03214 | Q7: =_xlfn.XLOOKUP(B7,April23!B:B,April23!D:D) -> 41.12 | R7: =_xlfn.XLOOKUP(B7,Sheet3!B:B,Sheet3!D:D) -> 41.12 | S7: 609 | T7: =IF(Q7>=R7,"No Change","Up") -> No Change | V7: =SUM(Q7*S7) -> 25042.08 | W7: =SUM(R7*S7) -> 25042.08
A8: 5024010 | B8: 5024010 | C8: CROW01 | D8: CROWN | E8: =_xlfn.XLOOKUP(B8,Sheet1!A:A,Sheet1!B:B) -> CRT Stronghold Masonry Smooth | F8: =D8&" - "&E8 -> CROWN - CRT Stronghold Masonry Smooth | G8: =_xlfn.XLOOKUP(B8,Sheet1!A:A,Sheet1!C:C) -> Magnolia | H8: =_xlfn.XLOOKUP(B8,Sheet1!A:A,Sheet1!D:D) -> 5L | I8: Item | J8: Item | K8: Paint | L8: 19.73 | M8: STD20 | N8: 3105 | O8: =_xlfn.XLOOKUP(B8,Sheet1!A:A,Sheet1!E:E) -> 19.73 | P8: =_xlfn.XLOOKUP(A8,Sheet2!F:F,Sheet2!H:H) -> 410.59199 | Q8: =_xlfn.XLOOKUP(B8,April23!B:B,April23!D:D) -> 20.32 | R8: =_xlfn.XLOOKUP(B8,Sheet3!B:B,Sheet3!D:D) -> 20.32 | S8: 540 | T8: =IF(Q8>=R8,"No Change","Up") -> No Change | V8: =SUM(Q8*S8) -> 10972.8 | W8: =SUM(R8*S8) -> 10972.8
A9: 6041133 | B9: 6041133 | C9: CROW01 | D9: CROWN | E9: =_xlfn.XLOOKUP(B9,Sheet1!A:A,Sheet1!B:B) -> DS INDASA MTE MASKING TAPE 48MM | F9: =D9&" - "&E9 -> CROWN - DS INDASA MTE MASKING TAPE 48MM | H9: Each | I9: Item | J9: Item | K9: Paint | L9: 3.79 | M9: STD20 | N9: 3105 | O9: =_xlfn.XLOOKUP(B9,Sheet1!A:A,Sheet1!E:E) -> 3.79 | P9: =_xlfn.XLOOKUP(A9,Sheet2!F:F,Sheet2!H:H) -> 907.52507 | Q9: =_xlfn.XLOOKUP(B9,April23!B:B,April23!D:D) -> 3.5 | R9: 3.3 | S9: 536 | T9: Down | V9: =SUM(Q9*S9) -> 1876 | W9: =SUM(R9*S9) -> 1768.8
A10: 6061706 | B10: 6061706 | C10: CROW01 | D10: CROWN | E10: =_xlfn.XLOOKUP(B10,Sheet1!A:A,Sheet1!B:B) -> DE PROF CAULK WHITE 380ML | F10: =D10&" - "&E10 -> CROWN - DE PROF CAULK WHITE 380ML | H10: Each | I10: Item | J10: Item | K10: Paint | M10: STD20 | N10: 3105 | O10: =_xlfn.XLOOKUP(B10,Sheet1!A:A,Sheet1!E:E) -> 1.08 | P10: =_xlfn.XLOOKUP(A10,Sheet2!F:F,Sheet2!H:H) -> 5364.9352 | Q10: =O10*1.05 -> 1.134 | R10: =_xlfn.XLOOKUP(B10,Sheet4!B:B,Sheet4!D:D) -> 1.11 | S10: 437.84295 | T10: =IF(Q10>=R10,"No Change","Up") -> No Change | V10: =SUM(Q10*S10) -> 496.51391 | W10: =SUM(R10*S10) -> 486.00568
A11: 5026956 | B11: 5026956 | C11: CROW01 | D11: CROWN | E11: =_xlfn.XLOOKUP(B11,Sheet1!A:A,Sheet1!B:B) -> CRT Solvent-borne Full Gloss | F11: =D11&" - "&E11 -> CROWN - CRT Solvent-borne Full Gloss | G11: =_xlfn.XLOOKUP(B11,Sheet1!A:A,Sheet1!C:C) -> White | H11: =_xlfn.XLOOKUP(B11,Sheet1!A:A,Sheet1!D:D) -> 5L | I11: Item | J11: Item | K11: Paint | L11: 16.32 | M11: STD20 | N11: 3105 | O11: =_xlfn.XLOOKUP(B11,Sheet1!A:A,Sheet1!E:E) -> 16.32 | P11: =_xlfn.XLOOKUP(A11,Sheet2!F:F,Sheet2!H:H) -> 1494.5821 | Q11: =_xlfn.XLOOKUP(B11,April23!B:B,April23!D:D) -> 25.72 | R11: =_xlfn.XLOOKUP(B11,Sheet3!B:B,Sheet3!D:D) -> 25.72 | S11: 434 | T11: =IF(Q11>=R11,"No Change","Up") -> No Change | V11: =SUM(Q11*S11) -> 11162.48 | W11: =SUM(R11*S11) -> 11162.48
A12: 5024059 | B12: 5024059 | C12: CROW01 | D12: CROWN | E12: =_xlfn.XLOOKUP(B12,Sheet1!A:A,Sheet1!B:B) -> CRT Vinyl Matt | F12: =D12&" - "&E12 -> CROWN - CRT Vinyl Matt | G12: =_xlfn.XLOOKUP(B12,Sheet1!A:A,Sheet1!C:C) -> White | H12: =_xlfn.XLOOKUP(B12,Sheet1!A:A,Sheet1!D:D) -> 10L | I12: Item | J12: Item | K12: Paint | L12: 21.01 | M12: STD20 | N12: 3105 | O12: =_xlfn.XLOOKUP(B12,Sheet1!A:A,Sheet1!E:E) -> 21.01 | P12: =_xlfn.XLOOKUP(A12,Sheet2!F:F,Sheet2!H:H) -> 1135.9324 | Q12: =_xlfn.XLOOKUP(B12,April23!B:B,April23!D:D) -> 21.64 | R12: =_xlfn.XLOOKUP(B12,Sheet3!B:B,Sheet3!D:D) -> 21.64 | S12: 376 | T12: =IF(Q12>=R12,"No Change","Up") -> No Change | V12: =SUM(Q12*S12) -> 8136.64 | W12: =SUM(R12*S12) -> 8136.64
A13: 6041126 | B13: 6041126 | C13: CROW01 | D13: CROWN | E13: =_xlfn.XLOOKUP(B13,Sheet1!A:A,Sheet1!B:B) -> DS INDASA MTG MASKING TAPE 50MM 45MT | F13: =D13&" - "&E13 -> CROWN - DS INDASA MTG MASKING TAPE 50MM 45MT | H13: Each | I13: Item | J13: Item | K13: Paint | L13: 1.33 | M13: STD20 | N13: 3105 | O13: =_xlfn.XLOOKUP(B13,Sheet1!A:A,Sheet1!E:E) -> 1.33 | P13: =_xlfn.XLOOKUP(A13,Sheet2!F:F,Sheet2!H:H) -> 2287.0602 | Q13: =_xlfn.XLOOKUP(B13,April23!B:B,April23!D:D) -> 1.4 | R13: =_xlfn.XLOOKUP(B13,Sheet4!B:B,Sheet4!D:D) -> 1.4 | S13: 366 | T13: =IF(Q13>=R13,"No Change","Up") -> No Change | V13: =SUM(Q13*S13) -> 512.4 | W13: =SUM(R13*S13) -> 512.4
A14: 5024174 | B14: 5024174 | C14: CROW01 | D14: CROWN | E14: =_xlfn.XLOOKUP(B14,Sheet1!A:A,Sheet1!B:B) -> CRT Acrylic Primer Undercoat | F14: =D14&" - "&E14 -> CROWN - CRT Acrylic Primer Undercoat | G14: =_xlfn.XLOOKUP(B14,Sheet1!A:A,Sheet1!C:C) -> White | H14: =_xlfn.XLOOKUP(B14,Sheet1!A:A,Sheet1!D:D) -> 5L | I14: Item | J14: Item | K14: Paint | L14: 25.39 | M14: STD20 | N14: 3105 | O14: =_xlfn.XLOOKUP(B14,Sheet1!A:A,Sheet1!E:E) -> 25.39 | P14: =_xlfn.XLOOKUP(A14,Sheet2!F:F,Sheet2!H:H) -> 895.60181 | Q14: =_xlfn.XLOOKUP(B14,April23!B:B,April23!D:D) -> 18 | R14: =_xlfn.XLOOKUP(B14,Sheet3!B:B,Sheet3!D:D) -> 18 | S14: 325 | T14: =IF(Q14>=R14,"No Change","Up") -> No Change | V14: =SUM(Q14*S14) -> 5850 | W14: =SUM(R14*S14) -> 5850
A15: 6062944 | B15: 6062944 | C15: CROW01 | D15: CROWN | E15: =_xlfn.XLOOKUP(B15,Sheet1!A:A,Sheet1!B:B) -> DS Q1 CONTRACTOR MASKING TAPE 50M 48MM | F15: =D15&" - "&E15 -> CROWN - DS Q1 CONTRACTOR MASKING TAPE 50M 48MM | H15: Each | I15: Item | J15: Item | K15: Paint | M15: STD20 | N15: 3105 | O15: =_xlfn.XLOOKUP(B15,Sheet1!A:A,Sheet1!E:E) -> 2 | Q15: =O15*1.05 -> 2.1 | R15: 2.1 | S15: 297 | T15: =IF(Q15>=R15,"No Change","Up") -> No Change | V15: =SUM(Q15*S15) -> 623.7 | W15: =SUM(R15*S15) -> 623.7
A16: 5027127 | B16: 5027127 | C16: CROW01 | D16: CROWN | E16: =_xlfn.XLOOKUP(B16,Sheet1!A:A,Sheet1!B:B) -> CRT Solvent-borne Undercoat | F16: =D16&" - "&E16 -> CROWN - CRT Solvent-borne Undercoat | G16: =_xlfn.XLOOKUP(B16,Sheet1!A:A,Sheet1!C:C) -> White | H16: =_xlfn.XLOOKUP(B16,Sheet1!A:A,Sheet1!D:D) -> 5L | I16: Item | J16: Item | K16: Paint | L16: 16.32 | M16: STD20 | N16: 3105 | O16: =_xlfn.XLOOKUP(B16,Sheet1!A:A,Sheet1!E:E) -> 16.32 | P16: =_xlfn.XLOOKUP(A16,Sheet2!F:F,Sheet2!H:H) -> 530.75797 | Q16: =_xlfn.XLOOKUP(B16,April23!B:B,April23!D:D) -> 24.2 | R16: =_xlfn.XLOOKUP(B16,Sheet3!B:B,Sheet3!D:D) -> 24.2 | S16: 289 | T16: =IF(Q16>=R16,"No Change","Up") -> No Change | V16: =SUM(Q16*S16) -> 6993.8 | W16: =SUM(R16*S16) -> 6993.8
A17: 5024026 | B17: 5024026 | C17: CROW01 | D17: CROWN | E17: =_xlfn.XLOOKUP(B17,Sheet1!A:A,Sheet1!B:B) -> CRT Stronghold Masonry Smooth | F17: =D17&" - "&E17 -> CROWN - CRT Stronghold Masonry Smooth | G17: =_xlfn.XLOOKUP(B17,Sheet1!A:A,Sheet1!C:C) -> White | H17: =_xlfn.XLOOKUP(B17,Sheet1!A:A,Sheet1!D:D) -> 5L | I17: Item | J17: Item | K17: Paint | L17: 19.73 | M17: STD20 | N17: 3105 | O17: =_xlfn.XLOOKUP(B17,Sheet1!A:A,Sheet1!E:E) -> 19.73 | P17: =_xlfn.XLOOKUP(A17,Sheet2!F:F,Sheet2!H:H) -> 211.16574 | Q17: =_xlfn.XLOOKUP(B17,April23!B:B,April23!D:D) -> 20.32 | R17: =_xlfn.XLOOKUP(B17,Sheet3!B:B,Sheet3!D:D) -> 20.32 | S17: 258 | T17: =IF(Q17>=R17,"No Change","Up") -> No Change | V17: =SUM(Q17*S17) -> 5242.56 | W17: =SUM(R17*S17) -> 5242.56
A18: 5027850 | B18: 5027850 | C18: CROW01 | D18: CROWN | E18: =_xlfn.XLOOKUP(B18,Sheet1!A:A,Sheet1!B:B) -> MAC Powerkote Masonry Smooth | F18: =D18&" - "&E18 -> CROWN - MAC Powerkote Masonry Smooth | G18: =_xlfn.XLOOKUP(B18,Sheet1!A:A,Sheet1!C:C) -> Magnolia | H18: =_xlfn.XLOOKUP(B18,Sheet1!A:A,Sheet1!D:D) -> 5L | I18: Item | J18: Item | K18: Paint | L18: 18.7 | M18: STD20 | N18: 3105 | O18: =_xlfn.XLOOKUP(B18,Sheet1!A:A,Sheet1!E:E) -> 18.7 | P18: =_xlfn.XLOOKUP(A18,Sheet2!F:F,Sheet2!H:H) -> 48.109091 | Q18: =_xlfn.XLOOKUP(B18,April23!B:B,April23!D:D) -> 22.45 | R18: =_xlfn.XLOOKUP(B18,Sheet3!B:B,Sheet3!D:D) -> 23.12 | S18: 194 | T18: =IF(Q18>=R18,"No Change","Up") -> Up | V18: =SUM(Q18*S18) -> 4355.3 | W18: =SUM(R18*S18) -> 4485.28
A19: 5094753 | B19: 5094753 | C19: CROW01 | D19: CROWN | E19: =_xlfn.XLOOKUP(B19,Sheet1!A:A,Sheet1!B:B) -> CRT Alkali Resistant Primer PX4 - W/BASED | F19: =D19&" - "&E19 -> CROWN - CRT Alkali Resistant Primer PX4 - W/BASED | G19: =_xlfn.XLOOKUP(B19,Sheet1!A:A,Sheet1!C:C) -> Off White | H19: =_xlfn.XLOOKUP(B19,Sheet1!A:A,Sheet1!D:D) -> 5L | I19: Item | J19: Item | K19: Paint | L19: 25.54 | M19: STD20 | N19: 3105 | O19: =_xlfn.XLOOKUP(B19,Sheet1!A:A,Sheet1!E:E) -> 25.54 | P19: =_xlfn.XLOOKUP(A19,Sheet2!F:F,Sheet2!H:H) -> 199.07087 | Q19: =_xlfn.XLOOKUP(B19,April23!B:B,April23!D:D) -> 35.56 | R19: =Q19 -> 35.56 | S19: 184 | T19: =IF(Q19>=R19,"No Change","Up") -> No Change | V19: =SUM(Q19*S19) -> 6543.04 | W19: =SUM(R19*S19) -> 6543.04
A20: 5061839 | B20: 5061839 | C20: CROW01 | D20: CROWN | E20: =_xlfn.XLOOKUP(B20,Sheet1!A:A,Sheet1!B:B) -> CRT Clean Extreme | F20: =D20&" - "&E20 -> CROWN - CRT Clean Extreme | G20: =_xlfn.XLOOKUP(B20,Sheet1!A:A,Sheet1!C:C) -> Magnolia | H20: =_xlfn.XLOOKUP(B20,Sheet1!A:A,Sheet1!D:D) -> 5L | I20: Item | J20: Item | K20: Paint | L20: 24.9 | M20: STD20 | N20: 3105 | O20: =_xlfn.XLOOKUP(B20,Sheet1!A:A,Sheet1!E:E) -> 24.9 | P20: =_xlfn.XLOOKUP(A20,Sheet2!F:F,Sheet2!H:H) -> 253.13012 | Q20: =_xlfn.XLOOKUP(B20,April23!B:B,April23!D:D) -> 25.97 | R20: =Q20 -> 25.97 | S20: 177 | T20: =IF(Q20>=R20,"No Change","Up") -> No Change | V20: =SUM(Q20*S20) -> 4596.69 | W20: =SUM(R20*S20) -> 4596.69
A21: 5025052 | B21: 5025052 | C21: CROW01 | D21: CROWN | E21: =_xlfn.XLOOKUP(B21,Sheet1!A:A,Sheet1!B:B) -> MAC Eclipse | F21: =D21&" - "&E21 -> CROWN - MAC Eclipse | G21: =_xlfn.XLOOKUP(B21,Sheet1!A:A,Sheet1!C:C) -> Magnolia | H21: =_xlfn.XLOOKUP(B21,Sheet1!A:A,Sheet1!D:D) -> 10L | I21: Item | J21: Item | K21: Paint | L21: 18.16 | M21: STD20 | N21: 3105 | O21: =_xlfn.XLOOKUP(B21,Sheet1!A:A,Sheet1!E:E) -> 18.16 | P21: =_xlfn.XLOOKUP(A21,Sheet2!F:F,Sheet2!H:H) -> 485.89042 | Q21: =_xlfn.XLOOKUP(B21,April23!B:B,April23!D:D) -> 19.92 | R21: =_xlfn.XLOOKUP(B21,Sheet3!B:B,Sheet3!D:D) -> 20.52 | S21: 162 | T21: =IF(Q21>=R21,"No Change","Up") -> Up | V21: =SUM(Q21*S21) -> 3227.04 | W21: =SUM(R21*S21) -> 3324.24
A22: 6055142 | B22: 6055142 | C22: CROW01 | D22: CROWN | E22: =_xlfn.XLOOKUP(B22,Sheet1!A:A,Sheet1!B:B) -> DS ULTRAGRIME PRO XXL+MULTI WIPES 100PK | F22: =D22&" - "&E22 -> CROWN - DS ULTRAGRIME PRO XXL+MULTI WIPES 100PK | H22: Each | I22: Item | J22: Item | K22: Paint | M22: STD20 | N22: 3105 | O22: =_xlfn.XLOOKUP(B22,Sheet1!A:A,Sheet1!E:E) -> 13.09 | P22: =_xlfn.XLOOKUP(A22,Sheet2!F:F,Sheet2!H:H) -> 188.64706 | Q22: =O22*1.05 -> 13.7445 | R22: 13.5 | S22: 159.33646 | T22: Down | V22: =SUM(Q22*S22) -> 2190 | W22: =SUM(R22*S22) -> 2151.0422
A23: 5025056 | B23: 5025056 | C23: CROW01 | D23: CROWN | E23: =_xlfn.XLOOKUP(B23,Sheet1!A:A,Sheet1!B:B) -> MAC Eclipse | F23: =D23&" - "&E23 -> CROWN - MAC Eclipse | G23: =_xlfn.XLOOKUP(B23,Sheet1!A:A,Sheet1!C:C) -> Brilliant White | H23: =_xlfn.XLOOKUP(B23,Sheet1!A:A,Sheet1!D:D) -> 10L | I23: Item | J23: Item | K23: Paint | L23: 18.16 | M23: STD20 | N23: 3105 | O23: =_xlfn.XLOOKUP(B23,Sheet1!A:A,Sheet1!E:E) -> 18.16 | P23: =_xlfn.XLOOKUP(A23,Sheet2!F:F,Sheet2!H:H) -> 529.5011 | Q23: =_xlfn.XLOOKUP(B23,April23!B:B,April23!D:D) -> 18.27 | R23: =_xlfn.XLOOKUP(B23,Sheet3!B:B,Sheet3!D:D) -> 18.82 | S23: 158 | T23: =IF(Q23>=R23,"No Change","Up") -> Up | V23: =SUM(Q23*S23) -> 2886.66 | W23: =SUM(R23*S23) -> 2973.56
A24: 5061965 | B24: 5061965 | C24: CROW01 | D24: CROWN | E24: =_xlfn.XLOOKUP(B24,Sheet1!A:A,Sheet1!B:B) -> CRT Clean Extreme | F24: =D24&" - "&E24 -> CROWN - CRT Clean Extreme | G24: =_xlfn.XLOOKUP(B24,Sheet1!A:A,Sheet1!C:C) -> White | H24: =_xlfn.XLOOKUP(B24,Sheet1!A:A,Sheet1!D:D) -> 5L | I24: Item | J24: Item | K24: Paint | L24: 24.9 | M24: STD20 | N24: 3105 | O24: =_xlfn.XLOOKUP(B24,Sheet1!A:A,Sheet1!E:E) -> 24.9 | P24: =_xlfn.XLOOKUP(A24,Sheet2!F:F,Sheet2!H:H) -> 234.39277 | Q24: =_xlfn.XLOOKUP(B24,April23!B:B,April23!D:D) -> 25.04 | R24: =Q24 -> 25.04 | S24: 152 | T24: =IF(Q24>=R24,"No Change","Up") -> No Change | V24: =SUM(Q24*S24) -> 3806.08 | W24: =SUM(R24*S24) -> 3806.08
A25: 5090804 | B25: 5090804 | C25: CROW01 | D25: CROWN | E25: =_xlfn.XLOOKUP(B25,Sheet1!A:A,Sheet1!B:B) -> CRT Fastflow Quick Dry Gloss | F25: =D25&" - "&E25 -> CROWN - CRT Fastflow Quick Dry Gloss | G25: =_xlfn.XLOOKUP(B25,Sheet1!A:A,Sheet1!C:C) -> White | H25: =_xlfn.XLOOKUP(B25,Sheet1!A:A,Sheet1!D:D) -> 5L | I25: Item | J25: Item | K25: Paint | L25: 25.8 | M25: STD20 | N25: 3105 | O25: =_xlfn.XLOOKUP(B25,Sheet1!A:A,Sheet1!E:E) -> 25.8 | P25: =_xlfn.XLOOKUP(A25,Sheet2!F:F,Sheet2!H:H) -> 290.94884 | Q25: =_xlfn.XLOOKUP(B25,April23!B:B,April23!D:D) -> 25.29 | R25: =_xlfn.XLOOKUP(B25,Sheet3!B:B,Sheet3!D:D) -> 26.05 | S25: 151 | T25: =IF(Q25>=R25,"No Change","Up") -> Up | V25: =SUM(Q25*S25) -> 3818.79 | W25: =SUM(R25*S25) -> 3933.55
A26: 6042334 | B26: 6042334 | C26: CROW01 | D26: CROWN | E26: =_xlfn.XLOOKUP(B26,Sheet1!A:A,Sheet1!B:B) -> DS PRODEC EXTRA LONG POLYESTER ROL 9IN | F26: =D26&" - "&E26 -> CROWN - DS PRODEC EXTRA LONG POLYESTER ROL 9IN | H26: Each | I26: Item | J26: Item | K26: Paint | M26: STD20 | N26: 3105 | O26: =_xlfn.XLOOKUP(B26,Sheet1!A:A,Sheet1!E:E) -> 3.24 | P26: =_xlfn.XLOOKUP(A26,Sheet2!F:F,Sheet2!H:H) -> 76.388889 | Q26: =O26*1.05 -> 3.402 | R26: 3.4 | S26: 149.91182 | T26: =IF(Q26>=R26,"No Change","Up") -> No Change | V26: =SUM(Q26*S26) -> 510 | W26: =SUM(R26*S26) -> 509.70018
A27: 5090816 | B27: 5090816 | C27: CROW01 | D27: CROWN | E27: =_xlfn.XLOOKUP(B27,Sheet1!A:A,Sheet1!B:B) -> CRT Fastflow Quick Dry Primer Undercoat | F27: =D27&" - "&E27 -> CROWN - CRT Fastflow Quick Dry Primer Undercoat | G27: =_xlfn.XLOOKUP(B27,Sheet1!A:A,Sheet1!C:C) -> White | H27: =_xlfn.XLOOKUP(B27,Sheet1!A:A,Sheet1!D:D) -> 5L | I27: Item | J27: Item | K27: Paint | L27: 25.8 | M27: STD20 | N27: 3105 | O27: =_xlfn.XLOOKUP(B27,Sheet1!A:A,Sheet1!E:E) -> 25.8 | P27: =_xlfn.XLOOKUP(A27,Sheet2!F:F,Sheet2!H:H) -> 318.7845 | Q27: =_xlfn.XLOOKUP(B27,April23!B:B,April23!D:D) -> 26 | R27: =_xlfn.XLOOKUP(B27,Sheet3!B:B,Sheet3!D:D) -> 26 | S27: 147 | T27: =IF(Q27>=R27,"No Change","Up") -> No Change | V27: =SUM(Q27*S27) -> 3822 | W27: =SUM(R27*S27) -> 3822
A28: 6055912 | B28: 6055912 | C28: CROW01 | D28: CROWN | E28: =_xlfn.XLOOKUP(B28,Sheet1!A:A,Sheet1!B:B) -> DS TRIMACO BROWN MASKING PAPER 180FT | F28: =D28&" - "&E28 -> CROWN - DS TRIMACO BROWN MASKING PAPER 180FT | H28: Each | I28: Item | J28: Item | K28: Paint | L28: 7.26 | M28: STD20 | N28: 3105 | O28: =_xlfn.XLOOKUP(B28,Sheet1!A:A,Sheet1!E:E) -> 7.26 | P28: =_xlfn.XLOOKUP(A28,Sheet2!F:F,Sheet2!H:H) -> 149.64738 | Q28: =_xlfn.XLOOKUP(B28,April23!B:B,April23!D:D) -> 5.25 | R28: =Q28*1.03 -> 5.4075 | S28: 140 | T28: =IF(Q28>=R28,"No Change","Up") -> Up | V28: =SUM(Q28*S28) -> 735 | W28: =SUM(R28*S28) -> 757.05
A29: 5024213 | B29: 5024213 | C29: CROW01 | D29: CROWN | E29: =_xlfn.XLOOKUP(B29,Sheet1!A:A,Sheet1!B:B) -> CRT Silk | F29: =D29&" - "&E29 -> CROWN - CRT Silk | G29: =_xlfn.XLOOKUP(B29,Sheet1!A:A,Sheet1!C:C) -> Magnolia | H29: =_xlfn.XLOOKUP(B29,Sheet1!A:A,Sheet1!D:D) -> 10L | I29: Item | J29: Item | K29: Paint | L29: 26.29 | M29: STD20 | N29: 3105 | O29: =_xlfn.XLOOKUP(B29,Sheet1!A:A,Sheet1!E:E) -> 26.29 | P29: =_xlfn.XLOOKUP(A29,Sheet2!F:F,Sheet2!H:H) -> 1081.8414 | Q29: =_xlfn.XLOOKUP(B29,April23!B:B,April23!D:D) -> 28.09 | R29: =_xlfn.XLOOKUP(B29,Sheet3!B:B,Sheet3!D:D) -> 28.09 | S29: 138 | T29: =IF(Q29>=R29,"No Change","Up") -> No Change | V29: =SUM(Q29*S29) -> 3876.42 | W29: =SUM(R29*S29) -> 3876.42
A30: 5064671 | B30: 5064671 | C30: CROW01 | D30: CROWN | E30: =_xlfn.XLOOKUP(B30,Sheet1!A:A,Sheet1!B:B) -> CRT Acrylic Eggshell | F30: =D30&" - "&E30 -> CROWN - CRT Acrylic Eggshell | G30: =_xlfn.XLOOKUP(B30,Sheet1!A:A,Sheet1!C:C) -> Magnolia | H30: =_xlfn.XLOOKUP(B30,Sheet1!A:A,Sheet1!D:D) -> 5L | I30: Item | J30: Item | K30: Paint | L30: 21.01 | M30: STD20 | N30: 3105 | O30: =_xlfn.XLOOKUP(B30,Sheet1!A:A,Sheet1!E:E) -> 21.01 | P30: =_xlfn.XLOOKUP(A30,Sheet2!F:F,Sheet2!H:H) -> 307.99714 | Q30: =_xlfn.XLOOKUP(B30,April23!B:B,April23!D:D) -> 26.14 | R30: =Q30 -> 26.14 | S30: 135 | T30: =IF(Q30>=R30,"No Change","Up") -> No Change | V30: =SUM(Q30*S30) -> 3528.9 | W30: =SUM(R30*S30) -> 3528.9
A31: 6055707 | B31: 6055707 | C31: CROW01 | D31: CROWN | E31: =_xlfn.XLOOKUP(B31,Sheet1!A:A,Sheet1!B:B) -> DS OAKEY FLEXIBLE FINISH PADS EX MED/CRS | F31: =D31&" - "&E31 -> CROWN - DS OAKEY FLEXIBLE FINISH PADS EX MED/CRS | H31: Each | I31: Item | J31: Item | K31: Paint | L31: 1.06 | M31: STD20 | N31: 3105 | O31: =_xlfn.XLOOKUP(B31,Sheet1!A:A,Sheet1!E:E) -> 1.06 | P31: =_xlfn.XLOOKUP(A31,Sheet2!F:F,Sheet2!H:H) -> 0 | Q31: =_xlfn.XLOOKUP(B31,April23!B:B,April23!D:D) -> 1.11 | R31: 1.11 | S31: 133 | T31: =IF(Q31>=R31,"No Change","Up") -> No Change | V31: =SUM(Q31*S31) -> 147.63 | W31: =SUM(R31*S31) -> 147.63
A32: 5093395 | B32: 5093395 | C32: CROW01 | D32: CROWN | E32: =_xlfn.XLOOKUP(B32,Sheet1!A:A,Sheet1!B:B) -> CRT Clean Extreme Mould Inhibiting Matt | F32: =D32&" - "&E32 -> CROWN - CRT Clean Extreme Mould Inhibiting Matt | G32: =_xlfn.XLOOKUP(B32,Sheet1!A:A,Sheet1!C:C) -> White | H32: =_xlfn.XLOOKUP(B32,Sheet1!A:A,Sheet1!D:D) -> 5L | I32: Item | J32: Item | K32: Paint | L32: 38.03 | M32: STD20 | N32: 3105 | O32: =_xlfn.XLOOKUP(B32,Sheet1!A:A,Sheet1!E:E) -> 38.03 | P32: =_xlfn.XLOOKUP(A32,Sheet2!F:F,Sheet2!H:H) -> 307.39968 | Q32: =_xlfn.XLOOKUP(B32,April23!B:B,April23!D:D) -> 33.87 | R32: =_xlfn.XLOOKUP(B32,Sheet3!B:B,Sheet3!D:D) -> 33.87 | S32: 125 | T32: =IF(Q32>=R32,"No Change","Up") -> No Change | V32: =SUM(Q32*S32) -> 4233.75 | W32: =SUM(R32*S32) -> 4233.75
A33: 5091987 | B33: 5091987 | C33: CROW01 | D33: CROWN | E33: =_xlfn.XLOOKUP(B33,Sheet1!A:A,Sheet1!B:B) -> CRT Fastflow QD Satin | F33: =D33&" - "&E33 -> CROWN - CRT Fastflow QD Satin | G33: =_xlfn.XLOOKUP(B33,Sheet1!A:A,Sheet1!C:C) -> White | H33: =_xlfn.XLOOKUP(B33,Sheet1!A:A,Sheet1!D:D) -> 5L | I33: Item | J33: Item | K33: Paint | L33: 30.77 | M33: STD20 | N33: 3105 | O33: =_xlfn.XLOOKUP(B33,Sheet1!A:A,Sheet1!E:E) -> 30.77 | P33: =_xlfn.XLOOKUP(A33,Sheet2!F:F,Sheet2!H:H) -> 282.51934 | Q33: =_xlfn.XLOOKUP(B33,April23!B:B,April23!D:D) -> 28 | R33: =_xlfn.XLOOKUP(B33,Sheet3!B:B,Sheet3!D:D) -> 28 | S33: 122 | T33: =IF(Q33>=R33,"No Change","Up") -> No Change | V33: =SUM(Q33*S33) -> 3416 | W33: =SUM(R33*S33) -> 3416
A34: 6061964 | B34: 6061964 | C34: CROW01 | D34: CROWN | E34: =_xlfn.XLOOKUP(B34,Sheet1!A:A,Sheet1!B:B) -> DS HAMILTON MEDIUM PILE ROLLER 4IN 10PK | F34: =D34&" - "&E34 -> CROWN - DS HAMILTON MEDIUM PILE ROLLER 4IN 10PK | H34: Each | I34: Item | J34: Item | K34: Paint | M34: STD20 | N34: 3105 | O34: =_xlfn.XLOOKUP(B34,Sheet1!A:A,Sheet1!E:E) -> 3.9 | P34: =_xlfn.XLOOKUP(A34,Sheet2!F:F,Sheet2!H:H) -> 109.17949 | Q34: =O34*1.05 -> 4.095 | R34: 4.1 | S34: 119.1453 | T34: =IF(Q34>=R34,"No Change","Up") -> Up | V34: =SUM(Q34*S34) -> 487.9 | W34: =SUM(R34*S34) -> 488.49573
A35: 5026990 | B35: 5026990 | C35: CROW01 | D35: CROWN | E35: =_xlfn.XLOOKUP(B35,Sheet1!A:A,Sheet1!B:B) -> CRT Solvent-borne Full Gloss | F35: =D35&" - "&E35 -> CROWN - CRT Solvent-borne Full Gloss | G35: =_xlfn.XLOOKUP(B35,Sheet1!A:A,Sheet1!C:C) -> Brilliant White | H35: =_xlfn.XLOOKUP(B35,Sheet1!A:A,Sheet1!D:D) -> 5L | I35: Item | J35: Item | K35: Paint | L35: 16.32 | M35: STD20 | N35: 3105 | O35: =_xlfn.XLOOKUP(B35,Sheet1!A:A,Sheet1!E:E) -> 16.32 | P35: =_xlfn.XLOOKUP(A35,Sheet2!F:F,Sheet2!H:H) -> 62.909926 | Q35: =_xlfn.XLOOKUP(B35,April23!B:B,April23!D:D) -> 19.68 | R35: =_xlfn.XLOOKUP(B35,Sheet3!B:B,Sheet3!D:D) -> 20.27 | S35: 118 | T35: =IF(Q35>=R35,"No Change","Up") -> Up | V35: =SUM(Q35*S35) -> 2322.24 | W35: =SUM(R35*S35) -> 2391.86
A36: 6040483 | B36: 6040483 | C36: CROW01 | D36: CROWN | E36: =_xlfn.XLOOKUP(B36,Sheet1!A:A,Sheet1!B:B) -> WA AS CREATION CASABLANCA 4 WALL | F36: =D36&" - "&E36 -> CROWN - WA AS CREATION CASABLANCA 4 WALL | H36: Each | I36: Item | J36: Item | K36: Paint | M36: STD20 | N36: 3105 | O36: =_xlfn.XLOOKUP(B36,Sheet1!A:A,Sheet1!E:E) -> 5 | P36: =_xlfn.XLOOKUP(A36,Sheet2!F:F,Sheet2!H:H) -> 1186.608 | Q36: =O36*1.05 -> 5.25 | R36: =Q36*1.03 -> 5.4075 | S36: 117.71429 | T36: =IF(Q36>=R36,"No Change","Up") -> Up | V36: =SUM(Q36*S36) -> 618 | W36: =SUM(R36*S36) -> 636.54
A37: 5073961 | B37: 5073961 | C37: CROW01 | D37: CROWN | E37: =_xlfn.XLOOKUP(B37,Sheet1!A:A,Sheet1!B:B) -> ST RUST INHIB PRIMER GREY 2.5L | F37: =D37&" - "&E37 -> CROWN - ST RUST INHIB PRIMER GREY 2.5L | H37: 5L | I37: Item | J37: Item | K37: Paint | L37: 43.03 | M37: STD20 | N37: 3105 | O37: =_xlfn.XLOOKUP(B37,Sheet1!A:A,Sheet1!E:E) -> 43.03 | P37: =_xlfn.XLOOKUP(A37,Sheet2!F:F,Sheet2!H:H) -> 0 | Q37: =O37*1.03 -> 44.3209 | R37: 40 | S37: 112.99771 | T37: Down | V37: =SUM(Q37*S37) -> 5008.16 | W37: =SUM(R37*S37) -> 4519.9082
A38: 6040125 | B38: 6040125 | C38: CROW01 | D38: CROWN | E38: =_xlfn.XLOOKUP(B38,Sheet1!A:A,Sheet1!B:B) -> WA ANAGLYPTA TEXT VINYL WILL BO RD804301 | F38: =D38&" - "&E38 -> CROWN - WA ANAGLYPTA TEXT VINYL WILL BO RD804301 | H38: Each | I38: Item | J38: Item | K38: Paint | L38: 4.8 | M38: STD20 | N38: 3105 | O38: =_xlfn.XLOOKUP(B38,Sheet1!A:A,Sheet1!E:E) -> 4.8 | P38: =_xlfn.XLOOKUP(A38,Sheet2!F:F,Sheet2!H:H) -> 2858.4188 | Q38: =_xlfn.XLOOKUP(B38,April23!B:B,April23!D:D) -> 4.94 | R38: =Q38*1.03 -> 5.0882 | S38: 107 | T38: =IF(Q38>=R38,"No Change","Up") -> Up | V38: =SUM(Q38*S38) -> 528.58 | W38: =SUM(R38*S38) -> 544.4374
A39: 6055201 | B39: 6055201 | C39: CROW01 | D39: CROWN | E39: =_xlfn.XLOOKUP(B39,Sheet1!A:A,Sheet1!B:B) -> DE ESS PAINT BRUSH 2IN(12) EACH | F39: =D39&" - "&E39 -> CROWN - DE ESS PAINT BRUSH 2IN(12) EACH | H39: Each | I39: Item | J39: Item | K39: Paint | L39: 1.38 | M39: STD20 | N39: 3105 | O39: =_xlfn.XLOOKUP(B39,Sheet1!A:A,Sheet1!E:E) -> 1.38 | P39: =_xlfn.XLOOKUP(A39,Sheet2!F:F,Sheet2!H:H) -> 563.89855 | Q39: =_xlfn.XLOOKUP(B39,April23!B:B,April23!D:D) -> 1.42 | R39: =_xlfn.XLOOKUP(B39,Sheet4!B:B,Sheet4!D:D) -> 1.42 | S39: 103 | T39: =IF(Q39>=R39,"No Change","Up") -> No Change | V39: =SUM(Q39*S39) -> 146.26 | W39: =SUM(R39*S39) -> 146.26
A40: 6062917 | B40: 6062917 | C40: CROW01 | D40: CROWN | E40: =_xlfn.XLOOKUP(B40,Sheet1!A:A,Sheet1!B:B) -> WA FINE DECOR CONTRACTOR BOOK 23 A | F40: =D40&" - "&E40 -> CROWN - WA FINE DECOR CONTRACTOR BOOK 23 A | H40: Each | I40: Item | J40: Item | K40: Paint | M40: STD20 | N40: 3105 | O40: =_xlfn.XLOOKUP(B40,Sheet1!A:A,Sheet1!E:E) -> 10 | P40: =_xlfn.XLOOKUP(A40,Sheet2!F:F,Sheet2!H:H) -> 36 | Q40: =O40*1.05 -> 10.5 | R40: =Q40*1.03 -> 10.815 | S40: 102.85714 | T40: =IF(Q40>=R40,"No Change","Up") -> Up | V40: =SUM(Q40*S40) -> 1080 | W40: =SUM(R40*S40) -> 1112.4
A41: 6042316 | B41: 6042316 | C41: CROW01 | D41: CROWN | E41: =_xlfn.XLOOKUP(B41,Sheet1!A:A,Sheet1!B:B) -> DS BLACKROCK PAINTERS L/W GRIPPER GLOVES | F41: =D41&" - "&E41 -> CROWN - DS BLACKROCK PAINTERS L/W GRIPPER GLOVES | H41: Each | I41: Item | J41: Item | K41: Paint | M41: STD20 | N41: 3105 | O41: =_xlfn.XLOOKUP(B41,Sheet1!A:A,Sheet1!E:E) -> 3.25 | P41: =_xlfn.XLOOKUP(A41,Sheet2!F:F,Sheet2!H:H) -> 248.2 | Q41: =O41*1.05 -> 3.4125 | R41: 3.41 | S41: 96.923077 | T41: =IF(Q41>=R41,"No Change","Up") -> No Change | V41: =SUM(Q41*S41) -> 330.75 | W41: =SUM(R41*S41) -> 330.50769
A42: 6048267 | B42: 6048267 | C42: CROW01 | D42: CROWN | E42: =_xlfn.XLOOKUP(B42,Sheet1!A:A,Sheet1!B:B) -> DE WHITE SPIRIT 2L | F42: =D42&" - "&E42 -> CROWN - DE WHITE SPIRIT 2L | H42: 2L | I42: Item | J42: Item | K42: Paint | L42: 3 | M42: STD20 | N42: 3105 | O42: =_xlfn.XLOOKUP(B42,Sheet1!A:A,Sheet1!E:E) -> 3 | P42: =_xlfn.XLOOKUP(A42,Sheet2!F:F,Sheet2!H:H) -> 279.83333 | Q42: =_xlfn.XLOOKUP(B42,April23!B:B,April23!D:D) -> 3.09 | R42: =_xlfn.XLOOKUP(B42,Sheet4!B:B,Sheet4!D:D) -> 3.09 | S42: 93 | T42: =IF(Q42>=R42,"No Change","Up") -> No Change | V42: =SUM(Q42*S42) -> 287.37 | W42: =SUM(R42*S42) -> 287.37
A43: 6062918 | B43: 6062918 | C43: CROW01 | D43: CROWN | E43: =_xlfn.XLOOKUP(B43,Sheet1!A:A,Sheet1!B:B) -> WA FINE DECOR CONTRACTOR BOOK 23 B | F43: =D43&" - "&E43 -> CROWN - WA FINE DECOR CONTRACTOR BOOK 23 B | H43: Each | I43: Item | J43: Item | K43: Paint | M43: STD20 | N43: 3105 | O43: =_xlfn.XLOOKUP(B43,Sheet1!A:A,Sheet1!E:E) -> 10 | P43: =_xlfn.XLOOKUP(A43,Sheet2!F:F,Sheet2!H:H) -> 0 | Q43: =O43*1.05 -> 10.5 | R43: =Q43*1.03 -> 10.815 | S43: 91.428571 | T43: =IF(Q43>=R43,"No Change","Up") -> Up | V43: =SUM(Q43*S43) -> 960 | W43: =SUM(R43*S43) -> 988.8
A44: 6062122 | B44: 6062122 | C44: CROW01 | D44: CROWN | E44: =_xlfn.XLOOKUP(B44,Sheet1!A:A,Sheet1!B:B) -> DS HIPPO MP BAMBOO DRY CLOTH 60 SHEETS | F44: =D44&" - "&E44 -> CROWN - DS HIPPO MP BAMBOO DRY CLOTH 60 SHEETS | H44: Each | I44: Item | J44: Item | K44: Paint | M44: STD20 | N44: 3105 | O44: =_xlfn.XLOOKUP(B44,Sheet1!A:A,Sheet1!E:E) -> 10.3 | P44: =_xlfn.XLOOKUP(A44,Sheet2!F:F,Sheet2!H:H) -> 73 | Q44: =O44*1.05 -> 10.815 | R44: 10.82 | S44: 90.041609 | T44: No Change | V44: =SUM(Q44*S44) -> 973.8 | W44: =SUM(R44*S44) -> 974.25021
A45: 5064686 | B45: 5064686 | C45: CROW01 | D45: CROWN | E45: =_xlfn.XLOOKUP(B45,Sheet1!A:A,Sheet1!B:B) -> CRT Acrylic Eggshell | F45: =D45&" - "&E45 -> CROWN - CRT Acrylic Eggshell | G45: =_xlfn.XLOOKUP(B45,Sheet1!A:A,Sheet1!C:C) -> White | H45: =_xlfn.XLOOKUP(B45,Sheet1!A:A,Sheet1!D:D) -> 5L | I45: Item | J45: Item | K45: Paint | L45: 21.01 | M45: STD20 | N45: 3105 | O45: =_xlfn.XLOOKUP(B45,Sheet1!A:A,Sheet1!E:E) -> 21.01 | P45: =_xlfn.XLOOKUP(A45,Sheet2!F:F,Sheet2!H:H) -> 337.0238 | Q45: =_xlfn.XLOOKUP(B45,April23!B:B,April23!D:D) -> 24.03 | R45: =_xlfn.XLOOKUP(B45,Sheet3!B:B,Sheet3!D:D) -> 17.4 | S45: 89.313358 | T45: =IF(Q45>=R45,"No Change","Up") -> No Change | V45: =SUM(Q45*S45) -> 2146.2 | W45: =SUM(R45*S45) -> 1554.0524
A46: 5023888 | B46: 5023888 | C46: CROW01 | D46: CROWN | E46: =_xlfn.XLOOKUP(B46,Sheet1!A:A,Sheet1!B:B) -> CRT Covermatt Obliterating Emulsion | F46: =D46&" - "&E46 -> CROWN - CRT Covermatt Obliterating Emulsion | G46: =_xlfn.XLOOKUP(B46,Sheet1!A:A,Sheet1!C:C) -> Magnolia | H46: =_xlfn.XLOOKUP(B46,Sheet1!A:A,Sheet1!D:D) -> 10L | I46: Item | J46: Item | K46: Paint | L46: 23.15 | M46: STD20 | N46: 3105 | O46: =_xlfn.XLOOKUP(B46,Sheet1!A:A,Sheet1!E:E) -> 23.15 | P46: =_xlfn.XLOOKUP(A46,Sheet2!F:F,Sheet2!H:H) -> 103.53089 | Q46: =_xlfn.XLOOKUP(B46,April23!B:B,April23!D:D) -> 23.44 | R46: =Q46 -> 23.44 | S46: 89 | T46: =IF(Q46>=R46,"No Change","Up") -> No Change | V46: =SUM(Q46*S46) -> 2086.16 | W46: =SUM(R46*S46) -> 2086.16
A47: 6048367 | B47: 6048367 | C47: CROW01 | D47: CROWN | E47: =_xlfn.XLOOKUP(B47,Sheet1!A:A,Sheet1!B:B) -> DS ZINSSER DIF WALLPAPER STRIPPER 1L | F47: =D47&" - "&E47 -> CROWN - DS ZINSSER DIF WALLPAPER STRIPPER 1L | H47: 1L | I47: Item | J47: Item | K47: Paint | L47: 16.11 | M47: STD20 | N47: 3105 | O47: =_xlfn.XLOOKUP(B47,Sheet1!A:A,Sheet1!E:E) -> 10.25 | P47: =_xlfn.XLOOKUP(A47,Sheet2!F:F,Sheet2!H:H) -> 320.44 | Q47: =_xlfn.XLOOKUP(B47,April23!B:B,April23!D:D) -> 10.76 | R47: 10.76 | S47: 86 | T47: =IF(Q47>=R47,"No Change","Up") -> No Change | V47: =SUM(Q47*S47) -> 925.36 | W47: =SUM(R47*S47) -> 925.36
A48: 5028843 | B48: 5028843 | C48: CROW01 | D48: CROWN | E48: =_xlfn.XLOOKUP(B48,Sheet1!A:A,Sheet1!B:B) -> SD SUPERDEC BASE CLEAR 065 5L | F48: =D48&" - "&E48 -> CROWN - SD SUPERDEC BASE CLEAR 065 5L | G48: Clear | H48: =_xlfn.XLOOKUP(B48,Sheet1!A:A,Sheet1!D:D) -> 5L | I48: Item | J48: Item | K48: Paint | L48: 72.12 | M48: STD20 | N48: 3105 | O48: =_xlfn.XLOOKUP(B48,Sheet1!A:A,Sheet1!E:E) -> 72.12 | P48: =_xlfn.XLOOKUP(A48,Sheet2!F:F,Sheet2!H:H) -> 347.20993 | Q48: =_xlfn.XLOOKUP(B48,April23!B:B,April23!D:D) -> 74.29 | R48: =_xlfn.XLOOKUP(B48,Sheet5!B:B,Sheet5!D:D) -> 35 | S48: 84.8028 | T48: =IF(Q48>=R48,"No Change","Up") -> No Change | V48: =SUM(Q48*S48) -> 6300 | W48: =SUM(R48*S48) -> 2968.098
A49: 5074313 | B49: 5074313 | C49: CROW01 | D49: CROWN | E49: =_xlfn.XLOOKUP(B49,Sheet1!A:A,Sheet1!B:B) -> CRT Satin | F49: =D49&" - "&E49 -> CROWN - CRT Satin | G49: =_xlfn.XLOOKUP(B49,Sheet1!A:A,Sheet1!C:C) -> White | H49: =_xlfn.XLOOKUP(B49,Sheet1!A:A,Sheet1!D:D) -> 5L | I49: Item | J49: Item | K49: Paint | L49: 26.89 | M49: STD20 | N49: 3105 | O49: =_xlfn.XLOOKUP(B49,Sheet1!A:A,Sheet1!E:E) -> 26.89 | P49: =_xlfn.XLOOKUP(A49,Sheet2!F:F,Sheet2!H:H) -> 169.94868 | Q49: =_xlfn.XLOOKUP(B49,April23!B:B,April23!D:D) -> 26.39 | R49: =Q49 -> 26.39 | S49: 82 | T49: =IF(Q49>=R49,"No Change","Up") -> No Change | V49: =SUM(Q49*S49) -> 2163.98 | W49: =SUM(R49*S49) -> 2163.98
A50: 6042131 | B50: 6042131 | C50: CROW01 | D50: CROWN | E50: =_xlfn.XLOOKUP(B50,Sheet1!A:A,Sheet1!B:B) -> DS PRESTIGE BUCKET 15L | F50: =D50&" - "&E50 -> CROWN - DS PRESTIGE BUCKET 15L | H50: 15L | I50: Item | J50: Item | K50: Paint | L50: 4.73 | M50: STD20 | N50: 3105 | O50: =_xlfn.XLOOKUP(B50,Sheet1!A:A,Sheet1!E:E) -> 4.73 | P50: =_xlfn.XLOOKUP(A50,Sheet2!F:F,Sheet2!H:H) -> 193.94503 | Q50: =_xlfn.XLOOKUP(B50,April23!B:B,April23!D:D) -> 4.97 | R50: =_xlfn.XLOOKUP(B50,Sheet4!B:B,Sheet4!D:D) -> 4.97 | S50: 82 | T50: =IF(Q50>=R50,"No Change","Up") -> No Change | V50: =SUM(Q50*S50) -> 407.54 | W50: =SUM(R50*S50) -> 407.54
A51: 6040118 | B51: 6040118 | C51: CROW01 | D51: CROWN | E51: =_xlfn.XLOOKUP(B51,Sheet1!A:A,Sheet1!B:B) -> WA ANAGLYPTA TEXT VINYL HAVERSHAM 34365 | F51: =D51&" - "&E51 -> CROWN - WA ANAGLYPTA TEXT VINYL HAVERSHAM 34365 | H51: EACH | I51: Item | J51: Item | K51: Paint | L51: 4.8 | M51: STD20 | N51: 3105 | O51: =_xlfn.XLOOKUP(B51,Sheet1!A:A,Sheet1!E:E) -> 4.8 | P51: =_xlfn.XLOOKUP(A51,Sheet2!F:F,Sheet2!H:H) -> 62.80625 | Q51: =_xlfn.XLOOKUP(B51,April23!B:B,April23!D:D) -> 4.94 | R51: =_xlfn.XLOOKUP(B51,Sheet4!B:B,Sheet4!D:D) -> 4.94 | S51: 79 | T51: =IF(Q51>=R51,"No Change","Up") -> No Change | V51: =SUM(Q51*S51) -> 390.26 | W51: =SUM(R51*S51) -> 390.26
A52: 6042090 | B52: 6042090 | C52: CROW01 | D52: CROWN | E52: =_xlfn.XLOOKUP(B52,Sheet1!A:A,Sheet1!B:B) -> DS PERFECTION ROLLER X LONG 9IN | F52: =D52&" - "&E52 -> CROWN - DS PERFECTION ROLLER X LONG 9IN | H52: Each | I52: Item | J52: Item | K52: Paint | L52: 8.16 | M52: STD20 | N52: 3105 | O52: =_xlfn.XLOOKUP(B52,Sheet1!A:A,Sheet1!E:E) -> 8.16 | P52: =_xlfn.XLOOKUP(A52,Sheet2!F:F,Sheet2!H:H) -> 31.595588 | Q52: =_xlfn.XLOOKUP(B52,April23!B:B,April23!D:D) -> 5.75 | R52: 5.75 | S52: 78 | T52: =IF(Q52>=R52,"No Change","Up") -> No Change | V52: =SUM(Q52*S52) -> 448.5 | W52: =SUM(R52*S52) -> 448.5
A53: 6040197 | B53: 6040197 | C53: CROW01 | D53: CROWN | E53: =_xlfn.XLOOKUP(B53,Sheet1!A:A,Sheet1!B:B) -> WA ERFURT LINING 1200 DOUBLE | F53: =D53&" - "&E53 -> CROWN - WA ERFURT LINING 1200 DOUBLE | H53: Each | I53: Item | J53: Item | K53: Paint | L53: 4.07 | M53: STD20 | N53: 3105 | O53: =_xlfn.XLOOKUP(B53,Sheet1!A:A,Sheet1!E:E) -> 4.07 | P53: =_xlfn.XLOOKUP(A53,Sheet2!F:F,Sheet2!H:H) -> 108.02457 | Q53: =_xlfn.XLOOKUP(B53,April23!B:B,April23!D:D) -> 4.19 | R53: =_xlfn.XLOOKUP(B53,Sheet4!B:B,Sheet4!D:D) -> 4.19 | S53: 78 | T53: =IF(Q53>=R53,"No Change","Up") -> No Change | V53: =SUM(Q53*S53) -> 326.82 | W53: =SUM(R53*S53) -> 326.82
A54: 6060622 | B54: 6060622 | C54: CROW01 | D54: CROWN | E54: =_xlfn.XLOOKUP(B54,Sheet1!A:A,Sheet1!B:B) -> DS ULTRAGRIME PRO POWER SCRUB XXL+ 80PK | F54: =D54&" - "&E54 -> CROWN - DS ULTRAGRIME PRO POWER SCRUB XXL+ 80PK | H54: Each | I54: Item | J54: Item | K54: Paint | M54: STD20 | N54: 3105 | O54: =_xlfn.XLOOKUP(B54,Sheet1!A:A,Sheet1!E:E) -> 14.29 | P54: =_xlfn.XLOOKUP(A54,Sheet2!F:F,Sheet2!H:H) -> 52.412176 | Q54: =O54*1.05 -> 15.0045 | R54: 15 | S54: 74.044453 | T54: =IF(Q54>=R54,"No Change","Up") -> No Change | V54: =SUM(Q54*S54) -> 1111 | W54: =SUM(R54*S54) -> 1110.6668
A55: 6055424 | B55: 6055424 | C55: CROW01 | D55: CROWN | E55: =_xlfn.XLOOKUP(B55,Sheet1!A:A,Sheet1!B:B) -> DE PROFESSIONAL MEDUIM GPUR ROLLER 4IN | F55: =D55&" - "&E55 -> CROWN - DE PROFESSIONAL MEDUIM GPUR ROLLER 4IN | H55: Each | I55: Item | J55: Item | K55: Paint | L55: 0.38 | M55: STD20 | N55: 3105 | O55: =_xlfn.XLOOKUP(B55,Sheet1!A:A,Sheet1!E:E) -> 0.38 | P55: =_xlfn.XLOOKUP(A55,Sheet2!F:F,Sheet2!H:H) -> 653.18421 | Q55: =_xlfn.XLOOKUP(B55,April23!B:B,April23!D:D) -> 0.39 | R55: 0.39 | S55: 74 | T55: =IF(Q55>=R55,"No Change","Up") -> No Change | V55: =SUM(Q55*S55) -> 28.86 | W55: =SUM(R55*S55) -> 28.86
A56: 6041657 | B56: 6041657 | C56: CROW01 | D56: CROWN | E56: =_xlfn.XLOOKUP(B56,Sheet1!A:A,Sheet1!B:B) -> DS PRODEC REFUSE SACKS 10PK | F56: =D56&" - "&E56 -> CROWN - DS PRODEC REFUSE SACKS 10PK | H56: Each | I56: Item | J56: Item | K56: Paint | L56: 2.05 | M56: STD20 | N56: 3105 | O56: =_xlfn.XLOOKUP(B56,Sheet1!A:A,Sheet1!E:E) -> 2.05 | P56: =_xlfn.XLOOKUP(A56,Sheet2!F:F,Sheet2!H:H) -> 287.73171 | Q56: =_xlfn.XLOOKUP(B56,April23!B:B,April23!D:D) -> 2.15 | R56: =_xlfn.XLOOKUP(B56,Sheet4!B:B,Sheet4!D:D) -> 2.15 | S56: 72 | T56: =IF(Q56>=R56,"No Change","Up") -> No Change | V56: =SUM(Q56*S56) -> 154.8 | W56: =SUM(R56*S56) -> 154.8
A57: 6040768 | B57: 6040768 | C57: CROW01 | D57: CROWN | E57: =_xlfn.XLOOKUP(B57,Sheet1!A:A,Sheet1!B:B) -> DS SOLVITE ALL PURPOSE +50% 30ROLL | F57: =D57&" - "&E57 -> CROWN - DS SOLVITE ALL PURPOSE +50% 30ROLL | H57: Each | I57: Item | J57: Item | K57: Paint | M57: STD20 | N57: 3105 | O57: =_xlfn.XLOOKUP(B57,Sheet1!A:A,Sheet1!E:E) -> 6.33 | P57: =_xlfn.XLOOKUP(A57,Sheet2!F:F,Sheet2!H:H) -> 200.24329 | Q57: =O57*1.05 -> 6.6465 | R57: =Q57*1.03 -> 6.845895 | S57: 70.074475 | T57: =IF(Q57>=R57,"No Change","Up") -> Up | V57: =SUM(Q57*S57) -> 465.75 | W57: =SUM(R57*S57) -> 479.7225
A58: 6042877 | B58: 6042877 | C58: CROW01 | D58: CROWN | E58: =_xlfn.XLOOKUP(B58,Sheet1!A:A,Sheet1!B:B) -> DS CIRET BAG OF RAGS COLOURED 10K | F58: =D58&" - "&E58 -> CROWN - DS CIRET BAG OF RAGS COLOURED 10K | H58: Each | I58: Item | J58: Item | K58: Paint | M58: STD20 | N58: 3105 | O58: =_xlfn.XLOOKUP(B58,Sheet1!A:A,Sheet1!E:E) -> 31.51 | P58: =_xlfn.XLOOKUP(A58,Sheet2!F:F,Sheet2!H:H) -> 87.043161 | Q58: =O58*1.05 -> 33.0855 | R58: 33.09 | S58: 68.009249 | T58: No Change | V58: =SUM(Q58*S58) -> 2250.12 | W58: =SUM(R58*S58) -> 2250.426
A59: 5093393 | B59: 5093393 | C59: CROW01 | D59: CROWN | E59: =_xlfn.XLOOKUP(B59,Sheet1!A:A,Sheet1!B:B) -> CRT Clean Extreme Mould Inhibiting Matt | F59: =D59&" - "&E59 -> CROWN - CRT Clean Extreme Mould Inhibiting Matt | G59: =_xlfn.XLOOKUP(B59,Sheet1!A:A,Sheet1!C:C) -> Magnolia | H59: =_xlfn.XLOOKUP(B59,Sheet1!A:A,Sheet1!D:D) -> 5L | I59: Item | J59: Item | K59: Paint | L59: 38.92 | M59: STD20 | N59: 3105 | O59: =_xlfn.XLOOKUP(B59,Sheet1!A:A,Sheet1!E:E) -> 38.92 | P59: 232 | Q59: =_xlfn.XLOOKUP(B59,April23!B:B,April23!D:D) -> 33.87 | R59: =_xlfn.XLOOKUP(B59,Sheet3!B:B,Sheet3!D:D) -> 33.87 | S59: 68 | T59: =IF(Q59>=R59,"No Change","Up") -> No Change | V59: =SUM(Q59*S59) -> 2303.16 | W59: =SUM(R59*S59) -> 2303.16
A60: 5074787 | B60: 5074787 | C60: CROW01 | D60: CROWN | E60: =_xlfn.XLOOKUP(B60,Sheet1!A:A,Sheet1!B:B) -> CRT Timonox Bonding Primer | F60: =D60&" - "&E60 -> CROWN - CRT Timonox Bonding Primer | G60: =_xlfn.XLOOKUP(B60,Sheet1!A:A,Sheet1!C:C) -> White | H60: =_xlfn.XLOOKUP(B60,Sheet1!A:A,Sheet1!D:D) -> 5L | I60: Item | J60: Item | K60: Paint | L60: 50.58 | M60: STD20 | N60: 3105 | O60: =_xlfn.XLOOKUP(B60,Sheet1!A:A,Sheet1!E:E) -> 50.58 | P60: =_xlfn.XLOOKUP(A60,Sheet2!F:F,Sheet2!H:H) -> 229.06267 | Q60: =_xlfn.XLOOKUP(B60,April23!B:B,April23!D:D) -> 44 | R60: =_xlfn.XLOOKUP(B60,Sheet3!B:B,Sheet3!D:D) -> 44 | S60: 66 | T60: =IF(Q60>=R60,"No Change","Up") -> No Change | V60: =SUM(Q60*S60) -> 2904 | W60: =SUM(R60*S60) -> 2904
A61: 5088424 | B61: 5088424 | C61: CROW01 | D61: CROWN | E61: =_xlfn.XLOOKUP(B61,Sheet1!A:A,Sheet1!B:B) -> CRT Flexarb Opaque | F61: =D61&" - "&E61 -> CROWN - CRT Flexarb Opaque | G61: =_xlfn.XLOOKUP(B61,Sheet1!A:A,Sheet1!C:C) -> Brown | H61: =_xlfn.XLOOKUP(B61,Sheet1!A:A,Sheet1!D:D) -> 5L | I61: Item | J61: Item | K61: Paint | L61: 52.07 | M61: STD20 | N61: 3105 | O61: =_xlfn.XLOOKUP(B61,Sheet1!A:A,Sheet1!E:E) -> 52.07 | P61: =_xlfn.XLOOKUP(A61,Sheet2!F:F,Sheet2!H:H) -> 245.03284 | Q61: =_xlfn.XLOOKUP(B61,April23!B:B,April23!D:D) -> 45 | R61: =_xlfn.XLOOKUP(B61,Sheet3!B:B,Sheet3!D:D) -> 45 | S61: 65 | T61: =IF(Q61>=R61,"No Change","Up") -> No Change | V61: =SUM(Q61*S61) -> 2925 | W61: =SUM(R61*S61) -> 2925
A62: 6042088 | B62: 6042088 | C62: CROW01 | D62: CROWN | E62: =_xlfn.XLOOKUP(B62,Sheet1!A:A,Sheet1!B:B) -> DS PERFECTION ROLLER MEDIUM 9IN | F62: =D62&" - "&E62 -> CROWN - DS PERFECTION ROLLER MEDIUM 9IN | H62: Each | I62: Item | J62: Item | K62: Paint | L62: 5.43 | M62: STD20 | N62: 3105 | O62: =_xlfn.XLOOKUP(B62,Sheet1!A:A,Sheet1!E:E) -> 5.43 | P62: =_xlfn.XLOOKUP(A62,Sheet2!F:F,Sheet2!H:H) -> 69.810313 | Q62: =_xlfn.XLOOKUP(B62,April23!B:B,April23!D:D) -> 3.75 | R62: 3.75 | S62: 64 | T62: =IF(Q62>=R62,"No Change","Up") -> No Change | V62: =SUM(Q62*S62) -> 240 | W62: =SUM(R62*S62) -> 240
A63: 6063177 | B63: 6063177 | C63: CROW01 | D63: CROWN | E63: =_xlfn.XLOOKUP(B63,Sheet1!A:A,Sheet1!B:B) -> DS BARTOLINE 1876 AP ADHESIVE 30 ROLL | F63: =D63&" - "&E63 -> CROWN - DS BARTOLINE 1876 AP ADHESIVE 30 ROLL | H63: Each | I63: Item | J63: Item | K63: Paint | M63: STD20 | N63: 3105 | O63: =_xlfn.XLOOKUP(B63,Sheet1!A:A,Sheet1!E:E) -> 4.17 | Q63: =O63*1.05 -> 4.3785 | R63: 4.38 | S63: 59.06589 | T63: No Change | V63: =SUM(Q63*S63) -> 258.62 | W63: =SUM(R63*S63) -> 258.7086
A64: 5028216 | B64: 5028216 | C64: CROW01 | D64: CROWN | E64: =_xlfn.XLOOKUP(B64,Sheet1!A:A,Sheet1!B:B) -> ST 365 SMOOTH BRIL WHITE 5L | F64: =D64&" - "&E64 -> CROWN - ST 365 SMOOTH BRIL WHITE 5L | H64: 5L | I64: Item | J64: Item | K64: Paint | L64: 38.25 | M64: STD20 | N64: 3105 | O64: =_xlfn.XLOOKUP(B64,Sheet1!A:A,Sheet1!E:E) -> 38.25 | P64: =_xlfn.XLOOKUP(A64,Sheet2!F:F,Sheet2!H:H) -> 47.307451 | Q64: =_xlfn.XLOOKUP(B64,April23!B:B,April23!D:D) -> 39.4 | R64: 35 | S64: 59 | T64: Down | V64: =SUM(Q64*S64) -> 2324.6 | W64: =SUM(R64*S64) -> 2065
A65: 6061968 | B65: 6061968 | C65: CROW01 | D65: CROWN | E65: =_xlfn.XLOOKUP(B65,Sheet1!A:A,Sheet1!B:B) -> DS HAMILTON LONG PILE ROLLER 9IN | F65: =D65&" - "&E65 -> CROWN - DS HAMILTON LONG PILE ROLLER 9IN | H65: Each | I65: Item | J65: Item | K65: Paint | M65: STD20 | N65: 3105 | O65: =_xlfn.XLOOKUP(B65,Sheet1!A:A,Sheet1!E:E) -> 3.16 | P65: =_xlfn.XLOOKUP(A65,Sheet2!F:F,Sheet2!H:H) -> 0 | Q65: =O65*1.05 -> 3.318 | R65: 3.32 | S65: 57.034358 | T65: =IF(Q65>=R65,"No Change","Up") -> Up | V65: =SUM(Q65*S65) -> 189.24 | W65: =SUM(R65*S65) -> 189.35407
A66: 6055204 | B66: 6055204 | C66: CROW01 | D66: CROWN | E66: =_xlfn.XLOOKUP(B66,Sheet1!A:A,Sheet1!B:B) -> DE ESS PAINT BRUSH BOX SET(1) EACH | F66: =D66&" - "&E66 -> CROWN - DE ESS PAINT BRUSH BOX SET(1) EACH | H66: Each | I66: Item | J66: Item | K66: Paint | L66: 6.66 | M66: STD20 | N66: 3105 | O66: =_xlfn.XLOOKUP(B66,Sheet1!A:A,Sheet1!E:E) -> 6.66 | P66: =_xlfn.XLOOKUP(A66,Sheet2!F:F,Sheet2!H:H) -> 48.834835 | Q66: =_xlfn.XLOOKUP(B66,April23!B:B,April23!D:D) -> 6.86 | R66: =_xlfn.XLOOKUP(B66,Sheet4!B:B,Sheet4!D:D) -> 6.86 | S66: 57 | T66: =IF(Q66>=R66,"No Change","Up") -> No Change | V66: =SUM(Q66*S66) -> 391.02 | W66: =SUM(R66*S66) -> 391.02
A67: 6048207 | B67: 6048207 | C67: CROW01 | D67: CROWN | E67: =_xlfn.XLOOKUP(B67,Sheet1!A:A,Sheet1!B:B) -> DS REPAIR CARE DRY FLEX 4 | F67: =D67&" - "&E67 -> CROWN - DS REPAIR CARE DRY FLEX 4 | H67: Each | I67: Item | J67: Item | K67: Paint | M67: STD20 | N67: 3105 | O67: =_xlfn.XLOOKUP(B67,Sheet1!A:A,Sheet1!E:E) -> 54 | P67: =_xlfn.XLOOKUP(A67,Sheet2!F:F,Sheet2!H:H) -> 176.01593 | Q67: =O67*1.05 -> 56.7 | R67: 56.7 | S67: 56.266667 | T67: =IF(Q67>=R67,"No Change","Up") -> No Change | V67: =SUM(Q67*S67) -> 3190.32 | W67: =SUM(R67*S67) -> 3190.32
A68: 5090815 | B68: 5090815 | C68: CROW01 | D68: CROWN | E68: =_xlfn.XLOOKUP(B68,Sheet1!A:A,Sheet1!B:B) -> CRT Fastflow Quick Dry Primer Undercoat | F68: =D68&" - "&E68 -> CROWN - CRT Fastflow Quick Dry Primer Undercoat | G68: =_xlfn.XLOOKUP(B68,Sheet1!A:A,Sheet1!C:C) -> White | H68: =_xlfn.XLOOKUP(B68,Sheet1!A:A,Sheet1!D:D) -> 2.5L | I68: Item | J68: Item | K68: Paint | L68: 14.29 | M68: STD20 | N68: 3105 | O68: =_xlfn.XLOOKUP(B68,Sheet1!A:A,Sheet1!E:E) -> 14.29 | P68: =_xlfn.XLOOKUP(A68,Sheet2!F:F,Sheet2!H:H) -> 106.84325 | Q68: =_xlfn.XLOOKUP(B68,April23!B:B,April23!D:D) -> 14.01 | R68: =Q68 -> 14.01 | S68: 56 | T68: =IF(Q68>=R68,"No Change","Up") -> No Change | V68: =SUM(Q68*S68) -> 784.56 | W68: =SUM(R68*S68) -> 784.56
A69: 6040959 | B69: 6040959 | C69: CROW01 | D69: CROWN | E69: =_xlfn.XLOOKUP(B69,Sheet1!A:A,Sheet1!B:B) -> DS GYPROC EASI-FILL 60 5K | F69: =D69&" - "&E69 -> CROWN - DS GYPROC EASI-FILL 60 5K | H69: Each | I69: Item | J69: Item | K69: Paint | L69: 11.69 | M69: STD20 | N69: 3105 | O69: =_xlfn.XLOOKUP(B69,Sheet1!A:A,Sheet1!E:E) -> 11.69 | P69: =_xlfn.XLOOKUP(A69,Sheet2!F:F,Sheet2!H:H) -> 207.87596 | Q69: =O69*1.05 -> 12.2745 | R69: =Q69*1.03 -> 12.642735 | S69: 54.979836 | T69: =IF(Q69>=R69,"No Change","Up") -> Up | V69: =SUM(Q69*S69) -> 674.85 | W69: =SUM(R69*S69) -> 695.0955
A70: 5024058 | B70: 5024058 | C70: CROW01 | D70: CROWN | E70: =_xlfn.XLOOKUP(B70,Sheet1!A:A,Sheet1!B:B) -> CRT Vinyl Matt | F70: =D70&" - "&E70 -> CROWN - CRT Vinyl Matt | G70: =_xlfn.XLOOKUP(B70,Sheet1!A:A,Sheet1!C:C) -> White | H70: =_xlfn.XLOOKUP(B70,Sheet1!A:A,Sheet1!D:D) -> 5L | I70: Item | J70: Item | K70: Paint | L70: 12.47 | M70: STD20 | N70: 3105 | O70: =_xlfn.XLOOKUP(B70,Sheet1!A:A,Sheet1!E:E) -> 12.47 | P70: =_xlfn.XLOOKUP(A70,Sheet2!F:F,Sheet2!H:H) -> 211.93825 | Q70: =_xlfn.XLOOKUP(B70,April23!B:B,April23!D:D) -> 12.1 | R70: =_xlfn.XLOOKUP(B70,Sheet3!B:B,Sheet3!D:D) -> 12.1 | S70: 54 | T70: =IF(Q70>=R70,"No Change","Up") -> No Change | V70: =SUM(Q70*S70) -> 653.4 | W70: =SUM(R70*S70) -> 653.4
A71: 5090803 | B71: 5090803 | C71: CROW01 | D71: CROWN | E71: =_xlfn.XLOOKUP(B71,Sheet1!A:A,Sheet1!B:B) -> CRT Fastflow Quick Dry Gloss | F71: =D71&" - "&E71 -> CROWN - CRT Fastflow Quick Dry Gloss | G71: =_xlfn.XLOOKUP(B71,Sheet1!A:A,Sheet1!C:C) -> White | H71: =_xlfn.XLOOKUP(B71,Sheet1!A:A,Sheet1!D:D) -> 2.5L | I71: Item | J71: Item | K71: Paint | L71: 14.29 | M71: STD20 | N71: 3105 | O71: =_xlfn.XLOOKUP(B71,Sheet1!A:A,Sheet1!E:E) -> 14.29 | P71: =_xlfn.XLOOKUP(A71,Sheet2!F:F,Sheet2!H:H) -> 76.227432 | Q71: =_xlfn.XLOOKUP(B71,April23!B:B,April23!D:D) -> 14.01 | R71: =_xlfn.XLOOKUP(B71,Sheet3!B:B,Sheet3!D:D) -> 14.42 | S71: 54 | T71: =IF(Q71>=R71,"No Change","Up") -> Up | V71: =SUM(Q71*S71) -> 756.54 | W71: =SUM(R71*S71) -> 778.68
A72: 5024011 | B72: 5024011 | C72: CROW01 | D72: CROWN | E72: =_xlfn.XLOOKUP(B72,Sheet1!A:A,Sheet1!B:B) -> CRT Stronghold Masonry Smooth | F72: =D72&" - "&E72 -> CROWN - CRT Stronghold Masonry Smooth | G72: =_xlfn.XLOOKUP(B72,Sheet1!A:A,Sheet1!C:C) -> Magnolia | H72: =_xlfn.XLOOKUP(B72,Sheet1!A:A,Sheet1!D:D) -> 10L | I72: Item | J72: Item | K72: Paint | L72: 39.42 | M72: STD20 | N72: 3105 | O72: =_xlfn.XLOOKUP(B72,Sheet1!A:A,Sheet1!E:E) -> 39.42 | P72: =_xlfn.XLOOKUP(A72,Sheet2!F:F,Sheet2!H:H) -> 183.3516 | Q72: =_xlfn.XLOOKUP(B72,April23!B:B,April23!D:D) -> 44.89 | R72: =_xlfn.XLOOKUP(B72,Sheet3!B:B,Sheet3!D:D) -> 39 | S72: 52.996213 | T72: =IF(Q72>=R72,"No Change","Up") -> No Change | V72: =SUM(Q72*S72) -> 2379 | W72: =SUM(R72*S72) -> 2066.8523
A73: 5070051 | B73: 5070051 | C73: CROW01 | D73: CROWN | E73: =_xlfn.XLOOKUP(B73,Sheet1!A:A,Sheet1!B:B) -> CRT Clean Extreme | F73: =D73&" - "&E73 -> CROWN - CRT Clean Extreme | G73: =_xlfn.XLOOKUP(B73,Sheet1!A:A,Sheet1!C:C) -> White | H73: =_xlfn.XLOOKUP(B73,Sheet1!A:A,Sheet1!D:D) -> 10L | I73: Item | J73: Item | K73: Paint | L73: 49.64 | M73: STD20 | N73: 3105 | O73: =_xlfn.XLOOKUP(B73,Sheet1!A:A,Sheet1!E:E) -> 49.64 | P73: =_xlfn.XLOOKUP(A73,Sheet2!F:F,Sheet2!H:H) -> 203.24073 | Q73: =_xlfn.XLOOKUP(B73,April23!B:B,April23!D:D) -> 45.63 | R73: =_xlfn.XLOOKUP(B73,Sheet3!B:B,Sheet3!D:D) -> 45.63 | S73: 52 | T73: =IF(Q73>=R73,"No Change","Up") -> No Change | V73: =SUM(Q73*S73) -> 2372.76 | W73: =SUM(R73*S73) -> 2372.76
A74: 5092102 | B74: 5092102 | C74: CROW01 | D74: CROWN | E74: =_xlfn.XLOOKUP(B74,Sheet1!A:A,Sheet1!B:B) -> CRT Pro Co High Build Rust Inhibit Metal | F74: =D74&" - "&E74 -> CROWN - CRT Pro Co High Build Rust Inhibit Metal | G74: =_xlfn.XLOOKUP(B74,Sheet1!A:A,Sheet1!C:C) -> Colour | H74: =_xlfn.XLOOKUP(B74,Sheet1!A:A,Sheet1!D:D) -> 2.5L | I74: Item | J74: Item | K74: Paint | L74: 22.34 | M74: STD20 | N74: 3105 | O74: =_xlfn.XLOOKUP(B74,Sheet1!A:A,Sheet1!E:E) -> 22.34 | Q74: =_xlfn.XLOOKUP(B74,April23!B:B,April23!D:D) -> 21.93 | R74: =_xlfn.XLOOKUP(B74,Sheet3!B:B,Sheet3!D:D) -> 22.59 | S74: 51 | T74: =IF(Q74>=R74,"No Change","Up") -> Up | V74: =SUM(Q74*S74) -> 1118.43 | W74: =SUM(R74*S74) -> 1152.09
A75: 5025084 | B75: 5025084 | C75: CROW01 | D75: CROWN | E75: =_xlfn.XLOOKUP(B75,Sheet1!A:A,Sheet1!B:B) -> MAC Vinyl Matt | F75: =D75&" - "&E75 -> CROWN - MAC Vinyl Matt | G75: =_xlfn.XLOOKUP(B75,Sheet1!A:A,Sheet1!C:C) -> Brilliant White | H75: =_xlfn.XLOOKUP(B75,Sheet1!A:A,Sheet1!D:D) -> 5L | I75: Item | J75: Item | K75: Paint | L75: 11.17 | M75: STD20 | N75: 3105 | O75: =_xlfn.XLOOKUP(B75,Sheet1!A:A,Sheet1!E:E) -> 11.17 | P75: =_xlfn.XLOOKUP(A75,Sheet2!F:F,Sheet2!H:H) -> 0 | Q75: =_xlfn.XLOOKUP(B75,April23!B:B,April23!D:D) -> 11 | R75: =_xlfn.XLOOKUP(B75,Sheet3!B:B,Sheet3!D:D) -> 11.33 | S75: 51 | T75: =IF(Q75>=R75,"No Change","Up") -> Up | V75: =SUM(Q75*S75) -> 561 | W75: =SUM(R75*S75) -> 577.83
A76: 6042089 | B76: 6042089 | C76: CROW01 | D76: CROWN | E76: =_xlfn.XLOOKUP(B76,Sheet1!A:A,Sheet1!B:B) -> DS PERFECTION ROLLER LONG 9IN | F76: =D76&" - "&E76 -> CROWN - DS PERFECTION ROLLER LONG 9IN | H76: Each | I76: Item | J76: Item | K76: Paint | L76: 6.5 | M76: STD20 | N76: 3105 | O76: =_xlfn.XLOOKUP(B76,Sheet1!A:A,Sheet1!E:E) -> 6.5 | P76: =_xlfn.XLOOKUP(A76,Sheet2!F:F,Sheet2!H:H) -> 70.838462 | Q76: =_xlfn.XLOOKUP(B76,April23!B:B,April23!D:D) -> 4.5 | R76: 4.5 | S76: 49 | T76: =IF(Q76>=R76,"No Change","Up") -> No Change | V76: =SUM(Q76*S76) -> 220.5 | W76: =SUM(R76*S76) -> 220.5
A77: 6062061 | B77: 6062061 | C77: CROW01 | D77: CROWN | E77: =_xlfn.XLOOKUP(B77,Sheet1!A:A,Sheet1!B:B) -> WA GALERIE CDC HOME INSPIRATION B | F77: =D77&" - "&E77 -> CROWN - WA GALERIE CDC HOME INSPIRATION B | H77: Each | I77: Item | J77: Item | K77: Paint | M77: STD20 | N77: 3105 | O77: =_xlfn.XLOOKUP(B77,Sheet1!A:A,Sheet1!E:E) -> 17.5 | P77: =_xlfn.XLOOKUP(A77,Sheet2!F:F,Sheet2!H:H) -> 71 | Q77: =O77*1.05 -> 18.375 | R77: =Q77*1.03 -> 18.92625 | S77: 48.87619 | T77: =IF(Q77>=R77,"No Change","Up") -> Up | V77: =SUM(Q77*S77) -> 898.1 | W77: =SUM(R77*S77) -> 925.043
A78: 6053484 | B78: 6053484 | C78: CROW01 | D78: CROWN | E78: =_xlfn.XLOOKUP(B78,Sheet1!A:A,Sheet1!B:B) -> DS BLACKROCK PAINTERS LW GRIPPER GLOVE | F78: =D78&" - "&E78 -> CROWN - DS BLACKROCK PAINTERS LW GRIPPER GLOVE | H78: Each | I78: Item | J78: Item | K78: Paint | M78: STD20 | N78: 3105 | O78: =_xlfn.XLOOKUP(B78,Sheet1!A:A,Sheet1!E:E) -> 1.58 | P78: =_xlfn.XLOOKUP(A78,Sheet2!F:F,Sheet2!H:H) -> 0 | Q78: =O78*1.05 -> 1.659 | R78: 1.66 | S78: 47.02833 | T78: No Change | V78: =SUM(Q78*S78) -> 78.02 | W78: =SUM(R78*S78) -> 78.067028
A79: 6041658 | B79: 6041658 | C79: CROW01 | D79: CROWN | E79: =_xlfn.XLOOKUP(B79,Sheet1!A:A,Sheet1!B:B) -> DS PRODEC REFUSE SACKS 50 ROLL | F79: =D79&" - "&E79 -> CROWN - DS PRODEC REFUSE SACKS 50 ROLL | H79: Each | I79: Item | J79: Item | K79: Paint | M79: STD20 | N79: 3105 | O79: =_xlfn.XLOOKUP(B79,Sheet1!A:A,Sheet1!E:E) -> 7.91 | P79: =_xlfn.XLOOKUP(A79,Sheet2!F:F,Sheet2!H:H) -> 97.017699 | Q79: =O79*1.05 -> 8.3055 | R79: 8.31 | S79: 47.025465 | T79: No Change | V79: =SUM(Q79*S79) -> 390.57 | W79: =SUM(R79*S79) -> 390.78161
A80: 6042110 | B80: 6042110 | C80: CROW01 | D80: CROWN | E80: =_xlfn.XLOOKUP(B80,Sheet1!A:A,Sheet1!B:B) -> DS PRESTIGE CAGE FRAME 9IN | F80: =D80&" - "&E80 -> CROWN - DS PRESTIGE CAGE FRAME 9IN | H80: Each | I80: Item | J80: Item | K80: Paint | L80: 6.85 | M80: STD20 | N80: 3105 | O80: =_xlfn.XLOOKUP(B80,Sheet1!A:A,Sheet1!E:E) -> 6.85 | P80: =_xlfn.XLOOKUP(A80,Sheet2!F:F,Sheet2!H:H) -> 0 | Q80: =_xlfn.XLOOKUP(B80,April23!B:B,April23!D:D) -> 5.75 | R80: 5.75 | S80: 47 | T80: =IF(Q80>=R80,"No Change","Up") -> No Change | V80: =SUM(Q80*S80) -> 270.25 | W80: =SUM(R80*S80) -> 270.25
A81: 6040960 | B81: 6040960 | C81: CROW01 | D81: CROWN | E81: =_xlfn.XLOOKUP(B81,Sheet1!A:A,Sheet1!B:B) -> DS GYPROC JOINT FILLER 12.5K | F81: =D81&" - "&E81 -> CROWN - DS GYPROC JOINT FILLER 12.5K | H81: Each | I81: Item | J81: Item | K81: Paint | M81: STD20 | N81: 3105 | O81: =_xlfn.XLOOKUP(B81,Sheet1!A:A,Sheet1!E:E) -> 15.99 | P81: =_xlfn.XLOOKUP(A81,Sheet2!F:F,Sheet2!H:H) -> 46.348343 | Q81: =O81*1.05 -> 16.7895 | R81: =Q81*1.03 -> 17.293185 | S81: 45.54275 | T81: =IF(Q81>=R81,"No Change","Up") -> Up | V81: =SUM(Q81*S81) -> 764.64 | W81: =SUM(R81*S81) -> 787.5792
A82: 6041059 | B82: 6041059 | C82: CROW01 | D82: CROWN | E82: =_xlfn.XLOOKUP(B82,Sheet1!A:A,Sheet1!B:B) -> DS ZINSSER COVER STAIN 5L | F82: =D82&" - "&E82 -> CROWN - DS ZINSSER COVER STAIN 5L | H82: 5L | I82: Item | J82: Item | K82: Paint | L82: 45.39 | M82: STD20 | N82: 3105 | O82: =_xlfn.XLOOKUP(B82,Sheet1!A:A,Sheet1!E:E) -> 45.39 | P82: =_xlfn.XLOOKUP(A82,Sheet2!F:F,Sheet2!H:H) -> 10.016523 | Q82: =_xlfn.XLOOKUP(B82,April23!B:B,April23!D:D) -> 47.66 | R82: =_xlfn.XLOOKUP(B82,Sheet4!B:B,Sheet4!D:D) -> 47.66 | S82: 45 | T82: =IF(Q82>=R82,"No Change","Up") -> No Change | V82: =SUM(Q82*S82) -> 2144.7 | W82: =SUM(R82*S82) -> 2144.7
A83: 6060533 | B83: 6060533 | C83: CROW01 | D83: CROWN | E83: =_xlfn.XLOOKUP(B83,Sheet1!A:A,Sheet1!B:B) -> DS TOUPRET EXT MASONRY POWDER FILL 5K | F83: =D83&" - "&E83 -> CROWN - DS TOUPRET EXT MASONRY POWDER FILL 5K | H83: Each | I83: Item | J83: Item | K83: Paint | M83: STD20 | N83: 3105 | O83: =_xlfn.XLOOKUP(B83,Sheet1!A:A,Sheet1!E:E) -> 33.64 | P83: =_xlfn.XLOOKUP(A83,Sheet2!F:F,Sheet2!H:H) -> 39.865042 | Q83: =O83*1.05 -> 35.322 | R83: =_xlfn.XLOOKUP(B83,Sheet4!B:B,Sheet4!D:D) -> 26.93 | S83: 44.208425 | T83: =IF(Q83>=R83,"No Change","Up") -> No Change | V83: =SUM(Q83*S83) -> 1561.53 | W83: =SUM(R83*S83) -> 1190.5329
A84: 6046572 | B84: 6046572 | C84: CROW01 | D84: CROWN | E84: =_xlfn.XLOOKUP(B84,Sheet1!A:A,Sheet1!B:B) -> DS INDASA TUNGSTEN CARBIDE BLADES 50MM | F84: =D84&" - "&E84 -> CROWN - DS INDASA TUNGSTEN CARBIDE BLADES 50MM | H84: Each | I84: Item | J84: Item | K84: Paint | M84: STD20 | N84: 3105 | O84: =_xlfn.XLOOKUP(B84,Sheet1!A:A,Sheet1!E:E) -> 10.05 | P84: =_xlfn.XLOOKUP(A84,Sheet2!F:F,Sheet2!H:H) -> 65.364179 | Q84: =O84*1.05 -> 10.5525 | R84: =Q84*1.03 -> 10.869075 | S84: 44.065387 | T84: =IF(Q84>=R84,"No Change","Up") -> Up | V84: =SUM(Q84*S84) -> 465 | W84: =SUM(R84*S84) -> 478.95
A85: 5088422 | B85: 5088422 | C85: CROW01 | D85: CROWN | E85: =_xlfn.XLOOKUP(B85,Sheet1!A:A,Sheet1!B:B) -> CRT Flexarb Opaque | F85: =D85&" - "&E85 -> CROWN - CRT Flexarb Opaque | G85: =_xlfn.XLOOKUP(B85,Sheet1!A:A,Sheet1!C:C) -> Black | H85: =_xlfn.XLOOKUP(B85,Sheet1!A:A,Sheet1!D:D) -> 5L | I85: Item | J85: Item | K85: Paint | L85: 52.07 | M85: STD20 | N85: 3105 | O85: =_xlfn.XLOOKUP(B85,Sheet1!A:A,Sheet1!E:E) -> 52.07 | P85: =_xlfn.XLOOKUP(A85,Sheet2!F:F,Sheet2!H:H) -> 46.571154 | Q85: =_xlfn.XLOOKUP(B85,April23!B:B,April23!D:D) -> 45 | R85: =_xlfn.XLOOKUP(B85,Sheet3!B:B,Sheet3!D:D) -> 45 | S85: 44 | T85: =IF(Q85>=R85,"No Change","Up") -> No Change | V85: =SUM(Q85*S85) -> 1980 | W85: =SUM(R85*S85) -> 1980
A86: 5026955 | B86: 5026955 | C86: CROW01 | D86: CROWN | E86: =_xlfn.XLOOKUP(B86,Sheet1!A:A,Sheet1!B:B) -> CRT Solvent-borne Full Gloss | F86: =D86&" - "&E86 -> CROWN - CRT Solvent-borne Full Gloss | G86: =_xlfn.XLOOKUP(B86,Sheet1!A:A,Sheet1!C:C) -> White | H86: =_xlfn.XLOOKUP(B86,Sheet1!A:A,Sheet1!D:D) -> 2.5L | I86: Item | J86: Item | K86: Paint | L86: 9.34 | M86: STD20 | N86: 3105 | O86: =_xlfn.XLOOKUP(B86,Sheet1!A:A,Sheet1!E:E) -> 9.34 | P86: =_xlfn.XLOOKUP(A86,Sheet2!F:F,Sheet2!H:H) -> 313.88437 | Q86: =_xlfn.XLOOKUP(B86,April23!B:B,April23!D:D) -> 11.45 | R86: =_xlfn.XLOOKUP(B86,Sheet3!B:B,Sheet3!D:D) -> 11.79 | S86: 43 | T86: =IF(Q86>=R86,"No Change","Up") -> Up | V86: =SUM(Q86*S86) -> 492.35 | W86: =SUM(R86*S86) -> 506.97
A87: 5025063 | B87: 5025063 | C87: CROW01 | D87: CROWN | E87: =_xlfn.XLOOKUP(B87,Sheet1!A:A,Sheet1!B:B) -> MAC Acrylic Eggshell | F87: =D87&" - "&E87 -> CROWN - MAC Acrylic Eggshell | G87: =_xlfn.XLOOKUP(B87,Sheet1!A:A,Sheet1!C:C) -> Magnolia | H87: =_xlfn.XLOOKUP(B87,Sheet1!A:A,Sheet1!D:D) -> 5L | I87: Item | J87: Item | K87: Paint | L87: 21.64 | M87: STD20 | N87: 3105 | O87: =_xlfn.XLOOKUP(B87,Sheet1!A:A,Sheet1!E:E) -> 21.64 | P87: =_xlfn.XLOOKUP(A87,Sheet2!F:F,Sheet2!H:H) -> 48.045287 | Q87: =_xlfn.XLOOKUP(B87,April23!B:B,April23!D:D) -> 21.25 | R87: =_xlfn.XLOOKUP(B87,Sheet3!B:B,Sheet3!D:D) -> 21.88 | S87: 42 | T87: =IF(Q87>=R87,"No Change","Up") -> Up | V87: =SUM(Q87*S87) -> 892.5 | W87: =SUM(R87*S87) -> 918.96
A88: 6041055 | B88: 6041055 | C88: CROW01 | D88: CROWN | E88: =_xlfn.XLOOKUP(B88,Sheet1!A:A,Sheet1!B:B) -> DS ZINSSER BIN PRIMER WHITE 5L | F88: =D88&" - "&E88 -> CROWN - DS ZINSSER BIN PRIMER WHITE 5L | H88: 5L | I88: Item | J88: Item | K88: Paint | L88: 73.61 | M88: STD20 | N88: 3105 | O88: =_xlfn.XLOOKUP(B88,Sheet1!A:A,Sheet1!E:E) -> 73.61 | P88: =_xlfn.XLOOKUP(A88,Sheet2!F:F,Sheet2!H:H) -> 226.50414 | Q88: =_xlfn.XLOOKUP(B88,April23!B:B,April23!D:D) -> 77.29 | R88: =_xlfn.XLOOKUP(B88,Sheet4!B:B,Sheet4!D:D) -> 77.29 | S88: 42 | T88: =IF(Q88>=R88,"No Change","Up") -> No Change | V88: =SUM(Q88*S88) -> 3246.18 | W88: =SUM(R88*S88) -> 3246.18
A89: 6055310 | B89: 6055310 | C89: CROW01 | D89: CROWN | E89: =_xlfn.XLOOKUP(B89,Sheet1!A:A,Sheet1!B:B) -> DS PRODEC PREM SYN BRUSH SET + ANG 6PC | F89: =D89&" - "&E89 -> CROWN - DS PRODEC PREM SYN BRUSH SET + ANG 6PC | H89: Each | I89: Item | J89: Item | K89: Paint | M89: STD20 | N89: 3105 | O89: =_xlfn.XLOOKUP(B89,Sheet1!A:A,Sheet1!E:E) -> 16.68 | P89: =_xlfn.XLOOKUP(A89,Sheet2!F:F,Sheet2!H:H) -> 15.700839 | Q89: =O89*1.05 -> 17.514 | R89: =Q89*1.03 -> 18.03942 | S89: 39.990864 | T89: =IF(Q89>=R89,"No Change","Up") -> Up | V89: =SUM(Q89*S89) -> 700.4 | W89: =SUM(R89*S89) -> 721.412
A90: 5025077 | B90: 5025077 | C90: CROW01 | D90: CROWN | E90: =_xlfn.XLOOKUP(B90,Sheet1!A:A,Sheet1!B:B) -> MAC Vinyl Matt | F90: =D90&" - "&E90 -> CROWN - MAC Vinyl Matt | G90: =_xlfn.XLOOKUP(B90,Sheet1!A:A,Sheet1!C:C) -> Magnolia | H90: =_xlfn.XLOOKUP(B90,Sheet1!A:A,Sheet1!D:D) -> 10L | I90: Item | J90: Item | K90: Paint | L90: 21.82 | M90: STD20 | N90: 3105 | O90: =_xlfn.XLOOKUP(B90,Sheet1!A:A,Sheet1!E:E) -> 21.82 | P90: =_xlfn.XLOOKUP(A90,Sheet2!F:F,Sheet2!H:H) -> 0 | Q90: =_xlfn.XLOOKUP(B90,April23!B:B,April23!D:D) -> 23.54 | R90: =_xlfn.XLOOKUP(B90,Sheet3!B:B,Sheet3!D:D) -> 24.24 | S90: 39 | T90: =IF(Q90>=R90,"No Change","Up") -> Up | V90: =SUM(Q90*S90) -> 918.06 | W90: =SUM(R90*S90) -> 945.36
A91: 5038252 | B91: 5091205 | C91: CROW01 | D91: CROWN | E91: ST HIGHCOVER SMOOTH Plat Base 10L | F91: =D91&" - "&E91 -> CROWN - ST HIGHCOVER SMOOTH Plat Base 10L | H91: 10L | I91: Item | J91: Item | K91: Paint | L91: 47.09 | M91: STD20 | N91: 3105 | O91: 47.09 | P91: 11 | Q91: =O91*1.03 -> 48.5027 | R91: =_xlfn.XLOOKUP(B91,Sheet4!B:B,Sheet4!D:D) -> 49.96 | S91: 38.997829 | T91: =IF(Q91>=R91,"No Change","Up") -> Up | V91: =SUM(Q91*S91) -> 1891.5 | W91: =SUM(R91*S91) -> 1948.3315
A92: 6041136 | B92: 6041136 | C92: CROW01 | D92: CROWN | E92: =_xlfn.XLOOKUP(B92,Sheet1!A:A,Sheet1!B:B) -> DS INDASA RHYNOLITE YEL 120G 115MMX10M | F92: =D92&" - "&E92 -> CROWN - DS INDASA RHYNOLITE YEL 120G 115MMX10M | H92: Each | I92: Item | J92: Item | K92: Paint | L92: 3.68 | M92: STD20 | N92: 3105 | O92: =_xlfn.XLOOKUP(B92,Sheet1!A:A,Sheet1!E:E) -> 3.68 | P92: =_xlfn.XLOOKUP(A92,Sheet2!F:F,Sheet2!H:H) -> 70.975543 | Q92: =_xlfn.XLOOKUP(B92,April23!B:B,April23!D:D) -> 3.86 | R92: =_xlfn.XLOOKUP(B92,Sheet4!B:B,Sheet4!D:D) -> 3.86 | S92: 38 | T92: =IF(Q92>=R92,"No Change","Up") -> No Change | V92: =SUM(Q92*S92) -> 146.68 | W92: =SUM(R92*S92) -> 146.68
A93: 5089340 | B93: 5089340 | C93: CROW01 | D93: CROWN | E93: =_xlfn.XLOOKUP(B93,Sheet1!A:A,Sheet1!B:B) -> ST METAL GLOSS X-TRA BLACK 2.5L | F93: =D93&" - "&E93 -> CROWN - ST METAL GLOSS X-TRA BLACK 2.5L | H93: 5L | I93: Item | J93: Item | K93: Paint | L93: 38.92 | M93: STD20 | N93: 3105 | O93: =_xlfn.XLOOKUP(B93,Sheet1!A:A,Sheet1!E:E) -> 38.92 | P93: =_xlfn.XLOOKUP(A93,Sheet2!F:F,Sheet2!H:H) -> 50.920863 | Q93: =O93*1.03 -> 40.0876 | R93: 25.93 | S93: 37.002215 | T93: Down | V93: =SUM(Q93*S93) -> 1483.33 | W93: =SUM(R93*S93) -> 959.46744
A94: 6041130 | B94: 6041130 | C94: CROW01 | D94: CROWN | E94: =_xlfn.XLOOKUP(B94,Sheet1!A:A,Sheet1!B:B) -> DS INDASA COVERALL 1200MM 25M | F94: =D94&" - "&E94 -> CROWN - DS INDASA COVERALL 1200MM 25M | H94: Each | I94: Item | J94: Item | K94: Paint | M94: STD20 | N94: 3105 | O94: =_xlfn.XLOOKUP(B94,Sheet1!A:A,Sheet1!E:E) -> 7.34 | P94: =_xlfn.XLOOKUP(A94,Sheet2!F:F,Sheet2!H:H) -> 0 | Q94: =O94*1.05 -> 7.707 | R94: =Q94*1.03 -> 7.93821 | S94: 36.590113 | T94: =IF(Q94>=R94,"No Change","Up") -> Up | V94: =SUM(Q94*S94) -> 282 | W94: =SUM(R94*S94) -> 290.46
A95: 6055212 | B95: 6055212 | C95: CROW01 | D95: CROWN | E95: =_xlfn.XLOOKUP(B95,Sheet1!A:A,Sheet1!B:B) -> DE PROF SYN FLMNT BRUSH 2IN (12) EACH | F95: =D95&" - "&E95 -> CROWN - DE PROF SYN FLMNT BRUSH 2IN (12) EACH | H95: Each | I95: Item | J95: Item | K95: Paint | L95: 1.68 | M95: STD20 | N95: 3105 | O95: =_xlfn.XLOOKUP(B95,Sheet1!A:A,Sheet1!E:E) -> 1.68 | P95: =_xlfn.XLOOKUP(A95,Sheet2!F:F,Sheet2!H:H) -> 0 | Q95: =_xlfn.XLOOKUP(B95,April23!B:B,April23!D:D) -> 1.73 | R95: =_xlfn.XLOOKUP(B95,Sheet4!B:B,Sheet4!D:D) -> 1.78 | S95: 36 | T95: =IF(Q95>=R95,"No Change","Up") -> Up | V95: =SUM(Q95*S95) -> 62.28 | W95: =SUM(R95*S95) -> 64.08
A96: 5024052 | B96: 5024052 | C96: CROW01 | D96: CROWN | E96: =_xlfn.XLOOKUP(B96,Sheet1!A:A,Sheet1!B:B) -> CRT Vinyl Matt | F96: =D96&" - "&E96 -> CROWN - CRT Vinyl Matt | G96: =_xlfn.XLOOKUP(B96,Sheet1!A:A,Sheet1!C:C) -> Magnolia | H96: =_xlfn.XLOOKUP(B96,Sheet1!A:A,Sheet1!D:D) -> 10L | I96: Item | J96: Item | K96: Paint | L96: 21.81 | M96: STD20 | N96: 3105 | O96: =_xlfn.XLOOKUP(B96,Sheet1!A:A,Sheet1!E:E) -> 21.81 | P96: =_xlfn.XLOOKUP(A96,Sheet2!F:F,Sheet2!H:H) -> 221.26593 | Q96: =_xlfn.XLOOKUP(B96,April23!B:B,April23!D:D) -> 27.72 | R96: =_xlfn.XLOOKUP(B96,Sheet3!B:B,Sheet3!D:D) -> 23.5 | S96: 35.606061 | T96: =IF(Q96>=R96,"No Change","Up") -> No Change | V96: =SUM(Q96*S96) -> 987 | W96: =SUM(R96*S96) -> 836.74242
A97: 5024072 | B97: 5024072 | C97: CROW01 | D97: CROWN | E97: =_xlfn.XLOOKUP(B97,Sheet1!A:A,Sheet1!B:B) -> CRT Vinyl Matt | F97: =D97&" - "&E97 -> CROWN - CRT Vinyl Matt | G97: =_xlfn.XLOOKUP(B97,Sheet1!A:A,Sheet1!C:C) -> Brilliant White | H97: =_xlfn.XLOOKUP(B97,Sheet1!A:A,Sheet1!D:D) -> 10L | I97: Item | J97: Item | K97: Paint | L97: 21.81 | M97: STD20 | N97: 3105 | O97: =_xlfn.XLOOKUP(B97,Sheet1!A:A,Sheet1!E:E) -> 21.81 | P97: =_xlfn.XLOOKUP(A97,Sheet2!F:F,Sheet2!H:H) -> 53.317744 | Q97: =_xlfn.XLOOKUP(B97,April23!B:B,April23!D:D) -> 28.06 | R97: =_xlfn.XLOOKUP(B97,Sheet3!B:B,Sheet3!D:D) -> 24.5 | S97: 34.92516 | T97: =IF(Q97>=R97,"No Change","Up") -> No Change | V97: =SUM(Q97*S97) -> 980 | W97: =SUM(R97*S97) -> 855.66643
A98: 6055214 | B98: 6055214 | C98: CROW01 | D98: CROWN | E98: =_xlfn.XLOOKUP(B98,Sheet1!A:A,Sheet1!B:B) -> DE PROF SYN FLMNT BRUSH BOX SET(1) EACH | F98: =D98&" - "&E98 -> CROWN - DE PROF SYN FLMNT BRUSH BOX SET(1) EACH | H98: Each | I98: Item | J98: Item | K98: Paint | L98: 7.63 | M98: STD20 | N98: 3105 | O98: =_xlfn.XLOOKUP(B98,Sheet1!A:A,Sheet1!E:E) -> 7.63 | P98: =_xlfn.XLOOKUP(A98,Sheet2!F:F,Sheet2!H:H) -> 95.650066 | Q98: =_xlfn.XLOOKUP(B98,April23!B:B,April23!D:D) -> 7.86 | R98: =_xlfn.XLOOKUP(B98,Sheet4!B:B,Sheet4!D:D) -> 7.86 | S98: 34 | T98: =IF(Q98>=R98,"No Change","Up") -> No Change | V98: =SUM(Q98*S98) -> 267.24 | W98: =SUM(R98*S98) -> 267.24
A99: 6042135 | B99: 6042135 | C99: CROW01 | D99: CROWN | E99: =_xlfn.XLOOKUP(B99,Sheet1!A:A,Sheet1!B:B) -> DS PERFORMANCE KETTLE 2.5L | F99: =D99&" - "&E99 -> CROWN - DS PERFORMANCE KETTLE 2.5L | H99: 5L | I99: Item | J99: Item | K99: Paint | L99: 0.72 | M99: STD20 | N99: 3105 | O99: =_xlfn.XLOOKUP(B99,Sheet1!A:A,Sheet1!E:E) -> 0.72 | P99: =_xlfn.XLOOKUP(A99,Sheet2!F:F,Sheet2!H:H) -> 0 | Q99: =_xlfn.XLOOKUP(B99,April23!B:B,April23!D:D) -> 0.76 | R99: =_xlfn.XLOOKUP(B99,Sheet4!B:B,Sheet4!D:D) -> 0.78 | S99: 34 | T99: =IF(Q99>=R99,"No Change","Up") -> Up | V99: =SUM(Q99*S99) -> 25.84 | W99: =SUM(R99*S99) -> 26.52
A100: 6056954 | B100: 6056954 | C100: CROW01 | D100: CROWN | E100: =_xlfn.XLOOKUP(B100,Sheet1!A:A,Sheet1!B:B) -> DS PRODEC POLY DUST SHEET ROLL 50M | F100: =D100&" - "&E100 -> CROWN - DS PRODEC POLY DUST SHEET ROLL 50M | H100: Each | I100: Item | J100: Item | K100: Paint | M100: STD20 | N100: 3105 | O100: =_xlfn.XLOOKUP(B100,Sheet1!A:A,Sheet1!E:E) -> 3.45 | P100: =_xlfn.XLOOKUP(A100,Sheet2!F:F,Sheet2!H:H) -> 0 | Q100: =O100*1.05 -> 3.6225 | R100: =Q100*1.03 -> 3.731175 | S100: 33.976536 | T100: =IF(Q100>=R100,"No Change","Up") -> Up | V100: =SUM(Q100*S100) -> 123.08 | W100: =SUM(R100*S100) -> 126.7724
...

Sheet Sheet7
B1: REF:AC/CRT-TRC/22.05.23/V03
B2: Account Name | D2: Bell Group
B3: Payer Account Number | D3: 12973
B4: or
B5: Price Group
B6: Promotion Code (if applicable)
B7: Start Date
B8: End Date
B9: Authorised By | D9: Ayer/Nigel/Waqas
B10: Date Authorised | D10: 45496
B11: Maintained By (Pricing Dept)
B12: Date Maintained
A15: SAP number | B15: Material description | C15: Colour | D15: Size | E15: Load | F15: Price | H15: 6063177 | I15: DS BARTOLINE 1876 AP ADHESIVE 30 ROLL | J15: 4.38 | L15: 5091202 | M15: ST FLEXIGLOSS XTRA BASE PLATNUM LT 2.5L | N15: 25.93
A16: 5064671 | B16: CRT ACRYLIC EGGSHELL | C16: MAGNOLIA | D16: 5000 | E16: 5064671 | F16: 26.14 | H16: 6048207 | I16: DS REPAIR CARE DRY FLEX 4 | J16: 56.7 | L16: 5091203 | M16: ST FLEXIGLOSS XTRA BASE OPAL MID 2.5L | N16: 25.93
A17: 5024173 | B17: CRT ACRYLIC PRIMER UNDERCOAT | C17: WHITE | D17: 2500 | E17: 5024173 | F17: 14.38 | H17: 6041658 | I17: DS PRODEC REFUSE SACKS 50 ROLL | J17: 8.3055 | L17: 5091204 | M17: ST FLEXIGLOSS XTRA BASE CRYSTAL DK 2.5L | N17: 25.93
A18: 5027073 | B18: CRT ALL PURP PRIMER PX3 | C18: OFF WHITE | D18: 5000 | E18: 5027073 | F18: 25.12 | H18: 6048367 | I18: DS ZINSSER DIF WALLPAPER STRIPPER 1L | J18: 10.76 | L18: 5041062 | M18: ST FLEXIGLOSS X-TRA BRIL WHITE 1L | N18: 10.49
A19: 5094753 | B19: CRT ALL PURP PRIMER PX4 | C19: WHITE | D19: 5000 | E19: 5094753 | F19: 35.56 | H19: 6062944 | I19: DS Q1 CONTRACTOR MASKING TAPE 50M 48MM | J19: 2.1 | L19: 5041097 | M19: ST FLEXIGLOSS X-TRA BRIL WHITE 2.5L | N19: 21.5
A20: 5088598 | B20: CRT CLEAN EXTREME A-BAC SCRUBBABLE MATT | C20: WHITE | D20: 5000 | E20: 5088598 | F20: 35.05 | H20: 6061964 | I20: DS HAMILTON MEDIUM PILE ROLLER 4IN 10PK | J20: 4.1 | L20: 5041116 | M20: ST FLEXIGLOSS X-TRA BRIL WHITE 5L | N20: 43
A21: 5088591 | B21: CRT CLEAN EXTREME ACRYLIC EGGSHELL | C21: WHITE | D21: 5000 | E21: 5088591 | F21: 29.76 | H21: 6060622 | I21: DS ULTRAGRIME PRO POWER SCRUB XXL+ 80PK | J21: 15 | L21: 5089340 | M21: ST METAL GLOSS X-TRA BLACK 2.5L | N21: 25.93
A22: 5061965 | B22: CRT CLEAN EXTREME SCRUBBABLE MATT | C22: WHITE | D22: 5000 | E22: 5061965 | F22: 25.04 | H22: 6062122 | I22: DS HIPPO MP BAMBOO DRY CLOTH 60 SHEETS | J22: 10.82 | L22: 5089400 | M22: ST METAL GLOSS X-TRA WHITE 2.5L | N22: 30.86
A23: 5061839 | B23: CRT CLEAN EXTREME SCRUBBABLE MATT | C23: MAGNOLIA | D23: 5000 | E23: 5061839 | F23: 25.97 | H23: 6055142 | I23: DS ULTRAGRIME PRO XXL+MULTI WIPES 100PK | J23: 13.5 | L23: 5025656 | M23: ST FINE TEXT MATT BLACK 5L | N23: 22.22
A24: 5023890 | B24: CRT COVERMATT EMULSION | C24: WHITE | D24: 5000 | E24: 5023890 | F24: 11.45 | H24: 6058266 | I24: DS FLUXAF POWER CLEAN 750ML | J24: 7.98 | L24: 5025660 | M24: ST FINE TEXT MATT BRIL WHITE 5L | N24: 20.98
A25: 5023888 | B25: CRT COVERMATT EMULSION | C25: MAGNOLIA | D25: 10000 | E25: 5023888 | F25: 23.44 | H25: 6055424 | I25: DE PROFESSIONAL MEDUIM GPUR ROLLER 4IN | J25: 0.39 | L25: 5091199 | M25: ST FINE TEXT MATT BASE PLATNUM LT 5L | N25: 19.75
A26: 5027038 | B26: CRT EGGSHELL | C26: WHITE | D26: 5000 | E26: 5027038 | F26: 22.72 | H26: 6041133 | I26: DS INDASA MTE MASKING TAPE 48MM | J26: 3.3 | L26: 5091200 | M26: ST FINE TEXT MATT BASE OPAL MID 5L | N26: 19.75
A27: 5090805 | B27: CRT FASTFLOW QUICK DRY GLOSS | C27: BLACK | D27: 2500 | E27: 5090805 | F27: 16.13 | H27: 6061968 | I27: DS HAMILTON LONG PILE ROLLER 9IN | J27: 3.32
A28: 5090815 | B28: CRT FASTFLOW QUICK DRY PRIMER UNDERCOAT | C28: WHITE | D28: 2500 | E28: 5090815 | F28: 14.01 | H28: 6042334 | I28: DS PRODEC EXTRA LONG POLYESTER ROL 9IN | J28: 3.4
A29: 5093360 | B29: CRT FASTFLOW QUICK DRY PR U/COAT (FQU) | C29: COLOUR | D29: 2500 | E29: CRTFQUCOL2500 | F29: 16.13 | H29: 6042088 | I29: DS PERFECTION ROLLER MEDIUM 9IN | J29: 3.75
A30: 5092766 | B30: TRC FASTFLOW PRIMER U/COAT (FQU) | C30: COLOUR | D30: 2500 | E30: TRCFQUCOL2500 | F30: 16.13 | H30: 6042089 | I30: DS PERFECTION ROLLER LONG 9IN | J30: 4.5
A31: 5092691 | B31: TRC FASTFLOW PRIMER U/COAT | C31: BASE | D31: 2500 | E31: TRCFQUBAS2500 | F31: 16.13 | H31: 6042090 | I31: DS PERFECTION ROLLER X LONG 9IN | J31: 5.75
A32: 5091986 | B32: CRT FASTFLOW QUICK DRY SATIN | C32: WHITE | D32: 2500 | E32: 5091986 | F32: 16.72 | H32: 6042877 | I32: DS CIRET BAG OF RAGS COLOURED 10K | J32: 33.09
A33: 5024071 | B33: CRT MATT EMULSION | C33: BWT | D33: 5000 | E33: 5024071 | F33: 14.17 | H33: 6053484 | I33: DS BLACKROCK PAINTERS LW GRIPPER GLOVE | J33: 1.659
A34: 5024051 | B34: CRT MATT EMULSION | C34: MAGNOLIA | D34: 5000 | E34: 5024051 | F34: 14.02 | H34: 6055707 | I34: DS OAKEY FLEXIBLE FINISH PADS EX MED/CRS | J34: 1.11
A35: 5090088 | B35: CRT PRO-CO FD CLADDING FINISH | C35: WHITE | D35: 5000 | E35: 5090088 | F35: 44 | H35: 6042110 | I35: DS PRESTIGE CAGE FRAME 9IN | J35: 5.75
A36: 5089389 | B36: CRT PRO-CO HP GLOSS | C36: WHITE | D36: 2500 | E36: 5089389 | F36: 26.14 | H36: 6042316 | I36: DS BLACKROCK PAINTERS L/W GRIPPER GLOVES | J36: 3.41
A37: 5074313 | B37: CRT SATIN | C37: WHITE | D37: 5000 | E37: 5074313 | F37: 26.39 | H37: 5073961 | I37: ST RUST INHIB PRIMER GREY 2.5L | J37: 40
A38: 5074312 | B38: CRT SATIN | C38: WHITE | D38: 2500 | E38: 5074312 | F38: 15.44 | H38: 5028216 | I38: ST 365 SMOOTH BRIL WHITE 5L | J38: 35
A39: 5024027 | B39: CRT STRONGHOLD SMOOTH | C39: WHITE | D39: 10000 | E39: 5024027 | F39: 42.72
A41: Comments

Sheet Sheet6
A1: Product | C1: Sales Volume | D1: Sales Value | E1: Gross Margin | F1: ASP
A2: 5023891 | B2: CT COVERMATT WHITE 10L | C2: 18420 | D2: 43765.92 | E2: 27065.13 | F2: 2.376
A3: 5090984 | B3: CT ACR EGG TIMONOX BASE PLATNUM LT 5L | C3: 3300 | D3: 31680 | E3: 11942.59 | F3: 9.6
A4: 5040579 | B4: CT MATT EMUL TIMONOX BRIL WHITE 5L | C4: 3045 | D4: 25042.08 | E4: 14779.6 | F4: 8.224
A5: 5091032 | B5: CT MATT TIMONOX BASE PLATNUM LT 5L | C5: 1745 | D5: 15007 | E5: 8968.75 | F5: 8.6
A6: 6046432 | B6: WA ANAGLYPTA PRECISION ROYAL OAK RD7000 | C6: 0 | D6: 12392.72 | E6: 6802.09 | F6: 0
A7: 5090989 | B7: CT ACR EGGSHELL BASE PLATNUM LT 5L | C7: 2980 | D7: 12039.2 | E7: 6463.31 | F7: 4.04
A8: 5090996 | B8: CT CLNEX SR SC MATT BSE PLATNUM LT 5L | C8: 1920 | D8: 11500.8 | E8: 7072.71 | F8: 5.99
A9: 5026956 | B9: CT FULL GLOSS WHITE 5L | C9: 2170 | D9: 11162.48 | E9: 4038.2 | F9: 5.144
A10: 5024010 | B10: CT STRONGHOLD SMOOTH MAGNOLIA 5L | C10: 2700 | D10: 10972.8 | E10: 5507.76 | F10: 4.064
A11: 6058266 | B11: DS FLUXAF POWER CLEAN 750ML | C11: 0 | D11: 9583.98 | E11: 5392.49 | F11: 0
A12: 5088437 | B12: CT SHED&FENCE OPAQUE DARK BROWN 5L | C12: 2775 | D12: 9146.4 | E12: 3661.44 | F12: 3.296
A13: 5091086 | B13: CT TIMONOX SC MATT BASE PLATNUM LT 5L | C13: 725 | D13: 8202.65 | E13: 3854.1 | F13: 11.314
... A1593: 5023901 | B1593: CT COVERMATT SOFT WHITE 10L | C1593: -10 | D1593: -23.44 | E1593: -12.37 | F1593: 2.344
A1594: Total | C1594: 87182 | D1594: 523208.82 | E1594: 273508.99 | F1594: 6.00134

Sheet Sheet3
A1: Cust_No. | B1: SAP_Number | C1: Matl_Desc. | D1: Price | E1: Desc. | F1: Size | G1: Unit | H1: Date | I1: EAN-code | J1: Currency
A2: 12973 | B2: 5092337 | C2: MC ECLIPSE EMULSION TINT COL 10L | D2: 21.76 | E2: MC ECLIPSE EMULSION IDS COL | F2: 1 | G2: PC | H2: 45505 | J2: GBP
A3: 12973 | B3: 5092338 | C3: MC ECLIPSE EMULSION TINT COL 5L | D3: 11 | E3: MC ECLIPSE EMULSION IDS COL | F3: 1 | G3: PC | H3: 45505 | J3: GBP
A4: 12973 | B4: 5101250 | C4: MC QUICK DRY EGGSHELL BRIL WHITE 2.5L | D4: 12 | E4: MAC Quick Dry Eggshell BWT | F4: 1 | G4: PC | H4: 45505 | I4: 5010131585517 | J4: GBP
A5: 12973 | B5: 5101270 | C5: MC QUICK DRY EGGSHELL BLACK 2.5L | D5: 12.8 | E5: MAC Quick Dry Eggshell COL | F5: 1 | G5: PC | H5: 45505 | I5: 5010131585630 | J5: GBP
A6: 12973 | B6: 5101249 | C6: MC QUICK DRY GLOSS BRIL WHITE 1L | D6: 6.4 | E6: MAC Quick Dry Gloss BWT | F6: 1 | G6: PC | H6: 45505 | I6: 5010131585500 | J6: GBP
A7: 12973 | B7: 5101271 | C7: MC QUICK DRY GLOSS BRIL WHITE 5L | D7: 24.8 | E7: MAC Quick Dry Gloss BWT | F7: 1 | G7: PC | H7: 45505 | I7: 5010131585654 | J7: GBP
A8: 12973 | B8: 5101272 | C8: MC QUICK DRY GLOSS BLACK 2.5L | D8: 15.2 | E8: MAC Quick Dry Gloss COL | F8: 1 | G8: PC | H8: 45505 | I8: 5010131585661 | J8: GBP
A9: 12973 | B9: 5101276 | C9: MC QUICK DRY SATIN BRIL WHITE 5L | D9: 24.8 | E9: MAC Quick Dry Satin BWT | F9: 1 | G9: PC | H9: 45505 | I9: 5010131585715 | J9: GBP
A10: 12973 | B10: 5101252 | C10: MC QUICK DRY SATIN BRIL WHITE 2.5L | D10: 12.8 | E10: MAC Quick Dry Satin BWT | F10: 1 | G10: PC | H10: 45505 | I10: 5010131585531 | J10: GBP
A11: 12973 | B11: 5101251 | C11: MC QUICK DRY SATIN BRIL WHITE 1L | D11: 7.2 | E11: MAC Quick Dry Satin BWT | F11: 1 | G11: PC | H11: 45505 | I11: 5010131585524 | J11: GBP
A12: 12973 | B12: 5101277 | C12: MC QUICK DRY SATIN BLACK 2.5L | D12: 15.2 | E12: MAC Quick Dry Satin COL | F12: 1 | G12: PC | H12: 45505 | I12: 5010131585722 | J12: GBP
A13: 12973 | B13: 5092359 | C13: MC VINYL MATT EMULSION TINT COL 10L | D13: 27.75 | E13: MC VINYL MATT EMULSION IDS COL | F13: 1 | G13: PC | H13: 45505 | J13: GBP
A14: 12973 | B14: 5092358 | C14: MC VINYL MATT EMULSION TINT COL 5L | D14: 14.31 | E14: MC VINYL MATT EMULSION IDS COL | F14: 1 | G14: PC | H14: 45505 | J14: GBP
A15: 12973 | B15: 5092357 | C15: MC VINYL MATT EMULSION TINT COL 2.5L | D15: 9.63 | E15: MC VINYL MATT EMULSION IDS COL | F15: 1 | G15: PC | H15: 45505 | J15: GBP
A16: 12973 | B16: 5091756 | C16: MC MID SHEEN EMUL MC1 TINTED 5L | D16: 17.92 | E16: MC MID SHEEN EMULSION IDS COL | F16: 1 | G16: PC | H16: 45505 | J16: GBP
A17: 12973 | B17: 5091755 | C17: MC MID SHEEN EMUL MC1 TINTED 2.5L | D17: 11.43 | E17: MC MID SHEEN EMULSION IDS COL | F17: 1 | G17: PC | H17: 45505 | J17: GBP
A18: 12973 | B18: 5091754 | C18: MC MID SHEEN EMUL MC1 TINTED 10L | D18: 25.92 | E18: MC MID SHEEN EMULSION IDS COL | F18: 1 | G18: PC | H18: 45505 | J18: GBP
A19: 12973 | B19: 5091753 | C19: MC MID SHEEN EMUL MC2 TINTED 5L | D19: 17.92 | E19: MC MID SHEEN EMULSION IDS COL | F19: 1 | G19: PC | H19: 45505 | J19: GBP
A20: 12973 | B20: 5091752 | C20: MC MID SHEEN EMUL MC2 TINTED 2.5L | D20: 11.43 | E20: MC MID SHEEN EMULSION IDS COL | F20: 1 | G20: PC | H20: 45505 | J20: GBP
A21: 12973 | B21: 5091751 | C21: MC MID SHEEN EMUL MC3 TINTED 5L | D21: 17.92 | E21: MC MID SHEEN EMULSION IDS COL | F21: 1 | G21: PC | H21: 45505 | J21: GBP
A22: 12973 | B22: 5091750 | C22: MC MID SHEEN EMUL MC3 TINTED 2.5L | D22: 11.43 | E22: MC MID SHEEN EMULSION IDS COL | F22: 1 | G22: PC | H22: 45505 | J22: GBP
A23: 12973 | B23: 5092342 | C23: MC GLOSS TINT COL 1L | D23: 6.25 | E23: MC GLOSS IDS COL | F23: 1 | G23: PC | H23: 45505 | J23: GBP
A24: 12973 | B24: 5092336 | C24: MC ACRYLIC EGGSHELL TINT COL 5L | D24: 23.07 | E24: MC ACRYLIC EGGSHELL IDS COL | F24: 1 | G24: PC | H24: 45505 | J24: GBP
A25: 12973 | B25: 5088591 | C25: CT CLNEX SR AC EGG WHITE 5L | D25: 30.65 | E25: CRT Clean Extreme Acr Egg White | F25: 1 | G25: PC | H25: 45505 | I25: 5010131525407 | J25: GBP
A26: 12973 | B26: 5088704 | C26: CT CLN EXTREME ACR EGG 5L | D26: 35.83 | E26: CRT Clean Extreme Acr Egg Col | F26: 1 | G26: PC | H26: 45505 | I26: 5010131575341 | J26: GBP
A27: 12973 | B27: 5088596 | C27: CT CLNEX AB AC EGG WHITE 5L | D27: 36.1 | E27: CRT Steracryl A/Bac Acr Egg White | F27: 1 | G27: PC | H27: 45505 | I27: 5010131525452 | J27: GBP
A28: 12973 | B28: 5088693 | C28: CT CLNEX A/BAC ACR EGG 5L | D28: 44.92 | E28: CRT Steracryl A/Bac Acr Egg Col | F28: 1 | G28: PC | H28: 45505 | I28: 5010131575372 | J28: GBP
A29: 12973 | B29: 5090513 | C29: CT CLNEX MI AC EGGSHELL WHITE 2.5L | D29: 17.31 | E29: CRT Steracryl M/Inhibit Acr Egg White | F29: 1 | G29: PC | H29: 45505 | I29: 5010131548789 | J29: GBP
A30: 12973 | B30: 5088594 | C30: CT CLNEX MI AC EGGSHELL WHITE 5L | D30: 35.41 | E30: CRT Steracryl M/Inhibit Acr Egg White | F30: 1 | G30: PC | H30: 45505 | I30: 5010131525438 | J30: GBP
A31: 12973 | B31: 5088695 | C31: CT CLNEX M INH ACR EGG 5L | D31: 39.74 | E31: CRT Steracryl M/Inhibit Acr Egg Col | F31: 1 | G31: PC | H31: 45505 | I31: 5010131575396 | J31: GBP
A32: 12973 | B32: 5091934 | C32: CT CLNEX M INH ACR EGG 2.5L | D32: 21.53 | E32: CRT Steracryl M/Inhibit Acr Egg Col | F32: 1 | G32: PC | H32: 45505 | I32: 5010131575402 | J32: GBP
A33: 12973 | B33: 5064685 | C33: CT ACRYLIC EGGSHELL WHITE 2.5L | D33: 14.69 | E33: CRT Best Fin Acrylic Eggshell White | F33: 1 | G33: PC | H33: 45505 | I33: 5010131494567 | J33: GBP
A34: 12973 | B34: 5064686 | C34: CT ACRYLIC EGGSHELL WHITE 5L | D34: 17.4 | E34: CRT Best Fin Acrylic Eggshell White | F34: 1 | G34: PC | H34: 45505 | I34: 5010131494574 | J34: GBP
A35: 12973 | B35: 5097347 | C35: CT ACRYLIC EGGSHELL WHITE 10L | D35: 33 | E35: CRT Best Fin Acrylic Eggshell White | F35: 1 | G35: PC | H35: 45505 | I35: 5010131584220 | J35: GBP
A36: 12973 | B36: 5064671 | C36: CT ACRYLIC EGGSHELL MAGNOLIA 5L | D36: 26.92 | E36: CRT Best Fin Acrylic Eggshell Magnolia | F36: 1 | G36: PC | H36: 45505 | I36: 5010131494413 | J36: GBP
... A72: 12973 | B72: 5093674 | C72: CT FASTFLOW QD EGGSHELL WHITE 2.5L | D72: 18.94 | E72: CRT Fastflow Quick Dry Eggshell White | F72: 1 | G72: PC | H72: 45505 | I72: 5010131576942 | J72: GBP
A73: 12973 | B73: 5095633 | C73: CT FASTFLOW QD EGGSHELL 2.5L | D73: 25.36 | E73: CT FF QD Eggshell Base COL | F73: 1 | G73: PC | H73: 45505 | J73: GBP
A74: 12973 | B74: 5095632 | C74: CT FASTFLOW QD EGGSHELL 1L | D74: 11.58 | E74: CT FF QD Eggshell Base COL | F74: 1 | G74: PC | H74: 45505 | J74: GBP
A75: 12973 | B75: 5090805 | C75: CT FASTFLOW QD GLOSS BLACK 2.5L | D75: 16.61 | E75: CRT Fastflow Quick Dry Gloss Black | F75: 1 | G75: PC | H75: 45505 | I75: 5010131552809 | J75: GBP
A76: 12973 | B76: 5090869 | C76: CT FASTFLOW QD GLOSS BLACK 1L | D76: 8.43 | E76: CRT Fastflow Quick Dry Gloss Black | F76: 1 | G76: PC | H76: 45505 | I76: 5010131553417 | J76: GBP
A77: 12973 | B77: 5090804 | C77: CT FASTFLOW QD GLOSS WHITE 5L | D77: 26.05 | E77: CRT Fastflow Quick Dry Gloss White | F77: 1 | G77: PC | H77: 45505 | I77: 5010131552793 | J77: GBP
A78: 12973 | B78: 5090803 | C78: CT FASTFLOW QD GLOSS WHITE 2.5L | D78: 14.42 | E78: CRT Fastflow Quick Dry Gloss White | F78: 1 | G78: PC | H78: 45505 | I78: 5010131552786 | J78: GBP
A79: 12973 | B79: 5090802 | C79: CT FASTFLOW QD GLOSS WHITE 1L | D79: 7.33 | E79: CRT Fastflow Quick Dry Gloss White | F79: 1 | G79: PC | H79: 45505 | I79: 5010131552779 | J79: GBP
A80: 12973 | B80: 5093355 | C80: CT FASTFLOW GLOSS 5L | D80: 29.9 | E80: CRT Fastflow Quick Dry Gloss Colour | F80: 1 | G80: PC | H80: 45505 | I80: 5010131575167 | J80: GBP
A81: 12973 | B81: 5093354 | C81: CT FASTFLOW GLOSS 2.5L | D81: 16.61 | E81: CRT Fastflow Quick Dry Gloss Colour | F81: 1 | G81: PC | H81: 45505 | I81: 5010131575174 | J81: GBP
A82: 12973 | B82: 5093353 | C82: CT FASTFLOW GLOSS 1L | D82: 8.43 | E82: CRT Fastflow Quick Dry Gloss Colour | F82: 1 | G82: PC | H82: 45505 | I82: 5010131575181 | J82: GBP
A83: 12973 | B83: 5090814 | C83: CT FASTFLOW QD UNDRCOAT WHITE 1L | D83: 7.33 | E83: CRT Fastflow Quick Dry Primer U/coat Whi | F83: 1 | G83: PC | H83: 45505 | I83: 5010131552892 | J83: GBP
A84: 12973 | B84: 5090815 | C84: CT FASTFLOW QD UNDRCOAT WHITE 2.5L | D84: 14.42 | E84: CRT Fastflow Quick Dry Primer U/coat Whi | F84: 1 | G84: PC | H84: 45505 | I84: 5010131552908 | J84: GBP
A85: 12973 | B85: 5090816 | C85: CT FASTFLOW QD UNDRCOAT WHITE 5L | D85: 26 | E85: CRT Fastflow Quick Dry Primer U/coat Whi | F85: 1 | G85: PC | H85: 45505 | I85: 5010131552915 | J85: GBP
A86: 12973 | B86: 5093359 | C86: CT FASTFLOW UNDERCOAT 1L | D86: 8.43 | E86: CRT Fastflow Quick Dry Primer/Und Col | F86: 1 | G86: PC | H86: 45505 | I86: 5010131575204 | J86: GBP
... A281: 12973 | B281: 5029315 | C281: MC UNDERCOAT 1L | D281: 6.25 | E281: MAC Solvent-borne Undercoat COL | F281: 1 | G281: PC | H281: 45505 | I281: 5010131506123 | J281: GBP
A282: 12973 | B282: 5092261 | C282: CT ACRYLIC EGG TIMONOX TINT COL 5L | D282: 48 | E282: TRC Timonox Acrylic Egg Colour | F282: 1 | G282: PC | H282: 45505 | J282: GBP
A283: 12973 | B283: 5092262 | C283: CT ACRYLIC EGGSHELL TINT COL 2.5L | D283: 16.24 | E283: TRC Acrylic Eggshell Colour | F283: 1 | G283: PC | H283: 45505 | J283: GBP
A284: 12973 | B284: 5095922 | C284: CT CLN EXT MI SCR MATT TINT COL 5L | D284: 35 | E284: TRC Clean Extreme MI SC Matt Colour | F284: 1 | G284: PC | H284: 45505 | J284: GBP
A285: 12973 | B285: 5095923 | C285: CT CLN EXT MI SCR MATT TINT COL 2.5L | D285: 23.16 | E285: TRC Clean Extreme MI SC Matt Colour | F285: 1 | G285: PC | H285: 45505 | J285: GBP
A286: 12973 | B286: 5092299 | C286: CT FASTFLOW GLOSS TINT COL 2.5L | D286: 16.61 | E286: TRC Fastflow Quick Dry Gloss Colour | F286: 1 | G286: PC | H286: 45505 | J286: GBP
A287: 12973 | B287: 5092298 | C287: CT FASTFLOW GLOSS TINT COL 1L | D287: 8.43 | E287: TRC Fastflow Quick Dry Gloss Colour | F287: 1 | G287: PC | H287: 45505 | J287: GBP
A288: 12973 | B288: 5092766 | C288: CT FASTFLOW UNDERCOAT TINT COL 2.5L | D288: 16.61 | E288: TRC Primer/Undercoat Colour | F288: 1 | G288: PC | H288: 45505 | J288: GBP
A289: 12973 | B289: 5092335 | C289: CT FASTFLOW UNDERCOAT TINT COL 5L | D289: 29.88 | E289: TRC Primer/Undercoat Colour | F289: 1 | G289: PC | H289: 45505 | J289: GBP
A290: 12973 | B290: 5092334 | C290: CT FASTFLOW UNDERCOAT TINT COL 1L | D290: 8.43 | E290: TRC Primer/Undercoat Colour | F290: 1 | G290: PC | H290: 45505 | J290: GBP
A291: 12973 | B291: 5092267 | C291: CT COVERMATT TINT COL 10L | D291: 29.64 | E291: TRC Covermatt COL | F291: 1 | G291: PC | H291: 45505 | J291: GBP
A292: 12973 | B292: 5092268 | C292: CT COVERMATT TINT COL 5L | D292: 14.94 | E292: TRC Covermatt COL | F292: 1 | G292: PC | H292: 45505 | J292: GBP
A293: 12973 | B293: 5092310 | C293: CT MATT EMULSION TINT COL 10L | D293: 32.32 | E293: TRC Matt COL | F293: 1 | G293: PC | H293: 45505 | J293: GBP
... A323: 12973 | B323: 5097573 | C323: CT CLN AIR PLATINUM LT TINTED 5L | D323: 46.24 | E323: TRC Clean Air Scrub Matt Col Platinum | F323: 1 | G323: PC | H323: 45505 | J323: GBP

Sheet Sheet4
A1: Cust_No. | B1: SAP_Number | C1: Matl_Desc. | D1: Price | E1: Desc. | F1: Size | G1: Unit | H1: Date | I1: EAN-code | J1: Currency
A2: 12973 | B2: 6055954 | C2: DS OAKEY BTW CTS FINISH PAPER 240G 5M | D2: 8.24 | E2: BDS Abrasives | F2: 1 | G2: PC | H2: 45505 | I2: 3157629665138 | J2: GBP
A3: 12973 | B3: 6055709 | C3: DS OAKEY FLEX FINISH PAD EX FINE/FINE | D3: 1.14 | E3: BDS Abrasives | F3: 1 | G3: PC | H3: 45505 | I3: 3157629794685 | J3: GBP
A4: 12973 | B4: 6055707 | C4: DS OAKEY FLEXIBLE FINISH PADS EX MED/CRS | D4: 1.14 | E4: BDS Abrasives | F4: 1 | G4: PC | H4: 45505 | I4: 3157629794678 | J4: GBP
A5: 12973 | B5: 6053563 | C5: DS INDASA ABRASIVE BLOCK P100 1PC | D5: 1.03 | E5: BDS Abrasives | F5: 1 | G5: PC | H5: 45505 | I5: 5603902463000 | J5: GBP
A6: 12973 | B6: 6053562 | C6: DS INDASA RHYNALOX PLUSLINE ASSRTD 10PK | D6: 6.7 | E6: BDS Abrasives | F6: 1 | G6: PC | H6: 45505 | I6: 5603902583708 | J6: GBP
A7: 12973 | B7: 6053561 | C7: DS INDASA RHYNOWOOD ASSORTED 5PK | D7: 2.32 | E7: BDS Abrasives | F7: 1 | G7: PC | H7: 45505 | I7: 5603902583715 | J7: GBP
A8: 12973 | B8: 6053560 | C8: DS INDASA RHYNOWET W LINE ASSRTD 4PK | D8: 2.83 | E8: BDS Abrasives | F8: 1 | G8: PC | H8: 45505 | I8: 5603902583692 | J8: GBP
A9: 12973 | B9: 6047323 | C9: DS INDASA SPONGE PADS P120 10PK | D9: 5.67 | E9: BDS Abrasives | F9: 1 | G9: PC | H9: 45505 | I9: 5603902014493 | J9: GBP
A10: 12973 | B10: 6047322 | C10: DS INDASA SPONGE PADS P100 10PK | D10: 5.67 | E10: BDS Abrasives | F10: 1 | G10: PC | H10: 45505 | I10: 5603902014486 | J10: GBP
A11: 12973 | B11: 6047321 | C11: DS INDASA SPONGE PADS P80 10PK | D11: 5.67 | E11: BDS Abrasives | F11: 1 | G11: PC | H11: 45505 | I11: 5603902476314 | J11: GBP
A12: 12973 | B12: 6047320 | C12: DS INDASA SPONGE PADS P60 10PK | D12: 5.67 | E12: BDS Abrasives | F12: 1 | G12: PC | H12: 45505 | I12: 5603902014479 | J12: GBP
A13: 12973 | B13: 6046792 | C13: DS INDASA RHYNALOX PLUS P80 115MM 10M | D13: 9.27 | E13: BDS Abrasives | F13: 1 | G13: PC | H13: 45505 | I13: 5603902498637 | J13: GBP
... A513: 12973 | B513: 5091199 | C513: ST FINE TEXT MATT BASE PLATNUM LT 5L | D513: 26.62 | E513: ST FINE TEXT MATT BASE PLATINUM | F513: 1 | G513: PC | H513: 45505 | I513: 5010131556906 | J513: GBP
A514: 6041137 - DS INDASA RHYNOLITE YEL 60G 115MMX10M | B514: 0 | C514: 142.85 | E514: 6041137 | F514: 6041137
A515: 5012994 - SD EXTRA EBONY 2.5L | B515: 10 | C515: 142.16 | E515: 5012994 | F515: 5012994
A516: 6042110 - DS PRESTIGE CAGE FRAME 9IN | B516: 0 | C516: 141.9 | E516: 6042110 | F516: 6042110
A517: 5028579 - SD EXTRA NATURAL 2.5L | B517: 10 | C517: 140.47 | E517: 5028579 | F517: 5028579
A518: 5027813 - MC GLOSS BLACK 5L | B518: 40 | C518: 140.11 | E518: 5027813 | F518: 5027813
A519: 6041627 - DS PRODEC LONG LIFE MASK TAPE 50MM 50M | B519: 0 | C519: 139.8 | E519: 6041627 | F519: 6041627
A520: 6040923 - DS FROGTAPE M SURF MASK 41.1M 24MM | B520: 0 | C520: 139.17 | E520: 6040923 | F520: 6040923
A521: 5092804 - CT FFLOW QD SATIN BASE OPAL MID 2.5L | B521: 20 | C521: 138.75 | E521: 5092804 | F521: 5092804
A522: 6046274 - DS PRODEC PAINTERS TROUSERS 34IN | B522: 0 | C522: 137.91 | E522: 6046274 | F522: 6046274
A523: 5091198 - ST EGGSHELL X-TRA BASE CRYSTAL DK 2.5L | B523: 7.5 | C523: 137.54 | E523: 5091198 | F523: 5091198
A524: 5027902 - MC UNDERCOAT DEEP GRY 5L | B524: 40 | C524: 136.76 | E524: 5027902 | F524: 5027902
A525: 5091007 - CT EGGSHELL BASE OPAL MID 5L | B525: 25 | C525: 135.88 | E525: 5091007 | F525: 5091007
... A683: 6040200 - WA ERFURT LINING 2000 DOUBLE | B683: 0 | C683: 80.86 | E683: 6040200 | F683: 6040200
A684: 5026922 - CT STRONGHOLD PR UC DARK GREY 2.5L | B684: 15 | C684: 80.64 | E684: 5026922 | F684: 5026922 | G684: 16.67 | H684: 4.8374325
A685: 5027121 - CT UNDERCOAT DARK GREY 2.5L | B685: 22.5 | C685: 80.41 | E685: 5027121 | F685: 5027121
A686: 5040681 - CT MATT EMULSION MAGNOLIA 6L | B686: 12 | C686: 80.41 | E686: 5040681 | F686: 5040681
A687: 6047222 - DS FARR & BALL MODERN EMULSION 2.5L | B687: 0 | C687: 79.86 | E687: 6047222 | F687: 6047222
A688: 6056052 - DS GYPROC JOINT TAPE 153M | B688: 0 | C688: 79.36 | E688: 6056052 | F688: 6056052
A689: 6047049 - DS BOLLOM FGUARD UL MAT WHITE BASE 5L | B689: 0 | C689: 79.34 | E689: 6047049 | F689: 6047049
A690: 5028845 - SD SUPERDEC BASE WHITE W0 2.5L | B690: 5 | C690: 79.02 | E690: 5028845 | F690: 5028845
A691: 5091144 - MC VINYL MATT EMUL BASE MC1 10L | B691: 40 | C691: 78.76 | E691: 5091144 | F691: 5091144
A692: 6041625 - DS PRODEC PRE EDGE MASK 48MM 50M | B692: 0 | C692: 78.39 | E692: 6041625 | F692: 6041625
A693: 5028739 - SD PV67 GLOSS SET 5L | B693: 5 | C693: 78.08 | E693: 5028739 | F693: 5028739
A694: 6046066 - DS PRESTIGE BUCKET 25L | B694: 0 | C694: 77.81 | E694: 6046066 | F694: 6046066
A695: 6047194 - DS PURDY POWERLOCK EXTENSION POLE 4-8FT | B695: 0 | C695: 77.7 | E695: 6047194 | F695: 6047194
A696: 6046869 - DS BEDEC MSP GLOSS BLACK 750ML | B696: 0 | C696: 77.52 | E696: 6046869 | F696: 6046869
... A917: 6057416 - DS ARROWORTHY CL MFIBER MEDIUM 4IN 10PK | B917: 0 | C917: 34.74 | E917: 6057416 | F917: 6057416
A918: 6055429 - DE PROFESSIONAL LONG PILE ROLLER 12IN | B918: 0 | C918: 34.58 | E918: 6055429 | F918: 6055429 | H918: 25
A919: 5094752 - CT ALL PURP PRIMER PX4 WHITE 1L | B919: 4 | C919: 34.48 | E919: 5094752 | F919: 5094752
A920: 6053477 - DS PRODEC SUPERLOCK ELITE EXT POLE 2-4FT | B920: 0 | C920: 34.2 | E920: 6053477 | F920: 6053477
A921: 6041480 - DS BLACKFRIAR CHALKBOARD PAINT 500ML | B921: 0 | C921: 34.16 | E921: 6041480 | F921: 6041480
A922: 5028458 - SD CLASSIC ANTIQ PINE 2.5L | B922: 2.5 | C922: 34.05 | E922: 5028458 | F922: 5028458
A923: 5028476 - SD CLASSIC DK PALSNDR 2.5L | B923: 2.5 | C923: 34.05 | E923: 5028476 | F923: 5028476
A924: 6058621 - DS HB42 ULT MAX FLEX DEC CAULK 380ML | B924: 0 | C924: 34.04 | E924: 6058621 | F924: 6058621
A925: 6056837 - DS HIPPO PRO 3 BROWN 290ML | B925: 0 | C925: 33.93 | E925: 6056837 | F925: 6056837
A926: 5026915 - CT STRONGHOLD GLOSS BLACK 2.5L | B926: 5 | C926: 33.74 | E926: 5026915 | F926: 5026915 | G926: 16.67 | H926: 2.0239952
A927: 6048366 - DS ZINSSER DIF WALLPAPER STRIPPER 2.5L | B927: 0 | C927: 33.66 | E927: 6048366 | F927: 6048366
A928: 5028578 - SD EXTRA NATURAL 1L | B928: 2 | C928: 33.5 | E928: 5028578 | F928: 5028578
A929: 5096142 - CR CRAFTED LUX FL MATT SOW GOOD 2.5L | B929: 2.5 | C929: 33.33 | E929: 5096142 | F929: 5096142
A930: 6059800 - DE ULTIMATE MASONRY KIT 5PC | B930: 0 | C930: 33.3 | E930: 6059800 | F930: 6059800
A931: 5096601 - MC DURABLE MATT BRIL WHITE 10L | B931: 10 | C931: 33.29 | E931: 5096601 | F931: 5096601
A932: 5028793 - SD QD WOODSTAIN ROSEWOOD 2.5L | B932: 2.5 | C932: 33.24 | E932: 5028793 | F932: 5028793
A933: 6061548 - DS GO PAINT ROLL AND GO BUCKET LINER 15L | B933: 0 | C933: 33.06 | E933: 6061548 | F933: 6061548
A934: 6042051 - DS PRESTIGE SYNTHETIC BOX SET 5PC | B934: 0 | C934: 32.89 | E934: 6042051 | F934: 6042051
A935: 6056044 - DE ULT ADV SYNTH BRUSH OVAL SET 3PC | B935: 0 | C935: 32.88 | E935: 6056044 | F935: 6056044
A936: 5096091 - SD SHED AND FENCE PROT GRN FOREST 5L | B936: 10 | C936: 32.76 | E936: 5096091 | F936: 5096091
A937: 6054690 - DS PRODEC TROJAN BRUSHES+WOODWORKR 6PC | B937: 0 | C937: 32.66 | E937: 6054690 | F937: 6054690
A938: 6047323 - DS INDASA SPONGE PADS P120 10PK | B938: 0 | C938: 32.5 | E938: 6047323 | F938: 6047323
... A1188: 6057852 - DS KANA TANK BRUSH SET (1, 2 & 3IN) 3PC | B1188: 0 | C1188: 13.87 | E1188: 6057852 | F1188: 6057852
A1189: 6055448 - DE ESSENTIAL ROLLER KIT MEDUIM 9IN | B1189: 0 | C1189: 13.85 | E1189: 6055448 | F1189: 6055448 | H1189: 4
A1190: 6041145 - DS INDASA RHYNOSOFT SPONGE P240 20PK | B1190: 0 | C1190: 13.78 | E1190: 6041145 | F1190: 6041145
A1191: 6055536 - DS WRX SPRAY PAINT GLOSS WHT 400ML | B1191: 0 | C1191: 13.58 | E1191: 6055536 | F1191: 6055536
A1192: 6040572 - DS TETRION POWERFIL 2K FILLER 600ML | B1192: 0 | C1192: 13.55 | E1192: 6040572 | F1192: 6040572
A1193: 5028457 - SD CLASSIC ANTIQ PINE 1L | B1193: 1 | C1193: 13.31 | E1193: 5028457 | F1193: 5028457
A1194: 5028502 - SD CLASSIC NATURAL 1L | B1194: 1 | C1194: 13.31 | E1194: 5028502 | F1194: 5028502
A1195: 6060505 - DS TOUPRET INTERIOR POWDER FILLER 1K | B1195: 0 | C1195: 13.24 | E1195: 6060505 | F1195: 6060505
A1196: 6042181 - DS OLFA MP RAZOR SCRAPER C/W BLADE BTC1 | B1196: 0 | C1196: 13.17 | E1196: 6042181 | F1196: 6042181
A1197: 6055468 - DS INDASA RHYNALOX STRIPS P120 50PK | B1197: 0 | C1197: 13.17 | E1197: 6055468 | F1197: 6055468
A1198: 6061786 - DE PROF SOFT GRIP FILLING KNIFE 50MM | B1198: 0 | C1198: 13.16 | E1198: 6061786 | F1198: 6061786 | H1198: 5
A1199: 6061791 - DE PROF SOFT GRIP 6 IN 1 PAINTING TOOL | B1199: 0 | C1199: 13.11 | E1199: 6061791 | F1199: 6061791
A1200: 5028786 - SD QD WOODSTAIN REDWOOD 1L | B1200: 1 | C1200: 13.01 | E1200: 5028786 | F1200: 5028786
A1201: 6033648 - DS BTW CTS FINISH PAPER 180GRD(10) EACH | B1201: 0 | C1201: 13 | E1201: 6033648 | F1201: 6033648
A1202: 6053563 - DS INDASA ABRASIVE BLOCK P100 1PC | B1202: 0 | C1202: 12.88 | E1202: 6053563 | F1202: 6053563
A1203: 5027112 - CT UNDERCOAT CHARC GREY 1L | B1203: 3 | C1203: 12.78 | E1203: 5027112 | F1203: 5027112
A1204: 5028483 - SD CLASSIC AFRCN WNUT 1L | B1204: 1 | C1204: 12.68 | E1204: 5028483 | F1204: 5028483
A1205: 5027036 - CT EGGSHELL WHITE 1L | B1205: 2 | C1205: 12.61 | E1205: 5027036 | F1205: 5027036
A1206: 6057914 - DS PREP H/D STRIPPING KNIFE 3IN | B1206: 0 | C1206: 12.6 | E1206: 6057914 | F1206: 6057914
A1207: 6041579 - DS PRODEC VINYL SMOOTHER 12IN | B1207: 0 | C1207: 12.58 | E1207: 6041579 | F1207: 6041579
A1208: 6042825 - DS BEELINE OVERLAP & REPAIR ADHES 1K | B1208: 0 | C1208: 12.58 | E1208: 6042825 | F1208: 6042825
A1209: 6061953 - DS HAMILTON FINE TIP FLAT BRUSH 3IN | B1209: 0 | C1209: 12.57 | E1209: 6061953 | F1209: 6061953
A1210: 6043316 - DS PRODEC STAINLESS STEEL SCISSORS 11IN | B1210: 0 | C1210: 12.49 | E1210: 6043316 | F1210: 6043316
... A1426: 5024117 - CT MATT EMULSION BASE PREMIUM 2.5L | B1426: 0 | C1426: 0 | E1426: 5024117 | F1426: 5024117
A1427: 5024118 - CT MATT EMULSION BASE PREMIUM 5L | B1427: 0 | C1427: 0 | E1427: 5024118
A1428: 5024229 - CT SILK EMULSION BRIL WHITE 2.5L | B1428: 0 | C1428: 0 | E1428: 5024229
A1429: 5025050 - MC ECLIPSE EMULSION MAGNOLIA 15L | B1429: 0 | C1429: 0 | E1429: 5025050
A1430: 5025051 - MC ECLIPSE EMULSION MAGNOLIA 5L | B1430: 0 | C1430: 0 | E1430: 5025051
A1431: 5025065 - MC ACRYLIC EGGSHELL BSE 453 5L | B1431: 0 | C1431: 0 | E1431: 5025065
A1432: 5025098 - MC VINYL MATT EMUL BASE 450 5L | B1432: 0 | C1432: 0 | E1432: 5025098
A1433: 5025111 - MC MARBLETEX SMOOTH BRIL WHITE 5L | B1433: 0 | C1433: 0 | E1433: 5025111
A1434: 5025112 - MC MARBLETEX SMOOTH BRIL WHITE 10L | B1434: 0 | C1434: 0 | E1434: 5025112
A1435: 5025115 - MC MARBLETEX SMOOTH BSE 403 5L | B1435: 0 | C1435: 0 | E1435: 5025115
A1436: 5025194 - MC MID SHEEN EMULSION BRIL WHITE 2.5L | B1436: 0 | C1436: 0 | E1436: 5025194
A1437: 5025216 - MC VINYL SILK EMULSION BRIL WHITE 5L | B1437: 0 | C1437: 0 | E1437: 5025216
A1438: 5025223 - MC VINYL SILK EMUL BASE 452 5L | B1438: 0 | C1438: 0 | E1438: 5025223
... A1810: 6062544 - DS PRODEC DEC SYNTHETIC BRUSH SET 4PC | B1810: 0 | C1810: 0 | E1810: 6062544
A1811: 6049200 | B1811: DS BLACK + DECKER STRIPPER KX3300T 240V | E1811: 74.48 | F1811: 2408
...

Sheet Sheet5
A1: Cust_No. | B1: SAP_Number | C1: Matl_Desc. | D1: Price | E1: Desc. | F1: Size | G1: Unit | H1: Date | I1: EAN-code | J1: Currency
A2: 12973 | B2: 5091367 | C2: SD BEAUTIFLEX WHITE 2.5L | D2: 38.64 | E2: SAD Beautiflex White | F2: 1 | G2: PC | H2: 45505 | I2: 5010131557972 | J2: GBP
A3: 12973 | B3: 5091369 | C3: SD BEAUTIFLEX BLACK 2.5L | D3: 38.64 | E3: SAD Beautiflex Colour | F3: 1 | G3: PC | H3: 45505 | I3: 5010131557996 | J3: GBP
A4: 12973 | B4: 5091371 | C4: SD BEAUTIFLEX HICKORY 2.5L | D4: 37.52 | E4: SAD Beautiflex Colour | F4: 1 | G4: PC | H4: 45505 | I4: 5010131558016 | J4: GBP
A5: 12973 | B5: 5091374 | C5: SD BEAUTIFLEX BASE WHITE W0 1L | D5: 17.39 | E5: SAD Beautiflex Base White | F5: 1 | G5: PC | H5: 45505 | I5: 5010131558047 | J5: GBP
A6: 12973 | B6: 5091375 | C6: SD BEAUTIFLEX BASE WHITE W0 2.5L | D6: 38.64 | E6: SAD Beautiflex Base White | F6: 1 | G6: PC | H6: 45505 | I6: 5010131558054 | J6: GBP
A7: 12973 | B7: 5091372 | C7: SD BEAUTIFLEX BASE CLEAR 065 1L | D7: 17.39 | E7: SAD Beautiflex Base Clear | F7: 1 | G7: PC | H7: 45505 | I7: 5010131558023 | J7: GBP
A8: 12973 | B8: 5091373 | C8: SD BEAUTIFLEX BASE CLEAR 065 2.5L | D8: 38.64 | E8: SAD Beautiflex Base Clear | F8: 1 | G8: PC | H8: 45505 | I8: 5010131558030 | J8: GBP
A9: 12973 | B9: 5028473 | C9: SD CLASSIC REDWOOD 1L | D9: 15.46 | E9: SAD Classic Standard COL | F9: 1 | G9: PC | H9: 45505 | I9: 5721147600711 | J9: GBP
A10: 12973 | B10: 5028475 | C10: SD CLASSIC DK PALSNDR 1L | D10: 15.46 | E10: SAD Classic Standard COL | F10: 1 | G10: PC | H10: 45505 | I10: 5721147660913 | J10: GBP
A11: 12973 | B11: 5028476 | C11: SD CLASSIC DK PALSNDR 2.5L | D11: 36.12 | E11: SAD Classic Standard COL | F11: 1 | G11: PC | H11: 45505 | I11: 5721147660920 | J11: GBP
A12: 12973 | B12: 5028477 | C12: SD CLASSIC DK PALSNDR 5L | D12: 67.1 | E12: SAD Classic Standard COL | F12: 1 | G12: PC | H12: 45505 | I12: 5721147660937 | J12: GBP
A13: 12973 | B13: 5028479 | C13: SD CLASSIC BURMA TEAK 1L | D13: 15.46 | E13: SAD Classic Standard COL | F13: 1 | G13: PC | H13: 45505 | I13: 5721147602111 | J13: GBP
... A185: 12973 | B185: 5093217 | C185: SD SHED AND FENCE PROT WDLND WLK 5L | D185: 18.11 | E185: SAD Shed & Fence Prot COL | F185: 1 | G185: PC | H185: 45505 | I185: 5010131573842 | J185: GBP
A186: 6048267 - DE WHITE SPIRIT 2L | B186: 0 | C186: 839.5 | E186: 6048267 | F186: 6048267 | G186: 3 | H186: 279.83333
A187: 6041190 - DS COOVAR LO LINE MARK YELLOW 5L | B187: 0 | C187: 832.86 | E187: 6041190 | F187: 6041190 | G187: 74.66 | H187: 11.155371
A188: 5091090 - CT UNDERCOAT BASE OPAL MID 5L | B188: 530 | C188: 1562.36 | E188: 5091090 | F188: 5091090 | G188: 16.32 | H188: 95.732843
A189: 6055316 - CT FUNGICIDAL SOLUTION CLEAR 5L | B189: 190 | C189: 826.24 | E189: 6055316 | F189: 6055316 | G189: 24.23 | H189: 34.099876
A190: 5091093 - CT UNDERCOAT BASE PLATNUM LT 5L | B190: 170 | C190: 512.28 | E190: 5091093 | F190: 5091093 | G190: 16.32 | H190: 31.389706
A191: 6054132 - WA GALERIE PALAZZO | B191: 0 | C191: 823.4 | E191: 6054132 | F191: 6054132 | G191: 35.8 | H191: 23
A192: 6042316 - DS BLACKROCK PAINTERS L/W GRIPPER GLOVES | B192: 0 | C192: 806.65 | E192: 6042316 | F192: 6042316 | G192: 3.25 | H192: 248.2
A193: 6055427 - DE PROFESSIONAL LONG PILE ROLLER 4IN | B193: 0 | C193: 800.49 | E193: 6055427 | F193: 6055427 | G193: 0.38 | H193: 2106.5526
A194: 6041876 - DS RUSTOLEUM COMBICOL MATT BLACK 2.5L | B194: 0 | C194: 796 | E194: 6041876 | F194: 6041876 | G194: 47.2 | H194: 16.864407
A195: 5038010 - SD POLY EXT DUR VARNISH CLEAR GLOS 2.5L | B195: 70 | C195: 792.58 | E195: 5038010 | F195: 5038010 | G195: 30.58 | H195: 25.918247
A196: 6055201 - DE ESS PAINT BRUSH 2IN(12) EACH | B196: 0 | C196: 778.18 | E196: 6055201 | F196: 6055201 | G196: 1.38 | H196: 563.89855
A197: 6060534 - DS TOUPRET EXT MASONRY POWDER FILL 15K | B197: 0 | C197: 776.96 | E197: 6060534 | F197: 6060534 | G197: 61.67 | H197: 12.59867
... A224: 6055436 - DE ULTIMATE MICROFIBRE MEDUIM ROLL 4IN | B224: 0 | C224: 679.07 | E224: 6055436 | F224: 6055436 | G224: 0.39 | H224: 1741.2051
A225: 5091122 - MC MARBLETEX SMTH BASE MC2 5L | B225: 85 | C225: 288.01 | E225: 5091122 | F225: 5091122 | G225: 0 | H225: #DIV/0!
A226: 5091131 - MC POWERKOTE BASE MC1 5L | B226: 750 | C226: 2604.93 | E226: 5091131 | F226: 5091131 | G226: 18.7 | H226: 139.30107
A227: 5040770 - ST W/B STAB SOLUTION CLEAR 5L | B227: 80 | C227: 663.88 | E227: 5040770 | F227: 5040770 | G227: 44.38 | H227: 14.958991
A228: 5088598 - CT CLNEX AB SC MATT WHITE 5L | B228: 100 | C228: 661.7 | E228: 5088598 | F228: 5088598 | G228: 35.72 | H228: 18.524636
A229: 6046572 - DS INDASA TUNGSTEN CARBIDE BLADES 50MM | B229: 0 | C229: 656.91 | E229: 6046572 | F229: 6046572 | G229: 10.05 | H229: 65.364179
A230: 6040886 - DS BEELINE ONETIME LIGHTW FILLER 4L | B230: 0 | C230: 655.3 | E230: 6040886 | F230: 6040886 | G230: 43.34 | H230: 15.119982
A231: 6060532 - DS TOUPRET EXT MASONRY POWDER FILL 1.5K | B231: 0 | C231: 649.55 | E231: 6060532 | F231: 6060532 | G231: 13.44 | H231: 48.329613
A232: 6040885 - DS BEELINE ONETIME LIGHTW FILLER 1L | B232: 0 | C232: 648.24 | E232: 6040885 | F232: 6040885 | G232: 13.12 | H232: 49.408537
A233: 5028561 - SD EXTRA ROSEWOOD 5L | B233: 50 | C233: 633.92 | E233: 5028561 | F233: 5028561 | G233: 68.12 | H233: 9.3059307
A234: 5091147 - MC VINYL MATT EMUL BASE MC1 5L | B234: 470 | C234: 1005.32 | E234: 5091147 | F234: 5091147 | G234: 11.17 | H234: 90.001791
A235: 6061802 - DS PREP TWILL SHEET 3.6 X 2.7M 5PK | B235: 0 | C235: 632.13 | E235: 6061802 | F235: 6061802 | G235: 22.5 | H235: 28.094667
A236: 6042056 - DS PRESTIGE SYNTHETIC SASH BRUSH 3PK | B236: 0 | C236: 623.54 | E236: 6042056 | F236: 6042056 | G236: 10 | H236: 62.354
A237: 6053648 - DS MIRKA DEOS 353CV DECO SOLUTION KIT | B237: 0 | C237: 602.43 | E237: 6053648 | F237: 6053648 | G237: 638.58 | H237: 0.94339002
... A268: 5091208 - ST HIGHCOVER SMTH BASE CRYSTAL DK 5L | B268: 515 | C268: 2279.36 | E268: 5091208 | F268: 5091208 | G268: 23.92 | H268: 95.29097
A269: 5091209 - ST METAL GLOSS XTRA BSE CRYSTAL DK 2.5L | B269: 32.5 | C269: 455.26 | E269: 5091209 | F269: 5091209 | G269: 0 | H269: #DIV/0!
A270: 5027898 - MC UNDERCOAT WHITE 5L | B270: 165 | C270: 504.12 | E270: 5027898 | F270: 5027898 | G270: 16.75 | H270: 30.096716
A271: 6041132 - DS INDASA MTE MASKING TAPE 36MM | B271: 0 | C271: 502.4 | E271: 6041132 | F271: 6041132 | G271: 1.39 | H271: 361.43885
A272: 5091210 - ST XTREME XP SMTH BASE PLATNUM LT 5L | B272: 225 | C272: 1965.15 | E272: 5091210 | F272: 5091210 | G272: 0 | H272: #DIV/0!
A273: 5012999 - SD EXTRA EBONY 5L | B273: 40 | C273: 497.68 | E273: 5012999 | F273: 5012999 | G273: 68.12 | H273: 7.3059307
A274: 5091378 - CT MATT EMULSION BASE TTANIUM XL 10L | B274: 130 | C274: 258.92 | E274: 5091378 | F274: 5091378 | G274: 21.81 | H274: 11.871619
A275: 6061709 - DE ULT CAULK WHITE 380ML | B275: 0 | C275: 486.39 | E275: 6061709 | F275: 6061709 | G275: 1.51 | H275: 322.11258
A276: 5089400 - ST METAL GLOSS X-TRA WHITE 2.5L | B276: 27.5 | C276: 484.89 | E276: 5089400 | F276: 5089400 | G276: 45.15 | H276: 10.739535
A277: 6042824 - DS BEELINE ALL PURP ADHESIVE TR PK +50% | B277: 0 | C277: 483 | E277: 6042824 | F277: 6042824 | G277: 5.25 | H277: 92
A278: 6041335 - DS COOVAR HAMMER SMOOTH BLACK 2.5L | B278: 0 | C278: 482.13 | E278: 6041335 | F278: 6041335 | G278: 40.47 | H278: 11.913269
A279: 6045194 - DS SIKKENS RUB SATURA + W05 TINT 5L | B279: 0 | C279: 480.4 | E279: 6045194 | F279: 6045194 | G279: 96.08 | H279: 5
A280: 6041311 - DS TEAMAC FLOOR PAINT FLINT GREY 5L | B280: 0 | C280: 479.16 | E280: 6041311 | F280: 6041311 | G280: 37.21 | H280: 12.877184
A281: 5028842 - SD SUPERDEC BASE CLEAR 065 2.5L | B281: 32.5 | C281: 474.25 | E281: 5028842 | F281: 5028842 | G281: 39.51 | H281: 12.00329
A282: 6042099 - DS PRESTIGE ROLLER SLV MEDIUM 4IN | B282: 0 | C282: 471.78 | E282: 6042099 | F282: 6042099 | G282: 2.28 | H282: 206.92105
A283: 6040198 - WA ERFURT LINING 1400 DOUBLE | B283: 0 | C283: 467.89 | E283: 6040198 | F283: 6040198 | G283: 6.55 | H283: 71.433588
A284: 6041058 - DS ZINSSER BIN PRIMER AEROSOL 400ML | B284: 0 | C284: 465.2 | E284: 6041058 | F284: 6041058 | G284: 13.5 | H284: 34.459259
... A330: 6060981 - DS PRODEC PREMIER BRUSH SET+SASHES 7PC | B330: 0 | C330: 359.42 | E330: 6060981 | F330: 6060981 | G330: 14.56 | H330: 24.68544
A331: 5093202 - MC DURABLE MATT BASE MC1 5L | B331: 140 | C331: 540.12 | E331: 5093202 | F331: 5093202 | G331: 0 | H331: #DIV/0!
A332: 5025637 - ST FINE TEXT MATT MAGNOLIA 5L | B332: 65 | C332: 357.23 | E332: 5025637 | F332: 5025637 | G332: 29.87 | H332: 11.959491
A333: 5093400 - CT CLNEX MI SC MATT BSE PLATNUM LT 5L | B333: 265 | C333: 2128.81 | E333: 5093400 | F333: 5093400 | G333: 42.13 | H333: 50.529551
A334: 6041135 - DS INDASA RHYNOLITE YEL 80G 115MMX10M | B334: 0 | C334: 355.15 | E334: 6041135 | F334: 6041135 | G334: 4.15 | H334: 85.578313
A335: 6040937 - DS ARTEX CAULKER 250MM | B335: 0 | C335: 353.54 | E335: 6040937 | F335: 6040937 | G335: 9.99 | H335: 35.389389
A336: 6058137 - DS FILLTITE PREM MASK KN95/FFP2 2PK | B336: 0 | C336: 353.29 | E336: 6058137 | F336: 6058137 | G336: 14.89 | H336: 23.726662
A337: 6041641 - DS PRODEC GREY BRISTLE DUST BRUSH 4IN | B337: 0 | C337: 352.48 | E337: 6041641 | F337: 6041641 | G337: 12.58 | H337: 28.019078
A338: 6040880 - DS BEELINE WIPE TOP PASTE TABLE | B338: 0 | C338: 350.96 | E338: 6040880 | F338: 6040880 | G338: 40 | H338: 8.774
A339: 5028467 - SD CLASSIC JAC WALNUT 5L | B339: 30 | C339: 346.54 | E339: 5028467 | F339: 5028467 | G339: 63.24 | H339: 5.4797596
A340: 5094757 - CT MATT EMULSION BASE PLATNUM LT 10L | B340: 330 | C340: 668.65 | E340: 5094757 | F340: 5094757 | G340: 21.81 | H340: 30.657955
A341: 5094758 - CT CLNEX SR SC MATT BSE PLATNUM LT 10L | B341: 220 | C341: 1258.16 | E341: 5094758 | F341: 5094758 | G341: 49.64 | H341: 25.345689
A342: 6055439 - DE ULTIMATE POLY LONG PILE ROLLER 9IN | B342: 0 | C342: 340.48 | E342: 6055439 | F342: 6055439 | G342: 1.9 | H342: 179.2
A343: 5041097 - ST FLEXIGLOSS X-TRA BRIL WHITE 2.5L | B343: 25 | C343: 332.72 | E343: 5041097 | F343: 5041097 | G343: 33.86 | H343: 9.8263438
... A353: 6033644 - DS LIBERTY GREEN 10M 80GRD(10) EACH | B353: 0 | C353: 309.93 | E353: 6033644 | F353: 6033644 | G353: 24.15 | H353: 12.83354
A354: 6044313 - WA SANDERSON DESIGN GROUP GENERIC 1 | B354: 0 | C354: 1331.58 | E354: 6044313 | F354: 6044313 | G354: 0 | H354: #DIV/0!
A355: 6040559 - DS TETRION ALL PURP POWDER FILLER 10K | B355: 0 | C355: 309.09 | E355: 6040559 | F355: 6040559 | G355: 14.51 | H355: 21.301861
A356: 6059898 - WA GALERIE AVALON D | B356: 0 | C356: 307.92 | E356: 6059898 | F356: 6059898 | G356: 38.49 | H356: 8
A357: 5027065 - CT FD CONCRETE FLR PNT GREY 5L | B357: 75 | C357: 306.24 | E357: 5027065 | F357: 5027065 | G357: 22.94 | H357: 13.349608
A358: 6048266 - DE TURPS SUBSTITUTE 4L | B358: 0 | C358: 305.53 | E358: 6048266 | F358: 6048266 | G358: 5.7 | H358: 53.601754
A359: 6041053 - DS ZINSSER BULLSEYE 123 WHITE 2.5L | B359: 0 | C359: 304.34 | E359: 6041053 | F359: 6041053 | G359: 23.66 | H359: 12.86306
A360: 6044315 - WA MURASPEC PAPER BACKED GENERIC 1 | B360: 0 | C360: 396 | E360: 6044315 | F360: 6044315 | G360: 0 | H360: #DIV/0!
A361: 6040118 - WA ANAGLYPTA TEXT VINYL HAVERSHAM 34365 | B361: 0 | C361: 301.47 | E361: 6040118 | F361: 6040118 | G361: 4.8 | H361: 62.80625
A362: 6041214 - DS COOVAR SUREGRIP GREY 5L | B362: 0 | C362: 296.44 | E362: 6041214 | F362: 6041214 | G362: 79.27 | H362: 3.7396241
A363: 6058180 - DS Q1 MULTIPURP MASKING TAPE 50M 50MM | B363: 0 | C363: 295.92 | E363: 6058180 | F363: 6058180 | G363: 4.18 | H363: 70.794258
A364: 6045351 - DS KEIM MISC | B364: 0 | C364: 1226.6 | E364: 6045351 | F364: 6045351 | G364: 0 | H364: #DIV/0!
A365: 6042352 - DS PRODEC PAINTERS BIB & BRACE MED | B365: 0 | C365: 293.71 | E365: 6042352 | F365: 6042352 | G365: 25.99 | H365: 11.300885
A366: 5028802 - SD QD WOODSTAIN NATURAL 2.5L | B366: 22.5 | C366: 293.4 | E366: 5028802 | F366: 5028802 | G366: 33.24 | H366: 8.8267148
A367: 6045481 - DS WRIGHTS OF LYMM MISC | B367: 0 | C367: 552.5 | E367: 6045481 | F367: 6045481 | G367: 0 | H367: #DIV/0!
A368: 6033646 - DS LIBERTY GREEN 10M 120GRD(10) EACH | B368: 0 | C368: 292.74 | E368: 6033646 | F368: 6033646 | G368: 24.15 | H368: 12.121739
A369: 6047026 - DS FROGTAPE M SURF MASK 41.1M 48MM | B369: 0 | C369: 291.04 | E369: 6047026 | F369: 6047026 | G369: 7.77 | H369: 37.456885
A370: 6047491 - WA COLEMANS GENERIC 3 | B370: 0 | C370: 513.31 | E370: 6047491 | F370: 6047491 | G370: 0 | H370: #DIV/0!
A371: 5028837 - SD SUPERDEC WALNUT 2.5L | B371: 20 | C371: 285.26 | E371: 5028837 | F371: 5028837 | G371: 39.51 | H371: 7.2199443
A372: 6048265 - DE TURPS SUBSTITUTE 2L | B372: 0 | C372: 284.82 | E372: 6048265 | F372: 6048265 | G372: 2.97 | H372: 95.89899
A373: 6048268 - DE WHITE SPIRIT 4L | B373: 0 | C373: 283.82 | E373: 6048268 | F373: 6048268 | G373: 6 | H373: 47.303333
A374: 6062023 - DS PAINTERZ WIPES 80PK | B374: 0 | C374: 282.9 | E374: 6062023 | F374: 6062023 | G374: 6.18 | H374: 45.776699
A375: 5053184 - CT TIMONOX TOP COAT CLEAR 5L | B375: 15 | C375: 281.67 | E375: 5053184 | F375: 5053184 | G375: 93.89 | H375: 3
A376: 6041045 - DS ZINSSER BIN PRIMER WHITE 1L | B376: 0 | C376: 279.75 | E376: 6041045 | F376: 6041045 | G376: 18.81 | H376: 14.872408
A377: 6047509 - WA SANDERSON DESIGN GROUP GENERIC 3 | B377: 0 | C377: 396.68 | E377: 6047509 | F377: 6047509 | G377: 0 | H377: #DIV/0!
A378: 6040565 - DS TETRION WOODFIL NATUR/PINE 1.2K | B378: 0 | C378: 274.85 | E378: 6040565 | F378: 6040565 | G378: 25.83 | H378: 10.640728
A379: 6041944 - DS BARRETTINE PAINT PANTHER 4L | B379: 0 | C379: 273.84 | E379: 6041944 | F379: 6041944 | G379: 47.01 | H379: 5.8251436
A380: 6047514 - WA MURASPEC PAPER BACKED GENERIC 2 | B380: 0 | C380: 1705 | E380: 6047514 | F380: 6047514 | G380: 0 | H380: #DIV/0!
A381: 6047777 - WA GRAHAM & BROWN GENERIC EE | B381: 0 | C381: 1134 | E381: 6047777 | F381: 6047777 | G381: 0 | H381: #DIV/0!
...

Sheet Sheet2
A1: Product | B1: Sales Volume | C1: Sales Value | F1: NUMBER | H1: qty
A2: 5017788 - CT EPIMAC FLOOR PAINT TILE RED 5L | B2: 55 | C2: 309.85 | E2: =LEFT(A2,7) -> 5017788 | F2: 5017788 | G2: 1 | H2: 11 | J2: 5051235
A3: 5023891 - CT COVERMATT WHITE 10L | B3: 43290 | C3: 93635.03 | E3: =LEFT(A3,7) -> 5023891 | F3: 5023891 | G3: =_xlfn.XLOOKUP(F:F,'Crown Aug Uploads '!B:B,'Crown Aug Uploads '!O:O,0) -> 23.07 | H3: =C3/G3 -> 4058.7356
A4: 5040579 - CT MATT EMUL TIMONOX BRIL WHITE 5L | B4: 5220 | C4: 49302.6 | E4: =LEFT(A4,7) -> 5040579 | F4: 5040579 | G4: =_xlfn.XLOOKUP(F:F,'Crown Aug Uploads '!B:B,'Crown Aug Uploads '!O:O,0) -> 50.41 | H4: =C4/G4 -> 978.03214
A5: 5017821 - CT EPIMAC ANTISLIP MID GREY 5L | B5: 135 | C5: 856.93 | E5: =LEFT(A5,7) -> 5017821 | F5: 5017821 | G5: 33.8 | H5: =C5/G5 -> 25.352959
A6: 5040352 - CT TIM ANTI-GRAF GLAZE CLEAR 4L | B6: 580 | C6: 37251.9 | E6: =LEFT(A6,7) -> 5040352 | F6: 5040352 | G6: =_xlfn.XLOOKUP(F:F,'Crown Aug Uploads '!B:B,'Crown Aug Uploads '!O:O,0) -> 276.78 | H6: =C6/G6 -> 134.59029
A7: 5090859 - CT UPGRADE BASECOAT TIM WHITE 5L | B7: 2115 | C7: 28477.37 | E7: =LEFT(A7,7) -> 5090859 | F7: 5090859 | G7: =_xlfn.XLOOKUP(F:F,'Crown Aug Uploads '!B:B,'Crown Aug Uploads '!O:O,0) -> 73.26 | H7: =C7/G7 -> 388.71649
A8: 5024213 - CT SILK EMULSION MAGNOLIA 10L | B8: 11690 | C8: 28441.61 | E8: =LEFT(A8,7) -> 5024213 | F8: 5024213 | G8: =_xlfn.XLOOKUP(F:F,'Crown Aug Uploads '!B:B,'Crown Aug Uploads '!O:O,0) -> 26.29 | H8: =C8/G8 -> 1081.8414
A9: 6058266 - DS FLUXAF POWER CLEAN 750ML | B9: 0 | C9: 26686.9 | E9: =LEFT(A9,7) -> 6058266 | F9: 6058266 | G9: =_xlfn.XLOOKUP(F:F,'Crown Aug Uploads '!B:B,'Crown Aug Uploads '!O:O,0) -> 7.6 | H9: =C9/G9 -> 3511.4342
A10: 5024015 - CT STRONGHOLD SMOOTH IVORY 5L | B10: 185 | C10: 666.74 | E10: =LEFT(A10,7) -> 5024015 | F10: 5024015 | G10: 19.73 | H10: =C10/G10 -> 33.793208 | J10: =H2+H18 -> 24.699949
A11: 5028843 - SD SUPERDEC BASE CLEAR 065 5L | B11: 1840 | C11: 25040.78 | E11: =LEFT(A11,7) -> 5028843 | F11: 5028843 | G11: =_xlfn.XLOOKUP(F:F,'Crown Aug Uploads '!B:B,'Crown Aug Uploads '!O:O,0) -> 72.12 | H11: =C11/G11 -> 347.20993
A12: 5026956 - CT FULL GLOSS WHITE 5L | B12: 8045 | C12: 24391.58 | E12: =LEFT(A12,7) -> 5026956 | F12: 5026956 | G12: =_xlfn.XLOOKUP(F:F,'Crown Aug Uploads '!B:B,'Crown Aug Uploads '!O:O,0) -> 16.32 | H12: =C12/G12 -> 1494.5821
A13: 5024059 - CT MATT EMULSION WHITE 10L | B13: 12320 | C13: 23865.94 | E13: =LEFT(A13,7) -> 5024059 | F13: 5024059 | G13: =_xlfn.XLOOKUP(F:F,'Crown Aug Uploads '!B:B,'Crown Aug Uploads '!O:O,0) -> 21.01 | H13: =C13/G13 -> 1135.9324
A14: 5024029 - CT STRONGHOLD SMOOTH BLACK 5L | B14: 225 | C14: 824.53 | E14: =LEFT(A14,7) -> 5024029 | F14: 5024029 | G14: 19.73 | H14: =C14/G14 -> 41.790674
A15: 5024174 - CT ACRYLIC PRIMER UC WHITE 5L | B15: 4835 | C15: 22739.33 | E15: =LEFT(A15,7) -> 5024174 | F15: 5024174 | G15: =_xlfn.XLOOKUP(F:F,'Crown Aug Uploads '!B:B,'Crown Aug Uploads '!O:O,0) -> 25.39 | H15: =C15/G15 -> 895.60181
A16: 5040522 - CT ACRYLIC EGG TIMONOX BRIL WHITE 5L | B16: 1820 | C16: 18567.02 | E16: =LEFT(A16,7) -> 5040522 | F16: 5040522 | G16: =_xlfn.XLOOKUP(F:F,'Crown Aug Uploads '!B:B,'Crown Aug Uploads '!O:O,0) -> 52.07 | H16: =C16/G16 -> 356.57807
A17: 6041055 - DS ZINSSER BIN PRIMER WHITE 5L | B17: 0 | C17: 16672.97 | E17: =LEFT(A17,7) -> 6041055 | F17: 6041055 | G17: =_xlfn.XLOOKUP(F:F,'Crown Aug Uploads '!B:B,'Crown Aug Uploads '!O:O,0) -> 73.61 | H17: =C17/G17 -> 226.50414
A18: 5024034 - CT STRONGHOLD SMOOTH BUTTERMILK 5L | B18: 75 | C18: 270.3 | E18: =LEFT(A18,7) -> 5024034 | F18: 5024034 | G18: 19.73 | H18: =C18/G18 -> 13.699949
A19: 6040125 - WA ANAGLYPTA TEXT VINYL WILL BO RD804301 | B19: 0 | C19: 13720.41 | E19: =LEFT(A19,7) -> 6040125 | F19: 6040125 | G19: =_xlfn.XLOOKUP(F:F,'Crown Aug Uploads '!B:B,'Crown Aug Uploads '!O:O,0) -> 4.8 | H19: =C19/G19 -> 2858.4188
A20: 5088424 - CT FLEXARB OPAQUE BROWN 5L | B20: 1320 | C20: 12758.86 | E20: =LEFT(A20,7) -> 5088424 | F20: 5088424 | G20: =_xlfn.XLOOKUP(F:F,'Crown Aug Uploads '!B:B,'Crown Aug Uploads '!O:O,0) -> 52.07 | H20: =C20/G20 -> 245.03284
A21: 5093395 - CT CLNEX MI SC MATT WHITE 5L | B21: 1660 | C21: 11690.41 | E21: =LEFT(A21,7) -> 5093395 | F21: 5093395 | G21: =_xlfn.XLOOKUP(F:F,'Crown Aug Uploads '!B:B,'Crown Aug Uploads '!O:O,0) -> 38.03 | H21: =C21/G21 -> 307.39968
A22: 5074787 - CT TIMONOX BOND PRIMER WHITE 5L | B22: 1205 | C22: 11585.99 | E22: =LEFT(A22,7) -> 5074787 | F22: 5074787 | G22: =_xlfn.XLOOKUP(F:F,'Crown Aug Uploads '!B:B,'Crown Aug Uploads '!O:O,0) -> 50.58 | H22: =C22/G22 -> 229.06267
A23: 5025723 - ST HIGHCOVER SMOOTH MAGNOLIA 10L | B23: 2010 | C23: 11421.42 | E23: =LEFT(A23,7) -> 5025723 | F23: 5025723 | G23: =_xlfn.XLOOKUP(F:F,'Crown Aug Uploads '!B:B,'Crown Aug Uploads '!O:O,0) -> 59.78 | H23: =C23/G23 -> 191.05754
A24: 5026960 - CT FULL GLOSS BLACK 2.5L | B24: 285 | C24: 994.21 | E24: =LEFT(A24,7) -> 5026960 | F24: 5026960 | G24: 9.34 | H24: =C24/G24 -> 106.44647
A25: 5026961 - CT FULL GLOSS BLACK 5L | B25: 1815 | C25: 5446.33 | E25: =LEFT(A25,7) -> 5026961 | F25: 5026961 | G25: 16.32 | H25: =C25/G25 -> 333.7212
A26: 5070051 - CT CLNEX SR SC MATT WHITE 10L | B26: 2210 | C26: 10088.87 | E26: =LEFT(A26,7) -> 5070051 | F26: 5070051 | G26: =_xlfn.XLOOKUP(F:F,'Crown Aug Uploads '!B:B,'Crown Aug Uploads '!O:O,0) -> 49.64 | H26: =C26/G26 -> 203.24073
A27: 5025056 - MC ECLIPSE EMULSION BRIL WHITE 10L | B27: 5670 | C27: 9615.74 | E27: =LEFT(A27,7) -> 5025056 | F27: 5025056 | G27: =_xlfn.XLOOKUP(F:F,'Crown Aug Uploads '!B:B,'Crown Aug Uploads '!O:O,0) -> 18.16 | H27: =C27/G27 -> 529.5011
A28: 6048207 - DS REPAIR CARE DRY FLEX 4 | B28: 0 | C28: 9504.86 | E28: =LEFT(A28,7) -> 6048207 | F28: 6048207 | G28: =_xlfn.XLOOKUP(F:F,'Crown Aug Uploads '!B:B,'Crown Aug Uploads '!O:O,0) -> 54 | H28: =C28/G28 -> 176.01593
A29: 5025052 - MC ECLIPSE EMULSION MAGNOLIA 10L | B29: 5270 | C29: 8823.77 | E29: =LEFT(A29,7) -> 5025052 | F29: 5025052 | G29: =_xlfn.XLOOKUP(F:F,'Crown Aug Uploads '!B:B,'Crown Aug Uploads '!O:O,0) -> 18.16 | H29: =C29/G29 -> 485.89042
A30: 5091987 - CT FASTFLOW QD SATIN WHITE 5L | B30: 1555 | C30: 8693.12 | E30: =LEFT(A30,7) -> 5091987 | F30: 5091987 | G30: =_xlfn.XLOOKUP(F:F,'Crown Aug Uploads '!B:B,'Crown Aug Uploads '!O:O,0) -> 30.77 | H30: =C30/G30 -> 282.51934
A31: 5027127 - CT UNDERCOAT WHITE 5L | B31: 2855 | C31: 8661.97 | E31: =LEFT(A31,7) -> 5027127 | F31: 5027127 | G31: =_xlfn.XLOOKUP(F:F,'Crown Aug Uploads '!B:B,'Crown Aug Uploads '!O:O,0) -> 16.32 | H31: =C31/G31 -> 530.75797
A32: 5090816 - CT FASTFLOW QD UNDRCOAT WHITE 5L | B32: 1740 | C32: 8224.64 | E32: =LEFT(A32,7) -> 5090816 | F32: 5090816 | G32: =_xlfn.XLOOKUP(F:F,'Crown Aug Uploads '!B:B,'Crown Aug Uploads '!O:O,0) -> 25.8 | H32: =C32/G32 -> 318.7845
A33: 5024010 - CT STRONGHOLD SMOOTH MAGNOLIA 5L | B33: 2160 | C33: 8100.98 | E33: =LEFT(A33,7) -> 5024010 | F33: 5024010 | G33: =_xlfn.XLOOKUP(F:F,'Crown Aug Uploads '!B:B,'Crown Aug Uploads '!O:O,0) -> 19.73 | H33: =C33/G33 -> 410.59199
A34: 5027114 - CT UNDERCOAT CHARC GREY 5L | B34: 1480 | C34: 4442.35 | E34: =LEFT(A34,7) -> 5027114 | F34: 5027114 | G34: 16.32 | H34: =C34/G34 -> 272.20282
A35: 5028846 - SD SUPERDEC BASE WHITE W0 5L | B35: 575 | C35: 7905.6 | E35: =LEFT(A35,7) -> 5028846 | F35: 5028846 | G35: =_xlfn.XLOOKUP(F:F,'Crown Aug Uploads '!B:B,'Crown Aug Uploads '!O:O,0) -> 72.12 | H35: =C35/G35 -> 109.6173
A36: 6046432 - WA ANAGLYPTA PRECISION ROYAL OAK RD7000 | B36: 0 | C36: 7864.65 | E36: =LEFT(A36,7) -> 6046432 | F36: 6046432 | G36: =_xlfn.XLOOKUP(F:F,'Crown Aug Uploads '!B:B,'Crown Aug Uploads '!O:O,0) -> 7.53 | H36: =C36/G36 -> 1044.4422
A37: 5027122 - CT UNDERCOAT DARK GREY 5L | B37: 120 | C37: 361.86 | E37: =LEFT(A37,7) -> 5027122 | F37: 5027122 | G37: 16.32 | H37: =C37/G37 -> 22.172794
A38: 5090804 - CT FASTFLOW QD GLOSS WHITE 5L | B38: 1570 | C38: 7506.48 | E38: =LEFT(A38,7) -> 5090804 | F38: 5090804 | G38: =_xlfn.XLOOKUP(F:F,'Crown Aug Uploads '!B:B,'Crown Aug Uploads '!O:O,0) -> 25.8 | H38: =C38/G38 -> 290.94884
A39: 5024011 - CT STRONGHOLD SMOOTH MAGNOLIA 10L | B39: 1850 | C39: 7227.72 | E39: =LEFT(A39,7) -> 5024011 | F39: 5024011 | G39: =_xlfn.XLOOKUP(F:F,'Crown Aug Uploads '!B:B,'Crown Aug Uploads '!O:O,0) -> 39.42 | H39: =C39/G39 -> 183.3516
A40: 5064686 - CT ACRYLIC EGGSHELL WHITE 5L | B40: 1830 | C40: 7080.87 | E40: =LEFT(A40,7) -> 5064686 | F40: 5064686 | G40: =_xlfn.XLOOKUP(F:F,'Crown Aug Uploads '!B:B,'Crown Aug Uploads '!O:O,0) -> 21.01 | H40: =C40/G40 -> 337.0238
A41: 5093393 - CT CLNEX MI SC MATT MAGNOLIA 5L | B41: 990 | C41: 7047.06 | E41: =LEFT(A41,7) -> 5093393 | F41: 5093393 | G41: =_xlfn.XLOOKUP(F:F,'Crown Aug Uploads '!B:B,'Crown Aug Uploads '!O:O,0) -> 38.92 | H41: =C41/G41 -> 181.06526
A42: 5040680 - CT MATT EMULSION WHITE 6L | B42: 36 | C42: 241.23 | E42: =LEFT(A42,7) -> 5040680 | F42: 5040680 | G42: =_xlfn.XLOOKUP(F:F,'Crown Aug Uploads '!B:B,'Crown Aug Uploads '!O:O,0) -> 0 | H42: =C42/G42 -> #DIV/0!
A43: 5061961 - CT CLNEX SR SC MATT BSE PASTEL 5L | B43: 65 | C43: 295.62 | E43: =LEFT(A43,7) -> 5061961 | F43: 5061961 | G43: 24.9 | H43: =C43/G43 -> 11.872289
A44: 5064671 - CT ACRYLIC EGGSHELL MAGNOLIA 5L | B44: 1650 | C44: 6471.02 | E44: =LEFT(A44,7) -> 5064671 | F44: 5064671 | G44: =_xlfn.XLOOKUP(F:F,'Crown Aug Uploads '!B:B,'Crown Aug Uploads '!O:O,0) -> 21.01 | H44: =C44/G44 -> 307.99714
A45: 5061839 - CT CLNEX SR SC MATT MAGNOLIA 5L | B45: 1355 | C45: 6302.94 | E45: =LEFT(A45,7) -> 5061839 | F45: 5061839 | G45: =_xlfn.XLOOKUP(F:F,'Crown Aug Uploads '!B:B,'Crown Aug Uploads '!O:O,0) -> 24.9 | H45: =C45/G45 -> 253.13012
A46: 5028493 - SD CLASSIC MAHOGANY 5L | B46: 550 | C46: 6089.58 | E46: =LEFT(A46,7) -> 5028493 | F46: 5028493 | G46: =_xlfn.XLOOKUP(F:F,'Crown Aug Uploads '!B:B,'Crown Aug Uploads '!O:O,0) -> 63.24 | H46: =C46/G46 -> 96.293169
A47: 5025730 - ST HIGHCOVER SMOOTH BRIL WHITE 10L | B47: 1090 | C47: 6046.23 | E47: =LEFT(A47,7) -> 5025730 | F47: 5025730 | G47: =_xlfn.XLOOKUP(F:F,'Crown Aug Uploads '!B:B,'Crown Aug Uploads '!O:O,0) -> 59.78 | H47: =C47/G47 -> 101.14135
A48: 5068882 - SX M/SEAL SMTH MASONRY BRIL WHITE 2.5L | B48: 30 | C48: 250.08 | E48: =LEFT(A48,7) -> 5068882 | F48: 5068882 | G48: =_xlfn.XLOOKUP(F:F,'Crown Aug Uploads '!B:B,'Crown Aug Uploads '!O:O,0) -> 0 | H48: =C48/G48 -> #DIV/0!
A49: 5028208 - ST 365 SMOOTH MAGNOLIA 5L | B49: 800 | C49: 5988.86 | E49: =LEFT(A49,7) -> 5028208 | F49: 5028208 | G49: =_xlfn.XLOOKUP(F:F,'Crown Aug Uploads '!B:B,'Crown Aug Uploads '!O:O,0) -> 38.25 | H49: =C49/G49 -> 156.5715
A50: 6040483 - WA AS CREATION CASABLANCA 4 WALL | B50: 0 | C50: 5933.04 | E50: =LEFT(A50,7) -> 6040483 | F50: 6040483 | G50: =_xlfn.XLOOKUP(F:F,'Crown Aug Uploads '!B:B,'Crown Aug Uploads '!O:O,0) -> 5 | H50: =C50/G50 -> 1186.608
A51: 5061965 - CT CLNEX SR SC MATT WHITE 5L | B51: 1265 | C51: 5836.38 | E51: =LEFT(A51,7) -> 5061965 | F51: 5061965 | G51: =_xlfn.XLOOKUP(F:F,'Crown Aug Uploads '!B:B,'Crown Aug Uploads '!O:O,0) -> 24.9 | H51: =C51/G51 -> 234.39277
A52: 6061706 - DE PROF CAULK WHITE 380ML | B52: 0 | C52: 5794.13 | E52: =LEFT(A52,7) -> 6061706 | F52: 6061706 | G52: =_xlfn.XLOOKUP(F:F,'Crown Aug Uploads '!B:B,'Crown Aug Uploads '!O:O,0) -> 1.08 | H52: =C52/G52 -> 5364.9352
A53: 5088430 - CT QD FLEXARB OPAQUE BROWN 5L | B53: 70 | C53: 566.41 | E53: =LEFT(A53,7) -> 5088430 | F53: 5088430 | G53: 52.07 | H53: =C53/G53 -> 10.877857
A54: 5088436 - CT SHED&FENCE OPAQUE BLACK 5L | B54: 975 | C54: 3092.4 | E54: =LEFT(A54,7) -> 5088436 | F54: 5088436 | G54: 17.07 | H54: =C54/G54 -> 181.15993
A55: 5088437 - CT SHED&FENCE OPAQUE DARK BROWN 5L | B55: 2045 | C55: 6044.54 | E55: =LEFT(A55,7) -> 5088437 | F55: 5088437 | G55: 17.07 | H55: =C55/G55 -> 354.1031
A56: 5088479 - CT ALL PURPOSE VARN CLEAR GLOS 2.5L | B56: 30 | C56: 277.51 | E56: =LEFT(A56,7) -> 5088479 | F56: 5088479 | G56: =_xlfn.XLOOKUP(F:F,'Crown Aug Uploads '!B:B,'Crown Aug Uploads '!O:O,0) -> 0 | H56: =C56/G56 -> #DIV/0!
A57: 5094753 - CT ALL PURP PRIMER PX4 WHITE 5L | B57: 885 | C57: 5084.27 | E57: =LEFT(A57,7) -> 5094753 | F57: 5094753 | G57: =_xlfn.XLOOKUP(F:F,'Crown Aug Uploads '!B:B,'Crown Aug Uploads '!O:O,0) -> 25.54 | H57: =C57/G57 -> 199.07087
A58: 5088481 - CT ALL PURPOSE VARN CLEAR SATN 2.5L | B58: 25 | C58: 243.67 | E58: =LEFT(A58,7) -> 5088481 | F58: 5088481 | G58: =_xlfn.XLOOKUP(F:F,'Crown Aug Uploads '!B:B,'Crown Aug Uploads '!O:O,0) -> 0 | H58: =C58/G58 -> #DIV/0!
A59: 5024052 - CT MATT EMULSION MAGNOLIA 10L | B59: 2410 | C59: 4825.81 | E59: =LEFT(A59,7) -> 5024052 | F59: 5024052 | G59: =_xlfn.XLOOKUP(F:F,'Crown Aug Uploads '!B:B,'Crown Aug Uploads '!O:O,0) -> 21.81 | H59: =C59/G59 -> 221.26593
A60: 6040482 - WA AS CREATION CASABLANCA 4 WALL | B60: 0 | C60: 4787.28 | E60: =LEFT(A60,7) -> 6040482 | F60: 6040482 | G60: =_xlfn.XLOOKUP(F:F,'Crown Aug Uploads '!B:B,'Crown Aug Uploads '!O:O,0) -> 6.06 | H60: =C60/G60 -> 789.9802
A61: 5025045 - MC CONTRACT MATT EMULS BRIL WHITE 10L | B61: 3070 | C61: 4667.27 | E61: =LEFT(A61,7) -> 5025045 | F61: 5025045 | G61: =_xlfn.XLOOKUP(F:F,'Crown Aug Uploads '!B:B,'Crown Aug Uploads '!O:O,0) -> 16.61 | H61: =C61/G61 -> 280.99157
A62: 5074313 - CT SATIN WHITE 5L | B62: 910 | C62: 4569.92 | E62: =LEFT(A62,7) -> 5074313 | F62: 5074313 | G62: =_xlfn.XLOOKUP(F:F,'Crown Aug Uploads '!B:B,'Crown Aug Uploads '!O:O,0) -> 26.89 | H62: =C62/G62 -> 169.94868
A63: 5089345 - CT PRO-CO HP GLOSS BLACK 2.5L | B63: 460 | C63: 5152.1 | E63: =LEFT(A63,7) -> 5089345 | F63: 5089345 | G63: 29.6 | H63: =C63/G63 -> 174.05743
A64: 5090984 - CT ACR EGG TIMONOX BASE PLATNUM LT 5L | B64: 9165 | C64: 99994.3 | E64: =LEFT(A64,7) -> 5090984 | F64: 5051235 | G64: =_xlfn.XLOOKUP(F:F,'Crown Aug Uploads '!B:B,'Crown Aug Uploads '!O:O,0) -> 56.39 | H64: =C64/G64 -> 1773.263
A65: 5090985 - CT ACR EGG TIMONOX BASE OPAL MID 5L | B65: 1420 | C65: 16383.6 | E65: =LEFT(A65,7) -> 5090985 | F65: 5090985 | G65: 56.39 | H65: =C65/G65 -> 290.54088
A66: 5024026 - CT STRONGHOLD SMOOTH WHITE 5L | B66: 1140 | C66: 4166.3 | E66: =LEFT(A66,7) -> 5024026 | F66: 5024026 | G66: =_xlfn.XLOOKUP(F:F,'Crown Aug Uploads '!B:B,'Crown Aug Uploads '!O:O,0) -> 19.73 | H66: =C66/G66 -> 211.16574
A67: 5026921 - CT STRONGHOLD PR UC WHITE 2.5L | B67: 772.5 | C67: 3931.67 | E67: =LEFT(A67,7) -> 5026921 | F67: 5026921 | G67: =_xlfn.XLOOKUP(F:F,'Crown Aug Uploads '!B:B,'Crown Aug Uploads '!O:O,0) -> 13.95 | H67: =C67/G67 -> 281.84014
A68: 5090986 - CT ACR EGGSHELL BASE CRYSTAL DK 2.5L | B68: 55 | C68: 253.28 | E68: =LEFT(A68,7) -> 5090986 | F68: 5090986 | G68: 12.47 | H68: =C68/G68 -> 20.311147
A69: 5090987 - CT ACR EGGSHELL BASE CRYSTAL DK 5L | B69: 200 | C69: 764.87 | E69: =LEFT(A69,7) -> 5090987 | F69: 5090987 | G69: 12.47 | H69: =C69/G69 -> 61.336808
A70: 5026911 - CT STRONGHOLD GLOSS WHITE 2.5L | B70: 695 | C70: 3654.88 | E70: =LEFT(A70,7) -> 5026911 | F70: 5026911 | G70: =_xlfn.XLOOKUP(F:F,'Crown Aug Uploads '!B:B,'Crown Aug Uploads '!O:O,0) -> 14.28 | H70: =C70/G70 -> 255.94398
A71: 6041056 - DS ZINSSER BIN PRIMER WHITE 2.5L | B71: 0 | C71: 3542 | E71: =LEFT(A71,7) -> 6041056 | F71: 6041056 | G71: =_xlfn.XLOOKUP(F:F,'Crown Aug Uploads '!B:B,'Crown Aug Uploads '!O:O,0) -> 38.7 | H71: =C71/G71 -> 91.524548
A72: 6041133 - DS INDASA MTE MASKING TAPE 48MM | B72: 0 | C72: 3439.52 | E72: =LEFT(A72,7) -> 6041133 | F72: 6041133 | G72: =_xlfn.XLOOKUP(F:F,'Crown Aug Uploads '!B:B,'Crown Aug Uploads '!O:O,0) -> 3.79 | H72: =C72/G72 -> 907.52507
A73: 5025043 - MC CONTRACT MATT EMULS MAGNOLIA 10L | B73: 2080 | C73: 3387.4 | E73: =LEFT(A73,7) -> 5025043 | F73: 5025043 | G73: =_xlfn.XLOOKUP(F:F,'Crown Aug Uploads '!B:B,'Crown Aug Uploads '!O:O,0) -> 18.07 | H73: =C73/G73 -> 187.45988
A74: 6040958 - DS GYPROC EASI-FILL 20 10K | B74: 0 | C74: 3347.94 | E74: =LEFT(A74,7) -> 6040958 | F74: 6040958 | G74: =_xlfn.XLOOKUP(F:F,'Crown Aug Uploads '!B:B,'Crown Aug Uploads '!O:O,0) -> 33.96 | H74: =C74/G74 -> 98.584806
A75: 6048367 - DS ZINSSER DIF WALLPAPER STRIPPER 1L | B75: 0 | C75: 3284.51 | E75: =LEFT(A75,7) -> 6048367 | F75: 6048367 | G75: =_xlfn.XLOOKUP(F:F,'Crown Aug Uploads '!B:B,'Crown Aug Uploads '!O:O,0) -> 10.25 | H75: =C75/G75 -> 320.44
A76: 6040957 - DS GYPROC EASI-FILL 20 5K | B76: 0 | C76: 3174.07 | E76: =LEFT(A76,7) -> 6040957 | F76: 6040957 | G76: =_xlfn.XLOOKUP(F:F,'Crown Aug Uploads '!B:B,'Crown Aug Uploads '!O:O,0) -> 22.58 | H76: =C76/G76 -> 140.56997
A77: 5090988 - CT ACR EGGSHELL BASE PLATNUM LT 2.5L | B77: 80 | C77: 366.64 | E77: =LEFT(A77,7) -> 5090988 | F77: 5090988 | G77: 12.47 | H77: =C77/G77 -> 29.401764
A78: 5028827 - SD SUPERDEC SUPER WHTE 5L | B78: 225 | C78: 3076.71 | E78: =LEFT(A78,7) -> 5028827 | F78: 5028827 | G78: =_xlfn.XLOOKUP(F:F,'Crown Aug Uploads '!B:B,'Crown Aug Uploads '!O:O,0) -> 72.12 | H78: =C78/G78 -> 42.660982
A79: 6041126 - DS INDASA MTG MASKING TAPE 50MM 45MT | B79: 0 | C79: 3041.79 | E79: =LEFT(A79,7) -> 6041126 | F79: 6041126 | G79: =_xlfn.XLOOKUP(F:F,'Crown Aug Uploads '!B:B,'Crown Aug Uploads '!O:O,0) -> 1.33 | H79: =C79/G79 -> 2287.0602
A80: 5026955 - CT FULL GLOSS WHITE 2.5L | B80: 852.5 | C80: 2931.68 | E80: =LEFT(A80,7) -> 5026955 | F80: 5026955 | G80: =_xlfn.XLOOKUP(F:F,'Crown Aug Uploads '!B:B,'Crown Aug Uploads '!O:O,0) -> 9.34 | H80: =C80/G80 -> 313.88437
A81: 5090989 - CT ACR EGGSHELL BASE PLATNUM LT 5L | B81: 6155 | C81: 23625.62 | E81: =LEFT(A81,7) -> 5090989 | F81: 5051237 | G81: =_xlfn.XLOOKUP(F:F,'Crown Aug Uploads '!B:B,'Crown Aug Uploads '!O:O,0) -> 58.16 | H81: =C81/G81 -> 406.21768
A82: 5090991 - CT ACR EGGSHELL BASE OPAL MID 5L | B82: 590 | C82: 2309.92 | E82: =LEFT(A82,7) -> 5090991 | F82: 5090991 | G82: 21.01 | H82: =C82/G82 -> 109.94384
A83: 5090992 - CT CLNEX SR AC EGG BASE PLATNUM LT 5L | B83: 1055 | C83: 6810.66 | E83: =LEFT(A83,7) -> 5090992 | F83: 5090992 | G83: 35.43 | H83: =C83/G83 -> 192.22862
A84: 5028830 - SD SUPERDEC BLACK 5L | B84: 210 | C84: 2859.96 | E84: =LEFT(A84,7) -> 5028830 | F84: 5028830 | G84: =_xlfn.XLOOKUP(F:F,'Crown Aug Uploads '!B:B,'Crown Aug Uploads '!O:O,0) -> 72.12 | H84: =C84/G84 -> 39.655574
A85: 5090993 - CT CLNEX SR SC MATT BSE CRYSTAL DK 2.5L | B85: 42.5 | C85: 245.14 | E85: =LEFT(A85,7) -> 5090993 | F85: 5090993 | G85: 15.66 | H85: =C85/G85 -> 15.653895
A86: 6042877 - DS CIRET BAG OF RAGS COLOURED 10K | B86: 0 | C86: 2742.73 | E86: =LEFT(A86,7) -> 6042877 | F86: 6042877 | G86: =_xlfn.XLOOKUP(F:F,'Crown Aug Uploads '!B:B,'Crown Aug Uploads '!O:O,0) -> 31.51 | H86: =C86/G86 -> 87.043161
A87: 5090994 - CT CLNEX SR SC MATT BSE CRYSTAL DK 5L | B87: 640 | C87: 2921.52 | E87: =LEFT(A87,7) -> 5090994 | F87: 5090994 | G87: 15.66 | H87: =C87/G87 -> 186.55939
A88: 5024058 - CT MATT EMULSION WHITE 5L | B88: 1145 | C88: 2642.87 | E88: =LEFT(A88,7) -> 5024058 | F88: 5024058 | G88: =_xlfn.XLOOKUP(F:F,'Crown Aug Uploads '!B:B,'Crown Aug Uploads '!O:O,0) -> 12.47 | H88: =C88/G88 -> 211.93825
A89: 5090995 - CT CLNEX SR SC MATT BSE PLATNUM LT 2.5L | B89: 130 | C89: 757.88 | E89: =LEFT(A89,7) -> 5090995 | F89: 5090995 | G89: 15.66 | H89: =C89/G89 -> 48.395913
A90: 5090996 - CT CLNEX SR SC MATT BSE PLATNUM LT 5L | B90: 9230 | C90: 42181.08 | E90: =LEFT(A90,7) -> 5090996 | F90: 5087288 | G90: =_xlfn.XLOOKUP(F:F,'Crown Aug Uploads '!B:B,'Crown Aug Uploads '!O:O,0) -> 64.63 | H90: =C90/G90 -> 652.6548
A91: 5090998 - CT CLNEX SR SC MATT BSE OPAL MID 5L | B91: 1160 | C91: 5247.6 | E91: =LEFT(A91,7) -> 5090998 | F91: 5090998 | G91: 24.9 | H91: =C91/G91 -> 210.74699
A92: 6055142 - DS ULTRAGRIME PRO XXL+MULTI WIPES 100PK | B92: 0 | C92: 2469.39 | E92: =LEFT(A92,7) -> 6055142 | F92: 6055142 | G92: =_xlfn.XLOOKUP(F:F,'Crown Aug Uploads '!B:B,'Crown Aug Uploads '!O:O,0) -> 13.09 | H92: =C92/G92 -> 188.64706
A93: 5090999 - CT COVERMATT BASE PLATNUM LT 10L | B93: 2460 | C93: 5390.34 | E93: =LEFT(A93,7) -> 5090999 | F93: 5090999 | G93: 23.15 | H93: =C93/G93 -> 232.84406
A94: 6040959 - DS GYPROC EASI-FILL 60 5K | B94: 0 | C94: 2430.07 | E94: =LEFT(A94,7) -> 6040959 | F94: 6040959 | G94: =_xlfn.XLOOKUP(F:F,'Crown Aug Uploads '!B:B,'Crown Aug Uploads '!O:O,0) -> 11.69 | H94: =C94/G94 -> 207.87596
A95: 5088422 - CT FLEXARB OPAQUE BLACK 5L | B95: 250 | C95: 2424.96 | E95: =LEFT(A95,7) -> 5088422 | F95: 5088422 | G95: =_xlfn.XLOOKUP(F:F,'Crown Aug Uploads '!B:B,'Crown Aug Uploads '!O:O,0) -> 52.07 | H95: =C95/G95 -> 46.571154
A96: 5023888 - CT COVERMATT MAGNOLIA 10L | B96: 1110 | C96: 2396.74 | E96: =LEFT(A96,7) -> 5023888 | F96: 5023888 | G96: =_xlfn.XLOOKUP(F:F,'Crown Aug Uploads '!B:B,'Crown Aug Uploads '!O:O,0) -> 23.15 | H96: =C96/G96 -> 103.53089
A97: 6040932 - DS GYPROC PROMIX LITE 17L | B97: 0 | C97: 2353.83 | E97: =LEFT(A97,7) -> 6040932 | F97: 6040932 | G97: =_xlfn.XLOOKUP(F:F,'Crown Aug Uploads '!B:B,'Crown Aug Uploads '!O:O,0) -> 43 | H97: =C97/G97 -> 54.740233
A98: 5091003 - CT EGGSHELL BASE CRYSTAL DK 5L | B98: 60 | C98: 340.96 | E98: =LEFT(A98,7) -> 5091003 | F98: 5091003 | G98: 29.49 | H98: =C98/G98 -> 11.561885
A99: 5091005 - CT EGGSHELL BASE PLATNUM LT 5L | B99: 130 | C99: 735.76 | E99: =LEFT(A99,7) -> 5091005 | F99: 5091005 | G99: 29.49 | H99: =C99/G99 -> 24.949474
A100: 5091011 - CT FFLOW QD GLOSS BASE PLATNUM LT 2.5L | B100: 105 | C100: 632.65 | E100: =LEFT(A100,7) -> 5091011 | F100: 5091011 | G100: 16.46 | H100: =C100/G100 -> 38.435601
...

Sheet Sheet1
A1: SAP_Number | B1: Description | C1: Colour | D1: Size | E1: Price
A2: 5088591 | B2: CRT Clean Extreme Acrylic Eggshell | C2: White | D2: 5L | E2: 30.32 | F2: =MATCH(A:A,'Crown Aug Uploads '!B:B,0) -> 205
A3: 5088704 | B3: CRT Clean Extreme Acrylic Eggshell | C3: Colour | D3: 5L | E3: 35.43 | F3: =MATCH(A:A,'Crown Aug Uploads '!B:B,0) -> 811
A4: 5088596 | B4: CRT Clean Extreme Anti Bac Acrylic Egg | C4: White | D4: 5L | E4: 35.72 | F4: =MATCH(A:A,'Crown Aug Uploads '!B:B,0) -> 812
A5: 5088693 | B5: CRT Clean Extreme Anti Bac Acrylic Egg | C5: Colour | D5: 5L | E5: 44.44 | F5: =MATCH(A:A,'Crown Aug Uploads '!B:B,0) -> 813
A6: 5088594 | B6: CRT Clean Ext Mould Inhibit Acrylic Egg | C6: White | D6: 5L | E6: 35.02 | F6: =MATCH(A:A,'Crown Aug Uploads '!B:B,0) -> 814
A7: 5090513 | B7: CRT Clean Ext Mould Inhibit Acrylic Egg | C7: White | D7: 2.5L | E7: 17.14 | F7: =MATCH(A:A,'Crown Aug Uploads '!B:B,0) -> 815
A8: 5088695 | B8: CRT Clean Ext Mould Inhibit Acrylic Egg | C8: Colour | D8: 5L | E8: 39.29 | F8: =MATCH(A:A,'Crown Aug Uploads '!B:B,0) -> 817
A9: 5091934 | B9: CRT Clean Ext Mould Inhibit Acrylic Egg | C9: Colour | D9: 2.5L | E9: 21.3 | F9: =MATCH(A:A,'Crown Aug Uploads '!B:B,0) -> 816
A10: 5064686 | B10: CRT Acrylic Eggshell | C10: White | D10: 5L | E10: 21.01 | F10: =MATCH(A:A,'Crown Aug Uploads '!B:B,0) -> 45
A11: 5064685 | B11: CRT Acrylic Eggshell | C11: White | D11: 2.5L | E11: 12.47 | F11: =MATCH(A:A,'Crown Aug Uploads '!B:B,0) -> 818
A12: 5064671 | B12: CRT Acrylic Eggshell | C12: Magnolia | D12: 5L | E12: 21.01 | F12: =MATCH(A:A,'Crown Aug Uploads '!B:B,0) -> 30
A13: 5066078 | B13: CRT Acrylic Eggshell | C13: Colour | D13: 5L | E13: 21.01 | F13: =MATCH(A:A,'Crown Aug Uploads '!B:B,0) -> 820
... A279: 5027929 | B279: MAC Wood Primer | C279: White | D279: 5L | E279: 21.47 | F279: =MATCH(A:A,'Crown Aug Uploads '!B:B,0) -> 980
A280: 6048262 | B280: DS REPAIR CARE CONTRACTOR PACK | E280: 234.94 | F280: =MATCH(A:A,'Crown Aug Uploads '!B:B,0) -> 1364
A281: 6048260 | B281: DS REPAIR CARE TRIAL PACK | E281: 148.57 | F281: =MATCH(A:A,'Crown Aug Uploads '!B:B,0) -> 1365
A282: 6048225 | B282: DS REPAIR CARE MIX&FIX CUPS/STICKS 50PK | E282: 24.93 | F282: =MATCH(A:A,'Crown Aug Uploads '!B:B,0) -> 1366
A283: 6048224 | B283: DS REPAIR CARE MIXING PLATE | E283: 19 | F283: =MATCH(A:A,'Crown Aug Uploads '!B:B,0) -> 1367
A284: 6046083 | B284: DS PERFORMANCE EMULS MINI KIT ROLL 7PC | E284: 3.43 | F284: =MATCH(A:A,'Crown Aug Uploads '!B:B,0) -> 1368
A285: 6046391 | B285: DS FFJ EMULSION MINI ROLLER KIT | E285: 6.9 | F285: =MATCH(A:A,'Crown Aug Uploads '!B:B,0) -> 1369
A286: 6047737 | B286: DS ROTA MINI VELOUR REFILL ROLLER 4IN | E286: 1.5 | F286: =MATCH(A:A,'Crown Aug Uploads '!B:B,0) -> 1370
A287: 6048205 | B287: DS REPAIR CARE DRY FLEX 16 | E287: 47.49 | F287: =MATCH(A:A,'Crown Aug Uploads '!B:B,0) -> 1371
A288: 6048207 | B288: DS REPAIR CARE DRY FLEX 4 | E288: 54 | F288: =MATCH(A:A,'Crown Aug Uploads '!B:B,0) -> 67
A289: 6048208 | B289: DS REPAIR CARE DRY FLEX 4 (2-IN-1) | E289: 29.65 | F289: =MATCH(A:A,'Crown Aug Uploads '!B:B,0) -> 1372
A290: 6048209 | B290: DS REPAIR CARE DRY FIX 4 | E290: 44.82 | F290: =MATCH(A:A,'Crown Aug Uploads '!B:B,0) -> 1373
A291: 6048212 | B291: DS REPAIR CARE DRY FIX UNI | E291: 59.83 | F291: =MATCH(A:A,'Crown Aug Uploads '!B:B,0) -> 274
... A387: 6052888 | B387: DS ARC CHALK SPRAY PNT LONDON GRY 400ML | E387: 10.21 | F387: =MATCH(A:A,'Crown Aug Uploads '!B:B,0) -> 1468
A388: 6050088 | B388: DS RUSTOLEUM FURN FIN WAX DARK 400ML | D388: =RIGHT(B388,5) -> 400ML | E388: 26.51 | F388: =MATCH(A:A,'Crown Aug Uploads '!B:B,0) -> 1469
A389: 6050090 | B389: DS RUSTOLEUM CHALK FURN HESSIAN 125ML | D389: =RIGHT(B389,5) -> 125ML | E389: 8.5 | F389: =MATCH(A:A,'Crown Aug Uploads '!B:B,0) -> 1470
A390: 6050091 | B390: DS RUSTOLEUM CHALK FURN LAUREL GRN 125ML | D390: =RIGHT(B390,5) -> 125ML | E390: 8.5 | F390: =MATCH(A:A,'Crown Aug Uploads '!B:B,0) -> 1471
A391: 6050092 | B391: DS RUSTOLEUM CHALK FURN POWDR BLUE 125ML | D391: =RIGHT(B391,5) -> 125ML | E391: 8.5 | F391: =MATCH(A:A,'Crown Aug Uploads '!B:B,0) -> 1472
A392: 6050093 | B392: DS RUSTOLEUM CHALK FURN INK BLUE 125ML | D392: =RIGHT(B392,5) -> 125ML | E392: 8.5 | F392: =MATCH(A:A,'Crown Aug Uploads '!B:B,0) -> 1473
A393: 6050094 | B393: DS RUSTOLEUM CHALK FURN BUTTERSCOT 125ML | D393: =RIGHT(B393,5) -> 125ML | E393: 8.5 | F393: =MATCH(A:A,'Crown Aug Uploads '!B:B,0) -> 1474
A394: 6050095 | B394: DS RUSTOLEUM CHALK FURN CHINA ROSE 125ML | D394: =RIGHT(B394,5) -> 125ML | E394: 8.5 | F394: =MATCH(A:A,'Crown Aug Uploads '!B:B,0) -> 1475
A395: 6050096 | B395: DS RUSTOLEUM CHALK FURN CORAL 125ML | D395: =RIGHT(B395,5) -> 125ML | E395: 8.5 | F395: =MATCH(A:A,'Crown Aug Uploads '!B:B,0) -> 1476
A396: 6050097 | B396: DS RUSTOLEUM CHALK FURN LILAC WINE 125ML | D396: =RIGHT(B396,5) -> 125ML | E396: 8.5 | F396: =MATCH(A:A,'Crown Aug Uploads '!B:B,0) -> 1477
A397: 6050098 | B397: DS RUSTOLEUM CHALK FURN FLINT 125ML | D397: =RIGHT(B397,5) -> 125ML | E397: 8.5 | F397: =MATCH(A:A,'Crown Aug Uploads '!B:B,0) -> 1478
A398: 6050099 | B398: DS RUSTOLEUM CHALK FURN HESSIAN 750ML | D398: =RIGHT(B398,5) -> 750ML | E398: 17.96 | F398: =MATCH(A:A,'Crown Aug Uploads '!B:B,0) -> 1479
A399: 6050100 | B399: DS RUSTOLEUM CHALK FURN LAUREL GRN 750ML | D399: =RIGHT(B399,5) -> 750ML | E399: 17.96 | F399: =MATCH(A:A,'Crown Aug Uploads '!B:B,0) -> 1480
... A403: 6050104 | B403: DS RUSTOLEUM CHALK FURN CHINA ROSE 750ML | D403: =RIGHT(B403,5) -> 750ML | E403: 17.96 | F403: =MATCH(A:A,'Crown Aug Uploads '!B:B,0) -> 1484
A404: 6050105 | B404: DS RUSTOLEUM CHALK FURN CORAL 750ML | E404: 17.96 | F404: =MATCH(A:A,'Crown Aug Uploads '!B:B,0) -> 1485
A405: 6050106 | B405: DS RUSTOLEUM CHALK FURN LILAC WINE 750ML | E405: 17.96 | F405: =MATCH(A:A,'Crown Aug Uploads '!B:B,0) -> 1486
A406: 6050107 | B406: DS RUSTOLEUM CHALK FURN FLINT 750ML | E406: 17.96 | F406: =MATCH(A:A,'Crown Aug Uploads '!B:B,0) -> 1487
A407: 6050116 | B407: DS ZINSSER BULLSEYE 123 DEEP 500ML | E407: 18.32 | F407: =MATCH(A:A,'Crown Aug Uploads '!B:B,0) -> 1488
A408: 6050233 | B408: DS EVERBUILD JETCEM RAP SET CEMENT 3KG | E408: 5.39 | F408: =MATCH(A:A,'Crown Aug Uploads '!B:B,0) -> 1489
A409: 6050234 | B409: DS EVERBUILD JETCEM RAP SET CEMENT 6KG | E409: 7.69 | F409: =MATCH(A:A,'Crown Aug Uploads '!B:B,0) -> 1490
A410: 6054813 | B410: DS POLYVINE GLITTER MAKER RAINBOW 75G | E410: 11.02 | F410: =MATCH(A:A,'Crown Aug Uploads '!B:B,0) -> 1491
A411: 6054814 | B411: DS POLYVINE GLITTER MAKER SILVER 75G | E411: 11.02 | F411: =MATCH(A:A,'Crown Aug Uploads '!B:B,0) -> 1492
A412: 6055499 | B412: DS HAMILTON COTTON DUSTSHEETS 12X9 5PK | E412: 45.32 | F412: =MATCH(A:A,'Crown Aug Uploads '!B:B,0) -> 131
A413: 6055859 | B413: DS KANA ADVANTAGE BRUSH SET 10PC | E413: 8 | F413: =MATCH(A:A,'Crown Aug Uploads '!B:B,0) -> 1493
A414: 6055953 | B414: DS KANA TANK BRUSH 2IN | E414: 3 | F414: =MATCH(A:A,'Crown Aug Uploads '!B:B,0) -> 1494
A415: 6056016 | B415: DS PREP CARPET PROTECTION 600MM X 50M | E415: 12 | F415: =MATCH(A:A,'Crown Aug Uploads '!B:B,0) -> 1495
... A460: 6046606 | B460: DS FFJ COMBINATION SHAVEHOOK | E460: 4.67 | F460: =MATCH(A:A,'Crown Aug Uploads '!B:B,0) -> 1539
A461: 6046603 | B461: DS RUSTOLEUM FURNITURE FINISH WAX 400ML | D461: =RIGHT(B461,5) -> 400ML | E461: 22.11 | F461: =MATCH(A:A,'Crown Aug Uploads '!B:B,0) -> 1540
A462: 6046602 | B462: DS RUSTOLEUM CHALK FURN DUSKY PINK 750ML | D462: =RIGHT(B462,5) -> 750ML | E462: 17.96 | F462: =MATCH(A:A,'Crown Aug Uploads '!B:B,0) -> 1541
A463: 6046601 | B463: DS RUSTOLEUM CHALK FURN WINTER GRY 750ML | D463: =RIGHT(B463,5) -> 750ML | E463: 17.96 | F463: =MATCH(A:A,'Crown Aug Uploads '!B:B,0) -> 1542
A464: 6046600 | B464: DS RUSTOLEUM CHALK FURN ANTHRACITE 750ML | D464: =RIGHT(B464,5) -> 750ML | E464: 17.96 | F464: =MATCH(A:A,'Crown Aug Uploads '!B:B,0) -> 1543
A465: 6046599 | B465: DS RUSTOLEUM CHALK FURN GRAPHITE 750ML | D465: =RIGHT(B465,5) -> 750ML | E465: 17.96 | F465: =MATCH(A:A,'Crown Aug Uploads '!B:B,0) -> 1544
A466: 6046598 | B466: DS RUSTOLEUM CHALK FURN BELGRAVE 750ML | D466: =RIGHT(B466,5) -> 750ML | E466: 17.96 | F466: =MATCH(A:A,'Crown Aug Uploads '!B:B,0) -> 1545
A467: 6046597 | B467: DS RUSTOLEUM CHALK FURN BRAMWELL 750ML | D467: =RIGHT(B467,5) -> 750ML | E467: 17.96 | F467: =MATCH(A:A,'Crown Aug Uploads '!B:B,0) -> 1546
A468: 6046596 | B468: DS RUSTOLEUM CHALK FURN SAGE GREEN 750ML | D468: =RIGHT(B468,5) -> 750ML | E468: 17.96 | F468: =MATCH(A:A,'Crown Aug Uploads '!B:B,0) -> 1547
A469: 6046595 | B469: DS RUSTOLEUM CHALK FURN DUCK EGG 750ML | D469: =RIGHT(B469,5) -> 750ML | E469: 17.96 | F469: =MATCH(A:A,'Crown Aug Uploads '!B:B,0) -> 1548
A470: 6046594 | B470: DS RUSTOLEUM CHALK FURN COCOA 750ML | D470: =RIGHT(B470,5) -> 750ML | E470: 17.96 | F470: =MATCH(A:A,'Crown Aug Uploads '!B:B,0) -> 1549
A471: 6046806 | B471: DS ARDENBRITE QD BASE 2.5L | D471: =RIGHT(B471,5) -> 2.5L | E471: 72.93 | F471: =MATCH(A:A,'Crown Aug Uploads '!B:B,0) -> 1550
A472: 6046857 | B472: DS RUSTOLEUM APPLIANCE WHITE 400ML | D472: =RIGHT(B472,5) -> 400ML | E472: 11.88 | F472: =MATCH(A:A,'Crown Aug Uploads '!B:B,0) -> 1551
... A491: 6046835 | B491: DS RUSTOLEUM CHALK FURN WHITE 125ML | D491: =RIGHT(B491,5) -> 125ML | E491: 8.5 | F491: =MATCH(A:A,'Crown Aug Uploads '!B:B,0) -> 1570
A492: 6046813 | B492: DS ROTA CORNER ROLLER 22MM | E492: 7.37 | F492: =MATCH(A:A,'Crown Aug Uploads '!B:B,0) -> 1571
A493: 6046807 | B493: DS TEAMAC P101 2PK PU TOPCOAT SPEC 5L | E493: 251.19 | F493: =MATCH(A:A,'Crown Aug Uploads '!B:B,0) -> 1572
A494: 6046159 | B494: DS BLACKFRIAR PU FLOOR MID GREY 5L | E494: 88.29 | F494: =MATCH(A:A,'Crown Aug Uploads '!B:B,0) -> 1573
A495: 6046061 | B495: DS PRESTIGE H DUTY SCAPER BLADE 50MM | E495: 6.64 | F495: =MATCH(A:A,'Crown Aug Uploads '!B:B,0) -> 1574
A496: 6046060 | B496: DS PRESTIGE HEAVY DUTY SCAPER 50MM | E496: 10.32 | F496: =MATCH(A:A,'Crown Aug Uploads '!B:B,0) -> 1575
A497: 6046049 | B497: DS PRESTIGE WALL BRUSH 4IN | E497: 20.24 | F497: =MATCH(A:A,'Crown Aug Uploads '!B:B,0) -> 1576
A498: 6046046 | B498: DS PERFECTION SCISSORS 11IN | E498: 5.16 | F498: =MATCH(A:A,'Crown Aug Uploads '!B:B,0) -> 1577
A499: 6046026 | B499: DS TETRION NO NAILS TUBE 330G | E499: 1.8 | F499: =MATCH(A:A,'Crown Aug Uploads '!B:B,0) -> 1578
A500: 6045888 | B500: DS OWATROL POLYTROL 250ML | E500: 18.68 | F500: =MATCH(A:A,'Crown Aug Uploads '!B:B,0) -> 1579
A501: 6045844 | B501: DS COOVAR ZINC RICH PRIMER 2.5L | E501: 166.3 | F501: =MATCH(A:A,'Crown Aug Uploads '!B:B,0) -> 1580
A502: 6045838 | B502: DS COOVAR TILE & MELAMINE PRIMER 2.5L | E502: 54.45 | F502: =MATCH(A:A,'Crown Aug Uploads '!B:B,0) -> 1581
A503: 6045830 | B503: DS COOVAR WB ACRYL VARN GLOSS 2.5L | E503: 34.71 | F503: =MATCH(A:A,'Crown Aug Uploads '!B:B,0) -> 1582
... A515: 6046190 | B515: DS BLACKFRIAR AS FLOOR WHITE 1L | E515: 21.55 | F515: =MATCH(A:A,'Crown Aug Uploads '!B:B,0) -> 1594
A516: 6046593 | B516: DS RUSTOLEUM CHALK FURN FIREBRICK 750ML | D516: =RIGHT(B516,5) -> 750ML | E516: 17.96 | F516: =MATCH(A:A,'Crown Aug Uploads '!B:B,0) -> 1595
A517: 6046588 | B517: DS RUSTOLEUM CHALK FURN MUSTARD 750ML | D517: =RIGHT(B517,5) -> 750ML | E517: 17.96 | F517: =MATCH(A:A,'Crown Aug Uploads '!B:B,0) -> 1596
A518: 6046587 | B518: DS RUSTOLEUM CHALK FURN CLOT CREAM 750ML | D518: =RIGHT(B518,5) -> 750ML | E518: 17.96 | F518: =MATCH(A:A,'Crown Aug Uploads '!B:B,0) -> 1597
A519: 6046584 | B519: DS RUSTOLEUM CHALK FURN ANT WHITE 750ML | D519: =RIGHT(B519,5) -> 750ML | E519: 17.96 | F519: =MATCH(A:A,'Crown Aug Uploads '!B:B,0) -> 1598
A520: 6046583 | B520: DS RUSTOLEUM CHALK FURN WHITE 750ML | D520: =RIGHT(B520,5) -> 750ML | E520: 17.96 | F520: =MATCH(A:A,'Crown Aug Uploads '!B:B,0) -> 1599
A521: 6046575 | B521: DS TOOLBANK LETTER/NUM STENCIL KIT 100MM | E521: 53.3 | F521: =MATCH(A:A,'Crown Aug Uploads '!B:B,0) -> 1600
A522: 6046574 | B522: DS INDASA TUNGSTEN CARBIDE SCRAPER 50MM | E522: 17.78 | F522: =MATCH(A:A,'Crown Aug Uploads '!B:B,0) -> 157
A523: 6046531 | B523: DS COOVAR PROFLOOR PLUS FLINT GREY 5K | E523: 167.38 | F523: =MATCH(A:A,'Crown Aug Uploads '!B:B,0) -> 1601
A524: 6046456 | B524: DS ZINSSER ALLCOAT RAL9010 10L | E524: 228.57 | F524: =MATCH(A:A,'Crown Aug Uploads '!B:B,0) -> 1602
A525: 6046454 | B525: DS TEAMAC METALCOTE UND WHITE 2.5L | E525: 42.42 | F525: =MATCH(A:A,'Crown Aug Uploads '!B:B,0) -> 1603
A526: 6046418 | B526: DS GLIXTONE HIGHBUILD MAGNOLIA 15K | E526: 88.22 | F526: =MATCH(A:A,'Crown Aug Uploads '!B:B,0) -> 1604
A527: 6046417 | B527: DS POLYVINE HD WOOD VARNISH SATIN 500ML | E527: 14.37 | F527: =MATCH(A:A,'Crown Aug Uploads '!B:B,0) -> 1605
A528: 6046414 | B528: DS RODO ST LEDGER DECORATING KIT | E528: 41.35 | F528: =MATCH(A:A,'Crown Aug Uploads '!B:B,0) -> 1606
A529: 6046408 | B529: DS GRAY SC6+ TIP & SEAL 662-519 | E529: 70.47 | F529: =MATCH(A:A,'Crown Aug Uploads '!B:B,0) -> 1607
A530: 6046406 | B530: DS GRAY SC6+ TIP & SEAL 662-515 | E530: 70.47 | F530: =MATCH(A:A,'Crown Aug Uploads '!B:B,0) -> 1608
A531: 6046405 | B531: DS GRAY SC6+ TIP & SEAL 662-413 | E531: 70.47 | F531: =MATCH(A:A,'Crown Aug Uploads '!B:B,0) -> 1609
A532: 6046385 | B532: DS PRODEC LONG HANDLE SCRAPER 6IN | E532: 15.83 | F532: =MATCH(A:A,'Crown Aug Uploads '!B:B,0) -> 1610
... A536: 6046191 | B536: DS BLACKFRIAR ACR FLOOR WHITE 1L | E536: 23.05 | F536: =MATCH(A:A,'Crown Aug Uploads '!B:B,0) -> 1613
A537: 6050059 | B537: DS RUSTOLEUM CHALK SAT CORNF BLUE 125ML | D537: =RIGHT(B537,5) -> 125ML | E537: 10.15 | F537: =MATCH(A:A,'Crown Aug Uploads '!B:B,0) -> 1614
A538: 6050058 | B538: DS RUSTOLEUM CHALK SAT SKY 125ML | D538: =RIGHT(B538,5) -> 125ML | E538: 10.15 | F538: =MATCH(A:A,'Crown Aug Uploads '!B:B,0) -> 1615
A539: 6050057 | B539: DS RUSTOLEUM CHALK SAT MOCHA 125ML | D539: =RIGHT(B539,5) -> 125ML | E539: 10.15 | F539: =MATCH(A:A,'Crown Aug Uploads '!B:B,0) -> 1616
...

Sheet April23
A1: Cust_No. | B1: SAP_Number | C1: Matl_Desc. | D1: Price | E1: Desc. | F1: Size | G1: Unit | H1: Date | I1: EAN-code | J1: Currency | K1: text
A2: 12973 | B2: 6055954 | C2: DS OAKEY BTW CTS FINISH PAPER 240G 5M | D2: 8 | E2: BDS Abrasives | F2: 1 | G2: PC | H2: 45079 | I2: 3157629665138 | J2: GBP | K2: =_xlfn.XLOOKUP(B2,'Crown Aug Uploads '!A:A,'Crown Aug Uploads '!C:C) -> CROW01
A3: 12973 | B3: 6055709 | C3: DS OAKEY FLEX FINISH PAD EX FINE/FINE | D3: 1.11 | E3: BDS Abrasives | F3: 1 | G3: PC | H3: 45079 | I3: 3157629794685 | J3: GBP | K3: =_xlfn.XLOOKUP(B3,'Crown Aug Uploads '!A:A,'Crown Aug Uploads '!C:C) -> CROW01
A4: 12973 | B4: 6055707 | C4: DS OAKEY FLEXIBLE FINISH PADS EX MED/CRS | D4: 1.11 | E4: BDS Abrasives | F4: 1 | G4: PC | H4: 45079 | I4: 3157629794678 | J4: GBP | K4: =_xlfn.XLOOKUP(B4,'Crown Aug Uploads '!A:A,'Crown Aug Uploads '!C:C) -> CROW01
A5: 12973 | B5: 6053563 | C5: DS INDASA ABRASIVE BLOCK P100 1PC | D5: 1 | E5: BDS Abrasives | F5: 1 | G5: PC | H5: 45079 | I5: 5603902463000 | J5: GBP | K5: =_xlfn.XLOOKUP(B5,'Crown Aug Uploads '!A:A,'Crown Aug Uploads '!C:C) -> CROW01
A6: 12973 | B6: 6053562 | C6: DS INDASA RHYNALOX PLUSLINE ASSRTD 10PK | D6: 6.5 | E6: BDS Abrasives | F6: 1 | G6: PC | H6: 45079 | I6: 5603902583708 | J6: GBP | K6: =_xlfn.XLOOKUP(B6,'Crown Aug Uploads '!A:A,'Crown Aug Uploads '!C:C) -> CROW01
A7: 12973 | B7: 6053561 | C7: DS INDASA RHYNOWOOD ASSORTED 5PK | D7: 2.25 | E7: BDS Abrasives | F7: 1 | G7: PC | H7: 45079 | I7: 5603902583715 | J7: GBP | K7: =_xlfn.XLOOKUP(B7,'Crown Aug Uploads '!A:A,'Crown Aug Uploads '!C:C) -> CROW01
A8: 12973 | B8: 6053560 | C8: DS INDASA RHYNOWET W LINE ASSRTD 4PK | D8: 2.75 | E8: BDS Abrasives | F8: 1 | G8: PC | H8: 45079 | I8: 5603902583692 | J8: GBP | K8: =_xlfn.XLOOKUP(B8,'Crown Aug Uploads '!A:A,'Crown Aug Uploads '!C:C) -> CROW01
A9: 12973 | B9: 6047323 | C9: DS INDASA SPONGE PADS P120 10PK | D9: 5.5 | E9: BDS Abrasives | F9: 1 | G9: PC | H9: 45079 | I9: 5603902014493 | J9: GBP | K9: =_xlfn.XLOOKUP(B9,'Crown Aug Uploads '!A:A,'Crown Aug Uploads '!C:C) -> CROW01
A10: 12973 | B10: 6047322 | C10: DS INDASA SPONGE PADS P100 10PK | D10: 5.5 | E10: BDS Abrasives | F10: 1 | G10: PC | H10: 45079 | I10: 5603902014486 | J10: GBP | K10: =_xlfn.XLOOKUP(B10,'Crown Aug Uploads '!A:A,'Crown Aug Uploads '!C:C) -> CROW01
A11: 12973 | B11: 6047321 | C11: DS INDASA SPONGE PADS P80 10PK | D11: 5.5 | E11: BDS Abrasives | F11: 1 | G11: PC | H11: 45079 | I11: 5603902476314 | J11: GBP | K11: =_xlfn.XLOOKUP(B11,'Crown Aug Uploads '!A:A,'Crown Aug Uploads '!C:C) -> CROW01
A12: 12973 | B12: 6047320 | C12: DS INDASA SPONGE PADS P60 10PK | D12: 5.5 | E12: BDS Abrasives | F12: 1 | G12: PC | H12: 45079 | I12: 5603902014479 | J12: GBP | K12: =_xlfn.XLOOKUP(B12,'Crown Aug Uploads '!A:A,'Crown Aug Uploads '!C:C) -> CROW01
A13: 12973 | B13: 6046792 | C13: DS INDASA RHYNALOX PLUS P80 115MM 10M | D13: 9 | E13: BDS Abrasives | F13: 1 | G13: PC | H13: 45079 | I13: 5603902498637 | J13: GBP | K13: =_xlfn.XLOOKUP(B13,'Crown Aug Uploads '!A:A,'Crown Aug Uploads '!C:C) -> CROW01
... A385: 12973 | B385: 6054438 | C385: WA ANAGLYPTA TUFF STUFF TEXTURE 15M | D385: 6 | E385: WAL Whites Wallpaper | F385: 1 | G385: PC | H385: 45079 | I385: 5060075553653 | J385: GBP | K385: =_xlfn.XLOOKUP(B385,'Crown Aug Uploads '!A:A,'Crown Aug Uploads '!C:C) -> CROW01
A386: 12973 | B386: 6053183 | C386: WA SUPERFRESCO WHITE WW | D386: 18.44 | E386: WAL Whites Wallpaper | F386: 1 | G386: PC | H386: 45079 | J386: GBP | K386: =_xlfn.XLOOKUP(B386,'Crown Aug Uploads '!A:A,'Crown Aug Uploads '!C:C) -> CROW01
A387: 12973 | B387: 6053182 | C387: WA SUPERFRESCO WHITE WC | D387: 15.08 | E387: WAL Whites Wallpaper | F387: 1 | G387: PC | H387: 45079 | J387: GBP | K387: =_xlfn.XLOOKUP(B387,'Crown Aug Uploads '!A:A,'Crown Aug Uploads '!C:C) -> CROW01
A388: 12973 | B388: 6053181 | C388: WA SUPERFRESCO WHITE WL | D388: 15 | E388: WAL Whites Wallpaper | F388: 1 | G388: PC | H388: 45079 | J388: GBP | K388: =_xlfn.XLOOKUP(B388,'Crown Aug Uploads '!A:A,'Crown Aug Uploads '!C:C) -> CROW01
A389: 12973 | B389: 6046432 | C389: WA ANAGLYPTA PRECISION ROYAL OAK RD7000 | D389: 7.76 | E389: WAL Whites Wallpaper | F389: 1 | G389: PC | H389: 45079 | I389: 5060075554841 | J389: GBP | K389: =_xlfn.XLOOKUP(B389,'Crown Aug Uploads '!A:A,'Crown Aug Uploads '!C:C) -> CROW01
A390: 12973 | B390: 6040165 | C390: WA SUPERFRESCO WHITE NW | D390: 15 | E390: WAL Whites Wallpaper | F390: 1 | G390: PC | H390: 45079 | J390: GBP | K390: =_xlfn.XLOOKUP(B390,'Crown Aug Uploads '!A:A,'Crown Aug Uploads '!C:C) -> CROW01
A391: 12973 | B391: 6040164 | C391: WA SUPERFRESCO WHITE IH | D391: 6.62 | E391: WAL Whites Wallpaper | F391: 1 | G391: PC | H391: 45079 | J391: GBP | K391: =_xlfn.XLOOKUP(B391,'Crown Aug Uploads '!A:A,'Crown Aug Uploads '!C:C) -> CROW01
A392: 12973 | B392: 6040162 | C392: WA SUPERFRESCO WHITE HT | D392: 15 | E392: WAL Whites Wallpaper | F392: 1 | G392: PC | H392: 45079 | J392: GBP | K392: =_xlfn.XLOOKUP(B392,'Crown Aug Uploads '!A:A,'Crown Aug Uploads '!C:C) -> CROW01
A393: 12973 | B393: 6040161 | C393: WA SUPERFRESCO WHITE HS | D393: 13.29 | E393: WAL Whites Wallpaper | F393: 1 | G393: PC | H393: 45079 | J393: GBP | K393: =_xlfn.XLOOKUP(B393,'Crown Aug Uploads '!A:A,'Crown Aug Uploads '!C:C) -> CROW01
A394: 12973 | B394: 6040159 | C394: WA SUPERFRESCO WHITE HP | D394: 15 | E394: WAL Whites Wallpaper | F394: 1 | G394: PC | H394: 45079 | J394: GBP | K394: =_xlfn.XLOOKUP(B394,'Crown Aug Uploads '!A:A,'Crown Aug Uploads '!C:C) -> CROW01
A395: 12973 | B395: 6040125 | C395: WA ANAGLYPTA TEXT VINYL WILL BO RD804301 | D395: 4.94 | E395: WAL Whites Wallpaper | F395: 1 | G395: PC | H395: 45079 | I395: 5010409113145 | J395: GBP | K395: =_xlfn.XLOOKUP(B395,'Crown Aug Uploads '!A:A,'Crown Aug Uploads '!C:C) -> CROW01
A396: 12973 | B396: 6040118 | C396: WA ANAGLYPTA TEXT VINYL HAVERSHAM 34365 | D396: 4.94 | E396: WAL Whites Wallpaper | F396: 1 | G396: PC | H396: 45079 | I396: 5010907343655 | J396: GBP | K396: =_xlfn.XLOOKUP(B396,'Crown Aug Uploads '!A:A,'Crown Aug Uploads '!C:C) -> CROW01
A397: 12973 | B397: 6040077 | C397: WA ANAGLYPTA TEXT VINYL CITRINE RD016 | D397: 7.76 | E397: WAL Whites Wallpaper | F397: 1 | G397: PC | H397: 45079 | I397: 5034751803530 | J397: GBP | K397: =_xlfn.XLOOKUP(B397,'Crown Aug Uploads '!A:A,'Crown Aug Uploads '!C:C) -> CROW01
A398: 12973 | B398: 5088591 | C398: CT CLNEX SR AC EGG WHITE 5L | D398: 29.76 | E398: CRT Clean Extreme Acr Egg White | F398: 1 | G398: PC | H398: 45079 | I398: 5010131525407 | J398: GBP | K398: =_xlfn.XLOOKUP(B398,'Crown Aug Uploads '!A:A,'Crown Aug Uploads '!C:C) -> CROW01
A399: 12973 | B399: 5088704 | C399: CT CLN EXTREME ACR EGG 5L | D399: 34.78 | E399: CRT Clean Extreme Acr Egg Col | F399: 1 | G399: PC | H399: 45079 | I399: 5010131575341 | J399: GBP | K399: =_xlfn.XLOOKUP(B399,'Crown Aug Uploads '!A:A,'Crown Aug Uploads '!C:C) -> CROW01
A400: 12973 | B400: 5088596 | C400: CT CLNEX AB AC EGG WHITE 5L | D400: 35.05 | E400: CRT Steracryl A/Bac Acr Egg White | F400: 1 | G400: PC | H400: 45079 | I400: 5010131525452 | J400: GBP | K400: =_xlfn.XLOOKUP(B400,'Crown Aug Uploads '!A:A,'Crown Aug Uploads '!C:C) -> CROW01
A401: 12973 | B401: 5088693 | C401: CT CLNEX A/BAC ACR EGG 5L | D401: 43.61 | E401: CRT Steracryl A/Bac Acr Egg Col | F401: 1 | G401: PC | H401: 45079 | I401: 5010131575372 | J401: GBP | K401: =_xlfn.XLOOKUP(B401,'Crown Aug Uploads '!A:A,'Crown Aug Uploads '!C:C) -> CROW01
A402: 12973 | B402: 5090513 | C402: CT CLNEX MI AC EGGSHELL WHITE 2.5L | D402: 16.81 | E402: CRT Steracryl M/Inhibit Acr Egg White | F402: 1 | G402: PC | H402: 45079 | I402: 5010131548789 | J402: GBP | K402: =_xlfn.XLOOKUP(B402,'Crown Aug Uploads '!A:A,'Crown Aug Uploads '!C:C) -> CROW01
A403: 12973 | B403: 5088594 | C403: CT CLNEX MI AC EGGSHELL WHITE 5L | D403: 34.38 | E403: CRT Steracryl M/Inhibit Acr Egg White | F403: 1 | G403: PC | H403: 45079 | I403: 5010131525438 | J403: GBP | K403: =_xlfn.XLOOKUP(B403,'Crown Aug Uploads '!A:A,'Crown Aug Uploads '!C:C) -> CROW01
A404: 12973 | B404: 5091934 | C404: CT CLNEX M INH ACR EGG 2.5L | D404: 20.9 | E404: CRT Steracryl M/Inhibit Acr Egg Col | F404: 1 | G404: PC | H404: 45079 | I404: 5010131575402 | J404: GBP | K404: =_xlfn.XLOOKUP(B404,'Crown Aug Uploads '!A:A,'Crown Aug Uploads '!C:C) -> CROW01
A405: 12973 | B405: 5088695 | C405: CT CLNEX M INH ACR EGG 5L | D405: 38.58 | E405: CRT Steracryl M/Inhibit Acr Egg Col | F405: 1 | G405: PC | H405: 45079 | I405: 5010131575396 | J405: GBP | K405: =_xlfn.XLOOKUP(B405,'Crown Aug Uploads '!A:A,'Crown Aug Uploads '!C:C) -> CROW01
A406: 12973 | B406: 5064686 | C406: CT ACRYLIC EGGSHELL WHITE 5L | D406: 24.03 | E406: CRT Best Fin Acrylic Eggshell White | F406: 1 | G406: PC | H406: 45079 | I406: 5010131494574 | J406: GBP | K406: =_xlfn.XLOOKUP(B406,'Crown Aug Uploads '!A:A,'Crown Aug Uploads '!C:C) -> CROW01
... A443: 12973 | B443: 5093674 | C443: CT FASTFLOW QD EGGSHELL WHITE 2.5L | D443: 18.39 | E443: CRT Fastflow Quick Dry Eggshell White | F443: 1 | G443: PC | H443: 45079 | I443: 5010131576942 | J443: GBP | K443: =_xlfn.XLOOKUP(B443,'Crown Aug Uploads '!A:A,'Crown Aug Uploads '!C:C) -> CROW01
A444: 12973 | B444: 5095632 | C444: CT FASTFLOW QD EGGSHELL 1L | D444: 11.24 | E444: CT FF QD Eggshell Base COL | F444: 1 | G444: PC | H444: 45079 | J444: GBP | K444: =_xlfn.XLOOKUP(B444,'Crown Aug Uploads '!A:A,'Crown Aug Uploads '!C:C) -> CROW01
A445: 12973 | B445: 5095633 | C445: CT FASTFLOW QD EGGSHELL 2.5L | D445: 24.62 | E445: CT FF QD Eggshell Base COL | F445: 1 | G445: PC | H445: 45079 | J445: GBP | K445: =_xlfn.XLOOKUP(B445,'Crown Aug Uploads '!A:A,'Crown Aug Uploads '!C:C) -> CROW01
A446: 12973 | B446: 5090805 | C446: CT FASTFLOW QD GLOSS BLACK 2.5L | D446: 16.13 | E446: CRT Fastflow Quick Dry Gloss Black | F446: 1 | G446: PC | H446: 45079 | I446: 5010131552809 | J446: GBP | K446: =_xlfn.XLOOKUP(B446,'Crown Aug Uploads '!A:A,'Crown Aug Uploads '!C:C) -> CROW01
A447: 12973 | B447: 5090869 | C447: CT FASTFLOW QD GLOSS BLACK 1L | D447: 8.19 | E447: CRT Fastflow Quick Dry Gloss Black | F447: 1 | G447: PC | H447: 45079 | I447: 5010131553417 | J447: GBP | K447: =_xlfn.XLOOKUP(B447,'Crown Aug Uploads '!A:A,'Crown Aug Uploads '!C:C) -> CROW01
A448: 12973 | B448: 5090802 | C448: CT FASTFLOW QD GLOSS WHITE 1L | D448: 7.11 | E448: CRT Fastflow Quick Dry Gloss White | F448: 1 | G448: PC | H448: 45079 | I448: 5010131552779 | J448: GBP | K448: =_xlfn.XLOOKUP(B448,'Crown Aug Uploads '!A:A,'Crown Aug Uploads '!C:C) -> CROW01
A449: 12973 | B449: 5090803 | C449: CT FASTFLOW QD GLOSS WHITE 2.5L | D449: 14.01 | E449: CRT Fastflow Quick Dry Gloss White | F449: 1 | G449: PC | H449: 45079 | I449: 5010131552786 | J449: GBP | K449: =_xlfn.XLOOKUP(B449,'Crown Aug Uploads '!A:A,'Crown Aug Uploads '!C:C) -> CROW01
A450: 12973 | B450: 5090804 | C450: CT FASTFLOW QD GLOSS WHITE 5L | D450: 25.29 | E450: CRT Fastflow Quick Dry Gloss White | F450: 1 | G450: PC | H450: 45079 | I450: 5010131552793 | J450: GBP | K450: =_xlfn.XLOOKUP(B450,'Crown Aug Uploads '!A:A,'Crown Aug Uploads '!C:C) -> CROW01
A451: 12973 | B451: 5093355 | C451: CT FASTFLOW GLOSS 5L | D451: 29.03 | E451: CRT Fastflow Quick Dry Gloss Colour | F451: 1 | G451: PC | H451: 45079 | I451: 5010131575167 | J451: GBP | K451: =_xlfn.XLOOKUP(B451,'Crown Aug Uploads '!A:A,'Crown Aug Uploads '!C:C) -> CROW01
A452: 12973 | B452: 5093354 | C452: CT FASTFLOW GLOSS 2.5L | D452: 16.13 | E452: CRT Fastflow Quick Dry Gloss Colour | F452: 1 | G452: PC | H452: 45079 | I452: 5010131575174 | J452: GBP | K452: =_xlfn.XLOOKUP(B452,'Crown Aug Uploads '!A:A,'Crown Aug Uploads '!C:C) -> CROW01
A453: 12973 | B453: 5093353 | C453: CT FASTFLOW GLOSS 1L | D453: 8.19 | E453: CRT Fastflow Quick Dry Gloss Colour | F453: 1 | G453: PC | H453: 45079 | I453: 5010131575181 | J453: GBP | K453: =_xlfn.XLOOKUP(B453,'Crown Aug Uploads '!A:A,'Crown Aug Uploads '!C:C) -> CROW01
A454: 12973 | B454: 5090814 | C454: CT FASTFLOW QD UNDRCOAT WHITE 1L | D454: 7.11 | E454: CRT Fastflow Quick Dry Primer U/coat Whi | F454: 1 | G454: PC | H454: 45079 | I454: 5010131552892 | J454: GBP | K454: =_xlfn.XLOOKUP(B454,'Crown Aug Uploads '!A:A,'Crown Aug Uploads '!C:C) -> CROW01
A455: 12973 | B455: 5090815 | C455: CT FASTFLOW QD UNDRCOAT WHITE 2.5L | D455: 14.01 | E455: CRT Fastflow Quick Dry Primer U/coat Whi | F455: 1 | G455: PC | H455: 45079 | I455: 5010131552908 | J455: GBP | K455: =_xlfn.XLOOKUP(B455,'Crown Aug Uploads '!A:A,'Crown Aug Uploads '!C:C) -> CROW01
A456: 12973 | B456: 5090816 | C456: CT FASTFLOW QD UNDRCOAT WHITE 5L | D456: 26 | E456: CRT Fastflow Quick Dry Primer U/coat Whi | F456: 1 | G456: PC | H456: 45079 | I456: 5010131552915 | J456: GBP | K456: =_xlfn.XLOOKUP(B456,'Crown Aug Uploads '!A:A,'Crown Aug Uploads '!C:C) -> CROW01
A457: 12973 | B457: 5093361 | C457: CT FASTFLOW UNDERCOAT 5L | D457: 29.03 | E457: CRT Fastflow Quick Dry Primer/Und Col | F457: 1 | G457: PC | H457: 45079 | I457: 5010131574672 | J457: GBP | K457: =_xlfn.XLOOKUP(B457,'Crown Aug Uploads '!A:A,'Crown Aug Uploads '!C:C) -> CROW01
... A655: 12973 | B655: 5027928 | C655: MC WOOD PRIMER WHITE 2.5L | D655: 10.65 | E655: MAC Wood Primer WHT | F655: 1 | G655: PC | H655: 45079 | I655: 5010584095823 | J655: GBP | K655: =_xlfn.XLOOKUP(B655,'Crown Aug Uploads '!A:A,'Crown Aug Uploads '!C:C) -> CROW01
A656: 12973 | B656: 5092261 | C656: CT ACRYLIC EGG TIMONOX TINT COL 5L | D656: 48 | E656: TRC Timonox Acrylic Egg Colour | F656: 1 | G656: PC | H656: 45079 | J656: GBP | K656: =_xlfn.XLOOKUP(B656,'Crown Aug Uploads '!A:A,'Crown Aug Uploads '!C:C) -> CROW01
A657: 12973 | B657: 5092262 | C657: CT ACRYLIC EGGSHELL TINT COL 2.5L | D657: 15.76 | E657: TRC Acrylic Eggshell Colour | F657: 1 | G657: PC | H657: 45079 | J657: GBP | K657: =_xlfn.XLOOKUP(B657,'Crown Aug Uploads '!A:A,'Crown Aug Uploads '!C:C) -> CROW01
A658: 12973 | B658: 5095922 | C658: CT CLN EXT MI SCR MATT TINT COL 5L | D658: 35 | E658: TRC Clean Extreme MI SC Matt Colour | F658: 1 | G658: PC | H658: 45079 | J658: GBP | K658: =_xlfn.XLOOKUP(B658,'Crown Aug Uploads '!A:A,'Crown Aug Uploads '!C:C) -> CROW01
A659: 12973 | B659: 5092299 | C659: CT FASTFLOW GLOSS TINT COL 2.5L | D659: 16.13 | E659: TRC Fastflow Quick Dry Gloss Colour | F659: 1 | G659: PC | H659: 45079 | J659: GBP | K659: =_xlfn.XLOOKUP(B659,'Crown Aug Uploads '!A:A,'Crown Aug Uploads '!C:C) -> CROW01
A660: 12973 | B660: 5092298 | C660: CT FASTFLOW GLOSS TINT COL 1L | D660: 8.19 | E660: TRC Fastflow Quick Dry Gloss Colour | F660: 1 | G660: PC | H660: 45079 | J660: GBP | K660: =_xlfn.XLOOKUP(B660,'Crown Aug Uploads '!A:A,'Crown Aug Uploads '!C:C) -> CROW01
A661: 12973 | B661: 5092766 | C661: CT FASTFLOW UNDERCOAT TINT COL 2.5L | D661: 16.13 | E661: TRC Primer/Undercoat Colour | F661: 1 | G661: PC | H661: 45079 | J661: GBP | K661: =_xlfn.XLOOKUP(B661,'Crown Aug Uploads '!A:A,'Crown Aug Uploads '!C:C) -> CROW01
A662: 12973 | B662: 5092335 | C662: CT FASTFLOW UNDERCOAT TINT COL 5L | D662: 29.02 | E662: TRC Primer/Undercoat Colour | F662: 1 | G662: PC | H662: 45079 | J662: GBP | K662: =_xlfn.XLOOKUP(B662,'Crown Aug Uploads '!A:A,'Crown Aug Uploads '!C:C) -> CROW01
A663: 12973 | B663: 5092334 | C663: CT FASTFLOW UNDERCOAT TINT COL 1L | D663: 8.19 | E663: TRC Primer/Undercoat Colour | F663: 1 | G663: PC | H663: 45079 | J663: GBP | K663: =_xlfn.XLOOKUP(B663,'Crown Aug Uploads '!A:A,'Crown Aug Uploads '!C:C) -> CROW01
A664: 12973 | B664: 5092267 | C664: CT COVERMATT TINT COL 10L | D664: 28.78 | E664: TRC Covermatt COL | F664: 1 | G664: PC | H664: 45079 | J664: GBP | K664: =_xlfn.XLOOKUP(B664,'Crown Aug Uploads '!A:A,'Crown Aug Uploads '!C:C) -> CROW01
A665: 12973 | B665: 5092268 | C665: CT COVERMATT TINT COL 5L | D665: 14.51 | E665: TRC Covermatt COL | F665: 1 | G665: PC | H665: 45079 | J665: GBP | K665: =_xlfn.XLOOKUP(B665,'Crown Aug Uploads '!A:A,'Crown Aug Uploads '!C:C) -> CROW01
A666: 12973 | B666: 5092306 | C666: CT MATT EMULSION TINT COL 1L | D666: 5.25 | E666: TRC Matt COL | F666: 1 | G666: PC | H666: 45079 | J666: GBP | K666: =_xlfn.XLOOKUP(B666,'Crown Aug Uploads '!A:A,'Crown Aug Uploads '!C:C) -> CROW01
A667: 12973 | B667: 5092307 | C667: CT MATT EMULSION TINT COL 2.5L | D667: 10.03 | E667: TRC Matt COL | F667: 1 | G667: PC | H667: 45079 | J667: GBP | K667: =_xlfn.XLOOKUP(B667,'Crown Aug Uploads '!A:A,'Crown Aug Uploads '!C:C) -> CROW01
... A695: 12973 | B695: 5092264 | C695: CT CLN EXT ACR EGG TINT COL 5L | D695: 34.78 | E695: TRC Clean Extreme Acr Egg Col | F695: 1 | G695: PC | H695: 45079 | J695: GBP | K695: =_xlfn.XLOOKUP(B695,'Crown Aug Uploads '!A:A,'Crown Aug Uploads '!C:C) -> CROW01
A696: 12973 | B696: 5091367 | C696: SD BEAUTIFLEX WHITE 2.5L | D696: 37.52 | E696: SAD Beautiflex White | F696: 1 | G696: PC | H696: 45079 | I696: 5010131557972 | J696: GBP | K696: =_xlfn.XLOOKUP(B696,'Crown Aug Uploads '!A:A,'Crown Aug Uploads '!C:C) -> CROW01
A697: 12973 | B697: 5091369 | C697: SD BEAUTIFLEX BLACK 2.5L | D697: 37.52 | E697: SAD Beautiflex Colour | F697: 1 | G697: PC | H697: 45079 | I697: 5010131557996 | J697: GBP | K697: =_xlfn.XLOOKUP(B697,'Crown Aug Uploads '!A:A,'Crown Aug Uploads '!C:C) -> CROW01
A698: 12973 | B698: 5091371 | C698: SD BEAUTIFLEX HICKORY 2.5L | D698: 37.52 | E698: SAD Beautiflex Colour | F698: 1 | G698: PC | H698: 45079 | I698: 5010131558016 | J698: GBP | K698: =_xlfn.XLOOKUP(B698,'Crown Aug Uploads '!A:A,'Crown Aug Uploads '!C:C) -> CROW01
A699: 12973 | B699: 5091374 | C699: SD BEAUTIFLEX BASE WHITE W0 1L | D699: 16.89 | E699: SAD Beautiflex Base White | F699: 1 | G699: PC | H699: 45079 | I699: 5010131558047 | J699: GBP | K699: =_xlfn.XLOOKUP(B699,'Crown Aug Uploads '!A:A,'Crown Aug Uploads '!C:C) -> CROW01
A700: 12973 | B700: 5091375 | C700: SD BEAUTIFLEX BASE WHITE W0 2.5L | D700: 37.52 | E700: SAD Beautiflex Base White | F700: 1 | G700: PC | H700: 45079 | I700: 5010131558054 | J700: GBP | K700: =_xlfn.XLOOKUP(B700,'Crown Aug Uploads '!A:A,'Crown Aug Uploads '!C:C) -> CROW01
A701: 12973 | B701: 5091372 | C701: SD BEAUTIFLEX BASE CLEAR 065 1L | D701: 16.89 | E701: SAD Beautiflex Base Clear | F701: 1 | G701: PC | H701: 45079 | I701: 5010131558023 | J701: GBP | K701: =_xlfn.XLOOKUP(B701,'Crown Aug Uploads '!A:A,'Crown Aug Uploads '!C:C) -> CROW01
A702: 12973 | B702: 5091373 | C702: SD BEAUTIFLEX BASE CLEAR 065 2.5L | D702: 37.52 | E702: SAD Beautiflex Base Clear | F702: 1 | G702: PC | H702: 45079 | I702: 5010131558030 | J702: GBP | K702: =_xlfn.XLOOKUP(B702,'Crown Aug Uploads '!A:A,'Crown Aug Uploads '!C:C) -> CROW01
A703: 12973 | B703: 5028473 | C703: SD CLASSIC REDWOOD 1L | D703: 15.01 | E703: SAD Classic Standard COL | F703: 1 | G703: PC | H703: 45079 | I703: 5721147600711 | J703: GBP | K703: =_xlfn.XLOOKUP(B703,'Crown Aug Uploads '!A:A,'Crown Aug Uploads '!C:C) -> CROW01
A704: 12973 | B704: 5028475 | C704: SD CLASSIC DK PALSNDR 1L | D704: 15.01 | E704: SAD Classic Standard COL | F704: 1 | G704: PC | H704: 45079 | I704: 5721147660913 | J704: GBP | K704: =_xlfn.XLOOKUP(B704,'Crown Aug Uploads '!A:A,'Crown Aug Uploads '!C:C) -> CROW01
A705: 12973 | B705: 5028476 | C705: SD CLASSIC DK PALSNDR 2.5L | D705: 35.07 | E705: SAD Classic Standard COL | F705: 1 | G705: PC | H705: 45079 | I705: 5721147660920 | J705: GBP | K705: =_xlfn.XLOOKUP(B705,'Crown Aug Uploads '!A:A,'Crown Aug Uploads '!C:C) -> CROW01
A706: 12973 | B706: 5028477 | C706: SD CLASSIC DK PALSNDR 5L | D706: 65.14 | E706: SAD Classic Standard COL | F706: 1 | G706: PC | H706: 45079 | I706: 5721147660937 | J706: GBP | K706: =_xlfn.XLOOKUP(B706,'Crown Aug Uploads '!A:A,'Crown Aug Uploads '!C:C) -> CROW01
A707: 12973 | B707: 5028479 | C707: SD CLASSIC BURMA TEAK 1L | D707: 15.01 | E707: SAD Classic Standard COL | F707: 1 | G707: PC | H707: 45079 | I707: 5721147602111 | J707: GBP | K707: =_xlfn.XLOOKUP(B707,'Crown Aug Uploads '!A:A,'Crown Aug Uploads '!C:C) -> CROW01
... A879: 12973 | B879: 5093217 | C879: SD SHED AND FENCE PROT WDLND WLK 5L | D879: 17.58 | E879: SAD Shed & Fence Prot COL | F879: 1 | G879: PC | H879: 45079 | I879: 5010131573842 | J879: GBP | K879: =_xlfn.XLOOKUP(B879,'Crown Aug Uploads '!A:A,'Crown Aug Uploads '!C:C) -> CROW01
